Workbook

Sheet Instruções
B1: IMR Angels – Contrato 04/24 – CBAE
B2: Instrumento de Medição de Resultado – versão Excel, 60 períodos (equivalente ao formulário web da PR-6)
B4: ESTRUTURA DA PASTA DE TRABALHO
B5: Dados | C5: Contrato, unidade, contratada, fiscal, período inicial, postos contratados, valores de creche, pesos dos critérios e faixa de ajuste. Tudo o que é preenchido aqui vale para as 60 abas.
B6: Resumo Geral | C6: Consolida período, nota, conceito, %, glosa, creche e valor aprovado dos 60 períodos (equivale à exportação CSV do formulário web).
B7: P01 … P60 | C7: Uma aba por período (mês), com avaliação de desempenho, postos de trabalho, instrumento de cobrança, resumo financeiro, reembolso de creche, assinaturas e justificativas.
B9: COMO PREENCHER
B10: 1. Aba Dados – identificação | C10: Contrato, unidade, contratada, fiscal operacional e o PERÍODO INICIAL (ex.: 01/05/2024). As abas P01…P60 recebem os meses seguintes automaticamente, como a propagação de períodos do formulário web.
B11: 2. Aba Dados – postos | C11: Liste os postos com Item, Nome, Qtde Contratada e Valor Unitário Contratado. Eles são replicados nas 60 abas. A linha 12 traz um exemplo: substitua-a.
B12: 3. Em cada aba Pxx | C12: Escolha a NOTA de cada critério (lista suspensa 0, 1 ou 3), informe as HORAS SEM COBERTURA de cada posto, os DIAS TRABALHADOS (apenas em mês parcial) e os dados de creche do mês.
B13: 4. Justificativas | C13: Notas 0 ou 1 geram aviso na linha do critério e ao final da aba; a justificativa é obrigatória.
B14: 5. Assinaturas | C14: Nome e matrícula dos fiscais, nome e cargo do representante da contratada e data da aprovação.
B16: CÁLCULOS – idênticos ao formulário web
B17: Subtotal do critério | C17: Peso (a) × Nota (b)
B18: Nota Final | C18: Soma dos totais dos Grupos 1, 2 e 3 (máximo 9,00)
B19: Conceito e % liberado | C19: Faixa de ajuste: A = 100% (9,00 a 8,10), B = 95% (8,09 a 7,65), C = 90% (7,64 a 6,75), D = 85% (6,74 a 5,85), E = 80% (5,84 a 5,40), F = 75% (abaixo de 5,40)
B20: Horas Contratadas | C20: Qtde Contratada × 220
B21: Valor da Hora Contratada | C21: Valor Unitário ÷ 220, truncado em 2 casas
B22: Valor do Item após Descontos | C22: ((Qtde × Valor Unit.) − Valor da Hora × Horas sem Cobertura) ÷ 30 × Dias para Cálculo × % do Faturamento — truncado em 2 casas e nunca negativo
B23: Dias para Cálculo | C23: Mês cheio = 30 avos (inclusive em fevereiro e meses de 31 dias); mês parcial = dias trabalhados informados
B24: Mensal Contratado (por posto) | C24: Qtde × Valor Unitário, truncado em 2 casas (coluna de conferência; a soma é o Contratado Mensal do resumo financeiro)
B25: Valor Unit. Faturado (instrumento de cobrança) | C25: Valor do Item após Descontos ÷ Qtde Faturada, truncado em 2 casas
B26: Valor Glosado por Qualidade | C26: Contratado Mensal − (Contratado Mensal × % do Faturamento)
B27: Valor Aprovado para Pagamento | C27: Σ Valor dos Itens após Descontos + Valor Total dos Reembolsos de Creche
B28: Total dos Reembolsos de Creche | C28: Reembolsos Aprovados × Reembolso por dependente, truncado em 2 casas
B29: Saldo de Reembolso de Creche | C29: Acumulado: saldo da aba anterior + Retido − Total dos Reembolsos. Saldo negativo exibe o aviso de aditivo contratual.
B31: LEGENDA DE CORES
B32: Fundo amarelo com texto azul | C32: Campo de preenchimento manual
B33: Fundo verde claro | C33: Valor calculado por fórmula – não editar
B34: Texto verde | C34: Valor trazido da aba Dados
B35: Azul escuro / azul | C35: Títulos e cabeçalhos
B36: Vermelho | C36: Glosa, saldo negativo e avisos de justificativa
B37: Bege (Grupo 3) | C37: Critério preenchido pelo Fiscal Administrativo (¹)
B39: EQUIVALÊNCIA COM OS RECURSOS DO FORMULÁRIO WEB
B40: Travar formulário (senha) | C40: Revisão ▸ Proteger Planilha, com senha. Os campos de preenchimento já estão desbloqueados: a proteção trava apenas fórmulas, postos e dados do contrato.
B41: Salvamento automático e sincronização entre computadores | C41: Salve a pasta no OneDrive, SharePoint ou Google Drive: o salvamento automático e a edição simultânea passam a valer para todos os usuários.
B42: Salvar PDF da aba | C42: Arquivo ▸ Exportar ▸ PDF. Cada aba já está configurada para caber em 1 folha A4.
B43: Exportação CSV | C43: Aba Resumo Geral ▸ Arquivo ▸ Salvar como ▸ CSV.
B44: Validação das notas | C44: Lista suspensa com 0, 1 e 3 em cada critério; outros valores são recusados.
B46: Gerado a partir do formulário "Modelo IMR Vigilância Definitivo V2 Com CRECHE – PR6" (versão 60 períodos) por gen_imr_excel.py.

Sheet Dados
A1: DADOS DO CONTRATO – compartilhados pelas 60 abas de período
A2: CONTRATO Nº: | B2: 04/24
A3: UNIDADE: | B3: CBAE
A4: CONTRATADA: | B4: Angels
A5: FISCAL OPERACIONAL:
A6: OBSERVAÇÃO DO CABEÇALHO: | B6: Atualizado conforme Valor Unitário Contratado inicial
A7: PERÍODO INICIAL (1ª aba – P01):
A8: Digite qualquer dia do mês inicial (ex.: 01/05/2024). As abas P01…P60 recebem os meses seguintes automaticamente.
A10: POSTOS DE TRABALHO CONTRATADOS (replicados em todas as abas)
A11: Item | B11: POSTO | C11: Qtde Contratada | D11: Valor Unit. Contratado (R$) | E11: Observação / fonte do valor
A12: 1 | B12: Vigilante Diurno 12x36 (exemplo) | C12: 2 | D12: 5996.89 | E12: LINHA DE EXEMPLO – substitua pelos postos e valores do contrato
A27: CONTRATADO MENSAL – TOTAL (conferência) | D27: =SUMPRODUCT(C12:C26,D12:D26) -> 11993.78
A29: REEMBOLSO DE CRECHE – valores padrão das abas
A30: Valor Reembolso Creche Retido (R$) por mês | D30: 0
A31: Reembolso por dependente (R$) | D31: 0
A32: Entram em todas as abas e podem ser ajustados mês a mês dentro de cada aba.
A34: CRITÉRIOS E PESOS DA AVALIAÇÃO
A35: ID | B35: Critério de Avaliação | C35: Peso (a) | D35: Grupo
A36: g1_1 | B36: Cumprimento das Atividades | C36: 0.4 | D36: 1
A37: g1_2 | B37: Qualificação / Atendimento ao Público / Postura | C37: 0.35 | D37: 1
A38: g1_3 | B38: Uniformes e Identificação | C38: 0.25 | D38: 1
A39: g2_1 | B39: Especificação Técnica dos Serviços | C39: 0.4 | D39: 2
A40: g2_2 | B40: Equipamentos e Acessórios | C40: 0.2 | D40: 2
A41: g2_3 | B41: Atendimento às Ocorrências | C41: 0.4 | D41: 2
A42: g3_1 | B42: Periodicidade da Supervisão | C42: 0.2 | D42: 3
A43: g3_2 | B43: Gerenciamento das Atividades Operacionais | C43: 0.3 | D43: 3
A44: g3_3 | B44: Atendimento às Solicitações | C44: 0.25 | D44: 3
A45: g3_4 | B45: Salários, Benefícios e Obrigações Trabalhistas (¹ Fiscal Adm.) | C45: 0.25 | D45: 3
A46: SOMA DOS PESOS (deve ser 3,00 = 1,00 por grupo) | C46: =SUM(C36:C45) -> 3
A48: FAIXA DE AJUSTE DE PAGAMENTO
A49: Nota Mínima | B49: Conceito | C49: % do Faturamento a ser Pago | D49: Nota Média Mensal Apurada
A50: 0 | B50: F | C50: 0.75 | D50: Abaixo de 5,40
A51: 5.4 | B51: E | C51: 0.8 | D51: Entre 5,84 e 5,40
A52: 5.85 | B52: D | C52: 0.85 | D52: Entre 6,74 e 5,85
A53: 6.75 | B53: C | C53: 0.9 | D53: Entre 7,64 e 6,75
A54: 7.65 | B54: B | C54: 0.95 | D54: Entre 8,09 e 7,65
A55: 8.1 | B55: A | C55: 1 | D55: Entre 9,00 e 8,10
A56: Ordem crescente de nota mínima: é assim que as abas localizam o conceito e o % a liberar (INDEX/MATCH). Não reordene as linhas.

Sheet Resumo Geral
A1: RESUMO GERAL DOS 60 PERÍODOS
A2: Aba | B2: Período | C2: Nota Final | D2: Conceito | E2: % Liberado | F2: Dias Trab. | G2: Contratado Mensal (R$) | H2: Glosa por Qualidade (R$) | I2: Itens após Descontos (R$) | J2: Reembolsos Creche (R$) | K2: Saldo Creche (R$) | L2: Valor Aprovado (R$)
A3: P01 | B3: =P01!B7 -> (informe o período inicial na aba Dados) | C3: =P01!D28 -> 9 | D3: =P01!F28 -> A | E3: =P01!F71 -> 1 | F3: =P01!F74 -> 30 | G3: =P01!I47 -> 11993.78 | H3: =P01!F72 -> 0 | I3: =P01!H47 -> 11993.78 | J3: =P01!F83 -> 0 | K3: =P01!F84 -> 0 | L3: =P01!F77 -> 11993.78
A4: P02 | B4: =P02!B7 -> (informe o período inicial na aba Dados) | C4: =P02!D28 -> 9 | D4: =P02!F28 -> A | E4: =P02!F71 -> 1 | F4: =P02!F74 -> 30 | G4: =P02!I47 -> 11993.78 | H4: =P02!F72 -> 0 | I4: =P02!H47 -> 11993.78 | J4: =P02!F83 -> 0 | K4: =P02!F84 -> 0 | L4: =P02!F77 -> 11993.78
A5: P03 | B5: =P03!B7 -> (informe o período inicial na aba Dados) | C5: =P03!D28 -> 9 | D5: =P03!F28 -> A | E5: =P03!F71 -> 1 | F5: =P03!F74 -> 30 | G5: =P03!I47 -> 11993.78 | H5: =P03!F72 -> 0 | I5: =P03!H47 -> 11993.78 | J5: =P03!F83 -> 0 | K5: =P03!F84 -> 0 | L5: =P03!F77 -> 11993.78
A6: P04 | B6: =P04!B7 -> (informe o período inicial na aba Dados) | C6: =P04!D28 -> 9 | D6: =P04!F28 -> A | E6: =P04!F71 -> 1 | F6: =P04!F74 -> 30 | G6: =P04!I47 -> 11993.78 | H6: =P04!F72 -> 0 | I6: =P04!H47 -> 11993.78 | J6: =P04!F83 -> 0 | K6: =P04!F84 -> 0 | L6: =P04!F77 -> 11993.78
A7: P05 | B7: =P05!B7 -> (informe o período inicial na aba Dados) | C7: =P05!D28 -> 9 | D7: =P05!F28 -> A | E7: =P05!F71 -> 1 | F7: =P05!F74 -> 30 | G7: =P05!I47 -> 11993.78 | H7: =P05!F72 -> 0 | I7: =P05!H47 -> 11993.78 | J7: =P05!F83 -> 0 | K7: =P05!F84 -> 0 | L7: =P05!F77 -> 11993.78
A8: P06 | B8: =P06!B7 -> (informe o período inicial na aba Dados) | C8: =P06!D28 -> 9 | D8: =P06!F28 -> A | E8: =P06!F71 -> 1 | F8: =P06!F74 -> 30 | G8: =P06!I47 -> 11993.78 | H8: =P06!F72 -> 0 | I8: =P06!H47 -> 11993.78 | J8: =P06!F83 -> 0 | K8: =P06!F84 -> 0 | L8: =P06!F77 -> 11993.78
A9: P07 | B9: =P07!B7 -> (informe o período inicial na aba Dados) | C9: =P07!D28 -> 9 | D9: =P07!F28 -> A | E9: =P07!F71 -> 1 | F9: =P07!F74 -> 30 | G9: =P07!I47 -> 11993.78 | H9: =P07!F72 -> 0 | I9: =P07!H47 -> 11993.78 | J9: =P07!F83 -> 0 | K9: =P07!F84 -> 0 | L9: =P07!F77 -> 11993.78
A10: P08 | B10: =P08!B7 -> (informe o período inicial na aba Dados) | C10: =P08!D28 -> 9 | D10: =P08!F28 -> A | E10: =P08!F71 -> 1 | F10: =P08!F74 -> 30 | G10: =P08!I47 -> 11993.78 | H10: =P08!F72 -> 0 | I10: =P08!H47 -> 11993.78 | J10: =P08!F83 -> 0 | K10: =P08!F84 -> 0 | L10: =P08!F77 -> 11993.78
A11: P09 | B11: =P09!B7 -> (informe o período inicial na aba Dados) | C11: =P09!D28 -> 9 | D11: =P09!F28 -> A | E11: =P09!F71 -> 1 | F11: =P09!F74 -> 30 | G11: =P09!I47 -> 11993.78 | H11: =P09!F72 -> 0 | I11: =P09!H47 -> 11993.78 | J11: =P09!F83 -> 0 | K11: =P09!F84 -> 0 | L11: =P09!F77 -> 11993.78
A12: P10 | B12: =P10!B7 -> (informe o período inicial na aba Dados) | C12: =P10!D28 -> 9 | D12: =P10!F28 -> A | E12: =P10!F71 -> 1 | F12: =P10!F74 -> 30 | G12: =P10!I47 -> 11993.78 | H12: =P10!F72 -> 0 | I12: =P10!H47 -> 11993.78 | J12: =P10!F83 -> 0 | K12: =P10!F84 -> 0 | L12: =P10!F77 -> 11993.78
A13: P11 | B13: =P11!B7 -> (informe o período inicial na aba Dados) | C13: =P11!D28 -> 9 | D13: =P11!F28 -> A | E13: =P11!F71 -> 1 | F13: =P11!F74 -> 30 | G13: =P11!I47 -> 11993.78 | H13: =P11!F72 -> 0 | I13: =P11!H47 -> 11993.78 | J13: =P11!F83 -> 0 | K13: =P11!F84 -> 0 | L13: =P11!F77 -> 11993.78
A14: P12 | B14: =P12!B7 -> (informe o período inicial na aba Dados) | C14: =P12!D28 -> 9 | D14: =P12!F28 -> A | E14: =P12!F71 -> 1 | F14: =P12!F74 -> 30 | G14: =P12!I47 -> 11993.78 | H14: =P12!F72 -> 0 | I14: =P12!H47 -> 11993.78 | J14: =P12!F83 -> 0 | K14: =P12!F84 -> 0 | L14: =P12!F77 -> 11993.78
A15: P13 | B15: =P13!B7 -> (informe o período inicial na aba Dados) | C15: =P13!D28 -> 9 | D15: =P13!F28 -> A | E15: =P13!F71 -> 1 | F15: =P13!F74 -> 30 | G15: =P13!I47 -> 11993.78 | H15: =P13!F72 -> 0 | I15: =P13!H47 -> 11993.78 | J15: =P13!F83 -> 0 | K15: =P13!F84 -> 0 | L15: =P13!F77 -> 11993.78
A16: P14 | B16: =P14!B7 -> (informe o período inicial na aba Dados) | C16: =P14!D28 -> 9 | D16: =P14!F28 -> A | E16: =P14!F71 -> 1 | F16: =P14!F74 -> 30 | G16: =P14!I47 -> 11993.78 | H16: =P14!F72 -> 0 | I16: =P14!H47 -> 11993.78 | J16: =P14!F83 -> 0 | K16: =P14!F84 -> 0 | L16: =P14!F77 -> 11993.78
A17: P15 | B17: =P15!B7 -> (informe o período inicial na aba Dados) | C17: =P15!D28 -> 9 | D17: =P15!F28 -> A | E17: =P15!F71 -> 1 | F17: =P15!F74 -> 30 | G17: =P15!I47 -> 11993.78 | H17: =P15!F72 -> 0 | I17: =P15!H47 -> 11993.78 | J17: =P15!F83 -> 0 | K17: =P15!F84 -> 0 | L17: =P15!F77 -> 11993.78
A18: P16 | B18: =P16!B7 -> (informe o período inicial na aba Dados) | C18: =P16!D28 -> 9 | D18: =P16!F28 -> A | E18: =P16!F71 -> 1 | F18: =P16!F74 -> 30 | G18: =P16!I47 -> 11993.78 | H18: =P16!F72 -> 0 | I18: =P16!H47 -> 11993.78 | J18: =P16!F83 -> 0 | K18: =P16!F84 -> 0 | L18: =P16!F77 -> 11993.78
A19: P17 | B19: =P17!B7 -> (informe o período inicial na aba Dados) | C19: =P17!D28 -> 9 | D19: =P17!F28 -> A | E19: =P17!F71 -> 1 | F19: =P17!F74 -> 30 | G19: =P17!I47 -> 11993.78 | H19: =P17!F72 -> 0 | I19: =P17!H47 -> 11993.78 | J19: =P17!F83 -> 0 | K19: =P17!F84 -> 0 | L19: =P17!F77 -> 11993.78
A20: P18 | B20: =P18!B7 -> (informe o período inicial na aba Dados) | C20: =P18!D28 -> 9 | D20: =P18!F28 -> A | E20: =P18!F71 -> 1 | F20: =P18!F74 -> 30 | G20: =P18!I47 -> 11993.78 | H20: =P18!F72 -> 0 | I20: =P18!H47 -> 11993.78 | J20: =P18!F83 -> 0 | K20: =P18!F84 -> 0 | L20: =P18!F77 -> 11993.78
A21: P19 | B21: =P19!B7 -> (informe o período inicial na aba Dados) | C21: =P19!D28 -> 9 | D21: =P19!F28 -> A | E21: =P19!F71 -> 1 | F21: =P19!F74 -> 30 | G21: =P19!I47 -> 11993.78 | H21: =P19!F72 -> 0 | I21: =P19!H47 -> 11993.78 | J21: =P19!F83 -> 0 | K21: =P19!F84 -> 0 | L21: =P19!F77 -> 11993.78
A22: P20 | B22: =P20!B7 -> (informe o período inicial na aba Dados) | C22: =P20!D28 -> 9 | D22: =P20!F28 -> A | E22: =P20!F71 -> 1 | F22: =P20!F74 -> 30 | G22: =P20!I47 -> 11993.78 | H22: =P20!F72 -> 0 | I22: =P20!H47 -> 11993.78 | J22: =P20!F83 -> 0 | K22: =P20!F84 -> 0 | L22: =P20!F77 -> 11993.78
A23: P21 | B23: =P21!B7 -> (informe o período inicial na aba Dados) | C23: =P21!D28 -> 9 | D23: =P21!F28 -> A | E23: =P21!F71 -> 1 | F23: =P21!F74 -> 30 | G23: =P21!I47 -> 11993.78 | H23: =P21!F72 -> 0 | I23: =P21!H47 -> 11993.78 | J23: =P21!F83 -> 0 | K23: =P21!F84 -> 0 | L23: =P21!F77 -> 11993.78
A24: P22 | B24: =P22!B7 -> (informe o período inicial na aba Dados) | C24: =P22!D28 -> 9 | D24: =P22!F28 -> A | E24: =P22!F71 -> 1 | F24: =P22!F74 -> 30 | G24: =P22!I47 -> 11993.78 | H24: =P22!F72 -> 0 | I24: =P22!H47 -> 11993.78 | J24: =P22!F83 -> 0 | K24: =P22!F84 -> 0 | L24: =P22!F77 -> 11993.78
A25: P23 | B25: =P23!B7 -> (informe o período inicial na aba Dados) | C25: =P23!D28 -> 9 | D25: =P23!F28 -> A | E25: =P23!F71 -> 1 | F25: =P23!F74 -> 30 | G25: =P23!I47 -> 11993.78 | H25: =P23!F72 -> 0 | I25: =P23!H47 -> 11993.78 | J25: =P23!F83 -> 0 | K25: =P23!F84 -> 0 | L25: =P23!F77 -> 11993.78
A26: P24 | B26: =P24!B7 -> (informe o período inicial na aba Dados) | C26: =P24!D28 -> 9 | D26: =P24!F28 -> A | E26: =P24!F71 -> 1 | F26: =P24!F74 -> 30 | G26: =P24!I47 -> 11993.78 | H26: =P24!F72 -> 0 | I26: =P24!H47 -> 11993.78 | J26: =P24!F83 -> 0 | K26: =P24!F84 -> 0 | L26: =P24!F77 -> 11993.78
A27: P25 | B27: =P25!B7 -> (informe o período inicial na aba Dados) | C27: =P25!D28 -> 9 | D27: =P25!F28 -> A | E27: =P25!F71 -> 1 | F27: =P25!F74 -> 30 | G27: =P25!I47 -> 11993.78 | H27: =P25!F72 -> 0 | I27: =P25!H47 -> 11993.78 | J27: =P25!F83 -> 0 | K27: =P25!F84 -> 0 | L27: =P25!F77 -> 11993.78
A28: P26 | B28: =P26!B7 -> (informe o período inicial na aba Dados) | C28: =P26!D28 -> 9 | D28: =P26!F28 -> A | E28: =P26!F71 -> 1 | F28: =P26!F74 -> 30 | G28: =P26!I47 -> 11993.78 | H28: =P26!F72 -> 0 | I28: =P26!H47 -> 11993.78 | J28: =P26!F83 -> 0 | K28: =P26!F84 -> 0 | L28: =P26!F77 -> 11993.78
A29: P27 | B29: =P27!B7 -> (informe o período inicial na aba Dados) | C29: =P27!D28 -> 9 | D29: =P27!F28 -> A | E29: =P27!F71 -> 1 | F29: =P27!F74 -> 30 | G29: =P27!I47 -> 11993.78 | H29: =P27!F72 -> 0 | I29: =P27!H47 -> 11993.78 | J29: =P27!F83 -> 0 | K29: =P27!F84 -> 0 | L29: =P27!F77 -> 11993.78
A30: P28 | B30: =P28!B7 -> (informe o período inicial na aba Dados) | C30: =P28!D28 -> 9 | D30: =P28!F28 -> A | E30: =P28!F71 -> 1 | F30: =P28!F74 -> 30 | G30: =P28!I47 -> 11993.78 | H30: =P28!F72 -> 0 | I30: =P28!H47 -> 11993.78 | J30: =P28!F83 -> 0 | K30: =P28!F84 -> 0 | L30: =P28!F77 -> 11993.78
A31: P29 | B31: =P29!B7 -> (informe o período inicial na aba Dados) | C31: =P29!D28 -> 9 | D31: =P29!F28 -> A | E31: =P29!F71 -> 1 | F31: =P29!F74 -> 30 | G31: =P29!I47 -> 11993.78 | H31: =P29!F72 -> 0 | I31: =P29!H47 -> 11993.78 | J31: =P29!F83 -> 0 | K31: =P29!F84 -> 0 | L31: =P29!F77 -> 11993.78
A32: P30 | B32: =P30!B7 -> (informe o período inicial na aba Dados) | C32: =P30!D28 -> 9 | D32: =P30!F28 -> A | E32: =P30!F71 -> 1 | F32: =P30!F74 -> 30 | G32: =P30!I47 -> 11993.78 | H32: =P30!F72 -> 0 | I32: =P30!H47 -> 11993.78 | J32: =P30!F83 -> 0 | K32: =P30!F84 -> 0 | L32: =P30!F77 -> 11993.78
A33: P31 | B33: =P31!B7 -> (informe o período inicial na aba Dados) | C33: =P31!D28 -> 9 | D33: =P31!F28 -> A | E33: =P31!F71 -> 1 | F33: =P31!F74 -> 30 | G33: =P31!I47 -> 11993.78 | H33: =P31!F72 -> 0 | I33: =P31!H47 -> 11993.78 | J33: =P31!F83 -> 0 | K33: =P31!F84 -> 0 | L33: =P31!F77 -> 11993.78
A34: P32 | B34: =P32!B7 -> (informe o período inicial na aba Dados) | C34: =P32!D28 -> 9 | D34: =P32!F28 -> A | E34: =P32!F71 -> 1 | F34: =P32!F74 -> 30 | G34: =P32!I47 -> 11993.78 | H34: =P32!F72 -> 0 | I34: =P32!H47 -> 11993.78 | J34: =P32!F83 -> 0 | K34: =P32!F84 -> 0 | L34: =P32!F77 -> 11993.78
A35: P33 | B35: =P33!B7 -> (informe o período inicial na aba Dados) | C35: =P33!D28 -> 9 | D35: =P33!F28 -> A | E35: =P33!F71 -> 1 | F35: =P33!F74 -> 30 | G35: =P33!I47 -> 11993.78 | H35: =P33!F72 -> 0 | I35: =P33!H47 -> 11993.78 | J35: =P33!F83 -> 0 | K35: =P33!F84 -> 0 | L35: =P33!F77 -> 11993.78
A36: P34 | B36: =P34!B7 -> (informe o período inicial na aba Dados) | C36: =P34!D28 -> 9 | D36: =P34!F28 -> A | E36: =P34!F71 -> 1 | F36: =P34!F74 -> 30 | G36: =P34!I47 -> 11993.78 | H36: =P34!F72 -> 0 | I36: =P34!H47 -> 11993.78 | J36: =P34!F83 -> 0 | K36: =P34!F84 -> 0 | L36: =P34!F77 -> 11993.78
A37: P35 | B37: =P35!B7 -> (informe o período inicial na aba Dados) | C37: =P35!D28 -> 9 | D37: =P35!F28 -> A | E37: =P35!F71 -> 1 | F37: =P35!F74 -> 30 | G37: =P35!I47 -> 11993.78 | H37: =P35!F72 -> 0 | I37: =P35!H47 -> 11993.78 | J37: =P35!F83 -> 0 | K37: =P35!F84 -> 0 | L37: =P35!F77 -> 11993.78
A38: P36 | B38: =P36!B7 -> (informe o período inicial na aba Dados) | C38: =P36!D28 -> 9 | D38: =P36!F28 -> A | E38: =P36!F71 -> 1 | F38: =P36!F74 -> 30 | G38: =P36!I47 -> 11993.78 | H38: =P36!F72 -> 0 | I38: =P36!H47 -> 11993.78 | J38: =P36!F83 -> 0 | K38: =P36!F84 -> 0 | L38: =P36!F77 -> 11993.78
A39: P37 | B39: =P37!B7 -> (informe o período inicial na aba Dados) | C39: =P37!D28 -> 9 | D39: =P37!F28 -> A | E39: =P37!F71 -> 1 | F39: =P37!F74 -> 30 | G39: =P37!I47 -> 11993.78 | H39: =P37!F72 -> 0 | I39: =P37!H47 -> 11993.78 | J39: =P37!F83 -> 0 | K39: =P37!F84 -> 0 | L39: =P37!F77 -> 11993.78
A40: P38 | B40: =P38!B7 -> (informe o período inicial na aba Dados) | C40: =P38!D28 -> 9 | D40: =P38!F28 -> A | E40: =P38!F71 -> 1 | F40: =P38!F74 -> 30 | G40: =P38!I47 -> 11993.78 | H40: =P38!F72 -> 0 | I40: =P38!H47 -> 11993.78 | J40: =P38!F83 -> 0 | K40: =P38!F84 -> 0 | L40: =P38!F77 -> 11993.78
A41: P39 | B41: =P39!B7 -> (informe o período inicial na aba Dados) | C41: =P39!D28 -> 9 | D41: =P39!F28 -> A | E41: =P39!F71 -> 1 | F41: =P39!F74 -> 30 | G41: =P39!I47 -> 11993.78 | H41: =P39!F72 -> 0 | I41: =P39!H47 -> 11993.78 | J41: =P39!F83 -> 0 | K41: =P39!F84 -> 0 | L41: =P39!F77 -> 11993.78
A42: P40 | B42: =P40!B7 -> (informe o período inicial na aba Dados) | C42: =P40!D28 -> 9 | D42: =P40!F28 -> A | E42: =P40!F71 -> 1 | F42: =P40!F74 -> 30 | G42: =P40!I47 -> 11993.78 | H42: =P40!F72 -> 0 | I42: =P40!H47 -> 11993.78 | J42: =P40!F83 -> 0 | K42: =P40!F84 -> 0 | L42: =P40!F77 -> 11993.78
A43: P41 | B43: =P41!B7 -> (informe o período inicial na aba Dados) | C43: =P41!D28 -> 9 | D43: =P41!F28 -> A | E43: =P41!F71 -> 1 | F43: =P41!F74 -> 30 | G43: =P41!I47 -> 11993.78 | H43: =P41!F72 -> 0 | I43: =P41!H47 -> 11993.78 | J43: =P41!F83 -> 0 | K43: =P41!F84 -> 0 | L43: =P41!F77 -> 11993.78
A44: P42 | B44: =P42!B7 -> (informe o período inicial na aba Dados) | C44: =P42!D28 -> 9 | D44: =P42!F28 -> A | E44: =P42!F71 -> 1 | F44: =P42!F74 -> 30 | G44: =P42!I47 -> 11993.78 | H44: =P42!F72 -> 0 | I44: =P42!H47 -> 11993.78 | J44: =P42!F83 -> 0 | K44: =P42!F84 -> 0 | L44: =P42!F77 -> 11993.78
A45: P43 | B45: =P43!B7 -> (informe o período inicial na aba Dados) | C45: =P43!D28 -> 9 | D45: =P43!F28 -> A | E45: =P43!F71 -> 1 | F45: =P43!F74 -> 30 | G45: =P43!I47 -> 11993.78 | H45: =P43!F72 -> 0 | I45: =P43!H47 -> 11993.78 | J45: =P43!F83 -> 0 | K45: =P43!F84 -> 0 | L45: =P43!F77 -> 11993.78
A46: P44 | B46: =P44!B7 -> (informe o período inicial na aba Dados) | C46: =P44!D28 -> 9 | D46: =P44!F28 -> A | E46: =P44!F71 -> 1 | F46: =P44!F74 -> 30 | G46: =P44!I47 -> 11993.78 | H46: =P44!F72 -> 0 | I46: =P44!H47 -> 11993.78 | J46: =P44!F83 -> 0 | K46: =P44!F84 -> 0 | L46: =P44!F77 -> 11993.78
A47: P45 | B47: =P45!B7 -> (informe o período inicial na aba Dados) | C47: =P45!D28 -> 9 | D47: =P45!F28 -> A | E47: =P45!F71 -> 1 | F47: =P45!F74 -> 30 | G47: =P45!I47 -> 11993.78 | H47: =P45!F72 -> 0 | I47: =P45!H47 -> 11993.78 | J47: =P45!F83 -> 0 | K47: =P45!F84 -> 0 | L47: =P45!F77 -> 11993.78
A48: P46 | B48: =P46!B7 -> (informe o período inicial na aba Dados) | C48: =P46!D28 -> 9 | D48: =P46!F28 -> A | E48: =P46!F71 -> 1 | F48: =P46!F74 -> 30 | G48: =P46!I47 -> 11993.78 | H48: =P46!F72 -> 0 | I48: =P46!H47 -> 11993.78 | J48: =P46!F83 -> 0 | K48: =P46!F84 -> 0 | L48: =P46!F77 -> 11993.78
A49: P47 | B49: =P47!B7 -> (informe o período inicial na aba Dados) | C49: =P47!D28 -> 9 | D49: =P47!F28 -> A | E49: =P47!F71 -> 1 | F49: =P47!F74 -> 30 | G49: =P47!I47 -> 11993.78 | H49: =P47!F72 -> 0 | I49: =P47!H47 -> 11993.78 | J49: =P47!F83 -> 0 | K49: =P47!F84 -> 0 | L49: =P47!F77 -> 11993.78
A50: P48 | B50: =P48!B7 -> (informe o período inicial na aba Dados) | C50: =P48!D28 -> 9 | D50: =P48!F28 -> A | E50: =P48!F71 -> 1 | F50: =P48!F74 -> 30 | G50: =P48!I47 -> 11993.78 | H50: =P48!F72 -> 0 | I50: =P48!H47 -> 11993.78 | J50: =P48!F83 -> 0 | K50: =P48!F84 -> 0 | L50: =P48!F77 -> 11993.78
A51: P49 | B51: =P49!B7 -> (informe o período inicial na aba Dados) | C51: =P49!D28 -> 9 | D51: =P49!F28 -> A | E51: =P49!F71 -> 1 | F51: =P49!F74 -> 30 | G51: =P49!I47 -> 11993.78 | H51: =P49!F72 -> 0 | I51: =P49!H47 -> 11993.78 | J51: =P49!F83 -> 0 | K51: =P49!F84 -> 0 | L51: =P49!F77 -> 11993.78
A52: P50 | B52: =P50!B7 -> (informe o período inicial na aba Dados) | C52: =P50!D28 -> 9 | D52: =P50!F28 -> A | E52: =P50!F71 -> 1 | F52: =P50!F74 -> 30 | G52: =P50!I47 -> 11993.78 | H52: =P50!F72 -> 0 | I52: =P50!H47 -> 11993.78 | J52: =P50!F83 -> 0 | K52: =P50!F84 -> 0 | L52: =P50!F77 -> 11993.78
A53: P51 | B53: =P51!B7 -> (informe o período inicial na aba Dados) | C53: =P51!D28 -> 9 | D53: =P51!F28 -> A | E53: =P51!F71 -> 1 | F53: =P51!F74 -> 30 | G53: =P51!I47 -> 11993.78 | H53: =P51!F72 -> 0 | I53: =P51!H47 -> 11993.78 | J53: =P51!F83 -> 0 | K53: =P51!F84 -> 0 | L53: =P51!F77 -> 11993.78
A54: P52 | B54: =P52!B7 -> (informe o período inicial na aba Dados) | C54: =P52!D28 -> 9 | D54: =P52!F28 -> A | E54: =P52!F71 -> 1 | F54: =P52!F74 -> 30 | G54: =P52!I47 -> 11993.78 | H54: =P52!F72 -> 0 | I54: =P52!H47 -> 11993.78 | J54: =P52!F83 -> 0 | K54: =P52!F84 -> 0 | L54: =P52!F77 -> 11993.78
A55: P53 | B55: =P53!B7 -> (informe o período inicial na aba Dados) | C55: =P53!D28 -> 9 | D55: =P53!F28 -> A | E55: =P53!F71 -> 1 | F55: =P53!F74 -> 30 | G55: =P53!I47 -> 11993.78 | H55: =P53!F72 -> 0 | I55: =P53!H47 -> 11993.78 | J55: =P53!F83 -> 0 | K55: =P53!F84 -> 0 | L55: =P53!F77 -> 11993.78
A56: P54 | B56: =P54!B7 -> (informe o período inicial na aba Dados) | C56: =P54!D28 -> 9 | D56: =P54!F28 -> A | E56: =P54!F71 -> 1 | F56: =P54!F74 -> 30 | G56: =P54!I47 -> 11993.78 | H56: =P54!F72 -> 0 | I56: =P54!H47 -> 11993.78 | J56: =P54!F83 -> 0 | K56: =P54!F84 -> 0 | L56: =P54!F77 -> 11993.78
A57: P55 | B57: =P55!B7 -> (informe o período inicial na aba Dados) | C57: =P55!D28 -> 9 | D57: =P55!F28 -> A | E57: =P55!F71 -> 1 | F57: =P55!F74 -> 30 | G57: =P55!I47 -> 11993.78 | H57: =P55!F72 -> 0 | I57: =P55!H47 -> 11993.78 | J57: =P55!F83 -> 0 | K57: =P55!F84 -> 0 | L57: =P55!F77 -> 11993.78
A58: P56 | B58: =P56!B7 -> (informe o período inicial na aba Dados) | C58: =P56!D28 -> 9 | D58: =P56!F28 -> A | E58: =P56!F71 -> 1 | F58: =P56!F74 -> 30 | G58: =P56!I47 -> 11993.78 | H58: =P56!F72 -> 0 | I58: =P56!H47 -> 11993.78 | J58: =P56!F83 -> 0 | K58: =P56!F84 -> 0 | L58: =P56!F77 -> 11993.78
A59: P57 | B59: =P57!B7 -> (informe o período inicial na aba Dados) | C59: =P57!D28 -> 9 | D59: =P57!F28 -> A | E59: =P57!F71 -> 1 | F59: =P57!F74 -> 30 | G59: =P57!I47 -> 11993.78 | H59: =P57!F72 -> 0 | I59: =P57!H47 -> 11993.78 | J59: =P57!F83 -> 0 | K59: =P57!F84 -> 0 | L59: =P57!F77 -> 11993.78
A60: P58 | B60: =P58!B7 -> (informe o período inicial na aba Dados) | C60: =P58!D28 -> 9 | D60: =P58!F28 -> A | E60: =P58!F71 -> 1 | F60: =P58!F74 -> 30 | G60: =P58!I47 -> 11993.78 | H60: =P58!F72 -> 0 | I60: =P58!H47 -> 11993.78 | J60: =P58!F83 -> 0 | K60: =P58!F84 -> 0 | L60: =P58!F77 -> 11993.78
A61: P59 | B61: =P59!B7 -> (informe o período inicial na aba Dados) | C61: =P59!D28 -> 9 | D61: =P59!F28 -> A | E61: =P59!F71 -> 1 | F61: =P59!F74 -> 30 | G61: =P59!I47 -> 11993.78 | H61: =P59!F72 -> 0 | I61: =P59!H47 -> 11993.78 | J61: =P59!F83 -> 0 | K61: =P59!F84 -> 0 | L61: =P59!F77 -> 11993.78
A62: P60 | B62: =P60!B7 -> (informe o período inicial na aba Dados) | C62: =P60!D28 -> 9 | D62: =P60!F28 -> A | E62: =P60!F71 -> 1 | F62: =P60!F74 -> 30 | G62: =P60!I47 -> 11993.78 | H62: =P60!F72 -> 0 | I62: =P60!H47 -> 11993.78 | J62: =P60!F83 -> 0 | K62: =P60!F84 -> 0 | L62: =P60!F77 -> 11993.78
A63: TOTAIS DO CONTRATO | G63: =SUM(G3:G62) -> 719626.8 | H63: =SUM(H3:H62) -> 0 | I63: =SUM(I3:I62) -> 719626.8 | J63: =SUM(J3:J62) -> 0 | K63: =K62 -> 0 | L63: =SUM(L3:L62) -> 719626.8
A64: Saldo de Creche: valor acumulado do último período (não é soma). Linhas em vermelho indicam saldo negativo — exige aditivo contratual.

Sheet P01
A1: UFRJ – PRÓ-REITORIA DE GESTÃO E GOVERNANÇA – PR6 | IMR
A2: INSTRUMENTO DE MEDIÇÃO DE RESULTADO
A3: =IF(Dados!$B$6="","",Dados!$B$6) -> Atualizado conforme Valor Unitário Contratado inicial
A5: CONTRATO Nº: | B5: =IF(Dados!$B$2="","",Dados!$B$2) -> 04/24 | E5: UNIDADE: | G5: =IF(Dados!$B$3="","",Dados!$B$3) -> CBAE
A6: CONTRATADA: | B6: =IF(Dados!$B$4="","",Dados!$B$4) -> Angels | E6: FISCAL OPERACIONAL: | G6: =IF(Dados!$B$5="","",Dados!$B$5)
A7: AVALIAÇÃO REFERENTE AO PERÍODO: | B7: =IF(Dados!$B$7="","(informe o período inicial na aba Dados)",EDATE(Dados!$B$7,0)) -> (informe o período inicial na aba Dados) | E7: PERÍODO (ABA) Nº: | G7: 1 de 60
A8: ⚠ Para notas 0 e 1 o campo JUSTIFICATIVAS (fim da aba) é de preenchimento obrigatório. | Contrato, Unidade, Contratada e Postos são compartilhados por todas as abas (aba Dados).
A10: AVALIAÇÃO DE DESEMPENHO
A11: Critério de Avaliação | B11: PESO (a) | C11: NOTA (b) (0, 1 ou 3) | D11: SUBTOTAL (c = a × b) | E11: Status | F11: Aviso de Justificativa
A12: ▶ GRUPO 1 – DESEMPENHO PROFISSIONAL
A13: =Dados!$B$36 -> Cumprimento das Atividades | B13: =Dados!$C$36 -> 0.4 | C13: 3 | D13: =B13*C13 -> 1.2 | E13: =IF(OR(C13=0,C13=1,C13=3),"✓ Ok","⛔ Inválida") -> ✓ Ok | F13: =IF(OR(C13=0,C13=1),"⚠ Favor inserir justificativa da nota "&C13&" no campo JUSTIFICATIVAS","")
A14: =Dados!$B$37 -> Qualificação / Atendimento ao Público / Postura | B14: =Dados!$C$37 -> 0.35 | C14: 3 | D14: =B14*C14 -> 1.05 | E14: =IF(OR(C14=0,C14=1,C14=3),"✓ Ok","⛔ Inválida") -> ✓ Ok | F14: =IF(OR(C14=0,C14=1),"⚠ Favor inserir justificativa da nota "&C14&" no campo JUSTIFICATIVAS","")
A15: =Dados!$B$38 -> Uniformes e Identificação | B15: =Dados!$C$38 -> 0.25 | C15: 3 | D15: =B15*C15 -> 0.75 | E15: =IF(OR(C15=0,C15=1,C15=3),"✓ Ok","⛔ Inválida") -> ✓ Ok | F15: =IF(OR(C15=0,C15=1),"⚠ Favor inserir justificativa da nota "&C15&" no campo JUSTIFICATIVAS","")
A16: TOTAL GRUPO 1 | B16: =SUM(B13:B15) -> 1 | D16: =SUM(D13:D15) -> 3
A17: ▶ GRUPO 2 – DESEMPENHO DAS ATIVIDADES
A18: =Dados!$B$39 -> Especificação Técnica dos Serviços | B18: =Dados!$C$39 -> 0.4 | C18: 3 | D18: =B18*C18 -> 1.2 | E18: =IF(OR(C18=0,C18=1,C18=3),"✓ Ok","⛔ Inválida") -> ✓ Ok | F18: =IF(OR(C18=0,C18=1),"⚠ Favor inserir justificativa da nota "&C18&" no campo JUSTIFICATIVAS","")
A19: =Dados!$B$40 -> Equipamentos e Acessórios | B19: =Dados!$C$40 -> 0.2 | C19: 3 | D19: =B19*C19 -> 0.6 | E19: =IF(OR(C19=0,C19=1,C19=3),"✓ Ok","⛔ Inválida") -> ✓ Ok | F19: =IF(OR(C19=0,C19=1),"⚠ Favor inserir justificativa da nota "&C19&" no campo JUSTIFICATIVAS","")
A20: =Dados!$B$41 -> Atendimento às Ocorrências | B20: =Dados!$C$41 -> 0.4 | C20: 3 | D20: =B20*C20 -> 1.2 | E20: =IF(OR(C20=0,C20=1,C20=3),"✓ Ok","⛔ Inválida") -> ✓ Ok | F20: =IF(OR(C20=0,C20=1),"⚠ Favor inserir justificativa da nota "&C20&" no campo JUSTIFICATIVAS","")
A21: TOTAL GRUPO 2 | B21: =SUM(B18:B20) -> 1 | D21: =SUM(D18:D20) -> 3
A22: ▶ GRUPO 3 – GERENCIAMENTO
A23: =Dados!$B$42 -> Periodicidade da Supervisão | B23: =Dados!$C$42 -> 0.2 | C23: 3 | D23: =B23*C23 -> 0.6 | E23: =IF(OR(C23=0,C23=1,C23=3),"✓ Ok","⛔ Inválida") -> ✓ Ok | F23: =IF(OR(C23=0,C23=1),"⚠ Favor inserir justificativa da nota "&C23&" no campo JUSTIFICATIVAS","")
A24: =Dados!$B$43 -> Gerenciamento das Atividades Operacionais | B24: =Dados!$C$43 -> 0.3 | C24: 3 | D24: =B24*C24 -> 0.9 | E24: =IF(OR(C24=0,C24=1,C24=3),"✓ Ok","⛔ Inválida") -> ✓ Ok | F24: =IF(OR(C24=0,C24=1),"⚠ Favor inserir justificativa da nota "&C24&" no campo JUSTIFICATIVAS","")
A25: =Dados!$B$44 -> Atendimento às Solicitações | B25: =Dados!$C$44 -> 0.25 | C25: 3 | D25: =B25*C25 -> 0.75 | E25: =IF(OR(C25=0,C25=1,C25=3),"✓ Ok","⛔ Inválida") -> ✓ Ok | F25: =IF(OR(C25=0,C25=1),"⚠ Favor inserir justificativa da nota "&C25&" no campo JUSTIFICATIVAS","")
A26: =Dados!$B$45 -> Salários, Benefícios e Obrigações Trabalhistas (¹ Fiscal Adm.) | B26: =Dados!$C$45 -> 0.25 | C26: 3 | D26: =B26*C26 -> 0.75 | E26: =IF(OR(C26=0,C26=1,C26=3),"✓ Ok","⛔ Inválida") -> ✓ Ok | F26: =IF(OR(C26=0,C26=1),"⚠ Favor inserir justificativa da nota "&C26&" no campo JUSTIFICATIVAS","")
A27: TOTAL GRUPO 3 | B27: =SUM(B23:B26) -> 1 | D27: =SUM(D23:D26) -> 3
A28: NOTA FINAL (somatório dos Grupos 1, 2 e 3) | D28: =D16+D21+D27 -> 9 | E28: Conceito: | F28: =INDEX(Dados!$B$50:$B$55,MATCH(D28,Dados!$A$50:$A$55,1)) -> A | G28: (¹) Grupo 3 – Salários/Benefícios/Obrigações Trabalhistas: preenchido pelo Fiscal Administrativo
A30: POSTOS DE TRABALHO
A31: Item | B31: POSTO | C31: Qtde Contratada | D31: Valor Unit. Contratado (R$) | E31: Horas Contratadas | F31: Sem Cobertura (h) | G31: Valor da Hora Contratada (R$) | H31: Valor do Item após Descontos (R$) | I31: Mensal Contratado (R$)
A32: =IF(Dados!$A$12="","",Dados!$A$12) -> 1 | B32: =IF(Dados!$B$12="","",Dados!$B$12) -> Vigilante Diurno 12x36 (exemplo) | C32: =IF(Dados!$C$12="","",Dados!$C$12) -> 2 | D32: =IF(Dados!$D$12="","",Dados!$D$12) -> 5996.89 | E32: =IF(C32="","",C32*220) -> 440 | G32: =IF(C32="","",IF(C32>0,ROUNDDOWN(N(D32)/220,2),0)) -> 27.25 | H32: =IF(C32="","",IF(AND(C32>0,N(D32)>0),MAX(0,ROUNDDOWN((C32*N(D32)-G32*N(F32))/30*$F$75*$F$71,2)),0)) -> 11993.78 | I32: =IF(C32="","",ROUNDDOWN(C32*N(D32),2)) -> 11993.78
A33: =IF(Dados!$A$13="","",Dados!$A$13) | B33: =IF(Dados!$B$13="","",Dados!$B$13) | C33: =IF(Dados!$C$13="","",Dados!$C$13) | D33: =IF(Dados!$D$13="","",Dados!$D$13) | E33: =IF(C33="","",C33*220) | G33: =IF(C33="","",IF(C33>0,ROUNDDOWN(N(D33)/220,2),0)) | H33: =IF(C33="","",IF(AND(C33>0,N(D33)>0),MAX(0,ROUNDDOWN((C33*N(D33)-G33*N(F33))/30*$F$75*$F$71,2)),0)) | I33: =IF(C33="","",ROUNDDOWN(C33*N(D33),2))
A34: =IF(Dados!$A$14="","",Dados!$A$14) | B34: =IF(Dados!$B$14="","",Dados!$B$14) | C34: =IF(Dados!$C$14="","",Dados!$C$14) | D34: =IF(Dados!$D$14="","",Dados!$D$14) | E34: =IF(C34="","",C34*220) | G34: =IF(C34="","",IF(C34>0,ROUNDDOWN(N(D34)/220,2),0)) | H34: =IF(C34="","",IF(AND(C34>0,N(D34)>0),MAX(0,ROUNDDOWN((C34*N(D34)-G34*N(F34))/30*$F$75*$F$71,2)),0)) | I34: =IF(C34="","",ROUNDDOWN(C34*N(D34),2))
A35: =IF(Dados!$A$15="","",Dados!$A$15) | B35: =IF(Dados!$B$15="","",Dados!$B$15) | C35: =IF(Dados!$C$15="","",Dados!$C$15) | D35: =IF(Dados!$D$15="","",Dados!$D$15) | E35: =IF(C35="","",C35*220) | G35: =IF(C35="","",IF(C35>0,ROUNDDOWN(N(D35)/220,2),0)) | H35: =IF(C35="","",IF(AND(C35>0,N(D35)>0),MAX(0,ROUNDDOWN((C35*N(D35)-G35*N(F35))/30*$F$75*$F$71,2)),0)) | I35: =IF(C35="","",ROUNDDOWN(C35*N(D35),2))
A36: =IF(Dados!$A$16="","",Dados!$A$16) | B36: =IF(Dados!$B$16="","",Dados!$B$16) | C36: =IF(Dados!$C$16="","",Dados!$C$16) | D36: =IF(Dados!$D$16="","",Dados!$D$16) | E36: =IF(C36="","",C36*220) | G36: =IF(C36="","",IF(C36>0,ROUNDDOWN(N(D36)/220,2),0)) | H36: =IF(C36="","",IF(AND(C36>0,N(D36)>0),MAX(0,ROUNDDOWN((C36*N(D36)-G36*N(F36))/30*$F$75*$F$71,2)),0)) | I36: =IF(C36="","",ROUNDDOWN(C36*N(D36),2))
A37: =IF(Dados!$A$17="","",Dados!$A$17) | B37: =IF(Dados!$B$17="","",Dados!$B$17) | C37: =IF(Dados!$C$17="","",Dados!$C$17) | D37: =IF(Dados!$D$17="","",Dados!$D$17) | E37: =IF(C37="","",C37*220) | G37: =IF(C37="","",IF(C37>0,ROUNDDOWN(N(D37)/220,2),0)) | H37: =IF(C37="","",IF(AND(C37>0,N(D37)>0),MAX(0,ROUNDDOWN((C37*N(D37)-G37*N(F37))/30*$F$75*$F$71,2)),0)) | I37: =IF(C37="","",ROUNDDOWN(C37*N(D37),2))
A38: =IF(Dados!$A$18="","",Dados!$A$18) | B38: =IF(Dados!$B$18="","",Dados!$B$18) | C38: =IF(Dados!$C$18="","",Dados!$C$18) | D38: =IF(Dados!$D$18="","",Dados!$D$18) | E38: =IF(C38="","",C38*220) | G38: =IF(C38="","",IF(C38>0,ROUNDDOWN(N(D38)/220,2),0)) | H38: =IF(C38="","",IF(AND(C38>0,N(D38)>0),MAX(0,ROUNDDOWN((C38*N(D38)-G38*N(F38))/30*$F$75*$F$71,2)),0)) | I38: =IF(C38="","",ROUNDDOWN(C38*N(D38),2))
A39: =IF(Dados!$A$19="","",Dados!$A$19) | B39: =IF(Dados!$B$19="","",Dados!$B$19) | C39: =IF(Dados!$C$19="","",Dados!$C$19) | D39: =IF(Dados!$D$19="","",Dados!$D$19) | E39: =IF(C39="","",C39*220) | G39: =IF(C39="","",IF(C39>0,ROUNDDOWN(N(D39)/220,2),0)) | H39: =IF(C39="","",IF(AND(C39>0,N(D39)>0),MAX(0,ROUNDDOWN((C39*N(D39)-G39*N(F39))/30*$F$75*$F$71,2)),0)) | I39: =IF(C39="","",ROUNDDOWN(C39*N(D39),2))
A40: =IF(Dados!$A$20="","",Dados!$A$20) | B40: =IF(Dados!$B$20="","",Dados!$B$20) | C40: =IF(Dados!$C$20="","",Dados!$C$20) | D40: =IF(Dados!$D$20="","",Dados!$D$20) | E40: =IF(C40="","",C40*220) | G40: =IF(C40="","",IF(C40>0,ROUNDDOWN(N(D40)/220,2),0)) | H40: =IF(C40="","",IF(AND(C40>0,N(D40)>0),MAX(0,ROUNDDOWN((C40*N(D40)-G40*N(F40))/30*$F$75*$F$71,2)),0)) | I40: =IF(C40="","",ROUNDDOWN(C40*N(D40),2))
A41: =IF(Dados!$A$21="","",Dados!$A$21) | B41: =IF(Dados!$B$21="","",Dados!$B$21) | C41: =IF(Dados!$C$21="","",Dados!$C$21) | D41: =IF(Dados!$D$21="","",Dados!$D$21) | E41: =IF(C41="","",C41*220) | G41: =IF(C41="","",IF(C41>0,ROUNDDOWN(N(D41)/220,2),0)) | H41: =IF(C41="","",IF(AND(C41>0,N(D41)>0),MAX(0,ROUNDDOWN((C41*N(D41)-G41*N(F41))/30*$F$75*$F$71,2)),0)) | I41: =IF(C41="","",ROUNDDOWN(C41*N(D41),2))
A42: =IF(Dados!$A$22="","",Dados!$A$22) | B42: =IF(Dados!$B$22="","",Dados!$B$22) | C42: =IF(Dados!$C$22="","",Dados!$C$22) | D42: =IF(Dados!$D$22="","",Dados!$D$22) | E42: =IF(C42="","",C42*220) | G42: =IF(C42="","",IF(C42>0,ROUNDDOWN(N(D42)/220,2),0)) | H42: =IF(C42="","",IF(AND(C42>0,N(D42)>0),MAX(0,ROUNDDOWN((C42*N(D42)-G42*N(F42))/30*$F$75*$F$71,2)),0)) | I42: =IF(C42="","",ROUNDDOWN(C42*N(D42),2))
A43: =IF(Dados!$A$23="","",Dados!$A$23) | B43: =IF(Dados!$B$23="","",Dados!$B$23) | C43: =IF(Dados!$C$23="","",Dados!$C$23) | D43: =IF(Dados!$D$23="","",Dados!$D$23) | E43: =IF(C43="","",C43*220) | G43: =IF(C43="","",IF(C43>0,ROUNDDOWN(N(D43)/220,2),0)) | H43: =IF(C43="","",IF(AND(C43>0,N(D43)>0),MAX(0,ROUNDDOWN((C43*N(D43)-G43*N(F43))/30*$F$75*$F$71,2)),0)) | I43: =IF(C43="","",ROUNDDOWN(C43*N(D43),2))
A44: =IF(Dados!$A$24="","",Dados!$A$24) | B44: =IF(Dados!$B$24="","",Dados!$B$24) | C44: =IF(Dados!$C$24="","",Dados!$C$24) | D44: =IF(Dados!$D$24="","",Dados!$D$24) | E44: =IF(C44="","",C44*220) | G44: =IF(C44="","",IF(C44>0,ROUNDDOWN(N(D44)/220,2),0)) | H44: =IF(C44="","",IF(AND(C44>0,N(D44)>0),MAX(0,ROUNDDOWN((C44*N(D44)-G44*N(F44))/30*$F$75*$F$71,2)),0)) | I44: =IF(C44="","",ROUNDDOWN(C44*N(D44),2))
A45: =IF(Dados!$A$25="","",Dados!$A$25) | B45: =IF(Dados!$B$25="","",Dados!$B$25) | C45: =IF(Dados!$C$25="","",Dados!$C$25) | D45: =IF(Dados!$D$25="","",Dados!$D$25) | E45: =IF(C45="","",C45*220) | G45: =IF(C45="","",IF(C45>0,ROUNDDOWN(N(D45)/220,2),0)) | H45: =IF(C45="","",IF(AND(C45>0,N(D45)>0),MAX(0,ROUNDDOWN((C45*N(D45)-G45*N(F45))/30*$F$75*$F$71,2)),0)) | I45: =IF(C45="","",ROUNDDOWN(C45*N(D45),2))
A46: =IF(Dados!$A$26="","",Dados!$A$26) | B46: =IF(Dados!$B$26="","",Dados!$B$26) | C46: =IF(Dados!$C$26="","",Dados!$C$26) | D46: =IF(Dados!$D$26="","",Dados!$D$26) | E46: =IF(C46="","",C46*220) | G46: =IF(C46="","",IF(C46>0,ROUNDDOWN(N(D46)/220,2),0)) | H46: =IF(C46="","",IF(AND(C46>0,N(D46)>0),MAX(0,ROUNDDOWN((C46*N(D46)-G46*N(F46))/30*$F$75*$F$71,2)),0)) | I46: =IF(C46="","",ROUNDDOWN(C46*N(D46),2))
A47: TOTAIS | F47: =SUM(F32:F46) -> 0 | H47: =SUM(H32:H46) -> 11993.78 | I47: =SUM(I32:I46) -> 11993.78
A49: 📋 INSTRUMENTO DE COBRANÇA
A50: Item | B50: Posto | F50: Qtde Faturada | H50: Valor Unit. Faturado (R$)
A51: =IF(A32="","",A32) -> 1 | B51: =IF(B32="","",B32) -> Vigilante Diurno 12x36 (exemplo) | F51: =IF(C32="","",C32) -> 2 | H51: =IF(C32="","",IF(C32>0,ROUNDDOWN(H32/C32,2),0)) -> 5996.89
A52: =IF(A33="","",A33) | B52: =IF(B33="","",B33) | F52: =IF(C33="","",C33) | H52: =IF(C33="","",IF(C33>0,ROUNDDOWN(H33/C33,2),0))
A53: =IF(A34="","",A34) | B53: =IF(B34="","",B34) | F53: =IF(C34="","",C34) | H53: =IF(C34="","",IF(C34>0,ROUNDDOWN(H34/C34,2),0))
A54: =IF(A35="","",A35) | B54: =IF(B35="","",B35) | F54: =IF(C35="","",C35) | H54: =IF(C35="","",IF(C35>0,ROUNDDOWN(H35/C35,2),0))
A55: =IF(A36="","",A36) | B55: =IF(B36="","",B36) | F55: =IF(C36="","",C36) | H55: =IF(C36="","",IF(C36>0,ROUNDDOWN(H36/C36,2),0))
A56: =IF(A37="","",A37) | B56: =IF(B37="","",B37) | F56: =IF(C37="","",C37) | H56: =IF(C37="","",IF(C37>0,ROUNDDOWN(H37/C37,2),0))
A57: =IF(A38="","",A38) | B57: =IF(B38="","",B38) | F57: =IF(C38="","",C38) | H57: =IF(C38="","",IF(C38>0,ROUNDDOWN(H38/C38,2),0))
A58: =IF(A39="","",A39) | B58: =IF(B39="","",B39) | F58: =IF(C39="","",C39) | H58: =IF(C39="","",IF(C39>0,ROUNDDOWN(H39/C39,2),0))
A59: =IF(A40="","",A40) | B59: =IF(B40="","",B40) | F59: =IF(C40="","",C40) | H59: =IF(C40="","",IF(C40>0,ROUNDDOWN(H40/C40,2),0))
A60: =IF(A41="","",A41) | B60: =IF(B41="","",B41) | F60: =IF(C41="","",C41) | H60: =IF(C41="","",IF(C41>0,ROUNDDOWN(H41/C41,2),0))
A61: =IF(A42="","",A42) | B61: =IF(B42="","",B42) | F61: =IF(C42="","",C42) | H61: =IF(C42="","",IF(C42>0,ROUNDDOWN(H42/C42,2),0))
A62: =IF(A43="","",A43) | B62: =IF(B43="","",B43) | F62: =IF(C43="","",C43) | H62: =IF(C43="","",IF(C43>0,ROUNDDOWN(H43/C43,2),0))
... A65: =IF(A46="","",A46) | B65: =IF(B46="","",B46) | F65: =IF(C46="","",C46) | H65: =IF(C46="","",IF(C46>0,ROUNDDOWN(H46/C46,2),0))
A67: RESUMO FINANCEIRO
A68: Contratado Mensal – Total (R$) (Σ Qtde × Valor Unitário de todos os postos) | F68: =I47 -> 11993.78
A69: Nota Final Apurada | F69: =D28 -> 9
A70: Nota Atribuída pelo Avaliador (Conceito) | F70: =F28 -> A
A71: % do Faturamento a ser Liberado | F71: =INDEX(Dados!$C$50:$C$55,MATCH(D28,Dados!$A$50:$A$55,1)) -> 1
A72: Valor Glosado por QUALIDADE (R$) | F72: =ROUNDDOWN(I47-I47*$F$71,2) -> 0
A73: Número de Dias do Mês (calculado) | F73: =IF(ISNUMBER(B7),DAY(EOMONTH(B7,0)),30) -> 30
A74: Número de Dias Trabalhados no Mês | F74: =IF(ISNUMBER(B7),DAY(EOMONTH(B7,0)),30) -> 30 | H74: Campo de preenchimento: altere apenas em mês parcial (início/fim de contrato)
A75: Dias para Cálculo (mês cheio = 30 avos) | F75: =IF(N(F74)>=$F$73,30,MAX(0,N(F74))) -> 30
A76: Soma dos Itens após Descontos (R$) | F76: =H47 -> 11993.78
A77: VALOR APROVADO PARA PAGAMENTO (R$) (Σ Itens após Descontos + Total dos Reembolsos de Creche) | F77: =MAX(0,ROUNDDOWN(H47+F83,2)) -> 11993.78
A79: 🏫 REEMBOLSO DE CRECHE
A80: Valor Reembolso Creche Retido (R$) | F80: =Dados!$D30 -> 0 | H80: Campo de preenchimento
A81: Reembolsos Aprovados (quantidade) | H81: Campo de preenchimento
A82: Reembolso por dependente (R$) | F82: =Dados!$D31 -> 0 | H82: Campo de preenchimento
A83: Valor Total dos Reembolsos (R$) (Aprovados × Reembolso por dependente) | F83: =ROUNDDOWN(N(F81)*N(F82),2) -> 0
A84: Saldo de Reembolso (R$) (acumulado: saldo da aba anterior + Retido – Total) | F84: =ROUNDDOWN(N(F80)-N(F83),2) -> 0
A85: =IF(F84<0,"⚠ ATENÇÃO: Saldo negativo — será necessário ADITIVAR O CONTRATO PARA SUPORTAR A DESPESA!","")
A87: FAIXA DE AJUSTE DE PAGAMENTO
A88: Conceito | D88: % do Faturamento a ser Pago | G88: Nota Média Mensal Apurada
A89: =Dados!$B$55 -> A | D89: =Dados!$C$55 -> 1 | G89: =Dados!$D$55 -> Entre 9,00 e 8,10
A90: =Dados!$B$54 -> B | D90: =Dados!$C$54 -> 0.95 | G90: =Dados!$D$54 -> Entre 8,09 e 7,65
A91: =Dados!$B$53 -> C | D91: =Dados!$C$53 -> 0.9 | G91: =Dados!$D$53 -> Entre 7,64 e 6,75
A92: =Dados!$B$52 -> D | D92: =Dados!$C$52 -> 0.85 | G92: =Dados!$D$52 -> Entre 6,74 e 5,85
A93: =Dados!$B$51 -> E | D93: =Dados!$C$51 -> 0.8 | G93: =Dados!$D$51 -> Entre 5,84 e 5,40
A94: =Dados!$B$50 -> F | D94: =Dados!$C$50 -> 0.75 | G94: =Dados!$D$50 -> Abaixo de 5,40
A96: APROVAÇÃO E ASSINATURAS
A97: Fiscal Operacional | D97: Fiscal Administrativo (¹) | G97: Representante da Contratada | I97: Data da Aprovação
A100: Nome completo / Matrícula | D100: Nome completo / Matrícula | G100: Nome completo / Cargo | I100: dd/mm/aaaa
A102: 📝 JUSTIFICATIVAS (obrigatório para notas 0 e 1)
A107: =IF(COUNTIF(C13:C27,0)+COUNTIF(C13:C27,1)>0,"⚠ Existem notas 0 ou 1 nesta aba — a justificativa acima é OBRIGATÓRIA. Informe critério, nota e fundamentação.","Para cada nota 0 ou 1 informe: critério, nota atribuída e fundamentação.") -> Para cada nota 0 ou 1 informe: critério, nota atribuída e fundamentação.

Sheet P02
A1: UFRJ – PRÓ-REITORIA DE GESTÃO E GOVERNANÇA – PR6 | IMR
A2: INSTRUMENTO DE MEDIÇÃO DE RESULTADO
A3: =IF(Dados!$B$6="","",Dados!$B$6) -> Atualizado conforme Valor Unitário Contratado inicial
A5: CONTRATO Nº: | B5: =IF(Dados!$B$2="","",Dados!$B$2) -> 04/24 | E5: UNIDADE: | G5: =IF(Dados!$B$3="","",Dados!$B$3) -> CBAE
A6: CONTRATADA: | B6: =IF(Dados!$B$4="","",Dados!$B$4) -> Angels | E6: FISCAL OPERACIONAL: | G6: =IF(Dados!$B$5="","",Dados!$B$5)
A7: AVALIAÇÃO REFERENTE AO PERÍODO: | B7: =IF(Dados!$B$7="","(informe o período inicial na aba Dados)",EDATE(Dados!$B$7,1)) -> (informe o período inicial na aba Dados) | E7: PERÍODO (ABA) Nº: | G7: 2 de 60
A8: ⚠ Para notas 0 e 1 o campo JUSTIFICATIVAS (fim da aba) é de preenchimento obrigatório. | Contrato, Unidade, Contratada e Postos são compartilhados por todas as abas (aba Dados).
A10: AVALIAÇÃO DE DESEMPENHO
A11: Critério de Avaliação | B11: PESO (a) | C11: NOTA (b) (0, 1 ou 3) | D11: SUBTOTAL (c = a × b) | E11: Status | F11: Aviso de Justificativa
A12: ▶ GRUPO 1 – DESEMPENHO PROFISSIONAL
A13: =Dados!$B$36 -> Cumprimento das Atividades | B13: =Dados!$C$36 -> 0.4 | C13: 3 | D13: =B13*C13 -> 1.2 | E13: =IF(OR(C13=0,C13=1,C13=3),"✓ Ok","⛔ Inválida") -> ✓ Ok | F13: =IF(OR(C13=0,C13=1),"⚠ Favor inserir justificativa da nota "&C13&" no campo JUSTIFICATIVAS","")
A14: =Dados!$B$37 -> Qualificação / Atendimento ao Público / Postura | B14: =Dados!$C$37 -> 0.35 | C14: 3 | D14: =B14*C14 -> 1.05 | E14: =IF(OR(C14=0,C14=1,C14=3),"✓ Ok","⛔ Inválida") -> ✓ Ok | F14: =IF(OR(C14=0,C14=1),"⚠ Favor inserir justificativa da nota "&C14&" no campo JUSTIFICATIVAS","")
A15: =Dados!$B$38 -> Uniformes e Identificação | B15: =Dados!$C$38 -> 0.25 | C15: 3 | D15: =B15*C15 -> 0.75 | E15: =IF(OR(C15=0,C15=1,C15=3),"✓ Ok","⛔ Inválida") -> ✓ Ok | F15: =IF(OR(C15=0,C15=1),"⚠ Favor inserir justificativa da nota "&C15&" no campo JUSTIFICATIVAS","")
A16: TOTAL GRUPO 1 | B16: =SUM(B13:B15) -> 1 | D16: =SUM(D13:D15) -> 3
A17: ▶ GRUPO 2 – DESEMPENHO DAS ATIVIDADES
A18: =Dados!$B$39 -> Especificação Técnica dos Serviços | B18: =Dados!$C$39 -> 0.4 | C18: 3 | D18: =B18*C18 -> 1.2 | E18: =IF(OR(C18=0,C18=1,C18=3),"✓ Ok","⛔ Inválida") -> ✓ Ok | F18: =IF(OR(C18=0,C18=1),"⚠ Favor inserir justificativa da nota "&C18&" no campo JUSTIFICATIVAS","")
A19: =Dados!$B$40 -> Equipamentos e Acessórios | B19: =Dados!$C$40 -> 0.2 | C19: 3 | D19: =B19*C19 -> 0.6 | E19: =IF(OR(C19=0,C19=1,C19=3),"✓ Ok","⛔ Inválida") -> ✓ Ok | F19: =IF(OR(C19=0,C19=1),"⚠ Favor inserir justificativa da nota "&C19&" no campo JUSTIFICATIVAS","")
A20: =Dados!$B$41 -> Atendimento às Ocorrências | B20: =Dados!$C$41 -> 0.4 | C20: 3 | D20: =B20*C20 -> 1.2 | E20: =IF(OR(C20=0,C20=1,C20=3),"✓ Ok","⛔ Inválida") -> ✓ Ok | F20: =IF(OR(C20=0,C20=1),"⚠ Favor inserir justificativa da nota "&C20&" no campo JUSTIFICATIVAS","")
A21: TOTAL GRUPO 2 | B21: =SUM(B18:B20) -> 1 | D21: =SUM(D18:D20) -> 3
A22: ▶ GRUPO 3 – GERENCIAMENTO
A23: =Dados!$B$42 -> Periodicidade da Supervisão | B23: =Dados!$C$42 -> 0.2 | C23: 3 | D23: =B23*C23 -> 0.6 | E23: =IF(OR(C23=0,C23=1,C23=3),"✓ Ok","⛔ Inválida") -> ✓ Ok | F23: =IF(OR(C23=0,C23=1),"⚠ Favor inserir justificativa da nota "&C23&" no campo JUSTIFICATIVAS","")
A24: =Dados!$B$43 -> Gerenciamento das Atividades Operacionais | B24: =Dados!$C$43 -> 0.3 | C24: 3 | D24: =B24*C24 -> 0.9 | E24: =IF(OR(C24=0,C24=1,C24=3),"✓ Ok","⛔ Inválida") -> ✓ Ok | F24: =IF(OR(C24=0,C24=1),"⚠ Favor inserir justificativa da nota "&C24&" no campo JUSTIFICATIVAS","")
A25: =Dados!$B$44 -> Atendimento às Solicitações | B25: =Dados!$C$44 -> 0.25 | C25: 3 | D25: =B25*C25 -> 0.75 | E25: =IF(OR(C25=0,C25=1,C25=3),"✓ Ok","⛔ Inválida") -> ✓ Ok | F25: =IF(OR(C25=0,C25=1),"⚠ Favor inserir justificativa da nota "&C25&" no campo JUSTIFICATIVAS","")
A26: =Dados!$B$45 -> Salários, Benefícios e Obrigações Trabalhistas (¹ Fiscal Adm.) | B26: =Dados!$C$45 -> 0.25 | C26: 3 | D26: =B26*C26 -> 0.75 | E26: =IF(OR(C26=0,C26=1,C26=3),"✓ Ok","⛔ Inválida") -> ✓ Ok | F26: =IF(OR(C26=0,C26=1),"⚠ Favor inserir justificativa da nota "&C26&" no campo JUSTIFICATIVAS","")
A27: TOTAL GRUPO 3 | B27: =SUM(B23:B26) -> 1 | D27: =SUM(D23:D26) -> 3
A28: NOTA FINAL (somatório dos Grupos 1, 2 e 3) | D28: =D16+D21+D27 -> 9 | E28: Conceito: | F28: =INDEX(Dados!$B$50:$B$55,MATCH(D28,Dados!$A$50:$A$55,1)) -> A | G28: (¹) Grupo 3 – Salários/Benefícios/Obrigações Trabalhistas: preenchido pelo Fiscal Administrativo
A30: POSTOS DE TRABALHO
A31: Item | B31: POSTO | C31: Qtde Contratada | D31: Valor Unit. Contratado (R$) | E31: Horas Contratadas | F31: Sem Cobertura (h) | G31: Valor da Hora Contratada (R$) | H31: Valor do Item após Descontos (R$) | I31: Mensal Contratado (R$)
A32: =IF(Dados!$A$12="","",Dados!$A$12) -> 1 | B32: =IF(Dados!$B$12="","",Dados!$B$12) -> Vigilante Diurno 12x36 (exemplo) | C32: =IF(Dados!$C$12="","",Dados!$C$12) -> 2 | D32: =IF(Dados!$D$12="","",Dados!$D$12) -> 5996.89 | E32: =IF(C32="","",C32*220) -> 440 | G32: =IF(C32="","",IF(C32>0,ROUNDDOWN(N(D32)/220,2),0)) -> 27.25 | H32: =IF(C32="","",IF(AND(C32>0,N(D32)>0),MAX(0,ROUNDDOWN((C32*N(D32)-G32*N(F32))/30*$F$75*$F$71,2)),0)) -> 11993.78 | I32: =IF(C32="","",ROUNDDOWN(C32*N(D32),2)) -> 11993.78
A33: =IF(Dados!$A$13="","",Dados!$A$13) | B33: =IF(Dados!$B$13="","",Dados!$B$13) | C33: =IF(Dados!$C$13="","",Dados!$C$13) | D33: =IF(Dados!$D$13="","",Dados!$D$13) | E33: =IF(C33="","",C33*220) | G33: =IF(C33="","",IF(C33>0,ROUNDDOWN(N(D33)/220,2),0)) | H33: =IF(C33="","",IF(AND(C33>0,N(D33)>0),MAX(0,ROUNDDOWN((C33*N(D33)-G33*N(F33))/30*$F$75*$F$71,2)),0)) | I33: =IF(C33="","",ROUNDDOWN(C33*N(D33),2))
A34: =IF(Dados!$A$14="","",Dados!$A$14) | B34: =IF(Dados!$B$14="","",Dados!$B$14) | C34: =IF(Dados!$C$14="","",Dados!$C$14) | D34: =IF(Dados!$D$14="","",Dados!$D$14) | E34: =IF(C34="","",C34*220) | G34: =IF(C34="","",IF(C34>0,ROUNDDOWN(N(D34)/220,2),0)) | H34: =IF(C34="","",IF(AND(C34>0,N(D34)>0),MAX(0,ROUNDDOWN((C34*N(D34)-G34*N(F34))/30*$F$75*$F$71,2)),0)) | I34: =IF(C34="","",ROUNDDOWN(C34*N(D34),2))
A35: =IF(Dados!$A$15="","",Dados!$A$15) | B35: =IF(Dados!$B$15="","",Dados!$B$15) | C35: =IF(Dados!$C$15="","",Dados!$C$15) | D35: =IF(Dados!$D$15="","",Dados!$D$15) | E35: =IF(C35="","",C35*220) | G35: =IF(C35="","",IF(C35>0,ROUNDDOWN(N(D35)/220,2),0)) | H35: =IF(C35="","",IF(AND(C35>0,N(D35)>0),MAX(0,ROUNDDOWN((C35*N(D35)-G35*N(F35))/30*$F$75*$F$71,2)),0)) | I35: =IF(C35="","",ROUNDDOWN(C35*N(D35),2))
A36: =IF(Dados!$A$16="","",Dados!$A$16) | B36: =IF(Dados!$B$16="","",Dados!$B$16) | C36: =IF(Dados!$C$16="","",Dados!$C$16) | D36: =IF(Dados!$D$16="","",Dados!$D$16) | E36: =IF(C36="","",C36*220) | G36: =IF(C36="","",IF(C36>0,ROUNDDOWN(N(D36)/220,2),0)) | H36: =IF(C36="","",IF(AND(C36>0,N(D36)>0),MAX(0,ROUNDDOWN((C36*N(D36)-G36*N(F36))/30*$F$75*$F$71,2)),0)) | I36: =IF(C36="","",ROUNDDOWN(C36*N(D36),2))
A37: =IF(Dados!$A$17="","",Dados!$A$17) | B37: =IF(Dados!$B$17="","",Dados!$B$17) | C37: =IF(Dados!$C$17="","",Dados!$C$17) | D37: =IF(Dados!$D$17="","",Dados!$D$17) | E37: =IF(C37="","",C37*220) | G37: =IF(C37="","",IF(C37>0,ROUNDDOWN(N(D37)/220,2),0)) | H37: =IF(C37="","",IF(AND(C37>0,N(D37)>0),MAX(0,ROUNDDOWN((C37*N(D37)-G37*N(F37))/30*$F$75*$F$71,2)),0)) | I37: =IF(C37="","",ROUNDDOWN(C37*N(D37),2))
A38: =IF(Dados!$A$18="","",Dados!$A$18) | B38: =IF(Dados!$B$18="","",Dados!$B$18) | C38: =IF(Dados!$C$18="","",Dados!$C$18) | D38: =IF(Dados!$D$18="","",Dados!$D$18) | E38: =IF(C38="","",C38*220) | G38: =IF(C38="","",IF(C38>0,ROUNDDOWN(N(D38)/220,2),0)) | H38: =IF(C38="","",IF(AND(C38>0,N(D38)>0),MAX(0,ROUNDDOWN((C38*N(D38)-G38*N(F38))/30*$F$75*$F$71,2)),0)) | I38: =IF(C38="","",ROUNDDOWN(C38*N(D38),2))
A39: =IF(Dados!$A$19="","",Dados!$A$19) | B39: =IF(Dados!$B$19="","",Dados!$B$19) | C39: =IF(Dados!$C$19="","",Dados!$C$19) | D39: =IF(Dados!$D$19="","",Dados!$D$19) | E39: =IF(C39="","",C39*220) | G39: =IF(C39="","",IF(C39>0,ROUNDDOWN(N(D39)/220,2),0)) | H39: =IF(C39="","",IF(AND(C39>0,N(D39)>0),MAX(0,ROUNDDOWN((C39*N(D39)-G39*N(F39))/30*$F$75*$F$71,2)),0)) | I39: =IF(C39="","",ROUNDDOWN(C39*N(D39),2))
A40: =IF(Dados!$A$20="","",Dados!$A$20) | B40: =IF(Dados!$B$20="","",Dados!$B$20) | C40: =IF(Dados!$C$20="","",Dados!$C$20) | D40: =IF(Dados!$D$20="","",Dados!$D$20) | E40: =IF(C40="","",C40*220) | G40: =IF(C40="","",IF(C40>0,ROUNDDOWN(N(D40)/220,2),0)) | H40: =IF(C40="","",IF(AND(C40>0,N(D40)>0),MAX(0,ROUNDDOWN((C40*N(D40)-G40*N(F40))/30*$F$75*$F$71,2)),0)) | I40: =IF(C40="","",ROUNDDOWN(C40*N(D40),2))
A41: =IF(Dados!$A$21="","",Dados!$A$21) | B41: =IF(Dados!$B$21="","",Dados!$B$21) | C41: =IF(Dados!$C$21="","",Dados!$C$21) | D41: =IF(Dados!$D$21="","",Dados!$D$21) | E41: =IF(C41="","",C41*220) | G41: =IF(C41="","",IF(C41>0,ROUNDDOWN(N(D41)/220,2),0)) | H41: =IF(C41="","",IF(AND(C41>0,N(D41)>0),MAX(0,ROUNDDOWN((C41*N(D41)-G41*N(F41))/30*$F$75*$F$71,2)),0)) | I41: =IF(C41="","",ROUNDDOWN(C41*N(D41),2))
A42: =IF(Dados!$A$22="","",Dados!$A$22) | B42: =IF(Dados!$B$22="","",Dados!$B$22) | C42: =IF(Dados!$C$22="","",Dados!$C$22) | D42: =IF(Dados!$D$22="","",Dados!$D$22) | E42: =IF(C42="","",C42*220) | G42: =IF(C42="","",IF(C42>0,ROUNDDOWN(N(D42)/220,2),0)) | H42: =IF(C42="","",IF(AND(C42>0,N(D42)>0),MAX(0,ROUNDDOWN((C42*N(D42)-G42*N(F42))/30*$F$75*$F$71,2)),0)) | I42: =IF(C42="","",ROUNDDOWN(C42*N(D42),2))
A43: =IF(Dados!$A$23="","",Dados!$A$23) | B43: =IF(Dados!$B$23="","",Dados!$B$23) | C43: =IF(Dados!$C$23="","",Dados!$C$23) | D43: =IF(Dados!$D$23="","",Dados!$D$23) | E43: =IF(C43="","",C43*220) | G43: =IF(C43="","",IF(C43>0,ROUNDDOWN(N(D43)/220,2),0)) | H43: =IF(C43="","",IF(AND(C43>0,N(D43)>0),MAX(0,ROUNDDOWN((C43*N(D43)-G43*N(F43))/30*$F$75*$F$71,2)),0)) | I43: =IF(C43="","",ROUNDDOWN(C43*N(D43),2))
A44: =IF(Dados!$A$24="","",Dados!$A$24) | B44: =IF(Dados!$B$24="","",Dados!$B$24) | C44: =IF(Dados!$C$24="","",Dados!$C$24) | D44: =IF(Dados!$D$24="","",Dados!$D$24) | E44: =IF(C44="","",C44*220) | G44: =IF(C44="","",IF(C44>0,ROUNDDOWN(N(D44)/220,2),0)) | H44: =IF(C44="","",IF(AND(C44>0,N(D44)>0),MAX(0,ROUNDDOWN((C44*N(D44)-G44*N(F44))/30*$F$75*$F$71,2)),0)) | I44: =IF(C44="","",ROUNDDOWN(C44*N(D44),2))
A45: =IF(Dados!$A$25="","",Dados!$A$25) | B45: =IF(Dados!$B$25="","",Dados!$B$25) | C45: =IF(Dados!$C$25="","",Dados!$C$25) | D45: =IF(Dados!$D$25="","",Dados!$D$25) | E45: =IF(C45="","",C45*220) | G45: =IF(C45="","",IF(C45>0,ROUNDDOWN(N(D45)/220,2),0)) | H45: =IF(C45="","",IF(AND(C45>0,N(D45)>0),MAX(0,ROUNDDOWN((C45*N(D45)-G45*N(F45))/30*$F$75*$F$71,2)),0)) | I45: =IF(C45="","",ROUNDDOWN(C45*N(D45),2))
A46: =IF(Dados!$A$26="","",Dados!$A$26) | B46: =IF(Dados!$B$26="","",Dados!$B$26) | C46: =IF(Dados!$C$26="","",Dados!$C$26) | D46: =IF(Dados!$D$26="","",Dados!$D$26) | E46: =IF(C46="","",C46*220) | G46: =IF(C46="","",IF(C46>0,ROUNDDOWN(N(D46)/220,2),0)) | H46: =IF(C46="","",IF(AND(C46>0,N(D46)>0),MAX(0,ROUNDDOWN((C46*N(D46)-G46*N(F46))/30*$F$75*$F$71,2)),0)) | I46: =IF(C46="","",ROUNDDOWN(C46*N(D46),2))
A47: TOTAIS | F47: =SUM(F32:F46) -> 0 | H47: =SUM(H32:H46) -> 11993.78 | I47: =SUM(I32:I46) -> 11993.78
A49: 📋 INSTRUMENTO DE COBRANÇA
A50: Item | B50: Posto | F50: Qtde Faturada | H50: Valor Unit. Faturado (R$)
A51: =IF(A32="","",A32) -> 1 | B51: =IF(B32="","",B32) -> Vigilante Diurno 12x36 (exemplo) | F51: =IF(C32="","",C32) -> 2 | H51: =IF(C32="","",IF(C32>0,ROUNDDOWN(H32/C32,2),0)) -> 5996.89
A52: =IF(A33="","",A33) | B52: =IF(B33="","",B33) | F52: =IF(C33="","",C33) | H52: =IF(C33="","",IF(C33>0,ROUNDDOWN(H33/C33,2),0))
A53: =IF(A34="","",A34) | B53: =IF(B34="","",B34) | F53: =IF(C34="","",C34) | H53: =IF(C34="","",IF(C34>0,ROUNDDOWN(H34/C34,2),0))
A54: =IF(A35="","",A35) | B54: =IF(B35="","",B35) | F54: =IF(C35="","",C35) | H54: =IF(C35="","",IF(C35>0,ROUNDDOWN(H35/C35,2),0))
A55: =IF(A36="","",A36) | B55: =IF(B36="","",B36) | F55: =IF(C36="","",C36) | H55: =IF(C36="","",IF(C36>0,ROUNDDOWN(H36/C36,2),0))
A56: =IF(A37="","",A37) | B56: =IF(B37="","",B37) | F56: =IF(C37="","",C37) | H56: =IF(C37="","",IF(C37>0,ROUNDDOWN(H37/C37,2),0))
A57: =IF(A38="","",A38) | B57: =IF(B38="","",B38) | F57: =IF(C38="","",C38) | H57: =IF(C38="","",IF(C38>0,ROUNDDOWN(H38/C38,2),0))
A58: =IF(A39="","",A39) | B58: =IF(B39="","",B39) | F58: =IF(C39="","",C39) | H58: =IF(C39="","",IF(C39>0,ROUNDDOWN(H39/C39,2),0))
A59: =IF(A40="","",A40) | B59: =IF(B40="","",B40) | F59: =IF(C40="","",C40) | H59: =IF(C40="","",IF(C40>0,ROUNDDOWN(H40/C40,2),0))
A60: =IF(A41="","",A41) | B60: =IF(B41="","",B41) | F60: =IF(C41="","",C41) | H60: =IF(C41="","",IF(C41>0,ROUNDDOWN(H41/C41,2),0))
A61: =IF(A42="","",A42) | B61: =IF(B42="","",B42) | F61: =IF(C42="","",C42) | H61: =IF(C42="","",IF(C42>0,ROUNDDOWN(H42/C42,2),0))
A62: =IF(A43="","",A43) | B62: =IF(B43="","",B43) | F62: =IF(C43="","",C43) | H62: =IF(C43="","",IF(C43>0,ROUNDDOWN(H43/C43,2),0))
... A65: =IF(A46="","",A46) | B65: =IF(B46="","",B46) | F65: =IF(C46="","",C46) | H65: =IF(C46="","",IF(C46>0,ROUNDDOWN(H46/C46,2),0))
A67: RESUMO FINANCEIRO
A68: Contratado Mensal – Total (R$) (Σ Qtde × Valor Unitário de todos os postos) | F68: =I47 -> 11993.78
A69: Nota Final Apurada | F69: =D28 -> 9
A70: Nota Atribuída pelo Avaliador (Conceito) | F70: =F28 -> A
A71: % do Faturamento a ser Liberado | F71: =INDEX(Dados!$C$50:$C$55,MATCH(D28,Dados!$A$50:$A$55,1)) -> 1
A72: Valor Glosado por QUALIDADE (R$) | F72: =ROUNDDOWN(I47-I47*$F$71,2) -> 0
A73: Número de Dias do Mês (calculado) | F73: =IF(ISNUMBER(B7),DAY(EOMONTH(B7,0)),30) -> 30
A74: Número de Dias Trabalhados no Mês | F74: =IF(ISNUMBER(B7),DAY(EOMONTH(B7,0)),30) -> 30 | H74: Campo de preenchimento: altere apenas em mês parcial (início/fim de contrato)
A75: Dias para Cálculo (mês cheio = 30 avos) | F75: =IF(N(F74)>=$F$73,30,MAX(0,N(F74))) -> 30
A76: Soma dos Itens após Descontos (R$) | F76: =H47 -> 11993.78
A77: VALOR APROVADO PARA PAGAMENTO (R$) (Σ Itens após Descontos + Total dos Reembolsos de Creche) | F77: =MAX(0,ROUNDDOWN(H47+F83,2)) -> 11993.78
A79: 🏫 REEMBOLSO DE CRECHE
A80: Valor Reembolso Creche Retido (R$) | F80: =Dados!$D30 -> 0 | H80: Campo de preenchimento
A81: Reembolsos Aprovados (quantidade) | H81: Campo de preenchimento
A82: Reembolso por dependente (R$) | F82: =Dados!$D31 -> 0 | H82: Campo de preenchimento
A83: Valor Total dos Reembolsos (R$) (Aprovados × Reembolso por dependente) | F83: =ROUNDDOWN(N(F81)*N(F82),2) -> 0
A84: Saldo de Reembolso (R$) (acumulado: saldo da aba anterior + Retido – Total) | F84: =ROUNDDOWN(P01!F84+N(F80)-N(F83),2) -> 0
A85: =IF(F84<0,"⚠ ATENÇÃO: Saldo negativo — será necessário ADITIVAR O CONTRATO PARA SUPORTAR A DESPESA!","")
A87: FAIXA DE AJUSTE DE PAGAMENTO
A88: Conceito | D88: % do Faturamento a ser Pago | G88: Nota Média Mensal Apurada
A89: =Dados!$B$55 -> A | D89: =Dados!$C$55 -> 1 | G89: =Dados!$D$55 -> Entre 9,00 e 8,10
A90: =Dados!$B$54 -> B | D90: =Dados!$C$54 -> 0.95 | G90: =Dados!$D$54 -> Entre 8,09 e 7,65
A91: =Dados!$B$53 -> C | D91: =Dados!$C$53 -> 0.9 | G91: =Dados!$D$53 -> Entre 7,64 e 6,75
A92: =Dados!$B$52 -> D | D92: =Dados!$C$52 -> 0.85 | G92: =Dados!$D$52 -> Entre 6,74 e 5,85
A93: =Dados!$B$51 -> E | D93: =Dados!$C$51 -> 0.8 | G93: =Dados!$D$51 -> Entre 5,84 e 5,40
A94: =Dados!$B$50 -> F | D94: =Dados!$C$50 -> 0.75 | G94: =Dados!$D$50 -> Abaixo de 5,40
A96: APROVAÇÃO E ASSINATURAS
A97: Fiscal Operacional | D97: Fiscal Administrativo (¹) | G97: Representante da Contratada | I97: Data da Aprovação
A100: Nome completo / Matrícula | D100: Nome completo / Matrícula | G100: Nome completo / Cargo | I100: dd/mm/aaaa
A102: 📝 JUSTIFICATIVAS (obrigatório para notas 0 e 1)
A107: =IF(COUNTIF(C13:C27,0)+COUNTIF(C13:C27,1)>0,"⚠ Existem notas 0 ou 1 nesta aba — a justificativa acima é OBRIGATÓRIA. Informe critério, nota e fundamentação.","Para cada nota 0 ou 1 informe: critério, nota atribuída e fundamentação.") -> Para cada nota 0 ou 1 informe: critério, nota atribuída e fundamentação.

Sheet P03
A1: UFRJ – PRÓ-REITORIA DE GESTÃO E GOVERNANÇA – PR6 | IMR
A2: INSTRUMENTO DE MEDIÇÃO DE RESULTADO
A3: =IF(Dados!$B$6="","",Dados!$B$6) -> Atualizado conforme Valor Unitário Contratado inicial
A5: CONTRATO Nº: | B5: =IF(Dados!$B$2="","",Dados!$B$2) -> 04/24 | E5: UNIDADE: | G5: =IF(Dados!$B$3="","",Dados!$B$3) -> CBAE
A6: CONTRATADA: | B6: =IF(Dados!$B$4="","",Dados!$B$4) -> Angels | E6: FISCAL OPERACIONAL: | G6: =IF(Dados!$B$5="","",Dados!$B$5)
A7: AVALIAÇÃO REFERENTE AO PERÍODO: | B7: =IF(Dados!$B$7="","(informe o período inicial na aba Dados)",EDATE(Dados!$B$7,2)) -> (informe o período inicial na aba Dados) | E7: PERÍODO (ABA) Nº: | G7: 3 de 60
A8: ⚠ Para notas 0 e 1 o campo JUSTIFICATIVAS (fim da aba) é de preenchimento obrigatório. | Contrato, Unidade, Contratada e Postos são compartilhados por todas as abas (aba Dados).
A10: AVALIAÇÃO DE DESEMPENHO
A11: Critério de Avaliação | B11: PESO (a) | C11: NOTA (b) (0, 1 ou 3) | D11: SUBTOTAL (c = a × b) | E11: Status | F11: Aviso de Justificativa
A12: ▶ GRUPO 1 – DESEMPENHO PROFISSIONAL
A13: =Dados!$B$36 -> Cumprimento das Atividades | B13: =Dados!$C$36 -> 0.4 | C13: 3 | D13: =B13*C13 -> 1.2 | E13: =IF(OR(C13=0,C13=1,C13=3),"✓ Ok","⛔ Inválida") -> ✓ Ok | F13: =IF(OR(C13=0,C13=1),"⚠ Favor inserir justificativa da nota "&C13&" no campo JUSTIFICATIVAS","")
A14: =Dados!$B$37 -> Qualificação / Atendimento ao Público / Postura | B14: =Dados!$C$37 -> 0.35 | C14: 3 | D14: =B14*C14 -> 1.05 | E14: =IF(OR(C14=0,C14=1,C14=3),"✓ Ok","⛔ Inválida") -> ✓ Ok | F14: =IF(OR(C14=0,C14=1),"⚠ Favor inserir justificativa da nota "&C14&" no campo JUSTIFICATIVAS","")
A15: =Dados!$B$38 -> Uniformes e Identificação | B15: =Dados!$C$38 -> 0.25 | C15: 3 | D15: =B15*C15 -> 0.75 | E15: =IF(OR(C15=0,C15=1,C15=3),"✓ Ok","⛔ Inválida") -> ✓ Ok | F15: =IF(OR(C15=0,C15=1),"⚠ Favor inserir justificativa da nota "&C15&" no campo JUSTIFICATIVAS","")
A16: TOTAL GRUPO 1 | B16: =SUM(B13:B15) -> 1 | D16: =SUM(D13:D15) -> 3
A17: ▶ GRUPO 2 – DESEMPENHO DAS ATIVIDADES
A18: =Dados!$B$39 -> Especificação Técnica dos Serviços | B18: =Dados!$C$39 -> 0.4 | C18: 3 | D18: =B18*C18 -> 1.2 | E18: =IF(OR(C18=0,C18=1,C18=3),"✓ Ok","⛔ Inválida") -> ✓ Ok | F18: =IF(OR(C18=0,C18=1),"⚠ Favor inserir justificativa da nota "&C18&" no campo JUSTIFICATIVAS","")
A19: =Dados!$B$40 -> Equipamentos e Acessórios | B19: =Dados!$C$40 -> 0.2 | C19: 3 | D19: =B19*C19 -> 0.6 | E19: =IF(OR(C19=0,C19=1,C19=3),"✓ Ok","⛔ Inválida") -> ✓ Ok | F19: =IF(OR(C19=0,C19=1),"⚠ Favor inserir justificativa da nota "&C19&" no campo JUSTIFICATIVAS","")
A20: =Dados!$B$41 -> Atendimento às Ocorrências | B20: =Dados!$C$41 -> 0.4 | C20: 3 | D20: =B20*C20 -> 1.2 | E20: =IF(OR(C20=0,C20=1,C20=3),"✓ Ok","⛔ Inválida") -> ✓ Ok | F20: =IF(OR(C20=0,C20=1),"⚠ Favor inserir justificativa da nota "&C20&" no campo JUSTIFICATIVAS","")
A21: TOTAL GRUPO 2 | B21: =SUM(B18:B20) -> 1 | D21: =SUM(D18:D20) -> 3
A22: ▶ GRUPO 3 – GERENCIAMENTO
A23: =Dados!$B$42 -> Periodicidade da Supervisão | B23: =Dados!$C$42 -> 0.2 | C23: 3 | D23: =B23*C23 -> 0.6 | E23: =IF(OR(C23=0,C23=1,C23=3),"✓ Ok","⛔ Inválida") -> ✓ Ok | F23: =IF(OR(C23=0,C23=1),"⚠ Favor inserir justificativa da nota "&C23&" no campo JUSTIFICATIVAS","")
A24: =Dados!$B$43 -> Gerenciamento das Atividades Operacionais | B24: =Dados!$C$43 -> 0.3 | C24: 3 | D24: =B24*C24 -> 0.9 | E24: =IF(OR(C24=0,C24=1,C24=3),"✓ Ok","⛔ Inválida") -> ✓ Ok | F24: =IF(OR(C24=0,C24=1),"⚠ Favor inserir justificativa da nota "&C24&" no campo JUSTIFICATIVAS","")
A25: =Dados!$B$44 -> Atendimento às Solicitações | B25: =Dados!$C$44 -> 0.25 | C25: 3 | D25: =B25*C25 -> 0.75 | E25: =IF(OR(C25=0,C25=1,C25=3),"✓ Ok","⛔ Inválida") -> ✓ Ok | F25: =IF(OR(C25=0,C25=1),"⚠ Favor inserir justificativa da nota "&C25&" no campo JUSTIFICATIVAS","")
A26: =Dados!$B$45 -> Salários, Benefícios e Obrigações Trabalhistas (¹ Fiscal Adm.) | B26: =Dados!$C$45 -> 0.25 | C26: 3 | D26: =B26*C26 -> 0.75 | E26: =IF(OR(C26=0,C26=1,C26=3),"✓ Ok","⛔ Inválida") -> ✓ Ok | F26: =IF(OR(C26=0,C26=1),"⚠ Favor inserir justificativa da nota "&C26&" no campo JUSTIFICATIVAS","")
A27: TOTAL GRUPO 3 | B27: =SUM(B23:B26) -> 1 | D27: =SUM(D23:D26) -> 3
A28: NOTA FINAL (somatório dos Grupos 1, 2 e 3) | D28: =D16+D21+D27 -> 9 | E28: Conceito: | F28: =INDEX(Dados!$B$50:$B$55,MATCH(D28,Dados!$A$50:$A$55,1)) -> A | G28: (¹) Grupo 3 – Salários/Benefícios/Obrigações Trabalhistas: preenchido pelo Fiscal Administrativo
A30: POSTOS DE TRABALHO
A31: Item | B31: POSTO | C31: Qtde Contratada | D31: Valor Unit. Contratado (R$) | E31: Horas Contratadas | F31: Sem Cobertura (h) | G31: Valor da Hora Contratada (R$) | H31: Valor do Item após Descontos (R$) | I31: Mensal Contratado (R$)
A32: =IF(Dados!$A$12="","",Dados!$A$12) -> 1 | B32: =IF(Dados!$B$12="","",Dados!$B$12) -> Vigilante Diurno 12x36 (exemplo) | C32: =IF(Dados!$C$12="","",Dados!$C$12) -> 2 | D32: =IF(Dados!$D$12="","",Dados!$D$12) -> 5996.89 | E32: =IF(C32="","",C32*220) -> 440 | G32: =IF(C32="","",IF(C32>0,ROUNDDOWN(N(D32)/220,2),0)) -> 27.25 | H32: =IF(C32="","",IF(AND(C32>0,N(D32)>0),MAX(0,ROUNDDOWN((C32*N(D32)-G32*N(F32))/30*$F$75*$F$71,2)),0)) -> 11993.78 | I32: =IF(C32="","",ROUNDDOWN(C32*N(D32),2)) -> 11993.78
A33: =IF(Dados!$A$13="","",Dados!$A$13) | B33: =IF(Dados!$B$13="","",Dados!$B$13) | C33: =IF(Dados!$C$13="","",Dados!$C$13) | D33: =IF(Dados!$D$13="","",Dados!$D$13) | E33: =IF(C33="","",C33*220) | G33: =IF(C33="","",IF(C33>0,ROUNDDOWN(N(D33)/220,2),0)) | H33: =IF(C33="","",IF(AND(C33>0,N(D33)>0),MAX(0,ROUNDDOWN((C33*N(D33)-G33*N(F33))/30*$F$75*$F$71,2)),0)) | I33: =IF(C33="","",ROUNDDOWN(C33*N(D33),2))
A34: =IF(Dados!$A$14="","",Dados!$A$14) | B34: =IF(Dados!$B$14="","",Dados!$B$14) | C34: =IF(Dados!$C$14="","",Dados!$C$14) | D34: =IF(Dados!$D$14="","",Dados!$D$14) | E34: =IF(C34="","",C34*220) | G34: =IF(C34="","",IF(C34>0,ROUNDDOWN(N(D34)/220,2),0)) | H34: =IF(C34="","",IF(AND(C34>0,N(D34)>0),MAX(0,ROUNDDOWN((C34*N(D34)-G34*N(F34))/30*$F$75*$F$71,2)),0)) | I34: =IF(C34="","",ROUNDDOWN(C34*N(D34),2))
A35: =IF(Dados!$A$15="","",Dados!$A$15) | B35: =IF(Dados!$B$15="","",Dados!$B$15) | C35: =IF(Dados!$C$15="","",Dados!$C$15) | D35: =IF(Dados!$D$15="","",Dados!$D$15) | E35: =IF(C35="","",C35*220) | G35: =IF(C35="","",IF(C35>0,ROUNDDOWN(N(D35)/220,2),0)) | H35: =IF(C35="","",IF(AND(C35>0,N(D35)>0),MAX(0,ROUNDDOWN((C35*N(D35)-G35*N(F35))/30*$F$75*$F$71,2)),0)) | I35: =IF(C35="","",ROUNDDOWN(C35*N(D35),2))
A36: =IF(Dados!$A$16="","",Dados!$A$16) | B36: =IF(Dados!$B$16="","",Dados!$B$16) | C36: =IF(Dados!$C$16="","",Dados!$C$16) | D36: =IF(Dados!$D$16="","",Dados!$D$16) | E36: =IF(C36="","",C36*220) | G36: =IF(C36="","",IF(C36>0,ROUNDDOWN(N(D36)/220,2),0)) | H36: =IF(C36="","",IF(AND(C36>0,N(D36)>0),MAX(0,ROUNDDOWN((C36*N(D36)-G36*N(F36))/30*$F$75*$F$71,2)),0)) | I36: =IF(C36="","",ROUNDDOWN(C36*N(D36),2))
A37: =IF(Dados!$A$17="","",Dados!$A$17) | B37: =IF(Dados!$B$17="","",Dados!$B$17) | C37: =IF(Dados!$C$17="","",Dados!$C$17) | D37: =IF(Dados!$D$17="","",Dados!$D$17) | E37: =IF(C37="","",C37*220) | G37: =IF(C37="","",IF(C37>0,ROUNDDOWN(N(D37)/220,2),0)) | H37: =IF(C37="","",IF(AND(C37>0,N(D37)>0),MAX(0,ROUNDDOWN((C37*N(D37)-G37*N(F37))/30*$F$75*$F$71,2)),0)) | I37: =IF(C37="","",ROUNDDOWN(C37*N(D37),2))
A38: =IF(Dados!$A$18="","",Dados!$A$18) | B38: =IF(Dados!$B$18="","",Dados!$B$18) | C38: =IF(Dados!$C$18="","",Dados!$C$18) | D38: =IF(Dados!$D$18="","",Dados!$D$18) | E38: =IF(C38="","",C38*220) | G38: =IF(C38="","",IF(C38>0,ROUNDDOWN(N(D38)/220,2),0)) | H38: =IF(C38="","",IF(AND(C38>0,N(D38)>0),MAX(0,ROUNDDOWN((C38*N(D38)-G38*N(F38))/30*$F$75*$F$71,2)),0)) | I38: =IF(C38="","",ROUNDDOWN(C38*N(D38),2))
A39: =IF(Dados!$A$19="","",Dados!$A$19) | B39: =IF(Dados!$B$19="","",Dados!$B$19) | C39: =IF(Dados!$C$19="","",Dados!$C$19) | D39: =IF(Dados!$D$19="","",Dados!$D$19) | E39: =IF(C39="","",C39*220) | G39: =IF(C39="","",IF(C39>0,ROUNDDOWN(N(D39)/220,2),0)) | H39: =IF(C39="","",IF(AND(C39>0,N(D39)>0),MAX(0,ROUNDDOWN((C39*N(D39)-G39*N(F39))/30*$F$75*$F$71,2)),0)) | I39: =IF(C39="","",ROUNDDOWN(C39*N(D39),2))
A40: =IF(Dados!$A$20="","",Dados!$A$20) | B40: =IF(Dados!$B$20="","",Dados!$B$20) | C40: =IF(Dados!$C$20="","",Dados!$C$20) | D40: =IF(Dados!$D$20="","",Dados!$D$20) | E40: =IF(C40="","",C40*220) | G40: =IF(C40="","",IF(C40>0,ROUNDDOWN(N(D40)/220,2),0)) | H40: =IF(C40="","",IF(AND(C40>0,N(D40)>0),MAX(0,ROUNDDOWN((C40*N(D40)-G40*N(F40))/30*$F$75*$F$71,2)),0)) | I40: =IF(C40="","",ROUNDDOWN(C40*N(D40),2))
A41: =IF(Dados!$A$21="","",Dados!$A$21) | B41: =IF(Dados!$B$21="","",Dados!$B$21) | C41: =IF(Dados!$C$21="","",Dados!$C$21) | D41: =IF(Dados!$D$21="","",Dados!$D$21) | E41: =IF(C41="","",C41*220) | G41: =IF(C41="","",IF(C41>0,ROUNDDOWN(N(D41)/220,2),0)) | H41: =IF(C41="","",IF(AND(C41>0,N(D41)>0),MAX(0,ROUNDDOWN((C41*N(D41)-G41*N(F41))/30*$F$75*$F$71,2)),0)) | I41: =IF(C41="","",ROUNDDOWN(C41*N(D41),2))
A42: =IF(Dados!$A$22="","",Dados!$A$22) | B42: =IF(Dados!$B$22="","",Dados!$B$22) | C42: =IF(Dados!$C$22="","",Dados!$C$22) | D42: =IF(Dados!$D$22="","",Dados!$D$22) | E42: =IF(C42="","",C42*220) | G42: =IF(C42="","",IF(C42>0,ROUNDDOWN(N(D42)/220,2),0)) | H42: =IF(C42="","",IF(AND(C42>0,N(D42)>0),MAX(0,ROUNDDOWN((C42*N(D42)-G42*N(F42))/30*$F$75*$F$71,2)),0)) | I42: =IF(C42="","",ROUNDDOWN(C42*N(D42),2))
A43: =IF(Dados!$A$23="","",Dados!$A$23) | B43: =IF(Dados!$B$23="","",Dados!$B$23) | C43: =IF(Dados!$C$23="","",Dados!$C$23) | D43: =IF(Dados!$D$23="","",Dados!$D$23) | E43: =IF(C43="","",C43*220) | G43: =IF(C43="","",IF(C43>0,ROUNDDOWN(N(D43)/220,2),0)) | H43: =IF(C43="","",IF(AND(C43>0,N(D43)>0),MAX(0,ROUNDDOWN((C43*N(D43)-G43*N(F43))/30*$F$75*$F$71,2)),0)) | I43: =IF(C43="","",ROUNDDOWN(C43*N(D43),2))
A44: =IF(Dados!$A$24="","",Dados!$A$24) | B44: =IF(Dados!$B$24="","",Dados!$B$24) | C44: =IF(Dados!$C$24="","",Dados!$C$24) | D44: =IF(Dados!$D$24="","",Dados!$D$24) | E44: =IF(C44="","",C44*220) | G44: =IF(C44="","",IF(C44>0,ROUNDDOWN(N(D44)/220,2),0)) | H44: =IF(C44="","",IF(AND(C44>0,N(D44)>0),MAX(0,ROUNDDOWN((C44*N(D44)-G44*N(F44))/30*$F$75*$F$71,2)),0)) | I44: =IF(C44="","",ROUNDDOWN(C44*N(D44),2))
A45: =IF(Dados!$A$25="","",Dados!$A$25) | B45: =IF(Dados!$B$25="","",Dados!$B$25) | C45: =IF(Dados!$C$25="","",Dados!$C$25) | D45: =IF(Dados!$D$25="","",Dados!$D$25) | E45: =IF(C45="","",C45*220) | G45: =IF(C45="","",IF(C45>0,ROUNDDOWN(N(D45)/220,2),0)) | H45: =IF(C45="","",IF(AND(C45>0,N(D45)>0),MAX(0,ROUNDDOWN((C45*N(D45)-G45*N(F45))/30*$F$75*$F$71,2)),0)) | I45: =IF(C45="","",ROUNDDOWN(C45*N(D45),2))
A46: =IF(Dados!$A$26="","",Dados!$A$26) | B46: =IF(Dados!$B$26="","",Dados!$B$26) | C46: =IF(Dados!$C$26="","",Dados!$C$26) | D46: =IF(Dados!$D$26="","",Dados!$D$26) | E46: =IF(C46="","",C46*220) | G46: =IF(C46="","",IF(C46>0,ROUNDDOWN(N(D46)/220,2),0)) | H46: =IF(C46="","",IF(AND(C46>0,N(D46)>0),MAX(0,ROUNDDOWN((C46*N(D46)-G46*N(F46))/30*$F$75*$F$71,2)),0)) | I46: =IF(C46="","",ROUNDDOWN(C46*N(D46),2))
A47: TOTAIS | F47: =SUM(F32:F46) -> 0 | H47: =SUM(H32:H46) -> 11993.78 | I47: =SUM(I32:I46) -> 11993.78
A49: 📋 INSTRUMENTO DE COBRANÇA
A50: Item | B50: Posto | F50: Qtde Faturada | H50: Valor Unit. Faturado (R$)
A51: =IF(A32="","",A32) -> 1 | B51: =IF(B32="","",B32) -> Vigilante Diurno 12x36 (exemplo) | F51: =IF(C32="","",C32) -> 2 | H51: =IF(C32="","",IF(C32>0,ROUNDDOWN(H32/C32,2),0)) -> 5996.89
A52: =IF(A33="","",A33) | B52: =IF(B33="","",B33) | F52: =IF(C33="","",C33) | H52: =IF(C33="","",IF(C33>0,ROUNDDOWN(H33/C33,2),0))
A53: =IF(A34="","",A34) | B53: =IF(B34="","",B34) | F53: =IF(C34="","",C34) | H53: =IF(C34="","",IF(C34>0,ROUNDDOWN(H34/C34,2),0))
A54: =IF(A35="","",A35) | B54: =IF(B35="","",B35) | F54: =IF(C35="","",C35) | H54: =IF(C35="","",IF(C35>0,ROUNDDOWN(H35/C35,2),0))
A55: =IF(A36="","",A36) | B55: =IF(B36="","",B36) | F55: =IF(C36="","",C36) | H55: =IF(C36="","",IF(C36>0,ROUNDDOWN(H36/C36,2),0))
A56: =IF(A37="","",A37) | B56: =IF(B37="","",B37) | F56: =IF(C37="","",C37) | H56: =IF(C37="","",IF(C37>0,ROUNDDOWN(H37/C37,2),0))
A57: =IF(A38="","",A38) | B57: =IF(B38="","",B38) | F57: =IF(C38="","",C38) | H57: =IF(C38="","",IF(C38>0,ROUNDDOWN(H38/C38,2),0))
A58: =IF(A39="","",A39) | B58: =IF(B39="","",B39) | F58: =IF(C39="","",C39) | H58: =IF(C39="","",IF(C39>0,ROUNDDOWN(H39/C39,2),0))
A59: =IF(A40="","",A40) | B59: =IF(B40="","",B40) | F59: =IF(C40="","",C40) | H59: =IF(C40="","",IF(C40>0,ROUNDDOWN(H40/C40,2),0))
A60: =IF(A41="","",A41) | B60: =IF(B41="","",B41) | F60: =IF(C41="","",C41) | H60: =IF(C41="","",IF(C41>0,ROUNDDOWN(H41/C41,2),0))
A61: =IF(A42="","",A42) | B61: =IF(B42="","",B42) | F61: =IF(C42="","",C42) | H61: =IF(C42="","",IF(C42>0,ROUNDDOWN(H42/C42,2),0))
A62: =IF(A43="","",A43) | B62: =IF(B43="","",B43) | F62: =IF(C43="","",C43) | H62: =IF(C43="","",IF(C43>0,ROUNDDOWN(H43/C43,2),0))
... A65: =IF(A46="","",A46) | B65: =IF(B46="","",B46) | F65: =IF(C46="","",C46) | H65: =IF(C46="","",IF(C46>0,ROUNDDOWN(H46/C46,2),0))
A67: RESUMO FINANCEIRO
A68: Contratado Mensal – Total (R$) (Σ Qtde × Valor Unitário de todos os postos) | F68: =I47 -> 11993.78
A69: Nota Final Apurada | F69: =D28 -> 9
A70: Nota Atribuída pelo Avaliador (Conceito) | F70: =F28 -> A
A71: % do Faturamento a ser Liberado | F71: =INDEX(Dados!$C$50:$C$55,MATCH(D28,Dados!$A$50:$A$55,1)) -> 1
A72: Valor Glosado por QUALIDADE (R$) | F72: =ROUNDDOWN(I47-I47*$F$71,2) -> 0
A73: Número de Dias do Mês (calculado) | F73: =IF(ISNUMBER(B7),DAY(EOMONTH(B7,0)),30) -> 30
A74: Número de Dias Trabalhados no Mês | F74: =IF(ISNUMBER(B7),DAY(EOMONTH(B7,0)),30) -> 30 | H74: Campo de preenchimento: altere apenas em mês parcial (início/fim de contrato)
A75: Dias para Cálculo (mês cheio = 30 avos) | F75: =IF(N(F74)>=$F$73,30,MAX(0,N(F74))) -> 30
A76: Soma dos Itens após Descontos (R$) | F76: =H47 -> 11993.78
A77: VALOR APROVADO PARA PAGAMENTO (R$) (Σ Itens após Descontos + Total dos Reembolsos de Creche) | F77: =MAX(0,ROUNDDOWN(H47+F83,2)) -> 11993.78
A79: 🏫 REEMBOLSO DE CRECHE
A80: Valor Reembolso Creche Retido (R$) | F80: =Dados!$D30 -> 0 | H80: Campo de preenchimento
A81: Reembolsos Aprovados (quantidade) | H81: Campo de preenchimento
A82: Reembolso por dependente (R$) | F82: =Dados!$D31 -> 0 | H82: Campo de preenchimento
A83: Valor Total dos Reembolsos (R$) (Aprovados × Reembolso por dependente) | F83: =ROUNDDOWN(N(F81)*N(F82),2) -> 0
A84: Saldo de Reembolso (R$) (acumulado: saldo da aba anterior + Retido – Total) | F84: =ROUNDDOWN(P02!F84+N(F80)-N(F83),2) -> 0
A85: =IF(F84<0,"⚠ ATENÇÃO: Saldo negativo — será necessário ADITIVAR O CONTRATO PARA SUPORTAR A DESPESA!","")
A87: FAIXA DE AJUSTE DE PAGAMENTO
A88: Conceito | D88: % do Faturamento a ser Pago | G88: Nota Média Mensal Apurada
A89: =Dados!$B$55 -> A | D89: =Dados!$C$55 -> 1 | G89: =Dados!$D$55 -> Entre 9,00 e 8,10
A90: =Dados!$B$54 -> B | D90: =Dados!$C$54 -> 0.95 | G90: =Dados!$D$54 -> Entre 8,09 e 7,65
A91: =Dados!$B$53 -> C | D91: =Dados!$C$53 -> 0.9 | G91: =Dados!$D$53 -> Entre 7,64 e 6,75
A92: =Dados!$B$52 -> D | D92: =Dados!$C$52 -> 0.85 | G92: =Dados!$D$52 -> Entre 6,74 e 5,85
A93: =Dados!$B$51 -> E | D93: =Dados!$C$51 -> 0.8 | G93: =Dados!$D$51 -> Entre 5,84 e 5,40
A94: =Dados!$B$50 -> F | D94: =Dados!$C$50 -> 0.75 | G94: =Dados!$D$50 -> Abaixo de 5,40
A96: APROVAÇÃO E ASSINATURAS
A97: Fiscal Operacional | D97: Fiscal Administrativo (¹) | G97: Representante da Contratada | I97: Data da Aprovação
A100: Nome completo / Matrícula | D100: Nome completo / Matrícula | G100: Nome completo / Cargo | I100: dd/mm/aaaa
A102: 📝 JUSTIFICATIVAS (obrigatório para notas 0 e 1)
A107: =IF(COUNTIF(C13:C27,0)+COUNTIF(C13:C27,1)>0,"⚠ Existem notas 0 ou 1 nesta aba — a justificativa acima é OBRIGATÓRIA. Informe critério, nota e fundamentação.","Para cada nota 0 ou 1 informe: critério, nota atribuída e fundamentação.") -> Para cada nota 0 ou 1 informe: critério, nota atribuída e fundamentação.

Sheet P04
A1: UFRJ – PRÓ-REITORIA DE GESTÃO E GOVERNANÇA – PR6 | IMR
A2: INSTRUMENTO DE MEDIÇÃO DE RESULTADO
A3: =IF(Dados!$B$6="","",Dados!$B$6) -> Atualizado conforme Valor Unitário Contratado inicial
A5: CONTRATO Nº: | B5: =IF(Dados!$B$2="","",Dados!$B$2) -> 04/24 | E5: UNIDADE: | G5: =IF(Dados!$B$3="","",Dados!$B$3) -> CBAE
A6: CONTRATADA: | B6: =IF(Dados!$B$4="","",Dados!$B$4) -> Angels | E6: FISCAL OPERACIONAL: | G6: =IF(Dados!$B$5="","",Dados!$B$5)
A7: AVALIAÇÃO REFERENTE AO PERÍODO: | B7: =IF(Dados!$B$7="","(informe o período inicial na aba Dados)",EDATE(Dados!$B$7,3)) -> (informe o período inicial na aba Dados) | E7: PERÍODO (ABA) Nº: | G7: 4 de 60
A8: ⚠ Para notas 0 e 1 o campo JUSTIFICATIVAS (fim da aba) é de preenchimento obrigatório. | Contrato, Unidade, Contratada e Postos são compartilhados por todas as abas (aba Dados).
A10: AVALIAÇÃO DE DESEMPENHO
A11: Critério de Avaliação | B11: PESO (a) | C11: NOTA (b) (0, 1 ou 3) | D11: SUBTOTAL (c = a × b) | E11: Status | F11: Aviso de Justificativa
A12: ▶ GRUPO 1 – DESEMPENHO PROFISSIONAL
A13: =Dados!$B$36 -> Cumprimento das Atividades | B13: =Dados!$C$36 -> 0.4 | C13: 3 | D13: =B13*C13 -> 1.2 | E13: =IF(OR(C13=0,C13=1,C13=3),"✓ Ok","⛔ Inválida") -> ✓ Ok | F13: =IF(OR(C13=0,C13=1),"⚠ Favor inserir justificativa da nota "&C13&" no campo JUSTIFICATIVAS","")
A14: =Dados!$B$37 -> Qualificação / Atendimento ao Público / Postura | B14: =Dados!$C$37 -> 0.35 | C14: 3 | D14: =B14*C14 -> 1.05 | E14: =IF(OR(C14=0,C14=1,C14=3),"✓ Ok","⛔ Inválida") -> ✓ Ok | F14: =IF(OR(C14=0,C14=1),"⚠ Favor inserir justificativa da nota "&C14&" no campo JUSTIFICATIVAS","")
A15: =Dados!$B$38 -> Uniformes e Identificação | B15: =Dados!$C$38 -> 0.25 | C15: 3 | D15: =B15*C15 -> 0.75 | E15: =IF(OR(C15=0,C15=1,C15=3),"✓ Ok","⛔ Inválida") -> ✓ Ok | F15: =IF(OR(C15=0,C15=1),"⚠ Favor inserir justificativa da nota "&C15&" no campo JUSTIFICATIVAS","")
A16: TOTAL GRUPO 1 | B16: =SUM(B13:B15) -> 1 | D16: =SUM(D13:D15) -> 3
A17: ▶ GRUPO 2 – DESEMPENHO DAS ATIVIDADES
A18: =Dados!$B$39 -> Especificação Técnica dos Serviços | B18: =Dados!$C$39 -> 0.4 | C18: 3 | D18: =B18*C18 -> 1.2 | E18: =IF(OR(C18=0,C18=1,C18=3),"✓ Ok","⛔ Inválida") -> ✓ Ok | F18: =IF(OR(C18=0,C18=1),"⚠ Favor inserir justificativa da nota "&C18&" no campo JUSTIFICATIVAS","")
A19: =Dados!$B$40 -> Equipamentos e Acessórios | B19: =Dados!$C$40 -> 0.2 | C19: 3 | D19: =B19*C19 -> 0.6 | E19: =IF(OR(C19=0,C19=1,C19=3),"✓ Ok","⛔ Inválida") -> ✓ Ok | F19: =IF(OR(C19=0,C19=1),"⚠ Favor inserir justificativa da nota "&C19&" no campo JUSTIFICATIVAS","")
A20: =Dados!$B$41 -> Atendimento às Ocorrências | B20: =Dados!$C$41 -> 0.4 | C20: 3 | D20: =B20*C20 -> 1.2 | E20: =IF(OR(C20=0,C20=1,C20=3),"✓ Ok","⛔ Inválida") -> ✓ Ok | F20: =IF(OR(C20=0,C20=1),"⚠ Favor inserir justificativa da nota "&C20&" no campo JUSTIFICATIVAS","")
A21: TOTAL GRUPO 2 | B21: =SUM(B18:B20) -> 1 | D21: =SUM(D18:D20) -> 3
A22: ▶ GRUPO 3 – GERENCIAMENTO
A23: =Dados!$B$42 -> Periodicidade da Supervisão | B23: =Dados!$C$42 -> 0.2 | C23: 3 | D23: =B23*C23 -> 0.6 | E23: =IF(OR(C23=0,C23=1,C23=3),"✓ Ok","⛔ Inválida") -> ✓ Ok | F23: =IF(OR(C23=0,C23=1),"⚠ Favor inserir justificativa da nota "&C23&" no campo JUSTIFICATIVAS","")
A24: =Dados!$B$43 -> Gerenciamento das Atividades Operacionais | B24: =Dados!$C$43 -> 0.3 | C24: 3 | D24: =B24*C24 -> 0.9 | E24: =IF(OR(C24=0,C24=1,C24=3),"✓ Ok","⛔ Inválida") -> ✓ Ok | F24: =IF(OR(C24=0,C24=1),"⚠ Favor inserir justificativa da nota "&C24&" no campo JUSTIFICATIVAS","")
A25: =Dados!$B$44 -> Atendimento às Solicitações | B25: =Dados!$C$44 -> 0.25 | C25: 3 | D25: =B25*C25 -> 0.75 | E25: =IF(OR(C25=0,C25=1,C25=3),"✓ Ok","⛔ Inválida") -> ✓ Ok | F25: =IF(OR(C25=0,C25=1),"⚠ Favor inserir justificativa da nota "&C25&" no campo JUSTIFICATIVAS","")
A26: =Dados!$B$45 -> Salários, Benefícios e Obrigações Trabalhistas (¹ Fiscal Adm.) | B26: =Dados!$C$45 -> 0.25 | C26: 3 | D26: =B26*C26 -> 0.75 | E26: =IF(OR(C26=0,C26=1,C26=3),"✓ Ok","⛔ Inválida") -> ✓ Ok | F26: =IF(OR(C26=0,C26=1),"⚠ Favor inserir justificativa da nota "&C26&" no campo JUSTIFICATIVAS","")
A27: TOTAL GRUPO 3 | B27: =SUM(B23:B26) -> 1 | D27: =SUM(D23:D26) -> 3
A28: NOTA FINAL (somatório dos Grupos 1, 2 e 3) | D28: =D16+D21+D27 -> 9 | E28: Conceito: | F28: =INDEX(Dados!$B$50:$B$55,MATCH(D28,Dados!$A$50:$A$55,1)) -> A | G28: (¹) Grupo 3 – Salários/Benefícios/Obrigações Trabalhistas: preenchido pelo Fiscal Administrativo
A30: POSTOS DE TRABALHO
A31: Item | B31: POSTO | C31: Qtde Contratada | D31: Valor Unit. Contratado (R$) | E31: Horas Contratadas | F31: Sem Cobertura (h) | G31: Valor da Hora Contratada (R$) | H31: Valor do Item após Descontos (R$) | I31: Mensal Contratado (R$)
A32: =IF(Dados!$A$12="","",Dados!$A$12) -> 1 | B32: =IF(Dados!$B$12="","",Dados!$B$12) -> Vigilante Diurno 12x36 (exemplo) | C32: =IF(Dados!$C$12="","",Dados!$C$12) -> 2 | D32: =IF(Dados!$D$12="","",Dados!$D$12) -> 5996.89 | E32: =IF(C32="","",C32*220) -> 440 | G32: =IF(C32="","",IF(C32>0,ROUNDDOWN(N(D32)/220,2),0)) -> 27.25 | H32: =IF(C32="","",IF(AND(C32>0,N(D32)>0),MAX(0,ROUNDDOWN((C32*N(D32)-G32*N(F32))/30*$F$75*$F$71,2)),0)) -> 11993.78 | I32: =IF(C32="","",ROUNDDOWN(C32*N(D32),2)) -> 11993.78
A33: =IF(Dados!$A$13="","",Dados!$A$13) | B33: =IF(Dados!$B$13="","",Dados!$B$13) | C33: =IF(Dados!$C$13="","",Dados!$C$13) | D33: =IF(Dados!$D$13="","",Dados!$D$13) | E33: =IF(C33="","",C33*220) | G33: =IF(C33="","",IF(C33>0,ROUNDDOWN(N(D33)/220,2),0)) | H33: =IF(C33="","",IF(AND(C33>0,N(D33)>0),MAX(0,ROUNDDOWN((C33*N(D33)-G33*N(F33))/30*$F$75*$F$71,2)),0)) | I33: =IF(C33="","",ROUNDDOWN(C33*N(D33),2))
A34: =IF(Dados!$A$14="","",Dados!$A$14) | B34: =IF(Dados!$B$14="","",Dados!$B$14) | C34: =IF(Dados!$C$14="","",Dados!$C$14) | D34: =IF(Dados!$D$14="","",Dados!$D$14) | E34: =IF(C34="","",C34*220) | G34: =IF(C34="","",IF(C34>0,ROUNDDOWN(N(D34)/220,2),0)) | H34: =IF(C34="","",IF(AND(C34>0,N(D34)>0),MAX(0,ROUNDDOWN((C34*N(D34)-G34*N(F34))/30*$F$75*$F$71,2)),0)) | I34: =IF(C34="","",ROUNDDOWN(C34*N(D34),2))
A35: =IF(Dados!$A$15="","",Dados!$A$15) | B35: =IF(Dados!$B$15="","",Dados!$B$15) | C35: =IF(Dados!$C$15="","",Dados!$C$15) | D35: =IF(Dados!$D$15="","",Dados!$D$15) | E35: =IF(C35="","",C35*220) | G35: =IF(C35="","",IF(C35>0,ROUNDDOWN(N(D35)/220,2),0)) | H35: =IF(C35="","",IF(AND(C35>0,N(D35)>0),MAX(0,ROUNDDOWN((C35*N(D35)-G35*N(F35))/30*$F$75*$F$71,2)),0)) | I35: =IF(C35="","",ROUNDDOWN(C35*N(D35),2))
A36: =IF(Dados!$A$16="","",Dados!$A$16) | B36: =IF(Dados!$B$16="","",Dados!$B$16) | C36: =IF(Dados!$C$16="","",Dados!$C$16) | D36: =IF(Dados!$D$16="","",Dados!$D$16) | E36: =IF(C36="","",C36*220) | G36: =IF(C36="","",IF(C36>0,ROUNDDOWN(N(D36)/220,2),0)) | H36: =IF(C36="","",IF(AND(C36>0,N(D36)>0),MAX(0,ROUNDDOWN((C36*N(D36)-G36*N(F36))/30*$F$75*$F$71,2)),0)) | I36: =IF(C36="","",ROUNDDOWN(C36*N(D36),2))
A37: =IF(Dados!$A$17="","",Dados!$A$17) | B37: =IF(Dados!$B$17="","",Dados!$B$17) | C37: =IF(Dados!$C$17="","",Dados!$C$17) | D37: =IF(Dados!$D$17="","",Dados!$D$17) | E37: =IF(C37="","",C37*220) | G37: =IF(C37="","",IF(C37>0,ROUNDDOWN(N(D37)/220,2),0)) | H37: =IF(C37="","",IF(AND(C37>0,N(D37)>0),MAX(0,ROUNDDOWN((C37*N(D37)-G37*N(F37))/30*$F$75*$F$71,2)),0)) | I37: =IF(C37="","",ROUNDDOWN(C37*N(D37),2))
A38: =IF(Dados!$A$18="","",Dados!$A$18) | B38: =IF(Dados!$B$18="","",Dados!$B$18) | C38: =IF(Dados!$C$18="","",Dados!$C$18) | D38: =IF(Dados!$D$18="","",Dados!$D$18) | E38: =IF(C38="","",C38*220) | G38: =IF(C38="","",IF(C38>0,ROUNDDOWN(N(D38)/220,2),0)) | H38: =IF(C38="","",IF(AND(C38>0,N(D38)>0),MAX(0,ROUNDDOWN((C38*N(D38)-G38*N(F38))/30*$F$75*$F$71,2)),0)) | I38: =IF(C38="","",ROUNDDOWN(C38*N(D38),2))
A39: =IF(Dados!$A$19="","",Dados!$A$19) | B39: =IF(Dados!$B$19="","",Dados!$B$19) | C39: =IF(Dados!$C$19="","",Dados!$C$19) | D39: =IF(Dados!$D$19="","",Dados!$D$19) | E39: =IF(C39="","",C39*220) | G39: =IF(C39="","",IF(C39>0,ROUNDDOWN(N(D39)/220,2),0)) | H39: =IF(C39="","",IF(AND(C39>0,N(D39)>0),MAX(0,ROUNDDOWN((C39*N(D39)-G39*N(F39))/30*$F$75*$F$71,2)),0)) | I39: =IF(C39="","",ROUNDDOWN(C39*N(D39),2))
A40: =IF(Dados!$A$20="","",Dados!$A$20) | B40: =IF(Dados!$B$20="","",Dados!$B$20) | C40: =IF(Dados!$C$20="","",Dados!$C$20) | D40: =IF(Dados!$D$20="","",Dados!$D$20) | E40: =IF(C40="","",C40*220) | G40: =IF(C40="","",IF(C40>0,ROUNDDOWN(N(D40)/220,2),0)) | H40: =IF(C40="","",IF(AND(C40>0,N(D40)>0),MAX(0,ROUNDDOWN((C40*N(D40)-G40*N(F40))/30*$F$75*$F$71,2)),0)) | I40: =IF(C40="","",ROUNDDOWN(C40*N(D40),2))
A41: =IF(Dados!$A$21="","",Dados!$A$21) | B41: =IF(Dados!$B$21="","",Dados!$B$21) | C41: =IF(Dados!$C$21="","",Dados!$C$21) | D41: =IF(Dados!$D$21="","",Dados!$D$21) | E41: =IF(C41="","",C41*220) | G41: =IF(C41="","",IF(C41>0,ROUNDDOWN(N(D41)/220,2),0)) | H41: =IF(C41="","",IF(AND(C41>0,N(D41)>0),MAX(0,ROUNDDOWN((C41*N(D41)-G41*N(F41))/30*$F$75*$F$71,2)),0)) | I41: =IF(C41="","",ROUNDDOWN(C41*N(D41),2))
A42: =IF(Dados!$A$22="","",Dados!$A$22) | B42: =IF(Dados!$B$22="","",Dados!$B$22) | C42: =IF(Dados!$C$22="","",Dados!$C$22) | D42: =IF(Dados!$D$22="","",Dados!$D$22) | E42: =IF(C42="","",C42*220) | G42: =IF(C42="","",IF(C42>0,ROUNDDOWN(N(D42)/220,2),0)) | H42: =IF(C42="","",IF(AND(C42>0,N(D42)>0),MAX(0,ROUNDDOWN((C42*N(D42)-G42*N(F42))/30*$F$75*$F$71,2)),0)) | I42: =IF(C42="","",ROUNDDOWN(C42*N(D42),2))
A43: =IF(Dados!$A$23="","",Dados!$A$23) | B43: =IF(Dados!$B$23="","",Dados!$B$23) | C43: =IF(Dados!$C$23="","",Dados!$C$23) | D43: =IF(Dados!$D$23="","",Dados!$D$23) | E43: =IF(C43="","",C43*220) | G43: =IF(C43="","",IF(C43>0,ROUNDDOWN(N(D43)/220,2),0)) | H43: =IF(C43="","",IF(AND(C43>0,N(D43)>0),MAX(0,ROUNDDOWN((C43*N(D43)-G43*N(F43))/30*$F$75*$F$71,2)),0)) | I43: =IF(C43="","",ROUNDDOWN(C43*N(D43),2))
A44: =IF(Dados!$A$24="","",Dados!$A$24) | B44: =IF(Dados!$B$24="","",Dados!$B$24) | C44: =IF(Dados!$C$24="","",Dados!$C$24) | D44: =IF(Dados!$D$24="","",Dados!$D$24) | E44: =IF(C44="","",C44*220) | G44: =IF(C44="","",IF(C44>0,ROUNDDOWN(N(D44)/220,2),0)) | H44: =IF(C44="","",IF(AND(C44>0,N(D44)>0),MAX(0,ROUNDDOWN((C44*N(D44)-G44*N(F44))/30*$F$75*$F$71,2)),0)) | I44: =IF(C44="","",ROUNDDOWN(C44*N(D44),2))
A45: =IF(Dados!$A$25="","",Dados!$A$25) | B45: =IF(Dados!$B$25="","",Dados!$B$25) | C45: =IF(Dados!$C$25="","",Dados!$C$25) | D45: =IF(Dados!$D$25="","",Dados!$D$25) | E45: =IF(C45="","",C45*220) | G45: =IF(C45="","",IF(C45>0,ROUNDDOWN(N(D45)/220,2),0)) | H45: =IF(C45="","",IF(AND(C45>0,N(D45)>0),MAX(0,ROUNDDOWN((C45*N(D45)-G45*N(F45))/30*$F$75*$F$71,2)),0)) | I45: =IF(C45="","",ROUNDDOWN(C45*N(D45),2))
A46: =IF(Dados!$A$26="","",Dados!$A$26) | B46: =IF(Dados!$B$26="","",Dados!$B$26) | C46: =IF(Dados!$C$26="","",Dados!$C$26) | D46: =IF(Dados!$D$26="","",Dados!$D$26) | E46: =IF(C46="","",C46*220) | G46: =IF(C46="","",IF(C46>0,ROUNDDOWN(N(D46)/220,2),0)) | H46: =IF(C46="","",IF(AND(C46>0,N(D46)>0),MAX(0,ROUNDDOWN((C46*N(D46)-G46*N(F46))/30*$F$75*$F$71,2)),0)) | I46: =IF(C46="","",ROUNDDOWN(C46*N(D46),2))
A47: TOTAIS | F47: =SUM(F32:F46) -> 0 | H47: =SUM(H32:H46) -> 11993.78 | I47: =SUM(I32:I46) -> 11993.78
A49: 📋 INSTRUMENTO DE COBRANÇA
A50: Item | B50: Posto | F50: Qtde Faturada | H50: Valor Unit. Faturado (R$)
A51: =IF(A32="","",A32) -> 1 | B51: =IF(B32="","",B32) -> Vigilante Diurno 12x36 (exemplo) | F51: =IF(C32="","",C32) -> 2 | H51: =IF(C32="","",IF(C32>0,ROUNDDOWN(H32/C32,2),0)) -> 5996.89
A52: =IF(A33="","",A33) | B52: =IF(B33="","",B33) | F52: =IF(C33="","",C33) | H52: =IF(C33="","",IF(C33>0,ROUNDDOWN(H33/C33,2),0))
A53: =IF(A34="","",A34) | B53: =IF(B34="","",B34) | F53: =IF(C34="","",C34) | H53: =IF(C34="","",IF(C34>0,ROUNDDOWN(H34/C34,2),0))
A54: =IF(A35="","",A35) | B54: =IF(B35="","",B35) | F54: =IF(C35="","",C35) | H54: =IF(C35="","",IF(C35>0,ROUNDDOWN(H35/C35,2),0))
A55: =IF(A36="","",A36) | B55: =IF(B36="","",B36) | F55: =IF(C36="","",C36) | H55: =IF(C36="","",IF(C36>0,ROUNDDOWN(H36/C36,2),0))
A56: =IF(A37="","",A37) | B56: =IF(B37="","",B37) | F56: =IF(C37="","",C37) | H56: =IF(C37="","",IF(C37>0,ROUNDDOWN(H37/C37,2),0))
A57: =IF(A38="","",A38) | B57: =IF(B38="","",B38) | F57: =IF(C38="","",C38) | H57: =IF(C38="","",IF(C38>0,ROUNDDOWN(H38/C38,2),0))
A58: =IF(A39="","",A39) | B58: =IF(B39="","",B39) | F58: =IF(C39="","",C39) | H58: =IF(C39="","",IF(C39>0,ROUNDDOWN(H39/C39,2),0))
A59: =IF(A40="","",A40) | B59: =IF(B40="","",B40) | F59: =IF(C40="","",C40) | H59: =IF(C40="","",IF(C40>0,ROUNDDOWN(H40/C40,2),0))
A60: =IF(A41="","",A41) | B60: =IF(B41="","",B41) | F60: =IF(C41="","",C41) | H60: =IF(C41="","",IF(C41>0,ROUNDDOWN(H41/C41,2),0))
A61: =IF(A42="","",A42) | B61: =IF(B42="","",B42) | F61: =IF(C42="","",C42) | H61: =IF(C42="","",IF(C42>0,ROUNDDOWN(H42/C42,2),0))
A62: =IF(A43="","",A43) | B62: =IF(B43="","",B43) | F62: =IF(C43="","",C43) | H62: =IF(C43="","",IF(C43>0,ROUNDDOWN(H43/C43,2),0))
... A65: =IF(A46="","",A46) | B65: =IF(B46="","",B46) | F65: =IF(C46="","",C46) | H65: =IF(C46="","",IF(C46>0,ROUNDDOWN(H46/C46,2),0))
A67: RESUMO FINANCEIRO
A68: Contratado Mensal – Total (R$) (Σ Qtde × Valor Unitário de todos os postos) | F68: =I47 -> 11993.78
A69: Nota Final Apurada | F69: =D28 -> 9
A70: Nota Atribuída pelo Avaliador (Conceito) | F70: =F28 -> A
A71: % do Faturamento a ser Liberado | F71: =INDEX(Dados!$C$50:$C$55,MATCH(D28,Dados!$A$50:$A$55,1)) -> 1
A72: Valor Glosado por QUALIDADE (R$) | F72: =ROUNDDOWN(I47-I47*$F$71,2) -> 0
A73: Número de Dias do Mês (calculado) | F73: =IF(ISNUMBER(B7),DAY(EOMONTH(B7,0)),30) -> 30
A74: Número de Dias Trabalhados no Mês | F74: =IF(ISNUMBER(B7),DAY(EOMONTH(B7,0)),30) -> 30 | H74: Campo de preenchimento: altere apenas em mês parcial (início/fim de contrato)
A75: Dias para Cálculo (mês cheio = 30 avos) | F75: =IF(N(F74)>=$F$73,30,MAX(0,N(F74))) -> 30
A76: Soma dos Itens após Descontos (R$) | F76: =H47 -> 11993.78
A77: VALOR APROVADO PARA PAGAMENTO (R$) (Σ Itens após Descontos + Total dos Reembolsos de Creche) | F77: =MAX(0,ROUNDDOWN(H47+F83,2)) -> 11993.78
A79: 🏫 REEMBOLSO DE CRECHE
A80: Valor Reembolso Creche Retido (R$) | F80: =Dados!$D30 -> 0 | H80: Campo de preenchimento
A81: Reembolsos Aprovados (quantidade) | H81: Campo de preenchimento
A82: Reembolso por dependente (R$) | F82: =Dados!$D31 -> 0 | H82: Campo de preenchimento
A83: Valor Total dos Reembolsos (R$) (Aprovados × Reembolso por dependente) | F83: =ROUNDDOWN(N(F81)*N(F82),2) -> 0
A84: Saldo de Reembolso (R$) (acumulado: saldo da aba anterior + Retido – Total) | F84: =ROUNDDOWN(P03!F84+N(F80)-N(F83),2) -> 0
A85: =IF(F84<0,"⚠ ATENÇÃO: Saldo negativo — será necessário ADITIVAR O CONTRATO PARA SUPORTAR A DESPESA!","")
A87: FAIXA DE AJUSTE DE PAGAMENTO
A88: Conceito | D88: % do Faturamento a ser Pago | G88: Nota Média Mensal Apurada
A89: =Dados!$B$55 -> A | D89: =Dados!$C$55 -> 1 | G89: =Dados!$D$55 -> Entre 9,00 e 8,10
A90: =Dados!$B$54 -> B | D90: =Dados!$C$54 -> 0.95 | G90: =Dados!$D$54 -> Entre 8,09 e 7,65
A91: =Dados!$B$53 -> C | D91: =Dados!$C$53 -> 0.9 | G91: =Dados!$D$53 -> Entre 7,64 e 6,75
A92: =Dados!$B$52 -> D | D92: =Dados!$C$52 -> 0.85 | G92: =Dados!$D$52 -> Entre 6,74 e 5,85
A93: =Dados!$B$51 -> E | D93: =Dados!$C$51 -> 0.8 | G93: =Dados!$D$51 -> Entre 5,84 e 5,40
A94: =Dados!$B$50 -> F | D94: =Dados!$C$50 -> 0.75 | G94: =Dados!$D$50 -> Abaixo de 5,40
A96: APROVAÇÃO E ASSINATURAS
A97: Fiscal Operacional | D97: Fiscal Administrativo (¹) | G97: Representante da Contratada | I97: Data da Aprovação
A100: Nome completo / Matrícula | D100: Nome completo / Matrícula | G100: Nome completo / Cargo | I100: dd/mm/aaaa
A102: 📝 JUSTIFICATIVAS (obrigatório para notas 0 e 1)
A107: =IF(COUNTIF(C13:C27,0)+COUNTIF(C13:C27,1)>0,"⚠ Existem notas 0 ou 1 nesta aba — a justificativa acima é OBRIGATÓRIA. Informe critério, nota e fundamentação.","Para cada nota 0 ou 1 informe: critério, nota atribuída e fundamentação.") -> Para cada nota 0 ou 1 informe: critério, nota atribuída e fundamentação.

Sheet P05
A1: UFRJ – PRÓ-REITORIA DE GESTÃO E GOVERNANÇA – PR6 | IMR
A2: INSTRUMENTO DE MEDIÇÃO DE RESULTADO
A3: =IF(Dados!$B$6="","",Dados!$B$6) -> Atualizado conforme Valor Unitário Contratado inicial
A5: CONTRATO Nº: | B5: =IF(Dados!$B$2="","",Dados!$B$2) -> 04/24 | E5: UNIDADE: | G5: =IF(Dados!$B$3="","",Dados!$B$3) -> CBAE
A6: CONTRATADA: | B6: =IF(Dados!$B$4="","",Dados!$B$4) -> Angels | E6: FISCAL OPERACIONAL: | G6: =IF(Dados!$B$5="","",Dados!$B$5)
A7: AVALIAÇÃO REFERENTE AO PERÍODO: | B7: =IF(Dados!$B$7="","(informe o período inicial na aba Dados)",EDATE(Dados!$B$7,4)) -> (informe o período inicial na aba Dados) | E7: PERÍODO (ABA) Nº: | G7: 5 de 60
A8: ⚠ Para notas 0 e 1 o campo JUSTIFICATIVAS (fim da aba) é de preenchimento obrigatório. | Contrato, Unidade, Contratada e Postos são compartilhados por todas as abas (aba Dados).
A10: AVALIAÇÃO DE DESEMPENHO
A11: Critério de Avaliação | B11: PESO (a) | C11: NOTA (b) (0, 1 ou 3) | D11: SUBTOTAL (c = a × b) | E11: Status | F11: Aviso de Justificativa
A12: ▶ GRUPO 1 – DESEMPENHO PROFISSIONAL
A13: =Dados!$B$36 -> Cumprimento das Atividades | B13: =Dados!$C$36 -> 0.4 | C13: 3 | D13: =B13*C13 -> 1.2 | E13: =IF(OR(C13=0,C13=1,C13=3),"✓ Ok","⛔ Inválida") -> ✓ Ok | F13: =IF(OR(C13=0,C13=1),"⚠ Favor inserir justificativa da nota "&C13&" no campo JUSTIFICATIVAS","")
A14: =Dados!$B$37 -> Qualificação / Atendimento ao Público / Postura | B14: =Dados!$C$37 -> 0.35 | C14: 3 | D14: =B14*C14 -> 1.05 | E14: =IF(OR(C14=0,C14=1,C14=3),"✓ Ok","⛔ Inválida") -> ✓ Ok | F14: =IF(OR(C14=0,C14=1),"⚠ Favor inserir justificativa da nota "&C14&" no campo JUSTIFICATIVAS","")
A15: =Dados!$B$38 -> Uniformes e Identificação | B15: =Dados!$C$38 -> 0.25 | C15: 3 | D15: =B15*C15 -> 0.75 | E15: =IF(OR(C15=0,C15=1,C15=3),"✓ Ok","⛔ Inválida") -> ✓ Ok | F15: =IF(OR(C15=0,C15=1),"⚠ Favor inserir justificativa da nota "&C15&" no campo JUSTIFICATIVAS","")
A16: TOTAL GRUPO 1 | B16: =SUM(B13:B15) -> 1 | D16: =SUM(D13:D15) -> 3
A17: ▶ GRUPO 2 – DESEMPENHO DAS ATIVIDADES
A18: =Dados!$B$39 -> Especificação Técnica dos Serviços | B18: =Dados!$C$39 -> 0.4 | C18: 3 | D18: =B18*C18 -> 1.2 | E18: =IF(OR(C18=0,C18=1,C18=3),"✓ Ok","⛔ Inválida") -> ✓ Ok | F18: =IF(OR(C18=0,C18=1),"⚠ Favor inserir justificativa da nota "&C18&" no campo JUSTIFICATIVAS","")
A19: =Dados!$B$40 -> Equipamentos e Acessórios | B19: =Dados!$C$40 -> 0.2 | C19: 3 | D19: =B19*C19 -> 0.6 | E19: =IF(OR(C19=0,C19=1,C19=3),"✓ Ok","⛔ Inválida") -> ✓ Ok | F19: =IF(OR(C19=0,C19=1),"⚠ Favor inserir justificativa da nota "&C19&" no campo JUSTIFICATIVAS","")
A20: =Dados!$B$41 -> Atendimento às Ocorrências | B20: =Dados!$C$41 -> 0.4 | C20: 3 | D20: =B20*C20 -> 1.2 | E20: =IF(OR(C20=0,C20=1,C20=3),"✓ Ok","⛔ Inválida") -> ✓ Ok | F20: =IF(OR(C20=0,C20=1),"⚠ Favor inserir justificativa da nota "&C20&" no campo JUSTIFICATIVAS","")
A21: TOTAL GRUPO 2 | B21: =SUM(B18:B20) -> 1 | D21: =SUM(D18:D20) -> 3
A22: ▶ GRUPO 3 – GERENCIAMENTO
A23: =Dados!$B$42 -> Periodicidade da Supervisão | B23: =Dados!$C$42 -> 0.2 | C23: 3 | D23: =B23*C23 -> 0.6 | E23: =IF(OR(C23=0,C23=1,C23=3),"✓ Ok","⛔ Inválida") -> ✓ Ok | F23: =IF(OR(C23=0,C23=1),"⚠ Favor inserir justificativa da nota "&C23&" no campo JUSTIFICATIVAS","")
A24: =Dados!$B$43 -> Gerenciamento das Atividades Operacionais | B24: =Dados!$C$43 -> 0.3 | C24: 3 | D24: =B24*C24 -> 0.9 | E24: =IF(OR(C24=0,C24=1,C24=3),"✓ Ok","⛔ Inválida") -> ✓ Ok | F24: =IF(OR(C24=0,C24=1),"⚠ Favor inserir justificativa da nota "&C24&" no campo JUSTIFICATIVAS","")
A25: =Dados!$B$44 -> Atendimento às Solicitações | B25: =Dados!$C$44 -> 0.25 | C25: 3 | D25: =B25*C25 -> 0.75 | E25: =IF(OR(C25=0,C25=1,C25=3),"✓ Ok","⛔ Inválida") -> ✓ Ok | F25: =IF(OR(C25=0,C25=1),"⚠ Favor inserir justificativa da nota "&C25&" no campo JUSTIFICATIVAS","")
A26: =Dados!$B$45 -> Salários, Benefícios e Obrigações Trabalhistas (¹ Fiscal Adm.) | B26: =Dados!$C$45 -> 0.25 | C26: 3 | D26: =B26*C26 -> 0.75 | E26: =IF(OR(C26=0,C26=1,C26=3),"✓ Ok","⛔ Inválida") -> ✓ Ok | F26: =IF(OR(C26=0,C26=1),"⚠ Favor inserir justificativa da nota "&C26&" no campo JUSTIFICATIVAS","")
A27: TOTAL GRUPO 3 | B27: =SUM(B23:B26) -> 1 | D27: =SUM(D23:D26) -> 3
A28: NOTA FINAL (somatório dos Grupos 1, 2 e 3) | D28: =D16+D21+D27 -> 9 | E28: Conceito: | F28: =INDEX(Dados!$B$50:$B$55,MATCH(D28,Dados!$A$50:$A$55,1)) -> A | G28: (¹) Grupo 3 – Salários/Benefícios/Obrigações Trabalhistas: preenchido pelo Fiscal Administrativo
A30: POSTOS DE TRABALHO
A31: Item | B31: POSTO | C31: Qtde Contratada | D31: Valor Unit. Contratado (R$) | E31: Horas Contratadas | F31: Sem Cobertura (h) | G31: Valor da Hora Contratada (R$) | H31: Valor do Item após Descontos (R$) | I31: Mensal Contratado (R$)
A32: =IF(Dados!$A$12="","",Dados!$A$12) -> 1 | B32: =IF(Dados!$B$12="","",Dados!$B$12) -> Vigilante Diurno 12x36 (exemplo) | C32: =IF(Dados!$C$12="","",Dados!$C$12) -> 2 | D32: =IF(Dados!$D$12="","",Dados!$D$12) -> 5996.89 | E32: =IF(C32="","",C32*220) -> 440 | G32: =IF(C32="","",IF(C32>0,ROUNDDOWN(N(D32)/220,2),0)) -> 27.25 | H32: =IF(C32="","",IF(AND(C32>0,N(D32)>0),MAX(0,ROUNDDOWN((C32*N(D32)-G32*N(F32))/30*$F$75*$F$71,2)),0)) -> 11993.78 | I32: =IF(C32="","",ROUNDDOWN(C32*N(D32),2)) -> 11993.78
A33: =IF(Dados!$A$13="","",Dados!$A$13) | B33: =IF(Dados!$B$13="","",Dados!$B$13) | C33: =IF(Dados!$C$13="","",Dados!$C$13) | D33: =IF(Dados!$D$13="","",Dados!$D$13) | E33: =IF(C33="","",C33*220) | G33: =IF(C33="","",IF(C33>0,ROUNDDOWN(N(D33)/220,2),0)) | H33: =IF(C33="","",IF(AND(C33>0,N(D33)>0),MAX(0,ROUNDDOWN((C33*N(D33)-G33*N(F33))/30*$F$75*$F$71,2)),0)) | I33: =IF(C33="","",ROUNDDOWN(C33*N(D33),2))
A34: =IF(Dados!$A$14="","",Dados!$A$14) | B34: =IF(Dados!$B$14="","",Dados!$B$14) | C34: =IF(Dados!$C$14="","",Dados!$C$14) | D34: =IF(Dados!$D$14="","",Dados!$D$14) | E34: =IF(C34="","",C34*220) | G34: =IF(C34="","",IF(C34>0,ROUNDDOWN(N(D34)/220,2),0)) | H34: =IF(C34="","",IF(AND(C34>0,N(D34)>0),MAX(0,ROUNDDOWN((C34*N(D34)-G34*N(F34))/30*$F$75*$F$71,2)),0)) | I34: =IF(C34="","",ROUNDDOWN(C34*N(D34),2))
A35: =IF(Dados!$A$15="","",Dados!$A$15) | B35: =IF(Dados!$B$15="","",Dados!$B$15) | C35: =IF(Dados!$C$15="","",Dados!$C$15) | D35: =IF(Dados!$D$15="","",Dados!$D$15) | E35: =IF(C35="","",C35*220) | G35: =IF(C35="","",IF(C35>0,ROUNDDOWN(N(D35)/220,2),0)) | H35: =IF(C35="","",IF(AND(C35>0,N(D35)>0),MAX(0,ROUNDDOWN((C35*N(D35)-G35*N(F35))/30*$F$75*$F$71,2)),0)) | I35: =IF(C35="","",ROUNDDOWN(C35*N(D35),2))
A36: =IF(Dados!$A$16="","",Dados!$A$16) | B36: =IF(Dados!$B$16="","",Dados!$B$16) | C36: =IF(Dados!$C$16="","",Dados!$C$16) | D36: =IF(Dados!$D$16="","",Dados!$D$16) | E36: =IF(C36="","",C36*220) | G36: =IF(C36="","",IF(C36>0,ROUNDDOWN(N(D36)/220,2),0)) | H36: =IF(C36="","",IF(AND(C36>0,N(D36)>0),MAX(0,ROUNDDOWN((C36*N(D36)-G36*N(F36))/30*$F$75*$F$71,2)),0)) | I36: =IF(C36="","",ROUNDDOWN(C36*N(D36),2))
A37: =IF(Dados!$A$17="","",Dados!$A$17) | B37: =IF(Dados!$B$17="","",Dados!$B$17) | C37: =IF(Dados!$C$17="","",Dados!$C$17) | D37: =IF(Dados!$D$17="","",Dados!$D$17) | E37: =IF(C37="","",C37*220) | G37: =IF(C37="","",IF(C37>0,ROUNDDOWN(N(D37)/220,2),0)) | H37: =IF(C37="","",IF(AND(C37>0,N(D37)>0),MAX(0,ROUNDDOWN((C37*N(D37)-G37*N(F37))/30*$F$75*$F$71,2)),0)) | I37: =IF(C37="","",ROUNDDOWN(C37*N(D37),2))
A38: =IF(Dados!$A$18="","",Dados!$A$18) | B38: =IF(Dados!$B$18="","",Dados!$B$18) | C38: =IF(Dados!$C$18="","",Dados!$C$18) | D38: =IF(Dados!$D$18="","",Dados!$D$18) | E38: =IF(C38="","",C38*220) | G38: =IF(C38="","",IF(C38>0,ROUNDDOWN(N(D38)/220,2),0)) | H38: =IF(C38="","",IF(AND(C38>0,N(D38)>0),MAX(0,ROUNDDOWN((C38*N(D38)-G38*N(F38))/30*$F$75*$F$71,2)),0)) | I38: =IF(C38="","",ROUNDDOWN(C38*N(D38),2))
A39: =IF(Dados!$A$19="","",Dados!$A$19) | B39: =IF(Dados!$B$19="","",Dados!$B$19) | C39: =IF(Dados!$C$19="","",Dados!$C$19) | D39: =IF(Dados!$D$19="","",Dados!$D$19) | E39: =IF(C39="","",C39*220) | G39: =IF(C39="","",IF(C39>0,ROUNDDOWN(N(D39)/220,2),0)) | H39: =IF(C39="","",IF(AND(C39>0,N(D39)>0),MAX(0,ROUNDDOWN((C39*N(D39)-G39*N(F39))/30*$F$75*$F$71,2)),0)) | I39: =IF(C39="","",ROUNDDOWN(C39*N(D39),2))
A40: =IF(Dados!$A$20="","",Dados!$A$20) | B40: =IF(Dados!$B$20="","",Dados!$B$20) | C40: =IF(Dados!$C$20="","",Dados!$C$20) | D40: =IF(Dados!$D$20="","",Dados!$D$20) | E40: =IF(C40="","",C40*220) | G40: =IF(C40="","",IF(C40>0,ROUNDDOWN(N(D40)/220,2),0)) | H40: =IF(C40="","",IF(AND(C40>0,N(D40)>0),MAX(0,ROUNDDOWN((C40*N(D40)-G40*N(F40))/30*$F$75*$F$71,2)),0)) | I40: =IF(C40="","",ROUNDDOWN(C40*N(D40),2))
A41: =IF(Dados!$A$21="","",Dados!$A$21) | B41: =IF(Dados!$B$21="","",Dados!$B$21) | C41: =IF(Dados!$C$21="","",Dados!$C$21) | D41: =IF(Dados!$D$21="","",Dados!$D$21) | E41: =IF(C41="","",C41*220) | G41: =IF(C41="","",IF(C41>0,ROUNDDOWN(N(D41)/220,2),0)) | H41: =IF(C41="","",IF(AND(C41>0,N(D41)>0),MAX(0,ROUNDDOWN((C41*N(D41)-G41*N(F41))/30*$F$75*$F$71,2)),0)) | I41: =IF(C41="","",ROUNDDOWN(C41*N(D41),2))
A42: =IF(Dados!$A$22="","",Dados!$A$22) | B42: =IF(Dados!$B$22="","",Dados!$B$22) | C42: =IF(Dados!$C$22="","",Dados!$C$22) | D42: =IF(Dados!$D$22="","",Dados!$D$22) | E42: =IF(C42="","",C42*220) | G42: =IF(C42="","",IF(C42>0,ROUNDDOWN(N(D42)/220,2),0)) | H42: =IF(C42="","",IF(AND(C42>0,N(D42)>0),MAX(0,ROUNDDOWN((C42*N(D42)-G42*N(F42))/30*$F$75*$F$71,2)),0)) | I42: =IF(C42="","",ROUNDDOWN(C42*N(D42),2))
A43: =IF(Dados!$A$23="","",Dados!$A$23) | B43: =IF(Dados!$B$23="","",Dados!$B$23) | C43: =IF(Dados!$C$23="","",Dados!$C$23) | D43: =IF(Dados!$D$23="","",Dados!$D$23) | E43: =IF(C43="","",C43*220) | G43: =IF(C43="","",IF(C43>0,ROUNDDOWN(N(D43)/220,2),0)) | H43: =IF(C43="","",IF(AND(C43>0,N(D43)>0),MAX(0,ROUNDDOWN((C43*N(D43)-G43*N(F43))/30*$F$75*$F$71,2)),0)) | I43: =IF(C43="","",ROUNDDOWN(C43*N(D43),2))
A44: =IF(Dados!$A$24="","",Dados!$A$24) | B44: =IF(Dados!$B$24="","",Dados!$B$24) | C44: =IF(Dados!$C$24="","",Dados!$C$24) | D44: =IF(Dados!$D$24="","",Dados!$D$24) | E44: =IF(C44="","",C44*220) | G44: =IF(C44="","",IF(C44>0,ROUNDDOWN(N(D44)/220,2),0)) | H44: =IF(C44="","",IF(AND(C44>0,N(D44)>0),MAX(0,ROUNDDOWN((C44*N(D44)-G44*N(F44))/30*$F$75*$F$71,2)),0)) | I44: =IF(C44="","",ROUNDDOWN(C44*N(D44),2))
A45: =IF(Dados!$A$25="","",Dados!$A$25) | B45: =IF(Dados!$B$25="","",Dados!$B$25) | C45: =IF(Dados!$C$25="","",Dados!$C$25) | D45: =IF(Dados!$D$25="","",Dados!$D$25) | E45: =IF(C45="","",C45*220) | G45: =IF(C45="","",IF(C45>0,ROUNDDOWN(N(D45)/220,2),0)) | H45: =IF(C45="","",IF(AND(C45>0,N(D45)>0),MAX(0,ROUNDDOWN((C45*N(D45)-G45*N(F45))/30*$F$75*$F$71,2)),0)) | I45: =IF(C45="","",ROUNDDOWN(C45*N(D45),2))
A46: =IF(Dados!$A$26="","",Dados!$A$26) | B46: =IF(Dados!$B$26="","",Dados!$B$26) | C46: =IF(Dados!$C$26="","",Dados!$C$26) | D46: =IF(Dados!$D$26="","",Dados!$D$26) | E46: =IF(C46="","",C46*220) | G46: =IF(C46="","",IF(C46>0,ROUNDDOWN(N(D46)/220,2),0)) | H46: =IF(C46="","",IF(AND(C46>0,N(D46)>0),MAX(0,ROUNDDOWN((C46*N(D46)-G46*N(F46))/30*$F$75*$F$71,2)),0)) | I46: =IF(C46="","",ROUNDDOWN(C46*N(D46),2))
A47: TOTAIS | F47: =SUM(F32:F46) -> 0 | H47: =SUM(H32:H46) -> 11993.78 | I47: =SUM(I32:I46) -> 11993.78
A49: 📋 INSTRUMENTO DE COBRANÇA
A50: Item | B50: Posto | F50: Qtde Faturada | H50: Valor Unit. Faturado (R$)
A51: =IF(A32="","",A32) -> 1 | B51: =IF(B32="","",B32) -> Vigilante Diurno 12x36 (exemplo) | F51: =IF(C32="","",C32) -> 2 | H51: =IF(C32="","",IF(C32>0,ROUNDDOWN(H32/C32,2),0)) -> 5996.89
A52: =IF(A33="","",A33) | B52: =IF(B33="","",B33) | F52: =IF(C33="","",C33) | H52: =IF(C33="","",IF(C33>0,ROUNDDOWN(H33/C33,2),0))
A53: =IF(A34="","",A34) | B53: =IF(B34="","",B34) | F53: =IF(C34="","",C34) | H53: =IF(C34="","",IF(C34>0,ROUNDDOWN(H34/C34,2),0))
A54: =IF(A35="","",A35) | B54: =IF(B35="","",B35) | F54: =IF(C35="","",C35) | H54: =IF(C35="","",IF(C35>0,ROUNDDOWN(H35/C35,2),0))
A55: =IF(A36="","",A36) | B55: =IF(B36="","",B36) | F55: =IF(C36="","",C36) | H55: =IF(C36="","",IF(C36>0,ROUNDDOWN(H36/C36,2),0))
A56: =IF(A37="","",A37) | B56: =IF(B37="","",B37) | F56: =IF(C37="","",C37) | H56: =IF(C37="","",IF(C37>0,ROUNDDOWN(H37/C37,2),0))
A57: =IF(A38="","",A38) | B57: =IF(B38="","",B38) | F57: =IF(C38="","",C38) | H57: =IF(C38="","",IF(C38>0,ROUNDDOWN(H38/C38,2),0))
A58: =IF(A39="","",A39) | B58: =IF(B39="","",B39) | F58: =IF(C39="","",C39) | H58: =IF(C39="","",IF(C39>0,ROUNDDOWN(H39/C39,2),0))
A59: =IF(A40="","",A40) | B59: =IF(B40="","",B40) | F59: =IF(C40="","",C40) | H59: =IF(C40="","",IF(C40>0,ROUNDDOWN(H40/C40,2),0))
A60: =IF(A41="","",A41) | B60: =IF(B41="","",B41) | F60: =IF(C41="","",C41) | H60: =IF(C41="","",IF(C41>0,ROUNDDOWN(H41/C41,2),0))
A61: =IF(A42="","",A42) | B61: =IF(B42="","",B42) | F61: =IF(C42="","",C42) | H61: =IF(C42="","",IF(C42>0,ROUNDDOWN(H42/C42,2),0))
A62: =IF(A43="","",A43) | B62: =IF(B43="","",B43) | F62: =IF(C43="","",C43) | H62: =IF(C43="","",IF(C43>0,ROUNDDOWN(H43/C43,2),0))
... A65: =IF(A46="","",A46) | B65: =IF(B46="","",B46) | F65: =IF(C46="","",C46) | H65: =IF(C46="","",IF(C46>0,ROUNDDOWN(H46/C46,2),0))
A67: RESUMO FINANCEIRO
A68: Contratado Mensal – Total (R$) (Σ Qtde × Valor Unitário de todos os postos) | F68: =I47 -> 11993.78
A69: Nota Final Apurada | F69: =D28 -> 9
A70: Nota Atribuída pelo Avaliador (Conceito) | F70: =F28 -> A
A71: % do Faturamento a ser Liberado | F71: =INDEX(Dados!$C$50:$C$55,MATCH(D28,Dados!$A$50:$A$55,1)) -> 1
A72: Valor Glosado por QUALIDADE (R$) | F72: =ROUNDDOWN(I47-I47*$F$71,2) -> 0
A73: Número de Dias do Mês (calculado) | F73: =IF(ISNUMBER(B7),DAY(EOMONTH(B7,0)),30) -> 30
A74: Número de Dias Trabalhados no Mês | F74: =IF(ISNUMBER(B7),DAY(EOMONTH(B7,0)),30) -> 30 | H74: Campo de preenchimento: altere apenas em mês parcial (início/fim de contrato)
A75: Dias para Cálculo (mês cheio = 30 avos) | F75: =IF(N(F74)>=$F$73,30,MAX(0,N(F74))) -> 30
A76: Soma dos Itens após Descontos (R$) | F76: =H47 -> 11993.78
A77: VALOR APROVADO PARA PAGAMENTO (R$) (Σ Itens após Descontos + Total dos Reembolsos de Creche) | F77: =MAX(0,ROUNDDOWN(H47+F83,2)) -> 11993.78
A79: 🏫 REEMBOLSO DE CRECHE
A80: Valor Reembolso Creche Retido (R$) | F80: =Dados!$D30 -> 0 | H80: Campo de preenchimento
A81: Reembolsos Aprovados (quantidade) | H81: Campo de preenchimento
A82: Reembolso por dependente (R$) | F82: =Dados!$D31 -> 0 | H82: Campo de preenchimento
A83: Valor Total dos Reembolsos (R$) (Aprovados × Reembolso por dependente) | F83: =ROUNDDOWN(N(F81)*N(F82),2) -> 0
A84: Saldo de Reembolso (R$) (acumulado: saldo da aba anterior + Retido – Total) | F84: =ROUNDDOWN(P04!F84+N(F80)-N(F83),2) -> 0
A85: =IF(F84<0,"⚠ ATENÇÃO: Saldo negativo — será necessário ADITIVAR O CONTRATO PARA SUPORTAR A DESPESA!","")
A87: FAIXA DE AJUSTE DE PAGAMENTO
A88: Conceito | D88: % do Faturamento a ser Pago | G88: Nota Média Mensal Apurada
A89: =Dados!$B$55 -> A | D89: =Dados!$C$55 -> 1 | G89: =Dados!$D$55 -> Entre 9,00 e 8,10
A90: =Dados!$B$54 -> B | D90: =Dados!$C$54 -> 0.95 | G90: =Dados!$D$54 -> Entre 8,09 e 7,65
A91: =Dados!$B$53 -> C | D91: =Dados!$C$53 -> 0.9 | G91: =Dados!$D$53 -> Entre 7,64 e 6,75
A92: =Dados!$B$52 -> D | D92: =Dados!$C$52 -> 0.85 | G92: =Dados!$D$52 -> Entre 6,74 e 5,85
A93: =Dados!$B$51 -> E | D93: =Dados!$C$51 -> 0.8 | G93: =Dados!$D$51 -> Entre 5,84 e 5,40
A94: =Dados!$B$50 -> F | D94: =Dados!$C$50 -> 0.75 | G94: =Dados!$D$50 -> Abaixo de 5,40
A96: APROVAÇÃO E ASSINATURAS
A97: Fiscal Operacional | D97: Fiscal Administrativo (¹) | G97: Representante da Contratada | I97: Data da Aprovação
A100: Nome completo / Matrícula | D100: Nome completo / Matrícula | G100: Nome completo / Cargo | I100: dd/mm/aaaa
A102: 📝 JUSTIFICATIVAS (obrigatório para notas 0 e 1)
A107: =IF(COUNTIF(C13:C27,0)+COUNTIF(C13:C27,1)>0,"⚠ Existem notas 0 ou 1 nesta aba — a justificativa acima é OBRIGATÓRIA. Informe critério, nota e fundamentação.","Para cada nota 0 ou 1 informe: critério, nota atribuída e fundamentação.") -> Para cada nota 0 ou 1 informe: critério, nota atribuída e fundamentação.

Sheet P06
A1: UFRJ – PRÓ-REITORIA DE GESTÃO E GOVERNANÇA – PR6 | IMR
A2: INSTRUMENTO DE MEDIÇÃO DE RESULTADO
A3: =IF(Dados!$B$6="","",Dados!$B$6) -> Atualizado conforme Valor Unitário Contratado inicial
A5: CONTRATO Nº: | B5: =IF(Dados!$B$2="","",Dados!$B$2) -> 04/24 | E5: UNIDADE: | G5: =IF(Dados!$B$3="","",Dados!$B$3) -> CBAE
A6: CONTRATADA: | B6: =IF(Dados!$B$4="","",Dados!$B$4) -> Angels | E6: FISCAL OPERACIONAL: | G6: =IF(Dados!$B$5="","",Dados!$B$5)
A7: AVALIAÇÃO REFERENTE AO PERÍODO: | B7: =IF(Dados!$B$7="","(informe o período inicial na aba Dados)",EDATE(Dados!$B$7,5)) -> (informe o período inicial na aba Dados) | E7: PERÍODO (ABA) Nº: | G7: 6 de 60
A8: ⚠ Para notas 0 e 1 o campo JUSTIFICATIVAS (fim da aba) é de preenchimento obrigatório. | Contrato, Unidade, Contratada e Postos são compartilhados por todas as abas (aba Dados).
A10: AVALIAÇÃO DE DESEMPENHO
A11: Critério de Avaliação | B11: PESO (a) | C11: NOTA (b) (0, 1 ou 3) | D11: SUBTOTAL (c = a × b) | E11: Status | F11: Aviso de Justificativa
A12: ▶ GRUPO 1 – DESEMPENHO PROFISSIONAL
A13: =Dados!$B$36 -> Cumprimento das Atividades | B13: =Dados!$C$36 -> 0.4 | C13: 3 | D13: =B13*C13 -> 1.2 | E13: =IF(OR(C13=0,C13=1,C13=3),"✓ Ok","⛔ Inválida") -> ✓ Ok | F13: =IF(OR(C13=0,C13=1),"⚠ Favor inserir justificativa da nota "&C13&" no campo JUSTIFICATIVAS","")
A14: =Dados!$B$37 -> Qualificação / Atendimento ao Público / Postura | B14: =Dados!$C$37 -> 0.35 | C14: 3 | D14: =B14*C14 -> 1.05 | E14: =IF(OR(C14=0,C14=1,C14=3),"✓ Ok","⛔ Inválida") -> ✓ Ok | F14: =IF(OR(C14=0,C14=1),"⚠ Favor inserir justificativa da nota "&C14&" no campo JUSTIFICATIVAS","")
A15: =Dados!$B$38 -> Uniformes e Identificação | B15: =Dados!$C$38 -> 0.25 | C15: 3 | D15: =B15*C15 -> 0.75 | E15: =IF(OR(C15=0,C15=1,C15=3),"✓ Ok","⛔ Inválida") -> ✓ Ok | F15: =IF(OR(C15=0,C15=1),"⚠ Favor inserir justificativa da nota "&C15&" no campo JUSTIFICATIVAS","")
A16: TOTAL GRUPO 1 | B16: =SUM(B13:B15) -> 1 | D16: =SUM(D13:D15) -> 3
A17: ▶ GRUPO 2 – DESEMPENHO DAS ATIVIDADES
A18: =Dados!$B$39 -> Especificação Técnica dos Serviços | B18: =Dados!$C$39 -> 0.4 | C18: 3 | D18: =B18*C18 -> 1.2 | E18: =IF(OR(C18=0,C18=1,C18=3),"✓ Ok","⛔ Inválida") -> ✓ Ok | F18: =IF(OR(C18=0,C18=1),"⚠ Favor inserir justificativa da nota "&C18&" no campo JUSTIFICATIVAS","")
A19: =Dados!$B$40 -> Equipamentos e Acessórios | B19: =Dados!$C$40 -> 0.2 | C19: 3 | D19: =B19*C19 -> 0.6 | E19: =IF(OR(C19=0,C19=1,C19=3),"✓ Ok","⛔ Inválida") -> ✓ Ok | F19: =IF(OR(C19=0,C19=1),"⚠ Favor inserir justificativa da nota "&C19&" no campo JUSTIFICATIVAS","")
A20: =Dados!$B$41 -> Atendimento às Ocorrências | B20: =Dados!$C$41 -> 0.4 | C20: 3 | D20: =B20*C20 -> 1.2 | E20: =IF(OR(C20=0,C20=1,C20=3),"✓ Ok","⛔ Inválida") -> ✓ Ok | F20: =IF(OR(C20=0,C20=1),"⚠ Favor inserir justificativa da nota "&C20&" no campo JUSTIFICATIVAS","")
A21: TOTAL GRUPO 2 | B21: =SUM(B18:B20) -> 1 | D21: =SUM(D18:D20) -> 3
A22: ▶ GRUPO 3 – GERENCIAMENTO
A23: =Dados!$B$42 -> Periodicidade da Supervisão | B23: =Dados!$C$42 -> 0.2 | C23: 3 | D23: =B23*C23 -> 0.6 | E23: =IF(OR(C23=0,C23=1,C23=3),"✓ Ok","⛔ Inválida") -> ✓ Ok | F23: =IF(OR(C23=0,C23=1),"⚠ Favor inserir justificativa da nota "&C23&" no campo JUSTIFICATIVAS","")
A24: =Dados!$B$43 -> Gerenciamento das Atividades Operacionais | B24: =Dados!$C$43 -> 0.3 | C24: 3 | D24: =B24*C24 -> 0.9 | E24: =IF(OR(C24=0,C24=1,C24=3),"✓ Ok","⛔ Inválida") -> ✓ Ok | F24: =IF(OR(C24=0,C24=1),"⚠ Favor inserir justificativa da nota "&C24&" no campo JUSTIFICATIVAS","")
A25: =Dados!$B$44 -> Atendimento às Solicitações | B25: =Dados!$C$44 -> 0.25 | C25: 3 | D25: =B25*C25 -> 0.75 | E25: =IF(OR(C25=0,C25=1,C25=3),"✓ Ok","⛔ Inválida") -> ✓ Ok | F25: =IF(OR(C25=0,C25=1),"⚠ Favor inserir justificativa da nota "&C25&" no campo JUSTIFICATIVAS","")
A26: =Dados!$B$45 -> Salários, Benefícios e Obrigações Trabalhistas (¹ Fiscal Adm.) | B26: =Dados!$C$45 -> 0.25 | C26: 3 | D26: =B26*C26 -> 0.75 | E26: =IF(OR(C26=0,C26=1,C26=3),"✓ Ok","⛔ Inválida") -> ✓ Ok | F26: =IF(OR(C26=0,C26=1),"⚠ Favor inserir justificativa da nota "&C26&" no campo JUSTIFICATIVAS","")
A27: TOTAL GRUPO 3 | B27: =SUM(B23:B26) -> 1 | D27: =SUM(D23:D26) -> 3
A28: NOTA FINAL (somatório dos Grupos 1, 2 e 3) | D28: =D16+D21+D27 -> 9 | E28: Conceito: | F28: =INDEX(Dados!$B$50:$B$55,MATCH(D28,Dados!$A$50:$A$55,1)) -> A | G28: (¹) Grupo 3 – Salários/Benefícios/Obrigações Trabalhistas: preenchido pelo Fiscal Administrativo
A30: POSTOS DE TRABALHO
A31: Item | B31: POSTO | C31: Qtde Contratada | D31: Valor Unit. Contratado (R$) | E31: Horas Contratadas | F31: Sem Cobertura (h) | G31: Valor da Hora Contratada (R$) | H31: Valor do Item após Descontos (R$) | I31: Mensal Contratado (R$)
A32: =IF(Dados!$A$12="","",Dados!$A$12) -> 1 | B32: =IF(Dados!$B$12="","",Dados!$B$12) -> Vigilante Diurno 12x36 (exemplo) | C32: =IF(Dados!$C$12="","",Dados!$C$12) -> 2 | D32: =IF(Dados!$D$12="","",Dados!$D$12) -> 5996.89 | E32: =IF(C32="","",C32*220) -> 440 | G32: =IF(C32="","",IF(C32>0,ROUNDDOWN(N(D32)/220,2),0)) -> 27.25 | H32: =IF(C32="","",IF(AND(C32>0,N(D32)>0),MAX(0,ROUNDDOWN((C32*N(D32)-G32*N(F32))/30*$F$75*$F$71,2)),0)) -> 11993.78 | I32: =IF(C32="","",ROUNDDOWN(C32*N(D32),2)) -> 11993.78
A33: =IF(Dados!$A$13="","",Dados!$A$13) | B33: =IF(Dados!$B$13="","",Dados!$B$13) | C33: =IF(Dados!$C$13="","",Dados!$C$13) | D33: =IF(Dados!$D$13="","",Dados!$D$13) | E33: =IF(C33="","",C33*220) | G33: =IF(C33="","",IF(C33>0,ROUNDDOWN(N(D33)/220,2),0)) | H33: =IF(C33="","",IF(AND(C33>0,N(D33)>0),MAX(0,ROUNDDOWN((C33*N(D33)-G33*N(F33))/30*$F$75*$F$71,2)),0)) | I33: =IF(C33="","",ROUNDDOWN(C33*N(D33),2))
A34: =IF(Dados!$A$14="","",Dados!$A$14) | B34: =IF(Dados!$B$14="","",Dados!$B$14) | C34: =IF(Dados!$C$14="","",Dados!$C$14) | D34: =IF(Dados!$D$14="","",Dados!$D$14) | E34: =IF(C34="","",C34*220) | G34: =IF(C34="","",IF(C34>0,ROUNDDOWN(N(D34)/220,2),0)) | H34: =IF(C34="","",IF(AND(C34>0,N(D34)>0),MAX(0,ROUNDDOWN((C34*N(D34)-G34*N(F34))/30*$F$75*$F$71,2)),0)) | I34: =IF(C34="","",ROUNDDOWN(C34*N(D34),2))
A35: =IF(Dados!$A$15="","",Dados!$A$15) | B35: =IF(Dados!$B$15="","",Dados!$B$15) | C35: =IF(Dados!$C$15="","",Dados!$C$15) | D35: =IF(Dados!$D$15="","",Dados!$D$15) | E35: =IF(C35="","",C35*220) | G35: =IF(C35="","",IF(C35>0,ROUNDDOWN(N(D35)/220,2),0)) | H35: =IF(C35="","",IF(AND(C35>0,N(D35)>0),MAX(0,ROUNDDOWN((C35*N(D35)-G35*N(F35))/30*$F$75*$F$71,2)),0)) | I35: =IF(C35="","",ROUNDDOWN(C35*N(D35),2))
A36: =IF(Dados!$A$16="","",Dados!$A$16) | B36: =IF(Dados!$B$16="","",Dados!$B$16) | C36: =IF(Dados!$C$16="","",Dados!$C$16) | D36: =IF(Dados!$D$16="","",Dados!$D$16) | E36: =IF(C36="","",C36*220) | G36: =IF(C36="","",IF(C36>0,ROUNDDOWN(N(D36)/220,2),0)) | H36: =IF(C36="","",IF(AND(C36>0,N(D36)>0),MAX(0,ROUNDDOWN((C36*N(D36)-G36*N(F36))/30*$F$75*$F$71,2)),0)) | I36: =IF(C36="","",ROUNDDOWN(C36*N(D36),2))
A37: =IF(Dados!$A$17="","",Dados!$A$17) | B37: =IF(Dados!$B$17="","",Dados!$B$17) | C37: =IF(Dados!$C$17="","",Dados!$C$17) | D37: =IF(Dados!$D$17="","",Dados!$D$17) | E37: =IF(C37="","",C37*220) | G37: =IF(C37="","",IF(C37>0,ROUNDDOWN(N(D37)/220,2),0)) | H37: =IF(C37="","",IF(AND(C37>0,N(D37)>0),MAX(0,ROUNDDOWN((C37*N(D37)-G37*N(F37))/30*$F$75*$F$71,2)),0)) | I37: =IF(C37="","",ROUNDDOWN(C37*N(D37),2))
A38: =IF(Dados!$A$18="","",Dados!$A$18) | B38: =IF(Dados!$B$18="","",Dados!$B$18) | C38: =IF(Dados!$C$18="","",Dados!$C$18) | D38: =IF(Dados!$D$18="","",Dados!$D$18) | E38: =IF(C38="","",C38*220) | G38: =IF(C38="","",IF(C38>0,ROUNDDOWN(N(D38)/220,2),0)) | H38: =IF(C38="","",IF(AND(C38>0,N(D38)>0),MAX(0,ROUNDDOWN((C38*N(D38)-G38*N(F38))/30*$F$75*$F$71,2)),0)) | I38: =IF(C38="","",ROUNDDOWN(C38*N(D38),2))
A39: =IF(Dados!$A$19="","",Dados!$A$19) | B39: =IF(Dados!$B$19="","",Dados!$B$19) | C39: =IF(Dados!$C$19="","",Dados!$C$19) | D39: =IF(Dados!$D$19="","",Dados!$D$19) | E39: =IF(C39="","",C39*220) | G39: =IF(C39="","",IF(C39>0,ROUNDDOWN(N(D39)/220,2),0)) | H39: =IF(C39="","",IF(AND(C39>0,N(D39)>0),MAX(0,ROUNDDOWN((C39*N(D39)-G39*N(F39))/30*$F$75*$F$71,2)),0)) | I39: =IF(C39="","",ROUNDDOWN(C39*N(D39),2))
A40: =IF(Dados!$A$20="","",Dados!$A$20) | B40: =IF(Dados!$B$20="","",Dados!$B$20) | C40: =IF(Dados!$C$20="","",Dados!$C$20) | D40: =IF(Dados!$D$20="","",Dados!$D$20) | E40: =IF(C40="","",C40*220) | G40: =IF(C40="","",IF(C40>0,ROUNDDOWN(N(D40)/220,2),0)) | H40: =IF(C40="","",IF(AND(C40>0,N(D40)>0),MAX(0,ROUNDDOWN((C40*N(D40)-G40*N(F40))/30*$F$75*$F$71,2)),0)) | I40: =IF(C40="","",ROUNDDOWN(C40*N(D40),2))
A41: =IF(Dados!$A$21="","",Dados!$A$21) | B41: =IF(Dados!$B$21="","",Dados!$B$21) | C41: =IF(Dados!$C$21="","",Dados!$C$21) | D41: =IF(Dados!$D$21="","",Dados!$D$21) | E41: =IF(C41="","",C41*220) | G41: =IF(C41="","",IF(C41>0,ROUNDDOWN(N(D41)/220,2),0)) | H41: =IF(C41="","",IF(AND(C41>0,N(D41)>0),MAX(0,ROUNDDOWN((C41*N(D41)-G41*N(F41))/30*$F$75*$F$71,2)),0)) | I41: =IF(C41="","",ROUNDDOWN(C41*N(D41),2))
A42: =IF(Dados!$A$22="","",Dados!$A$22) | B42: =IF(Dados!$B$22="","",Dados!$B$22) | C42: =IF(Dados!$C$22="","",Dados!$C$22) | D42: =IF(Dados!$D$22="","",Dados!$D$22) | E42: =IF(C42="","",C42*220) | G42: =IF(C42="","",IF(C42>0,ROUNDDOWN(N(D42)/220,2),0)) | H42: =IF(C42="","",IF(AND(C42>0,N(D42)>0),MAX(0,ROUNDDOWN((C42*N(D42)-G42*N(F42))/30*$F$75*$F$71,2)),0)) | I42: =IF(C42="","",ROUNDDOWN(C42*N(D42),2))
A43: =IF(Dados!$A$23="","",Dados!$A$23) | B43: =IF(Dados!$B$23="","",Dados!$B$23) | C43: =IF(Dados!$C$23="","",Dados!$C$23) | D43: =IF(Dados!$D$23="","",Dados!$D$23) | E43: =IF(C43="","",C43*220) | G43: =IF(C43="","",IF(C43>0,ROUNDDOWN(N(D43)/220,2),0)) | H43: =IF(C43="","",IF(AND(C43>0,N(D43)>0),MAX(0,ROUNDDOWN((C43*N(D43)-G43*N(F43))/30*$F$75*$F$71,2)),0)) | I43: =IF(C43="","",ROUNDDOWN(C43*N(D43),2))
A44: =IF(Dados!$A$24="","",Dados!$A$24) | B44: =IF(Dados!$B$24="","",Dados!$B$24) | C44: =IF(Dados!$C$24="","",Dados!$C$24) | D44: =IF(Dados!$D$24="","",Dados!$D$24) | E44: =IF(C44="","",C44*220) | G44: =IF(C44="","",IF(C44>0,ROUNDDOWN(N(D44)/220,2),0)) | H44: =IF(C44="","",IF(AND(C44>0,N(D44)>0),MAX(0,ROUNDDOWN((C44*N(D44)-G44*N(F44))/30*$F$75*$F$71,2)),0)) | I44: =IF(C44="","",ROUNDDOWN(C44*N(D44),2))
A45: =IF(Dados!$A$25="","",Dados!$A$25) | B45: =IF(Dados!$B$25="","",Dados!$B$25) | C45: =IF(Dados!$C$25="","",Dados!$C$25) | D45: =IF(Dados!$D$25="","",Dados!$D$25) | E45: =IF(C45="","",C45*220) | G45: =IF(C45="","",IF(C45>0,ROUNDDOWN(N(D45)/220,2),0)) | H45: =IF(C45="","",IF(AND(C45>0,N(D45)>0),MAX(0,ROUNDDOWN((C45*N(D45)-G45*N(F45))/30*$F$75*$F$71,2)),0)) | I45: =IF(C45="","",ROUNDDOWN(C45*N(D45),2))
A46: =IF(Dados!$A$26="","",Dados!$A$26) | B46: =IF(Dados!$B$26="","",Dados!$B$26) | C46: =IF(Dados!$C$26="","",Dados!$C$26) | D46: =IF(Dados!$D$26="","",Dados!$D$26) | E46: =IF(C46="","",C46*220) | G46: =IF(C46="","",IF(C46>0,ROUNDDOWN(N(D46)/220,2),0)) | H46: =IF(C46="","",IF(AND(C46>0,N(D46)>0),MAX(0,ROUNDDOWN((C46*N(D46)-G46*N(F46))/30*$F$75*$F$71,2)),0)) | I46: =IF(C46="","",ROUNDDOWN(C46*N(D46),2))
A47: TOTAIS | F47: =SUM(F32:F46) -> 0 | H47: =SUM(H32:H46) -> 11993.78 | I47: =SUM(I32:I46) -> 11993.78
A49: 📋 INSTRUMENTO DE COBRANÇA
A50: Item | B50: Posto | F50: Qtde Faturada | H50: Valor Unit. Faturado (R$)
A51: =IF(A32="","",A32) -> 1 | B51: =IF(B32="","",B32) -> Vigilante Diurno 12x36 (exemplo) | F51: =IF(C32="","",C32) -> 2 | H51: =IF(C32="","",IF(C32>0,ROUNDDOWN(H32/C32,2),0)) -> 5996.89
A52: =IF(A33="","",A33) | B52: =IF(B33="","",B33) | F52: =IF(C33="","",C33) | H52: =IF(C33="","",IF(C33>0,ROUNDDOWN(H33/C33,2),0))
A53: =IF(A34="","",A34) | B53: =IF(B34="","",B34) | F53: =IF(C34="","",C34) | H53: =IF(C34="","",IF(C34>0,ROUNDDOWN(H34/C34,2),0))
A54: =IF(A35="","",A35) | B54: =IF(B35="","",B35) | F54: =IF(C35="","",C35) | H54: =IF(C35="","",IF(C35>0,ROUNDDOWN(H35/C35,2),0))
A55: =IF(A36="","",A36) | B55: =IF(B36="","",B36) | F55: =IF(C36="","",C36) | H55: =IF(C36="","",IF(C36>0,ROUNDDOWN(H36/C36,2),0))
A56: =IF(A37="","",A37) | B56: =IF(B37="","",B37) | F56: =IF(C37="","",C37) | H56: =IF(C37="","",IF(C37>0,ROUNDDOWN(H37/C37,2),0))
A57: =IF(A38="","",A38) | B57: =IF(B38="","",B38) | F57: =IF(C38="","",C38) | H57: =IF(C38="","",IF(C38>0,ROUNDDOWN(H38/C38,2),0))
A58: =IF(A39="","",A39) | B58: =IF(B39="","",B39) | F58: =IF(C39="","",C39) | H58: =IF(C39="","",IF(C39>0,ROUNDDOWN(H39/C39,2),0))
A59: =IF(A40="","",A40) | B59: =IF(B40="","",B40) | F59: =IF(C40="","",C40) | H59: =IF(C40="","",IF(C40>0,ROUNDDOWN(H40/C40,2),0))
A60: =IF(A41="","",A41) | B60: =IF(B41="","",B41) | F60: =IF(C41="","",C41) | H60: =IF(C41="","",IF(C41>0,ROUNDDOWN(H41/C41,2),0))
A61: =IF(A42="","",A42) | B61: =IF(B42="","",B42) | F61: =IF(C42="","",C42) | H61: =IF(C42="","",IF(C42>0,ROUNDDOWN(H42/C42,2),0))
A62: =IF(A43="","",A43) | B62: =IF(B43="","",B43) | F62: =IF(C43="","",C43) | H62: =IF(C43="","",IF(C43>0,ROUNDDOWN(H43/C43,2),0))
... A65: =IF(A46="","",A46) | B65: =IF(B46="","",B46) | F65: =IF(C46="","",C46) | H65: =IF(C46="","",IF(C46>0,ROUNDDOWN(H46/C46,2),0))
A67: RESUMO FINANCEIRO
A68: Contratado Mensal – Total (R$) (Σ Qtde × Valor Unitário de todos os postos) | F68: =I47 -> 11993.78
A69: Nota Final Apurada | F69: =D28 -> 9
A70: Nota Atribuída pelo Avaliador (Conceito) | F70: =F28 -> A
A71: % do Faturamento a ser Liberado | F71: =INDEX(Dados!$C$50:$C$55,MATCH(D28,Dados!$A$50:$A$55,1)) -> 1
A72: Valor Glosado por QUALIDADE (R$) | F72: =ROUNDDOWN(I47-I47*$F$71,2) -> 0
A73: Número de Dias do Mês (calculado) | F73: =IF(ISNUMBER(B7),DAY(EOMONTH(B7,0)),30) -> 30
A74: Número de Dias Trabalhados no Mês | F74: =IF(ISNUMBER(B7),DAY(EOMONTH(B7,0)),30) -> 30 | H74: Campo de preenchimento: altere apenas em mês parcial (início/fim de contrato)
A75: Dias para Cálculo (mês cheio = 30 avos) | F75: =IF(N(F74)>=$F$73,30,MAX(0,N(F74))) -> 30
A76: Soma dos Itens após Descontos (R$) | F76: =H47 -> 11993.78
A77: VALOR APROVADO PARA PAGAMENTO (R$) (Σ Itens após Descontos + Total dos Reembolsos de Creche) | F77: =MAX(0,ROUNDDOWN(H47+F83,2)) -> 11993.78
A79: 🏫 REEMBOLSO DE CRECHE
A80: Valor Reembolso Creche Retido (R$) | F80: =Dados!$D30 -> 0 | H80: Campo de preenchimento
A81: Reembolsos Aprovados (quantidade) | H81: Campo de preenchimento
A82: Reembolso por dependente (R$) | F82: =Dados!$D31 -> 0 | H82: Campo de preenchimento
A83: Valor Total dos Reembolsos (R$) (Aprovados × Reembolso por dependente) | F83: =ROUNDDOWN(N(F81)*N(F82),2) -> 0
A84: Saldo de Reembolso (R$) (acumulado: saldo da aba anterior + Retido – Total) | F84: =ROUNDDOWN(P05!F84+N(F80)-N(F83),2) -> 0
A85: =IF(F84<0,"⚠ ATENÇÃO: Saldo negativo — será necessário ADITIVAR O CONTRATO PARA SUPORTAR A DESPESA!","")
A87: FAIXA DE AJUSTE DE PAGAMENTO
A88: Conceito | D88: % do Faturamento a ser Pago | G88: Nota Média Mensal Apurada
A89: =Dados!$B$55 -> A | D89: =Dados!$C$55 -> 1 | G89: =Dados!$D$55 -> Entre 9,00 e 8,10
A90: =Dados!$B$54 -> B | D90: =Dados!$C$54 -> 0.95 | G90: =Dados!$D$54 -> Entre 8,09 e 7,65
A91: =Dados!$B$53 -> C | D91: =Dados!$C$53 -> 0.9 | G91: =Dados!$D$53 -> Entre 7,64 e 6,75
A92: =Dados!$B$52 -> D | D92: =Dados!$C$52 -> 0.85 | G92: =Dados!$D$52 -> Entre 6,74 e 5,85
A93: =Dados!$B$51 -> E | D93: =Dados!$C$51 -> 0.8 | G93: =Dados!$D$51 -> Entre 5,84 e 5,40
A94: =Dados!$B$50 -> F | D94: =Dados!$C$50 -> 0.75 | G94: =Dados!$D$50 -> Abaixo de 5,40
A96: APROVAÇÃO E ASSINATURAS
A97: Fiscal Operacional | D97: Fiscal Administrativo (¹) | G97: Representante da Contratada | I97: Data da Aprovação
A100: Nome completo / Matrícula | D100: Nome completo / Matrícula | G100: Nome completo / Cargo | I100: dd/mm/aaaa
A102: 📝 JUSTIFICATIVAS (obrigatório para notas 0 e 1)
A107: =IF(COUNTIF(C13:C27,0)+COUNTIF(C13:C27,1)>0,"⚠ Existem notas 0 ou 1 nesta aba — a justificativa acima é OBRIGATÓRIA. Informe critério, nota e fundamentação.","Para cada nota 0 ou 1 informe: critério, nota atribuída e fundamentação.") -> Para cada nota 0 ou 1 informe: critério, nota atribuída e fundamentação.

Sheet P07
A1: UFRJ – PRÓ-REITORIA DE GESTÃO E GOVERNANÇA – PR6 | IMR
A2: INSTRUMENTO DE MEDIÇÃO DE RESULTADO
A3: =IF(Dados!$B$6="","",Dados!$B$6) -> Atualizado conforme Valor Unitário Contratado inicial
A5: CONTRATO Nº: | B5: =IF(Dados!$B$2="","",Dados!$B$2) -> 04/24 | E5: UNIDADE: | G5: =IF(Dados!$B$3="","",Dados!$B$3) -> CBAE
A6: CONTRATADA: | B6: =IF(Dados!$B$4="","",Dados!$B$4) -> Angels | E6: FISCAL OPERACIONAL: | G6: =IF(Dados!$B$5="","",Dados!$B$5)
A7: AVALIAÇÃO REFERENTE AO PERÍODO: | B7: =IF(Dados!$B$7="","(informe o período inicial na aba Dados)",EDATE(Dados!$B$7,6)) -> (informe o período inicial na aba Dados) | E7: PERÍODO (ABA) Nº: | G7: 7 de 60
A8: ⚠ Para notas 0 e 1 o campo JUSTIFICATIVAS (fim da aba) é de preenchimento obrigatório. | Contrato, Unidade, Contratada e Postos são compartilhados por todas as abas (aba Dados).
A10: AVALIAÇÃO DE DESEMPENHO
A11: Critério de Avaliação | B11: PESO (a) | C11: NOTA (b) (0, 1 ou 3) | D11: SUBTOTAL (c = a × b) | E11: Status | F11: Aviso de Justificativa
A12: ▶ GRUPO 1 – DESEMPENHO PROFISSIONAL
A13: =Dados!$B$36 -> Cumprimento das Atividades | B13: =Dados!$C$36 -> 0.4 | C13: 3 | D13: =B13*C13 -> 1.2 | E13: =IF(OR(C13=0,C13=1,C13=3),"✓ Ok","⛔ Inválida") -> ✓ Ok | F13: =IF(OR(C13=0,C13=1),"⚠ Favor inserir justificativa da nota "&C13&" no campo JUSTIFICATIVAS","")
A14: =Dados!$B$37 -> Qualificação / Atendimento ao Público / Postura | B14: =Dados!$C$37 -> 0.35 | C14: 3 | D14: =B14*C14 -> 1.05 | E14: =IF(OR(C14=0,C14=1,C14=3),"✓ Ok","⛔ Inválida") -> ✓ Ok | F14: =IF(OR(C14=0,C14=1),"⚠ Favor inserir justificativa da nota "&C14&" no campo JUSTIFICATIVAS","")
A15: =Dados!$B$38 -> Uniformes e Identificação | B15: =Dados!$C$38 -> 0.25 | C15: 3 | D15: =B15*C15 -> 0.75 | E15: =IF(OR(C15=0,C15=1,C15=3),"✓ Ok","⛔ Inválida") -> ✓ Ok | F15: =IF(OR(C15=0,C15=1),"⚠ Favor inserir justificativa da nota "&C15&" no campo JUSTIFICATIVAS","")
A16: TOTAL GRUPO 1 | B16: =SUM(B13:B15) -> 1 | D16: =SUM(D13:D15) -> 3
A17: ▶ GRUPO 2 – DESEMPENHO DAS ATIVIDADES
A18: =Dados!$B$39 -> Especificação Técnica dos Serviços | B18: =Dados!$C$39 -> 0.4 | C18: 3 | D18: =B18*C18 -> 1.2 | E18: =IF(OR(C18=0,C18=1,C18=3),"✓ Ok","⛔ Inválida") -> ✓ Ok | F18: =IF(OR(C18=0,C18=1),"⚠ Favor inserir justificativa da nota "&C18&" no campo JUSTIFICATIVAS","")
A19: =Dados!$B$40 -> Equipamentos e Acessórios | B19: =Dados!$C$40 -> 0.2 | C19: 3 | D19: =B19*C19 -> 0.6 | E19: =IF(OR(C19=0,C19=1,C19=3),"✓ Ok","⛔ Inválida") -> ✓ Ok | F19: =IF(OR(C19=0,C19=1),"⚠ Favor inserir justificativa da nota "&C19&" no campo JUSTIFICATIVAS","")
A20: =Dados!$B$41 -> Atendimento às Ocorrências | B20: =Dados!$C$41 -> 0.4 | C20: 3 | D20: =B20*C20 -> 1.2 | E20: =IF(OR(C20=0,C20=1,C20=3),"✓ Ok","⛔ Inválida") -> ✓ Ok | F20: =IF(OR(C20=0,C20=1),"⚠ Favor inserir justificativa da nota "&C20&" no campo JUSTIFICATIVAS","")
A21: TOTAL GRUPO 2 | B21: =SUM(B18:B20) -> 1 | D21: =SUM(D18:D20) -> 3
A22: ▶ GRUPO 3 – GERENCIAMENTO
A23: =Dados!$B$42 -> Periodicidade da Supervisão | B23: =Dados!$C$42 -> 0.2 | C23: 3 | D23: =B23*C23 -> 0.6 | E23: =IF(OR(C23=0,C23=1,C23=3),"✓ Ok","⛔ Inválida") -> ✓ Ok | F23: =IF(OR(C23=0,C23=1),"⚠ Favor inserir justificativa da nota "&C23&" no campo JUSTIFICATIVAS","")
A24: =Dados!$B$43 -> Gerenciamento das Atividades Operacionais | B24: =Dados!$C$43 -> 0.3 | C24: 3 | D24: =B24*C24 -> 0.9 | E24: =IF(OR(C24=0,C24=1,C24=3),"✓ Ok","⛔ Inválida") -> ✓ Ok | F24: =IF(OR(C24=0,C24=1),"⚠ Favor inserir justificativa da nota "&C24&" no campo JUSTIFICATIVAS","")
A25: =Dados!$B$44 -> Atendimento às Solicitações | B25: =Dados!$C$44 -> 0.25 | C25: 3 | D25: =B25*C25 -> 0.75 | E25: =IF(OR(C25=0,C25=1,C25=3),"✓ Ok","⛔ Inválida") -> ✓ Ok | F25: =IF(OR(C25=0,C25=1),"⚠ Favor inserir justificativa da nota "&C25&" no campo JUSTIFICATIVAS","")
A26: =Dados!$B$45 -> Salários, Benefícios e Obrigações Trabalhistas (¹ Fiscal Adm.) | B26: =Dados!$C$45 -> 0.25 | C26: 3 | D26: =B26*C26 -> 0.75 | E26: =IF(OR(C26=0,C26=1,C26=3),"✓ Ok","⛔ Inválida") -> ✓ Ok | F26: =IF(OR(C26=0,C26=1),"⚠ Favor inserir justificativa da nota "&C26&" no campo JUSTIFICATIVAS","")
A27: TOTAL GRUPO 3 | B27: =SUM(B23:B26) -> 1 | D27: =SUM(D23:D26) -> 3
A28: NOTA FINAL (somatório dos Grupos 1, 2 e 3) | D28: =D16+D21+D27 -> 9 | E28: Conceito: | F28: =INDEX(Dados!$B$50:$B$55,MATCH(D28,Dados!$A$50:$A$55,1)) -> A | G28: (¹) Grupo 3 – Salários/Benefícios/Obrigações Trabalhistas: preenchido pelo Fiscal Administrativo
A30: POSTOS DE TRABALHO
A31: Item | B31: POSTO | C31: Qtde Contratada | D31: Valor Unit. Contratado (R$) | E31: Horas Contratadas | F31: Sem Cobertura (h) | G31: Valor da Hora Contratada (R$) | H31: Valor do Item após Descontos (R$) | I31: Mensal Contratado (R$)
A32: =IF(Dados!$A$12="","",Dados!$A$12) -> 1 | B32: =IF(Dados!$B$12="","",Dados!$B$12) -> Vigilante Diurno 12x36 (exemplo) | C32: =IF(Dados!$C$12="","",Dados!$C$12) -> 2 | D32: =IF(Dados!$D$12="","",Dados!$D$12) -> 5996.89 | E32: =IF(C32="","",C32*220) -> 440 | G32: =IF(C32="","",IF(C32>0,ROUNDDOWN(N(D32)/220,2),0)) -> 27.25 | H32: =IF(C32="","",IF(AND(C32>0,N(D32)>0),MAX(0,ROUNDDOWN((C32*N(D32)-G32*N(F32))/30*$F$75*$F$71,2)),0)) -> 11993.78 | I32: =IF(C32="","",ROUNDDOWN(C32*N(D32),2)) -> 11993.78
A33: =IF(Dados!$A$13="","",Dados!$A$13) | B33: =IF(Dados!$B$13="","",Dados!$B$13) | C33: =IF(Dados!$C$13="","",Dados!$C$13) | D33: =IF(Dados!$D$13="","",Dados!$D$13) | E33: =IF(C33="","",C33*220) | G33: =IF(C33="","",IF(C33>0,ROUNDDOWN(N(D33)/220,2),0)) | H33: =IF(C33="","",IF(AND(C33>0,N(D33)>0),MAX(0,ROUNDDOWN((C33*N(D33)-G33*N(F33))/30*$F$75*$F$71,2)),0)) | I33: =IF(C33="","",ROUNDDOWN(C33*N(D33),2))
A34: =IF(Dados!$A$14="","",Dados!$A$14) | B34: =IF(Dados!$B$14="","",Dados!$B$14) | C34: =IF(Dados!$C$14="","",Dados!$C$14) | D34: =IF(Dados!$D$14="","",Dados!$D$14) | E34: =IF(C34="","",C34*220) | G34: =IF(C34="","",IF(C34>0,ROUNDDOWN(N(D34)/220,2),0)) | H34: =IF(C34="","",IF(AND(C34>0,N(D34)>0),MAX(0,ROUNDDOWN((C34*N(D34)-G34*N(F34))/30*$F$75*$F$71,2)),0)) | I34: =IF(C34="","",ROUNDDOWN(C34*N(D34),2))
A35: =IF(Dados!$A$15="","",Dados!$A$15) | B35: =IF(Dados!$B$15="","",Dados!$B$15) | C35: =IF(Dados!$C$15="","",Dados!$C$15) | D35: =IF(Dados!$D$15="","",Dados!$D$15) | E35: =IF(C35="","",C35*220) | G35: =IF(C35="","",IF(C35>0,ROUNDDOWN(N(D35)/220,2),0)) | H35: =IF(C35="","",IF(AND(C35>0,N(D35)>0),MAX(0,ROUNDDOWN((C35*N(D35)-G35*N(F35))/30*$F$75*$F$71,2)),0)) | I35: =IF(C35="","",ROUNDDOWN(C35*N(D35),2))
A36: =IF(Dados!$A$16="","",Dados!$A$16) | B36: =IF(Dados!$B$16="","",Dados!$B$16) | C36: =IF(Dados!$C$16="","",Dados!$C$16) | D36: =IF(Dados!$D$16="","",Dados!$D$16) | E36: =IF(C36="","",C36*220) | G36: =IF(C36="","",IF(C36>0,ROUNDDOWN(N(D36)/220,2),0)) | H36: =IF(C36="","",IF(AND(C36>0,N(D36)>0),MAX(0,ROUNDDOWN((C36*N(D36)-G36*N(F36))/30*$F$75*$F$71,2)),0)) | I36: =IF(C36="","",ROUNDDOWN(C36*N(D36),2))
A37: =IF(Dados!$A$17="","",Dados!$A$17) | B37: =IF(Dados!$B$17="","",Dados!$B$17) | C37: =IF(Dados!$C$17="","",Dados!$C$17) | D37: =IF(Dados!$D$17="","",Dados!$D$17) | E37: =IF(C37="","",C37*220) | G37: =IF(C37="","",IF(C37>0,ROUNDDOWN(N(D37)/220,2),0)) | H37: =IF(C37="","",IF(AND(C37>0,N(D37)>0),MAX(0,ROUNDDOWN((C37*N(D37)-G37*N(F37))/30*$F$75*$F$71,2)),0)) | I37: =IF(C37="","",ROUNDDOWN(C37*N(D37),2))
A38: =IF(Dados!$A$18="","",Dados!$A$18) | B38: =IF(Dados!$B$18="","",Dados!$B$18) | C38: =IF(Dados!$C$18="","",Dados!$C$18) | D38: =IF(Dados!$D$18="","",Dados!$D$18) | E38: =IF(C38="","",C38*220) | G38: =IF(C38="","",IF(C38>0,ROUNDDOWN(N(D38)/220,2),0)) | H38: =IF(C38="","",IF(AND(C38>0,N(D38)>0),MAX(0,ROUNDDOWN((C38*N(D38)-G38*N(F38))/30*$F$75*$F$71,2)),0)) | I38: =IF(C38="","",ROUNDDOWN(C38*N(D38),2))
A39: =IF(Dados!$A$19="","",Dados!$A$19) | B39: =IF(Dados!$B$19="","",Dados!$B$19) | C39: =IF(Dados!$C$19="","",Dados!$C$19) | D39: =IF(Dados!$D$19="","",Dados!$D$19) | E39: =IF(C39="","",C39*220) | G39: =IF(C39="","",IF(C39>0,ROUNDDOWN(N(D39)/220,2),0)) | H39: =IF(C39="","",IF(AND(C39>0,N(D39)>0),MAX(0,ROUNDDOWN((C39*N(D39)-G39*N(F39))/30*$F$75*$F$71,2)),0)) | I39: =IF(C39="","",ROUNDDOWN(C39*N(D39),2))
A40: =IF(Dados!$A$20="","",Dados!$A$20) | B40: =IF(Dados!$B$20="","",Dados!$B$20) | C40: =IF(Dados!$C$20="","",Dados!$C$20) | D40: =IF(Dados!$D$20="","",Dados!$D$20) | E40: =IF(C40="","",C40*220) | G40: =IF(C40="","",IF(C40>0,ROUNDDOWN(N(D40)/220,2),0)) | H40: =IF(C40="","",IF(AND(C40>0,N(D40)>0),MAX(0,ROUNDDOWN((C40*N(D40)-G40*N(F40))/30*$F$75*$F$71,2)),0)) | I40: =IF(C40="","",ROUNDDOWN(C40*N(D40),2))
A41: =IF(Dados!$A$21="","",Dados!$A$21) | B41: =IF(Dados!$B$21="","",Dados!$B$21) | C41: =IF(Dados!$C$21="","",Dados!$C$21) | D41: =IF(Dados!$D$21="","",Dados!$D$21) | E41: =IF(C41="","",C41*220) | G41: =IF(C41="","",IF(C41>0,ROUNDDOWN(N(D41)/220,2),0)) | H41: =IF(C41="","",IF(AND(C41>0,N(D41)>0),MAX(0,ROUNDDOWN((C41*N(D41)-G41*N(F41))/30*$F$75*$F$71,2)),0)) | I41: =IF(C41="","",ROUNDDOWN(C41*N(D41),2))
A42: =IF(Dados!$A$22="","",Dados!$A$22) | B42: =IF(Dados!$B$22="","",Dados!$B$22) | C42: =IF(Dados!$C$22="","",Dados!$C$22) | D42: =IF(Dados!$D$22="","",Dados!$D$22) | E42: =IF(C42="","",C42*220) | G42: =IF(C42="","",IF(C42>0,ROUNDDOWN(N(D42)/220,2),0)) | H42: =IF(C42="","",IF(AND(C42>0,N(D42)>0),MAX(0,ROUNDDOWN((C42*N(D42)-G42*N(F42))/30*$F$75*$F$71,2)),0)) | I42: =IF(C42="","",ROUNDDOWN(C42*N(D42),2))
A43: =IF(Dados!$A$23="","",Dados!$A$23) | B43: =IF(Dados!$B$23="","",Dados!$B$23) | C43: =IF(Dados!$C$23="","",Dados!$C$23) | D43: =IF(Dados!$D$23="","",Dados!$D$23) | E43: =IF(C43="","",C43*220) | G43: =IF(C43="","",IF(C43>0,ROUNDDOWN(N(D43)/220,2),0)) | H43: =IF(C43="","",IF(AND(C43>0,N(D43)>0),MAX(0,ROUNDDOWN((C43*N(D43)-G43*N(F43))/30*$F$75*$F$71,2)),0)) | I43: =IF(C43="","",ROUNDDOWN(C43*N(D43),2))
A44: =IF(Dados!$A$24="","",Dados!$A$24) | B44: =IF(Dados!$B$24="","",Dados!$B$24) | C44: =IF(Dados!$C$24="","",Dados!$C$24) | D44: =IF(Dados!$D$24="","",Dados!$D$24) | E44: =IF(C44="","",C44*220) | G44: =IF(C44="","",IF(C44>0,ROUNDDOWN(N(D44)/220,2),0)) | H44: =IF(C44="","",IF(AND(C44>0,N(D44)>0),MAX(0,ROUNDDOWN((C44*N(D44)-G44*N(F44))/30*$F$75*$F$71,2)),0)) | I44: =IF(C44="","",ROUNDDOWN(C44*N(D44),2))
A45: =IF(Dados!$A$25="","",Dados!$A$25) | B45: =IF(Dados!$B$25="","",Dados!$B$25) | C45: =IF(Dados!$C$25="","",Dados!$C$25) | D45: =IF(Dados!$D$25="","",Dados!$D$25) | E45: =IF(C45="","",C45*220) | G45: =IF(C45="","",IF(C45>0,ROUNDDOWN(N(D45)/220,2),0)) | H45: =IF(C45="","",IF(AND(C45>0,N(D45)>0),MAX(0,ROUNDDOWN((C45*N(D45)-G45*N(F45))/30*$F$75*$F$71,2)),0)) | I45: =IF(C45="","",ROUNDDOWN(C45*N(D45),2))
A46: =IF(Dados!$A$26="","",Dados!$A$26) | B46: =IF(Dados!$B$26="","",Dados!$B$26) | C46: =IF(Dados!$C$26="","",Dados!$C$26) | D46: =IF(Dados!$D$26="","",Dados!$D$26) | E46: =IF(C46="","",C46*220) | G46: =IF(C46="","",IF(C46>0,ROUNDDOWN(N(D46)/220,2),0)) | H46: =IF(C46="","",IF(AND(C46>0,N(D46)>0),MAX(0,ROUNDDOWN((C46*N(D46)-G46*N(F46))/30*$F$75*$F$71,2)),0)) | I46: =IF(C46="","",ROUNDDOWN(C46*N(D46),2))
A47: TOTAIS | F47: =SUM(F32:F46) -> 0 | H47: =SUM(H32:H46) -> 11993.78 | I47: =SUM(I32:I46) -> 11993.78
A49: 📋 INSTRUMENTO DE COBRANÇA
A50: Item | B50: Posto | F50: Qtde Faturada | H50: Valor Unit. Faturado (R$)
A51: =IF(A32="","",A32) -> 1 | B51: =IF(B32="","",B32) -> Vigilante Diurno 12x36 (exemplo) | F51: =IF(C32="","",C32) -> 2 | H51: =IF(C32="","",IF(C32>0,ROUNDDOWN(H32/C32,2),0)) -> 5996.89
A52: =IF(A33="","",A33) | B52: =IF(B33="","",B33) | F52: =IF(C33="","",C33) | H52: =IF(C33="","",IF(C33>0,ROUNDDOWN(H33/C33,2),0))
A53: =IF(A34="","",A34) | B53: =IF(B34="","",B34) | F53: =IF(C34="","",C34) | H53: =IF(C34="","",IF(C34>0,ROUNDDOWN(H34/C34,2),0))
A54: =IF(A35="","",A35) | B54: =IF(B35="","",B35) | F54: =IF(C35="","",C35) | H54: =IF(C35="","",IF(C35>0,ROUNDDOWN(H35/C35,2),0))
A55: =IF(A36="","",A36) | B55: =IF(B36="","",B36) | F55: =IF(C36="","",C36) | H55: =IF(C36="","",IF(C36>0,ROUNDDOWN(H36/C36,2),0))
A56: =IF(A37="","",A37) | B56: =IF(B37="","",B37) | F56: =IF(C37="","",C37) | H56: =IF(C37="","",IF(C37>0,ROUNDDOWN(H37/C37,2),0))
A57: =IF(A38="","",A38) | B57: =IF(B38="","",B38) | F57: =IF(C38="","",C38) | H57: =IF(C38="","",IF(C38>0,ROUNDDOWN(H38/C38,2),0))
A58: =IF(A39="","",A39) | B58: =IF(B39="","",B39) | F58: =IF(C39="","",C39) | H58: =IF(C39="","",IF(C39>0,ROUNDDOWN(H39/C39,2),0))
A59: =IF(A40="","",A40) | B59: =IF(B40="","",B40) | F59: =IF(C40="","",C40) | H59: =IF(C40="","",IF(C40>0,ROUNDDOWN(H40/C40,2),0))
A60: =IF(A41="","",A41) | B60: =IF(B41="","",B41) | F60: =IF(C41="","",C41) | H60: =IF(C41="","",IF(C41>0,ROUNDDOWN(H41/C41,2),0))
A61: =IF(A42="","",A42) | B61: =IF(B42="","",B42) | F61: =IF(C42="","",C42) | H61: =IF(C42="","",IF(C42>0,ROUNDDOWN(H42/C42,2),0))
A62: =IF(A43="","",A43) | B62: =IF(B43="","",B43) | F62: =IF(C43="","",C43) | H62: =IF(C43="","",IF(C43>0,ROUNDDOWN(H43/C43,2),0))
... A65: =IF(A46="","",A46) | B65: =IF(B46="","",B46) | F65: =IF(C46="","",C46) | H65: =IF(C46="","",IF(C46>0,ROUNDDOWN(H46/C46,2),0))
A67: RESUMO FINANCEIRO
A68: Contratado Mensal – Total (R$) (Σ Qtde × Valor Unitário de todos os postos) | F68: =I47 -> 11993.78
A69: Nota Final Apurada | F69: =D28 -> 9
A70: Nota Atribuída pelo Avaliador (Conceito) | F70: =F28 -> A
A71: % do Faturamento a ser Liberado | F71: =INDEX(Dados!$C$50:$C$55,MATCH(D28,Dados!$A$50:$A$55,1)) -> 1
A72: Valor Glosado por QUALIDADE (R$) | F72: =ROUNDDOWN(I47-I47*$F$71,2) -> 0
A73: Número de Dias do Mês (calculado) | F73: =IF(ISNUMBER(B7),DAY(EOMONTH(B7,0)),30) -> 30
A74: Número de Dias Trabalhados no Mês | F74: =IF(ISNUMBER(B7),DAY(EOMONTH(B7,0)),30) -> 30 | H74: Campo de preenchimento: altere apenas em mês parcial (início/fim de contrato)
A75: Dias para Cálculo (mês cheio = 30 avos) | F75: =IF(N(F74)>=$F$73,30,MAX(0,N(F74))) -> 30
A76: Soma dos Itens após Descontos (R$) | F76: =H47 -> 11993.78
A77: VALOR APROVADO PARA PAGAMENTO (R$) (Σ Itens após Descontos + Total dos Reembolsos de Creche) | F77: =MAX(0,ROUNDDOWN(H47+F83,2)) -> 11993.78
A79: 🏫 REEMBOLSO DE CRECHE
A80: Valor Reembolso Creche Retido (R$) | F80: =Dados!$D30 -> 0 | H80: Campo de preenchimento
A81: Reembolsos Aprovados (quantidade) | H81: Campo de preenchimento
A82: Reembolso por dependente (R$) | F82: =Dados!$D31 -> 0 | H82: Campo de preenchimento
A83: Valor Total dos Reembolsos (R$) (Aprovados × Reembolso por dependente) | F83: =ROUNDDOWN(N(F81)*N(F82),2) -> 0
A84: Saldo de Reembolso (R$) (acumulado: saldo da aba anterior + Retido – Total) | F84: =ROUNDDOWN(P06!F84+N(F80)-N(F83),2) -> 0
A85: =IF(F84<0,"⚠ ATENÇÃO: Saldo negativo — será necessário ADITIVAR O CONTRATO PARA SUPORTAR A DESPESA!","")
A87: FAIXA DE AJUSTE DE PAGAMENTO
A88: Conceito | D88: % do Faturamento a ser Pago | G88: Nota Média Mensal Apurada
A89: =Dados!$B$55 -> A | D89: =Dados!$C$55 -> 1 | G89: =Dados!$D$55 -> Entre 9,00 e 8,10
A90: =Dados!$B$54 -> B | D90: =Dados!$C$54 -> 0.95 | G90: =Dados!$D$54 -> Entre 8,09 e 7,65
A91: =Dados!$B$53 -> C | D91: =Dados!$C$53 -> 0.9 | G91: =Dados!$D$53 -> Entre 7,64 e 6,75
A92: =Dados!$B$52 -> D | D92: =Dados!$C$52 -> 0.85 | G92: =Dados!$D$52 -> Entre 6,74 e 5,85
A93: =Dados!$B$51 -> E | D93: =Dados!$C$51 -> 0.8 | G93: =Dados!$D$51 -> Entre 5,84 e 5,40
A94: =Dados!$B$50 -> F | D94: =Dados!$C$50 -> 0.75 | G94: =Dados!$D$50 -> Abaixo de 5,40
A96: APROVAÇÃO E ASSINATURAS
A97: Fiscal Operacional | D97: Fiscal Administrativo (¹) | G97: Representante da Contratada | I97: Data da Aprovação
A100: Nome completo / Matrícula | D100: Nome completo / Matrícula | G100: Nome completo / Cargo | I100: dd/mm/aaaa
A102: 📝 JUSTIFICATIVAS (obrigatório para notas 0 e 1)
A107: =IF(COUNTIF(C13:C27,0)+COUNTIF(C13:C27,1)>0,"⚠ Existem notas 0 ou 1 nesta aba — a justificativa acima é OBRIGATÓRIA. Informe critério, nota e fundamentação.","Para cada nota 0 ou 1 informe: critério, nota atribuída e fundamentação.") -> Para cada nota 0 ou 1 informe: critério, nota atribuída e fundamentação.

Sheet P08
A1: UFRJ – PRÓ-REITORIA DE GESTÃO E GOVERNANÇA – PR6 | IMR
A2: INSTRUMENTO DE MEDIÇÃO DE RESULTADO
A3: =IF(Dados!$B$6="","",Dados!$B$6) -> Atualizado conforme Valor Unitário Contratado inicial
A5: CONTRATO Nº: | B5: =IF(Dados!$B$2="","",Dados!$B$2) -> 04/24 | E5: UNIDADE: | G5: =IF(Dados!$B$3="","",Dados!$B$3) -> CBAE
A6: CONTRATADA: | B6: =IF(Dados!$B$4="","",Dados!$B$4) -> Angels | E6: FISCAL OPERACIONAL: | G6: =IF(Dados!$B$5="","",Dados!$B$5)
A7: AVALIAÇÃO REFERENTE AO PERÍODO: | B7: =IF(Dados!$B$7="","(informe o período inicial na aba Dados)",EDATE(Dados!$B$7,7)) -> (informe o período inicial na aba Dados) | E7: PERÍODO (ABA) Nº: | G7: 8 de 60
A8: ⚠ Para notas 0 e 1 o campo JUSTIFICATIVAS (fim da aba) é de preenchimento obrigatório. | Contrato, Unidade, Contratada e Postos são compartilhados por todas as abas (aba Dados).
A10: AVALIAÇÃO DE DESEMPENHO
A11: Critério de Avaliação | B11: PESO (a) | C11: NOTA (b) (0, 1 ou 3) | D11: SUBTOTAL (c = a × b) | E11: Status | F11: Aviso de Justificativa
A12: ▶ GRUPO 1 – DESEMPENHO PROFISSIONAL
A13: =Dados!$B$36 -> Cumprimento das Atividades | B13: =Dados!$C$36 -> 0.4 | C13: 3 | D13: =B13*C13 -> 1.2 | E13: =IF(OR(C13=0,C13=1,C13=3),"✓ Ok","⛔ Inválida") -> ✓ Ok | F13: =IF(OR(C13=0,C13=1),"⚠ Favor inserir justificativa da nota "&C13&" no campo JUSTIFICATIVAS","")
A14: =Dados!$B$37 -> Qualificação / Atendimento ao Público / Postura | B14: =Dados!$C$37 -> 0.35 | C14: 3 | D14: =B14*C14 -> 1.05 | E14: =IF(OR(C14=0,C14=1,C14=3),"✓ Ok","⛔ Inválida") -> ✓ Ok | F14: =IF(OR(C14=0,C14=1),"⚠ Favor inserir justificativa da nota "&C14&" no campo JUSTIFICATIVAS","")
A15: =Dados!$B$38 -> Uniformes e Identificação | B15: =Dados!$C$38 -> 0.25 | C15: 3 | D15: =B15*C15 -> 0.75 | E15: =IF(OR(C15=0,C15=1,C15=3),"✓ Ok","⛔ Inválida") -> ✓ Ok | F15: =IF(OR(C15=0,C15=1),"⚠ Favor inserir justificativa da nota "&C15&" no campo JUSTIFICATIVAS","")
A16: TOTAL GRUPO 1 | B16: =SUM(B13:B15) -> 1 | D16: =SUM(D13:D15) -> 3
A17: ▶ GRUPO 2 – DESEMPENHO DAS ATIVIDADES
A18: =Dados!$B$39 -> Especificação Técnica dos Serviços | B18: =Dados!$C$39 -> 0.4 | C18: 3 | D18: =B18*C18 -> 1.2 | E18: =IF(OR(C18=0,C18=1,C18=3),"✓ Ok","⛔ Inválida") -> ✓ Ok | F18: =IF(OR(C18=0,C18=1),"⚠ Favor inserir justificativa da nota "&C18&" no campo JUSTIFICATIVAS","")
A19: =Dados!$B$40 -> Equipamentos e Acessórios | B19: =Dados!$C$40 -> 0.2 | C19: 3 | D19: =B19*C19 -> 0.6 | E19: =IF(OR(C19=0,C19=1,C19=3),"✓ Ok","⛔ Inválida") -> ✓ Ok | F19: =IF(OR(C19=0,C19=1),"⚠ Favor inserir justificativa da nota "&C19&" no campo JUSTIFICATIVAS","")
A20: =Dados!$B$41 -> Atendimento às Ocorrências | B20: =Dados!$C$41 -> 0.4 | C20: 3 | D20: =B20*C20 -> 1.2 | E20: =IF(OR(C20=0,C20=1,C20=3),"✓ Ok","⛔ Inválida") -> ✓ Ok | F20: =IF(OR(C20=0,C20=1),"⚠ Favor inserir justificativa da nota "&C20&" no campo JUSTIFICATIVAS","")
A21: TOTAL GRUPO 2 | B21: =SUM(B18:B20) -> 1 | D21: =SUM(D18:D20) -> 3
A22: ▶ GRUPO 3 – GERENCIAMENTO
A23: =Dados!$B$42 -> Periodicidade da Supervisão | B23: =Dados!$C$42 -> 0.2 | C23: 3 | D23: =B23*C23 -> 0.6 | E23: =IF(OR(C23=0,C23=1,C23=3),"✓ Ok","⛔ Inválida") -> ✓ Ok | F23: =IF(OR(C23=0,C23=1),"⚠ Favor inserir justificativa da nota "&C23&" no campo JUSTIFICATIVAS","")
A24: =Dados!$B$43 -> Gerenciamento das Atividades Operacionais | B24: =Dados!$C$43 -> 0.3 | C24: 3 | D24: =B24*C24 -> 0.9 | E24: =IF(OR(C24=0,C24=1,C24=3),"✓ Ok","⛔ Inválida") -> ✓ Ok | F24: =IF(OR(C24=0,C24=1),"⚠ Favor inserir justificativa da nota "&C24&" no campo JUSTIFICATIVAS","")
A25: =Dados!$B$44 -> Atendimento às Solicitações | B25: =Dados!$C$44 -> 0.25 | C25: 3 | D25: =B25*C25 -> 0.75 | E25: =IF(OR(C25=0,C25=1,C25=3),"✓ Ok","⛔ Inválida") -> ✓ Ok | F25: =IF(OR(C25=0,C25=1),"⚠ Favor inserir justificativa da nota "&C25&" no campo JUSTIFICATIVAS","")
A26: =Dados!$B$45 -> Salários, Benefícios e Obrigações Trabalhistas (¹ Fiscal Adm.) | B26: =Dados!$C$45 -> 0.25 | C26: 3 | D26: =B26*C26 -> 0.75 | E26: =IF(OR(C26=0,C26=1,C26=3),"✓ Ok","⛔ Inválida") -> ✓ Ok | F26: =IF(OR(C26=0,C26=1),"⚠ Favor inserir justificativa da nota "&C26&" no campo JUSTIFICATIVAS","")
A27: TOTAL GRUPO 3 | B27: =SUM(B23:B26) -> 1 | D27: =SUM(D23:D26) -> 3
A28: NOTA FINAL (somatório dos Grupos 1, 2 e 3) | D28: =D16+D21+D27 -> 9 | E28: Conceito: | F28: =INDEX(Dados!$B$50:$B$55,MATCH(D28,Dados!$A$50:$A$55,1)) -> A | G28: (¹) Grupo 3 – Salários/Benefícios/Obrigações Trabalhistas: preenchido pelo Fiscal Administrativo
A30: POSTOS DE TRABALHO
A31: Item | B31: POSTO | C31: Qtde Contratada | D31: Valor Unit. Contratado (R$) | E31: Horas Contratadas | F31: Sem Cobertura (h) | G31: Valor da Hora Contratada (R$) | H31: Valor do Item após Descontos (R$) | I31: Mensal Contratado (R$)
A32: =IF(Dados!$A$12="","",Dados!$A$12) -> 1 | B32: =IF(Dados!$B$12="","",Dados!$B$12) -> Vigilante Diurno 12x36 (exemplo) | C32: =IF(Dados!$C$12="","",Dados!$C$12) -> 2 | D32: =IF(Dados!$D$12="","",Dados!$D$12) -> 5996.89 | E32: =IF(C32="","",C32*220) -> 440 | G32: =IF(C32="","",IF(C32>0,ROUNDDOWN(N(D32)/220,2),0)) -> 27.25 | H32: =IF(C32="","",IF(AND(C32>0,N(D32)>0),MAX(0,ROUNDDOWN((C32*N(D32)-G32*N(F32))/30*$F$75*$F$71,2)),0)) -> 11993.78 | I32: =IF(C32="","",ROUNDDOWN(C32*N(D32),2)) -> 11993.78
A33: =IF(Dados!$A$13="","",Dados!$A$13) | B33: =IF(Dados!$B$13="","",Dados!$B$13) | C33: =IF(Dados!$C$13="","",Dados!$C$13) | D33: =IF(Dados!$D$13="","",Dados!$D$13) | E33: =IF(C33="","",C33*220) | G33: =IF(C33="","",IF(C33>0,ROUNDDOWN(N(D33)/220,2),0)) | H33: =IF(C33="","",IF(AND(C33>0,N(D33)>0),MAX(0,ROUNDDOWN((C33*N(D33)-G33*N(F33))/30*$F$75*$F$71,2)),0)) | I33: =IF(C33="","",ROUNDDOWN(C33*N(D33),2))
A34: =IF(Dados!$A$14="","",Dados!$A$14) | B34: =IF(Dados!$B$14="","",Dados!$B$14) | C34: =IF(Dados!$C$14="","",Dados!$C$14) | D34: =IF(Dados!$D$14="","",Dados!$D$14) | E34: =IF(C34="","",C34*220) | G34: =IF(C34="","",IF(C34>0,ROUNDDOWN(N(D34)/220,2),0)) | H34: =IF(C34="","",IF(AND(C34>0,N(D34)>0),MAX(0,ROUNDDOWN((C34*N(D34)-G34*N(F34))/30*$F$75*$F$71,2)),0)) | I34: =IF(C34="","",ROUNDDOWN(C34*N(D34),2))
A35: =IF(Dados!$A$15="","",Dados!$A$15) | B35: =IF(Dados!$B$15="","",Dados!$B$15) | C35: =IF(Dados!$C$15="","",Dados!$C$15) | D35: =IF(Dados!$D$15="","",Dados!$D$15) | E35: =IF(C35="","",C35*220) | G35: =IF(C35="","",IF(C35>0,ROUNDDOWN(N(D35)/220,2),0)) | H35: =IF(C35="","",IF(AND(C35>0,N(D35)>0),MAX(0,ROUNDDOWN((C35*N(D35)-G35*N(F35))/30*$F$75*$F$71,2)),0)) | I35: =IF(C35="","",ROUNDDOWN(C35*N(D35),2))
A36: =IF(Dados!$A$16="","",Dados!$A$16) | B36: =IF(Dados!$B$16="","",Dados!$B$16) | C36: =IF(Dados!$C$16="","",Dados!$C$16) | D36: =IF(Dados!$D$16="","",Dados!$D$16) | E36: =IF(C36="","",C36*220) | G36: =IF(C36="","",IF(C36>0,ROUNDDOWN(N(D36)/220,2),0)) | H36: =IF(C36="","",IF(AND(C36>0,N(D36)>0),MAX(0,ROUNDDOWN((C36*N(D36)-G36*N(F36))/30*$F$75*$F$71,2)),0)) | I36: =IF(C36="","",ROUNDDOWN(C36*N(D36),2))
A37: =IF(Dados!$A$17="","",Dados!$A$17) | B37: =IF(Dados!$B$17="","",Dados!$B$17) | C37: =IF(Dados!$C$17="","",Dados!$C$17) | D37: =IF(Dados!$D$17="","",Dados!$D$17) | E37: =IF(C37="","",C37*220) | G37: =IF(C37="","",IF(C37>0,ROUNDDOWN(N(D37)/220,2),0)) | H37: =IF(C37="","",IF(AND(C37>0,N(D37)>0),MAX(0,ROUNDDOWN((C37*N(D37)-G37*N(F37))/30*$F$75*$F$71,2)),0)) | I37: =IF(C37="","",ROUNDDOWN(C37*N(D37),2))
A38: =IF(Dados!$A$18="","",Dados!$A$18) | B38: =IF(Dados!$B$18="","",Dados!$B$18) | C38: =IF(Dados!$C$18="","",Dados!$C$18) | D38: =IF(Dados!$D$18="","",Dados!$D$18) | E38: =IF(C38="","",C38*220) | G38: =IF(C38="","",IF(C38>0,ROUNDDOWN(N(D38)/220,2),0)) | H38: =IF(C38="","",IF(AND(C38>0,N(D38)>0),MAX(0,ROUNDDOWN((C38*N(D38)-G38*N(F38))/30*$F$75*$F$71,2)),0)) | I38: =IF(C38="","",ROUNDDOWN(C38*N(D38),2))
A39: =IF(Dados!$A$19="","",Dados!$A$19) | B39: =IF(Dados!$B$19="","",Dados!$B$19) | C39: =IF(Dados!$C$19="","",Dados!$C$19) | D39: =IF(Dados!$D$19="","",Dados!$D$19) | E39: =IF(C39="","",C39*220) | G39: =IF(C39="","",IF(C39>0,ROUNDDOWN(N(D39)/220,2),0)) | H39: =IF(C39="","",IF(AND(C39>0,N(D39)>0),MAX(0,ROUNDDOWN((C39*N(D39)-G39*N(F39))/30*$F$75*$F$71,2)),0)) | I39: =IF(C39="","",ROUNDDOWN(C39*N(D39),2))
A40: =IF(Dados!$A$20="","",Dados!$A$20) | B40: =IF(Dados!$B$20="","",Dados!$B$20) | C40: =IF(Dados!$C$20="","",Dados!$C$20) | D40: =IF(Dados!$D$20="","",Dados!$D$20) | E40: =IF(C40="","",C40*220) | G40: =IF(C40="","",IF(C40>0,ROUNDDOWN(N(D40)/220,2),0)) | H40: =IF(C40="","",IF(AND(C40>0,N(D40)>0),MAX(0,ROUNDDOWN((C40*N(D40)-G40*N(F40))/30*$F$75*$F$71,2)),0)) | I40: =IF(C40="","",ROUNDDOWN(C40*N(D40),2))
A41: =IF(Dados!$A$21="","",Dados!$A$21) | B41: =IF(Dados!$B$21="","",Dados!$B$21) | C41: =IF(Dados!$C$21="","",Dados!$C$21) | D41: =IF(Dados!$D$21="","",Dados!$D$21) | E41: =IF(C41="","",C41*220) | G41: =IF(C41="","",IF(C41>0,ROUNDDOWN(N(D41)/220,2),0)) | H41: =IF(C41="","",IF(AND(C41>0,N(D41)>0),MAX(0,ROUNDDOWN((C41*N(D41)-G41*N(F41))/30*$F$75*$F$71,2)),0)) | I41: =IF(C41="","",ROUNDDOWN(C41*N(D41),2))
A42: =IF(Dados!$A$22="","",Dados!$A$22) | B42: =IF(Dados!$B$22="","",Dados!$B$22) | C42: =IF(Dados!$C$22="","",Dados!$C$22) | D42: =IF(Dados!$D$22="","",Dados!$D$22) | E42: =IF(C42="","",C42*220) | G42: =IF(C42="","",IF(C42>0,ROUNDDOWN(N(D42)/220,2),0)) | H42: =IF(C42="","",IF(AND(C42>0,N(D42)>0),MAX(0,ROUNDDOWN((C42*N(D42)-G42*N(F42))/30*$F$75*$F$71,2)),0)) | I42: =IF(C42="","",ROUNDDOWN(C42*N(D42),2))
A43: =IF(Dados!$A$23="","",Dados!$A$23) | B43: =IF(Dados!$B$23="","",Dados!$B$23) | C43: =IF(Dados!$C$23="","",Dados!$C$23) | D43: =IF(Dados!$D$23="","",Dados!$D$23) | E43: =IF(C43="","",C43*220) | G43: =IF(C43="","",IF(C43>0,ROUNDDOWN(N(D43)/220,2),0)) | H43: =IF(C43="","",IF(AND(C43>0,N(D43)>0),MAX(0,ROUNDDOWN((C43*N(D43)-G43*N(F43))/30*$F$75*$F$71,2)),0)) | I43: =IF(C43="","",ROUNDDOWN(C43*N(D43),2))
A44: =IF(Dados!$A$24="","",Dados!$A$24) | B44: =IF(Dados!$B$24="","",Dados!$B$24) | C44: =IF(Dados!$C$24="","",Dados!$C$24) | D44: =IF(Dados!$D$24="","",Dados!$D$24) | E44: =IF(C44="","",C44*220) | G44: =IF(C44="","",IF(C44>0,ROUNDDOWN(N(D44)/220,2),0)) | H44: =IF(C44="","",IF(AND(C44>0,N(D44)>0),MAX(0,ROUNDDOWN((C44*N(D44)-G44*N(F44))/30*$F$75*$F$71,2)),0)) | I44: =IF(C44="","",ROUNDDOWN(C44*N(D44),2))
A45: =IF(Dados!$A$25="","",Dados!$A$25) | B45: =IF(Dados!$B$25="","",Dados!$B$25) | C45: =IF(Dados!$C$25="","",Dados!$C$25) | D45: =IF(Dados!$D$25="","",Dados!$D$25) | E45: =IF(C45="","",C45*220) | G45: =IF(C45="","",IF(C45>0,ROUNDDOWN(N(D45)/220,2),0)) | H45: =IF(C45="","",IF(AND(C45>0,N(D45)>0),MAX(0,ROUNDDOWN((C45*N(D45)-G45*N(F45))/30*$F$75*$F$71,2)),0)) | I45: =IF(C45="","",ROUNDDOWN(C45*N(D45),2))
A46: =IF(Dados!$A$26="","",Dados!$A$26) | B46: =IF(Dados!$B$26="","",Dados!$B$26) | C46: =IF(Dados!$C$26="","",Dados!$C$26) | D46: =IF(Dados!$D$26="","",Dados!$D$26) | E46: =IF(C46="","",C46*220) | G46: =IF(C46="","",IF(C46>0,ROUNDDOWN(N(D46)/220,2),0)) | H46: =IF(C46="","",IF(AND(C46>0,N(D46)>0),MAX(0,ROUNDDOWN((C46*N(D46)-G46*N(F46))/30*$F$75*$F$71,2)),0)) | I46: =IF(C46="","",ROUNDDOWN(C46*N(D46),2))
A47: TOTAIS | F47: =SUM(F32:F46) -> 0 | H47: =SUM(H32:H46) -> 11993.78 | I47: =SUM(I32:I46) -> 11993.78
A49: 📋 INSTRUMENTO DE COBRANÇA
A50: Item | B50: Posto | F50: Qtde Faturada | H50: Valor Unit. Faturado (R$)
A51: =IF(A32="","",A32) -> 1 | B51: =IF(B32="","",B32) -> Vigilante Diurno 12x36 (exemplo) | F51: =IF(C32="","",C32) -> 2 | H51: =IF(C32="","",IF(C32>0,ROUNDDOWN(H32/C32,2),0)) -> 5996.89
A52: =IF(A33="","",A33) | B52: =IF(B33="","",B33) | F52: =IF(C33="","",C33) | H52: =IF(C33="","",IF(C33>0,ROUNDDOWN(H33/C33,2),0))
A53: =IF(A34="","",A34) | B53: =IF(B34="","",B34) | F53: =IF(C34="","",C34) | H53: =IF(C34="","",IF(C34>0,ROUNDDOWN(H34/C34,2),0))
A54: =IF(A35="","",A35) | B54: =IF(B35="","",B35) | F54: =IF(C35="","",C35) | H54: =IF(C35="","",IF(C35>0,ROUNDDOWN(H35/C35,2),0))
A55: =IF(A36="","",A36) | B55: =IF(B36="","",B36) | F55: =IF(C36="","",C36) | H55: =IF(C36="","",IF(C36>0,ROUNDDOWN(H36/C36,2),0))
A56: =IF(A37="","",A37) | B56: =IF(B37="","",B37) | F56: =IF(C37="","",C37) | H56: =IF(C37="","",IF(C37>0,ROUNDDOWN(H37/C37,2),0))
A57: =IF(A38="","",A38) | B57: =IF(B38="","",B38) | F57: =IF(C38="","",C38) | H57: =IF(C38="","",IF(C38>0,ROUNDDOWN(H38/C38,2),0))
A58: =IF(A39="","",A39) | B58: =IF(B39="","",B39) | F58: =IF(C39="","",C39) | H58: =IF(C39="","",IF(C39>0,ROUNDDOWN(H39/C39,2),0))
A59: =IF(A40="","",A40) | B59: =IF(B40="","",B40) | F59: =IF(C40="","",C40) | H59: =IF(C40="","",IF(C40>0,ROUNDDOWN(H40/C40,2),0))
A60: =IF(A41="","",A41) | B60: =IF(B41="","",B41) | F60: =IF(C41="","",C41) | H60: =IF(C41="","",IF(C41>0,ROUNDDOWN(H41/C41,2),0))
A61: =IF(A42="","",A42) | B61: =IF(B42="","",B42) | F61: =IF(C42="","",C42) | H61: =IF(C42="","",IF(C42>0,ROUNDDOWN(H42/C42,2),0))
A62: =IF(A43="","",A43) | B62: =IF(B43="","",B43) | F62: =IF(C43="","",C43) | H62: =IF(C43="","",IF(C43>0,ROUNDDOWN(H43/C43,2),0))
... A65: =IF(A46="","",A46) | B65: =IF(B46="","",B46) | F65: =IF(C46="","",C46) | H65: =IF(C46="","",IF(C46>0,ROUNDDOWN(H46/C46,2),0))
A67: RESUMO FINANCEIRO
A68: Contratado Mensal – Total (R$) (Σ Qtde × Valor Unitário de todos os postos) | F68: =I47 -> 11993.78
A69: Nota Final Apurada | F69: =D28 -> 9
A70: Nota Atribuída pelo Avaliador (Conceito) | F70: =F28 -> A
A71: % do Faturamento a ser Liberado | F71: =INDEX(Dados!$C$50:$C$55,MATCH(D28,Dados!$A$50:$A$55,1)) -> 1
A72: Valor Glosado por QUALIDADE (R$) | F72: =ROUNDDOWN(I47-I47*$F$71,2) -> 0
A73: Número de Dias do Mês (calculado) | F73: =IF(ISNUMBER(B7),DAY(EOMONTH(B7,0)),30) -> 30
A74: Número de Dias Trabalhados no Mês | F74: =IF(ISNUMBER(B7),DAY(EOMONTH(B7,0)),30) -> 30 | H74: Campo de preenchimento: altere apenas em mês parcial (início/fim de contrato)
A75: Dias para Cálculo (mês cheio = 30 avos) | F75: =IF(N(F74)>=$F$73,30,MAX(0,N(F74))) -> 30
A76: Soma dos Itens após Descontos (R$) | F76: =H47 -> 11993.78
A77: VALOR APROVADO PARA PAGAMENTO (R$) (Σ Itens após Descontos + Total dos Reembolsos de Creche) | F77: =MAX(0,ROUNDDOWN(H47+F83,2)) -> 11993.78
A79: 🏫 REEMBOLSO DE CRECHE
A80: Valor Reembolso Creche Retido (R$) | F80: =Dados!$D30 -> 0 | H80: Campo de preenchimento
A81: Reembolsos Aprovados (quantidade) | H81: Campo de preenchimento
A82: Reembolso por dependente (R$) | F82: =Dados!$D31 -> 0 | H82: Campo de preenchimento
A83: Valor Total dos Reembolsos (R$) (Aprovados × Reembolso por dependente) | F83: =ROUNDDOWN(N(F81)*N(F82),2) -> 0
A84: Saldo de Reembolso (R$) (acumulado: saldo da aba anterior + Retido – Total) | F84: =ROUNDDOWN(P07!F84+N(F80)-N(F83),2) -> 0
A85: =IF(F84<0,"⚠ ATENÇÃO: Saldo negativo — será necessário ADITIVAR O CONTRATO PARA SUPORTAR A DESPESA!","")
A87: FAIXA DE AJUSTE DE PAGAMENTO
A88: Conceito | D88: % do Faturamento a ser Pago | G88: Nota Média Mensal Apurada
A89: =Dados!$B$55 -> A | D89: =Dados!$C$55 -> 1 | G89: =Dados!$D$55 -> Entre 9,00 e 8,10
A90: =Dados!$B$54 -> B | D90: =Dados!$C$54 -> 0.95 | G90: =Dados!$D$54 -> Entre 8,09 e 7,65
A91: =Dados!$B$53 -> C | D91: =Dados!$C$53 -> 0.9 | G91: =Dados!$D$53 -> Entre 7,64 e 6,75
A92: =Dados!$B$52 -> D | D92: =Dados!$C$52 -> 0.85 | G92: =Dados!$D$52 -> Entre 6,74 e 5,85
A93: =Dados!$B$51 -> E | D93: =Dados!$C$51 -> 0.8 | G93: =Dados!$D$51 -> Entre 5,84 e 5,40
A94: =Dados!$B$50 -> F | D94: =Dados!$C$50 -> 0.75 | G94: =Dados!$D$50 -> Abaixo de 5,40
A96: APROVAÇÃO E ASSINATURAS
A97: Fiscal Operacional | D97: Fiscal Administrativo (¹) | G97: Representante da Contratada | I97: Data da Aprovação
A100: Nome completo / Matrícula | D100: Nome completo / Matrícula | G100: Nome completo / Cargo | I100: dd/mm/aaaa
A102: 📝 JUSTIFICATIVAS (obrigatório para notas 0 e 1)
A107: =IF(COUNTIF(C13:C27,0)+COUNTIF(C13:C27,1)>0,"⚠ Existem notas 0 ou 1 nesta aba — a justificativa acima é OBRIGATÓRIA. Informe critério, nota e fundamentação.","Para cada nota 0 ou 1 informe: critério, nota atribuída e fundamentação.") -> Para cada nota 0 ou 1 informe: critério, nota atribuída e fundamentação.

Sheet P09
A1: UFRJ – PRÓ-REITORIA DE GESTÃO E GOVERNANÇA – PR6 | IMR
A2: INSTRUMENTO DE MEDIÇÃO DE RESULTADO
A3: =IF(Dados!$B$6="","",Dados!$B$6) -> Atualizado conforme Valor Unitário Contratado inicial
A5: CONTRATO Nº: | B5: =IF(Dados!$B$2="","",Dados!$B$2) -> 04/24 | E5: UNIDADE: | G5: =IF(Dados!$B$3="","",Dados!$B$3) -> CBAE
A6: CONTRATADA: | B6: =IF(Dados!$B$4="","",Dados!$B$4) -> Angels | E6: FISCAL OPERACIONAL: | G6: =IF(Dados!$B$5="","",Dados!$B$5)
A7: AVALIAÇÃO REFERENTE AO PERÍODO: | B7: =IF(Dados!$B$7="","(informe o período inicial na aba Dados)",EDATE(Dados!$B$7,8)) -> (informe o período inicial na aba Dados) | E7: PERÍODO (ABA) Nº: | G7: 9 de 60
A8: ⚠ Para notas 0 e 1 o campo JUSTIFICATIVAS (fim da aba) é de preenchimento obrigatório. | Contrato, Unidade, Contratada e Postos são compartilhados por todas as abas (aba Dados).
A10: AVALIAÇÃO DE DESEMPENHO
A11: Critério de Avaliação | B11: PESO (a) | C11: NOTA (b) (0, 1 ou 3) | D11: SUBTOTAL (c = a × b) | E11: Status | F11: Aviso de Justificativa
A12: ▶ GRUPO 1 – DESEMPENHO PROFISSIONAL
A13: =Dados!$B$36 -> Cumprimento das Atividades | B13: =Dados!$C$36 -> 0.4 | C13: 3 | D13: =B13*C13 -> 1.2 | E13: =IF(OR(C13=0,C13=1,C13=3),"✓ Ok","⛔ Inválida") -> ✓ Ok | F13: =IF(OR(C13=0,C13=1),"⚠ Favor inserir justificativa da nota "&C13&" no campo JUSTIFICATIVAS","")
A14: =Dados!$B$37 -> Qualificação / Atendimento ao Público / Postura | B14: =Dados!$C$37 -> 0.35 | C14: 3 | D14: =B14*C14 -> 1.05 | E14: =IF(OR(C14=0,C14=1,C14=3),"✓ Ok","⛔ Inválida") -> ✓ Ok | F14: =IF(OR(C14=0,C14=1),"⚠ Favor inserir justificativa da nota "&C14&" no campo JUSTIFICATIVAS","")
A15: =Dados!$B$38 -> Uniformes e Identificação | B15: =Dados!$C$38 -> 0.25 | C15: 3 | D15: =B15*C15 -> 0.75 | E15: =IF(OR(C15=0,C15=1,C15=3),"✓ Ok","⛔ Inválida") -> ✓ Ok | F15: =IF(OR(C15=0,C15=1),"⚠ Favor inserir justificativa da nota "&C15&" no campo JUSTIFICATIVAS","")
A16: TOTAL GRUPO 1 | B16: =SUM(B13:B15) -> 1 | D16: =SUM(D13:D15) -> 3
A17: ▶ GRUPO 2 – DESEMPENHO DAS ATIVIDADES
A18: =Dados!$B$39 -> Especificação Técnica dos Serviços | B18: =Dados!$C$39 -> 0.4 | C18: 3 | D18: =B18*C18 -> 1.2 | E18: =IF(OR(C18=0,C18=1,C18=3),"✓ Ok","⛔ Inválida") -> ✓ Ok | F18: =IF(OR(C18=0,C18=1),"⚠ Favor inserir justificativa da nota "&C18&" no campo JUSTIFICATIVAS","")
A19: =Dados!$B$40 -> Equipamentos e Acessórios | B19: =Dados!$C$40 -> 0.2 | C19: 3 | D19: =B19*C19 -> 0.6 | E19: =IF(OR(C19=0,C19=1,C19=3),"✓ Ok","⛔ Inválida") -> ✓ Ok | F19: =IF(OR(C19=0,C19=1),"⚠ Favor inserir justificativa da nota "&C19&" no campo JUSTIFICATIVAS","")
A20: =Dados!$B$41 -> Atendimento às Ocorrências | B20: =Dados!$C$41 -> 0.4 | C20: 3 | D20: =B20*C20 -> 1.2 | E20: =IF(OR(C20=0,C20=1,C20=3),"✓ Ok","⛔ Inválida") -> ✓ Ok | F20: =IF(OR(C20=0,C20=1),"⚠ Favor inserir justificativa da nota "&C20&" no campo JUSTIFICATIVAS","")
A21: TOTAL GRUPO 2 | B21: =SUM(B18:B20) -> 1 | D21: =SUM(D18:D20) -> 3
A22: ▶ GRUPO 3 – GERENCIAMENTO
A23: =Dados!$B$42 -> Periodicidade da Supervisão | B23: =Dados!$C$42 -> 0.2 | C23: 3 | D23: =B23*C23 -> 0.6 | E23: =IF(OR(C23=0,C23=1,C23=3),"✓ Ok","⛔ Inválida") -> ✓ Ok | F23: =IF(OR(C23=0,C23=1),"⚠ Favor inserir justificativa da nota "&C23&" no campo JUSTIFICATIVAS","")
A24: =Dados!$B$43 -> Gerenciamento das Atividades Operacionais | B24: =Dados!$C$43 -> 0.3 | C24: 3 | D24: =B24*C24 -> 0.9 | E24: =IF(OR(C24=0,C24=1,C24=3),"✓ Ok","⛔ Inválida") -> ✓ Ok | F24: =IF(OR(C24=0,C24=1),"⚠ Favor inserir justificativa da nota "&C24&" no campo JUSTIFICATIVAS","")
A25: =Dados!$B$44 -> Atendimento às Solicitações | B25: =Dados!$C$44 -> 0.25 | C25: 3 | D25: =B25*C25 -> 0.75 | E25: =IF(OR(C25=0,C25=1,C25=3),"✓ Ok","⛔ Inválida") -> ✓ Ok | F25: =IF(OR(C25=0,C25=1),"⚠ Favor inserir justificativa da nota "&C25&" no campo JUSTIFICATIVAS","")
A26: =Dados!$B$45 -> Salários, Benefícios e Obrigações Trabalhistas (¹ Fiscal Adm.) | B26: =Dados!$C$45 -> 0.25 | C26: 3 | D26: =B26*C26 -> 0.75 | E26: =IF(OR(C26=0,C26=1,C26=3),"✓ Ok","⛔ Inválida") -> ✓ Ok | F26: =IF(OR(C26=0,C26=1),"⚠ Favor inserir justificativa da nota "&C26&" no campo JUSTIFICATIVAS","")
A27: TOTAL GRUPO 3 | B27: =SUM(B23:B26) -> 1 | D27: =SUM(D23:D26) -> 3
A28: NOTA FINAL (somatório dos Grupos 1, 2 e 3) | D28: =D16+D21+D27 -> 9 | E28: Conceito: | F28: =INDEX(Dados!$B$50:$B$55,MATCH(D28,Dados!$A$50:$A$55,1)) -> A | G28: (¹) Grupo 3 – Salários/Benefícios/Obrigações Trabalhistas: preenchido pelo Fiscal Administrativo
A30: POSTOS DE TRABALHO
A31: Item | B31: POSTO | C31: Qtde Contratada | D31: Valor Unit. Contratado (R$) | E31: Horas Contratadas | F31: Sem Cobertura (h) | G31: Valor da Hora Contratada (R$) | H31: Valor do Item após Descontos (R$) | I31: Mensal Contratado (R$)
A32: =IF(Dados!$A$12="","",Dados!$A$12) -> 1 | B32: =IF(Dados!$B$12="","",Dados!$B$12) -> Vigilante Diurno 12x36 (exemplo) | C32: =IF(Dados!$C$12="","",Dados!$C$12) -> 2 | D32: =IF(Dados!$D$12="","",Dados!$D$12) -> 5996.89 | E32: =IF(C32="","",C32*220) -> 440 | G32: =IF(C32="","",IF(C32>0,ROUNDDOWN(N(D32)/220,2),0)) -> 27.25 | H32: =IF(C32="","",IF(AND(C32>0,N(D32)>0),MAX(0,ROUNDDOWN((C32*N(D32)-G32*N(F32))/30*$F$75*$F$71,2)),0)) -> 11993.78 | I32: =IF(C32="","",ROUNDDOWN(C32*N(D32),2)) -> 11993.78
A33: =IF(Dados!$A$13="","",Dados!$A$13) | B33: =IF(Dados!$B$13="","",Dados!$B$13) | C33: =IF(Dados!$C$13="","",Dados!$C$13) | D33: =IF(Dados!$D$13="","",Dados!$D$13) | E33: =IF(C33="","",C33*220) | G33: =IF(C33="","",IF(C33>0,ROUNDDOWN(N(D33)/220,2),0)) | H33: =IF(C33="","",IF(AND(C33>0,N(D33)>0),MAX(0,ROUNDDOWN((C33*N(D33)-G33*N(F33))/30*$F$75*$F$71,2)),0)) | I33: =IF(C33="","",ROUNDDOWN(C33*N(D33),2))
A34: =IF(Dados!$A$14="","",Dados!$A$14) | B34: =IF(Dados!$B$14="","",Dados!$B$14) | C34: =IF(Dados!$C$14="","",Dados!$C$14) | D34: =IF(Dados!$D$14="","",Dados!$D$14) | E34: =IF(C34="","",C34*220) | G34: =IF(C34="","",IF(C34>0,ROUNDDOWN(N(D34)/220,2),0)) | H34: =IF(C34="","",IF(AND(C34>0,N(D34)>0),MAX(0,ROUNDDOWN((C34*N(D34)-G34*N(F34))/30*$F$75*$F$71,2)),0)) | I34: =IF(C34="","",ROUNDDOWN(C34*N(D34),2))
A35: =IF(Dados!$A$15="","",Dados!$A$15) | B35: =IF(Dados!$B$15="","",Dados!$B$15) | C35: =IF(Dados!$C$15="","",Dados!$C$15) | D35: =IF(Dados!$D$15="","",Dados!$D$15) | E35: =IF(C35="","",C35*220) | G35: =IF(C35="","",IF(C35>0,ROUNDDOWN(N(D35)/220,2),0)) | H35: =IF(C35="","",IF(AND(C35>0,N(D35)>0),MAX(0,ROUNDDOWN((C35*N(D35)-G35*N(F35))/30*$F$75*$F$71,2)),0)) | I35: =IF(C35="","",ROUNDDOWN(C35*N(D35),2))
A36: =IF(Dados!$A$16="","",Dados!$A$16) | B36: =IF(Dados!$B$16="","",Dados!$B$16) | C36: =IF(Dados!$C$16="","",Dados!$C$16) | D36: =IF(Dados!$D$16="","",Dados!$D$16) | E36: =IF(C36="","",C36*220) | G36: =IF(C36="","",IF(C36>0,ROUNDDOWN(N(D36)/220,2),0)) | H36: =IF(C36="","",IF(AND(C36>0,N(D36)>0),MAX(0,ROUNDDOWN((C36*N(D36)-G36*N(F36))/30*$F$75*$F$71,2)),0)) | I36: =IF(C36="","",ROUNDDOWN(C36*N(D36),2))
A37: =IF(Dados!$A$17="","",Dados!$A$17) | B37: =IF(Dados!$B$17="","",Dados!$B$17) | C37: =IF(Dados!$C$17="","",Dados!$C$17) | D37: =IF(Dados!$D$17="","",Dados!$D$17) | E37: =IF(C37="","",C37*220) | G37: =IF(C37="","",IF(C37>0,ROUNDDOWN(N(D37)/220,2),0)) | H37: =IF(C37="","",IF(AND(C37>0,N(D37)>0),MAX(0,ROUNDDOWN((C37*N(D37)-G37*N(F37))/30*$F$75*$F$71,2)),0)) | I37: =IF(C37="","",ROUNDDOWN(C37*N(D37),2))
A38: =IF(Dados!$A$18="","",Dados!$A$18) | B38: =IF(Dados!$B$18="","",Dados!$B$18) | C38: =IF(Dados!$C$18="","",Dados!$C$18) | D38: =IF(Dados!$D$18="","",Dados!$D$18) | E38: =IF(C38="","",C38*220) | G38: =IF(C38="","",IF(C38>0,ROUNDDOWN(N(D38)/220,2),0)) | H38: =IF(C38="","",IF(AND(C38>0,N(D38)>0),MAX(0,ROUNDDOWN((C38*N(D38)-G38*N(F38))/30*$F$75*$F$71,2)),0)) | I38: =IF(C38="","",ROUNDDOWN(C38*N(D38),2))
A39: =IF(Dados!$A$19="","",Dados!$A$19) | B39: =IF(Dados!$B$19="","",Dados!$B$19) | C39: =IF(Dados!$C$19="","",Dados!$C$19) | D39: =IF(Dados!$D$19="","",Dados!$D$19) | E39: =IF(C39="","",C39*220) | G39: =IF(C39="","",IF(C39>0,ROUNDDOWN(N(D39)/220,2),0)) | H39: =IF(C39="","",IF(AND(C39>0,N(D39)>0),MAX(0,ROUNDDOWN((C39*N(D39)-G39*N(F39))/30*$F$75*$F$71,2)),0)) | I39: =IF(C39="","",ROUNDDOWN(C39*N(D39),2))
A40: =IF(Dados!$A$20="","",Dados!$A$20) | B40: =IF(Dados!$B$20="","",Dados!$B$20) | C40: =IF(Dados!$C$20="","",Dados!$C$20) | D40: =IF(Dados!$D$20="","",Dados!$D$20) | E40: =IF(C40="","",C40*220) | G40: =IF(C40="","",IF(C40>0,ROUNDDOWN(N(D40)/220,2),0)) | H40: =IF(C40="","",IF(AND(C40>0,N(D40)>0),MAX(0,ROUNDDOWN((C40*N(D40)-G40*N(F40))/30*$F$75*$F$71,2)),0)) | I40: =IF(C40="","",ROUNDDOWN(C40*N(D40),2))
A41: =IF(Dados!$A$21="","",Dados!$A$21) | B41: =IF(Dados!$B$21="","",Dados!$B$21) | C41: =IF(Dados!$C$21="","",Dados!$C$21) | D41: =IF(Dados!$D$21="","",Dados!$D$21) | E41: =IF(C41="","",C41*220) | G41: =IF(C41="","",IF(C41>0,ROUNDDOWN(N(D41)/220,2),0)) | H41: =IF(C41="","",IF(AND(C41>0,N(D41)>0),MAX(0,ROUNDDOWN((C41*N(D41)-G41*N(F41))/30*$F$75*$F$71,2)),0)) | I41: =IF(C41="","",ROUNDDOWN(C41*N(D41),2))
A42: =IF(Dados!$A$22="","",Dados!$A$22) | B42: =IF(Dados!$B$22="","",Dados!$B$22) | C42: =IF(Dados!$C$22="","",Dados!$C$22) | D42: =IF(Dados!$D$22="","",Dados!$D$22) | E42: =IF(C42="","",C42*220) | G42: =IF(C42="","",IF(C42>0,ROUNDDOWN(N(D42)/220,2),0)) | H42: =IF(C42="","",IF(AND(C42>0,N(D42)>0),MAX(0,ROUNDDOWN((C42*N(D42)-G42*N(F42))/30*$F$75*$F$71,2)),0)) | I42: =IF(C42="","",ROUNDDOWN(C42*N(D42),2))
A43: =IF(Dados!$A$23="","",Dados!$A$23) | B43: =IF(Dados!$B$23="","",Dados!$B$23) | C43: =IF(Dados!$C$23="","",Dados!$C$23) | D43: =IF(Dados!$D$23="","",Dados!$D$23) | E43: =IF(C43="","",C43*220) | G43: =IF(C43="","",IF(C43>0,ROUNDDOWN(N(D43)/220,2),0)) | H43: =IF(C43="","",IF(AND(C43>0,N(D43)>0),MAX(0,ROUNDDOWN((C43*N(D43)-G43*N(F43))/30*$F$75*$F$71,2)),0)) | I43: =IF(C43="","",ROUNDDOWN(C43*N(D43),2))
A44: =IF(Dados!$A$24="","",Dados!$A$24) | B44: =IF(Dados!$B$24="","",Dados!$B$24) | C44: =IF(Dados!$C$24="","",Dados!$C$24) | D44: =IF(Dados!$D$24="","",Dados!$D$24) | E44: =IF(C44="","",C44*220) | G44: =IF(C44="","",IF(C44>0,ROUNDDOWN(N(D44)/220,2),0)) | H44: =IF(C44="","",IF(AND(C44>0,N(D44)>0),MAX(0,ROUNDDOWN((C44*N(D44)-G44*N(F44))/30*$F$75*$F$71,2)),0)) | I44: =IF(C44="","",ROUNDDOWN(C44*N(D44),2))
A45: =IF(Dados!$A$25="","",Dados!$A$25) | B45: =IF(Dados!$B$25="","",Dados!$B$25) | C45: =IF(Dados!$C$25="","",Dados!$C$25) | D45: =IF(Dados!$D$25="","",Dados!$D$25) | E45: =IF(C45="","",C45*220) | G45: =IF(C45="","",IF(C45>0,ROUNDDOWN(N(D45)/220,2),0)) | H45: =IF(C45="","",IF(AND(C45>0,N(D45)>0),MAX(0,ROUNDDOWN((C45*N(D45)-G45*N(F45))/30*$F$75*$F$71,2)),0)) | I45: =IF(C45="","",ROUNDDOWN(C45*N(D45),2))
A46: =IF(Dados!$A$26="","",Dados!$A$26) | B46: =IF(Dados!$B$26="","",Dados!$B$26) | C46: =IF(Dados!$C$26="","",Dados!$C$26) | D46: =IF(Dados!$D$26="","",Dados!$D$26) | E46: =IF(C46="","",C46*220) | G46: =IF(C46="","",IF(C46>0,ROUNDDOWN(N(D46)/220,2),0)) | H46: =IF(C46="","",IF(AND(C46>0,N(D46)>0),MAX(0,ROUNDDOWN((C46*N(D46)-G46*N(F46))/30*$F$75*$F$71,2)),0)) | I46: =IF(C46="","",ROUNDDOWN(C46*N(D46),2))
A47: TOTAIS | F47: =SUM(F32:F46) -> 0 | H47: =SUM(H32:H46) -> 11993.78 | I47: =SUM(I32:I46) -> 11993.78
A49: 📋 INSTRUMENTO DE COBRANÇA
A50: Item | B50: Posto | F50: Qtde Faturada | H50: Valor Unit. Faturado (R$)
A51: =IF(A32="","",A32) -> 1 | B51: =IF(B32="","",B32) -> Vigilante Diurno 12x36 (exemplo) | F51: =IF(C32="","",C32) -> 2 | H51: =IF(C32="","",IF(C32>0,ROUNDDOWN(H32/C32,2),0)) -> 5996.89
A52: =IF(A33="","",A33) | B52: =IF(B33="","",B33) | F52: =IF(C33="","",C33) | H52: =IF(C33="","",IF(C33>0,ROUNDDOWN(H33/C33,2),0))
A53: =IF(A34="","",A34) | B53: =IF(B34="","",B34) | F53: =IF(C34="","",C34) | H53: =IF(C34="","",IF(C34>0,ROUNDDOWN(H34/C34,2),0))
A54: =IF(A35="","",A35) | B54: =IF(B35="","",B35) | F54: =IF(C35="","",C35) | H54: =IF(C35="","",IF(C35>0,ROUNDDOWN(H35/C35,2),0))
A55: =IF(A36="","",A36) | B55: =IF(B36="","",B36) | F55: =IF(C36="","",C36) | H55: =IF(C36="","",IF(C36>0,ROUNDDOWN(H36/C36,2),0))
A56: =IF(A37="","",A37) | B56: =IF(B37="","",B37) | F56: =IF(C37="","",C37) | H56: =IF(C37="","",IF(C37>0,ROUNDDOWN(H37/C37,2),0))
A57: =IF(A38="","",A38) | B57: =IF(B38="","",B38) | F57: =IF(C38="","",C38) | H57: =IF(C38="","",IF(C38>0,ROUNDDOWN(H38/C38,2),0))
A58: =IF(A39="","",A39) | B58: =IF(B39="","",B39) | F58: =IF(C39="","",C39) | H58: =IF(C39="","",IF(C39>0,ROUNDDOWN(H39/C39,2),0))
A59: =IF(A40="","",A40) | B59: =IF(B40="","",B40) | F59: =IF(C40="","",C40) | H59: =IF(C40="","",IF(C40>0,ROUNDDOWN(H40/C40,2),0))
A60: =IF(A41="","",A41) | B60: =IF(B41="","",B41) | F60: =IF(C41="","",C41) | H60: =IF(C41="","",IF(C41>0,ROUNDDOWN(H41/C41,2),0))
A61: =IF(A42="","",A42) | B61: =IF(B42="","",B42) | F61: =IF(C42="","",C42) | H61: =IF(C42="","",IF(C42>0,ROUNDDOWN(H42/C42,2),0))
A62: =IF(A43="","",A43) | B62: =IF(B43="","",B43) | F62: =IF(C43="","",C43) | H62: =IF(C43="","",IF(C43>0,ROUNDDOWN(H43/C43,2),0))
... A65: =IF(A46="","",A46) | B65: =IF(B46="","",B46) | F65: =IF(C46="","",C46) | H65: =IF(C46="","",IF(C46>0,ROUNDDOWN(H46/C46,2),0))
A67: RESUMO FINANCEIRO
A68: Contratado Mensal – Total (R$) (Σ Qtde × Valor Unitário de todos os postos) | F68: =I47 -> 11993.78
A69: Nota Final Apurada | F69: =D28 -> 9
A70: Nota Atribuída pelo Avaliador (Conceito) | F70: =F28 -> A
A71: % do Faturamento a ser Liberado | F71: =INDEX(Dados!$C$50:$C$55,MATCH(D28,Dados!$A$50:$A$55,1)) -> 1
A72: Valor Glosado por QUALIDADE (R$) | F72: =ROUNDDOWN(I47-I47*$F$71,2) -> 0
A73: Número de Dias do Mês (calculado) | F73: =IF(ISNUMBER(B7),DAY(EOMONTH(B7,0)),30) -> 30
A74: Número de Dias Trabalhados no Mês | F74: =IF(ISNUMBER(B7),DAY(EOMONTH(B7,0)),30) -> 30 | H74: Campo de preenchimento: altere apenas em mês parcial (início/fim de contrato)
A75: Dias para Cálculo (mês cheio = 30 avos) | F75: =IF(N(F74)>=$F$73,30,MAX(0,N(F74))) -> 30
A76: Soma dos Itens após Descontos (R$) | F76: =H47 -> 11993.78
A77: VALOR APROVADO PARA PAGAMENTO (R$) (Σ Itens após Descontos + Total dos Reembolsos de Creche) | F77: =MAX(0,ROUNDDOWN(H47+F83,2)) -> 11993.78
A79: 🏫 REEMBOLSO DE CRECHE
A80: Valor Reembolso Creche Retido (R$) | F80: =Dados!$D30 -> 0 | H80: Campo de preenchimento
A81: Reembolsos Aprovados (quantidade) | H81: Campo de preenchimento
A82: Reembolso por dependente (R$) | F82: =Dados!$D31 -> 0 | H82: Campo de preenchimento
A83: Valor Total dos Reembolsos (R$) (Aprovados × Reembolso por dependente) | F83: =ROUNDDOWN(N(F81)*N(F82),2) -> 0
A84: Saldo de Reembolso (R$) (acumulado: saldo da aba anterior + Retido – Total) | F84: =ROUNDDOWN(P08!F84+N(F80)-N(F83),2) -> 0
A85: =IF(F84<0,"⚠ ATENÇÃO: Saldo negativo — será necessário ADITIVAR O CONTRATO PARA SUPORTAR A DESPESA!","")
A87: FAIXA DE AJUSTE DE PAGAMENTO
A88: Conceito | D88: % do Faturamento a ser Pago | G88: Nota Média Mensal Apurada
A89: =Dados!$B$55 -> A | D89: =Dados!$C$55 -> 1 | G89: =Dados!$D$55 -> Entre 9,00 e 8,10
A90: =Dados!$B$54 -> B | D90: =Dados!$C$54 -> 0.95 | G90: =Dados!$D$54 -> Entre 8,09 e 7,65
A91: =Dados!$B$53 -> C | D91: =Dados!$C$53 -> 0.9 | G91: =Dados!$D$53 -> Entre 7,64 e 6,75
A92: =Dados!$B$52 -> D | D92: =Dados!$C$52 -> 0.85 | G92: =Dados!$D$52 -> Entre 6,74 e 5,85
A93: =Dados!$B$51 -> E | D93: =Dados!$C$51 -> 0.8 | G93: =Dados!$D$51 -> Entre 5,84 e 5,40
A94: =Dados!$B$50 -> F | D94: =Dados!$C$50 -> 0.75 | G94: =Dados!$D$50 -> Abaixo de 5,40
A96: APROVAÇÃO E ASSINATURAS
A97: Fiscal Operacional | D97: Fiscal Administrativo (¹) | G97: Representante da Contratada | I97: Data da Aprovação
A100: Nome completo / Matrícula | D100: Nome completo / Matrícula | G100: Nome completo / Cargo | I100: dd/mm/aaaa
A102: 📝 JUSTIFICATIVAS (obrigatório para notas 0 e 1)
A107: =IF(COUNTIF(C13:C27,0)+COUNTIF(C13:C27,1)>0,"⚠ Existem notas 0 ou 1 nesta aba — a justificativa acima é OBRIGATÓRIA. Informe critério, nota e fundamentação.","Para cada nota 0 ou 1 informe: critério, nota atribuída e fundamentação.") -> Para cada nota 0 ou 1 informe: critério, nota atribuída e fundamentação.

Sheet P10
A1: UFRJ – PRÓ-REITORIA DE GESTÃO E GOVERNANÇA – PR6 | IMR
A2: INSTRUMENTO DE MEDIÇÃO DE RESULTADO
A3: =IF(Dados!$B$6="","",Dados!$B$6) -> Atualizado conforme Valor Unitário Contratado inicial
A5: CONTRATO Nº: | B5: =IF(Dados!$B$2="","",Dados!$B$2) -> 04/24 | E5: UNIDADE: | G5: =IF(Dados!$B$3="","",Dados!$B$3) -> CBAE
A6: CONTRATADA: | B6: =IF(Dados!$B$4="","",Dados!$B$4) -> Angels | E6: FISCAL OPERACIONAL: | G6: =IF(Dados!$B$5="","",Dados!$B$5)
A7: AVALIAÇÃO REFERENTE AO PERÍODO: | B7: =IF(Dados!$B$7="","(informe o período inicial na aba Dados)",EDATE(Dados!$B$7,9)) -> (informe o período inicial na aba Dados) | E7: PERÍODO (ABA) Nº: | G7: 10 de 60
A8: ⚠ Para notas 0 e 1 o campo JUSTIFICATIVAS (fim da aba) é de preenchimento obrigatório. | Contrato, Unidade, Contratada e Postos são compartilhados por todas as abas (aba Dados).
A10: AVALIAÇÃO DE DESEMPENHO
A11: Critério de Avaliação | B11: PESO (a) | C11: NOTA (b) (0, 1 ou 3) | D11: SUBTOTAL (c = a × b) | E11: Status | F11: Aviso de Justificativa
A12: ▶ GRUPO 1 – DESEMPENHO PROFISSIONAL
A13: =Dados!$B$36 -> Cumprimento das Atividades | B13: =Dados!$C$36 -> 0.4 | C13: 3 | D13: =B13*C13 -> 1.2 | E13: =IF(OR(C13=0,C13=1,C13=3),"✓ Ok","⛔ Inválida") -> ✓ Ok | F13: =IF(OR(C13=0,C13=1),"⚠ Favor inserir justificativa da nota "&C13&" no campo JUSTIFICATIVAS","")
A14: =Dados!$B$37 -> Qualificação / Atendimento ao Público / Postura | B14: =Dados!$C$37 -> 0.35 | C14: 3 | D14: =B14*C14 -> 1.05 | E14: =IF(OR(C14=0,C14=1,C14=3),"✓ Ok","⛔ Inválida") -> ✓ Ok | F14: =IF(OR(C14=0,C14=1),"⚠ Favor inserir justificativa da nota "&C14&" no campo JUSTIFICATIVAS","")
A15: =Dados!$B$38 -> Uniformes e Identificação | B15: =Dados!$C$38 -> 0.25 | C15: 3 | D15: =B15*C15 -> 0.75 | E15: =IF(OR(C15=0,C15=1,C15=3),"✓ Ok","⛔ Inválida") -> ✓ Ok | F15: =IF(OR(C15=0,C15=1),"⚠ Favor inserir justificativa da nota "&C15&" no campo JUSTIFICATIVAS","")
A16: TOTAL GRUPO 1 | B16: =SUM(B13:B15) -> 1 | D16: =SUM(D13:D15) -> 3
A17: ▶ GRUPO 2 – DESEMPENHO DAS ATIVIDADES
A18: =Dados!$B$39 -> Especificação Técnica dos Serviços | B18: =Dados!$C$39 -> 0.4 | C18: 3 | D18: =B18*C18 -> 1.2 | E18: =IF(OR(C18=0,C18=1,C18=3),"✓ Ok","⛔ Inválida") -> ✓ Ok | F18: =IF(OR(C18=0,C18=1),"⚠ Favor inserir justificativa da nota "&C18&" no campo JUSTIFICATIVAS","")
A19: =Dados!$B$40 -> Equipamentos e Acessórios | B19: =Dados!$C$40 -> 0.2 | C19: 3 | D19: =B19*C19 -> 0.6 | E19: =IF(OR(C19=0,C19=1,C19=3),"✓ Ok","⛔ Inválida") -> ✓ Ok | F19: =IF(OR(C19=0,C19=1),"⚠ Favor inserir justificativa da nota "&C19&" no campo JUSTIFICATIVAS","")
A20: =Dados!$B$41 -> Atendimento às Ocorrências | B20: =Dados!$C$41 -> 0.4 | C20: 3 | D20: =B20*C20 -> 1.2 | E20: =IF(OR(C20=0,C20=1,C20=3),"✓ Ok","⛔ Inválida") -> ✓ Ok | F20: =IF(OR(C20=0,C20=1),"⚠ Favor inserir justificativa da nota "&C20&" no campo JUSTIFICATIVAS","")
A21: TOTAL GRUPO 2 | B21: =SUM(B18:B20) -> 1 | D21: =SUM(D18:D20) -> 3
A22: ▶ GRUPO 3 – GERENCIAMENTO
A23: =Dados!$B$42 -> Periodicidade da Supervisão | B23: =Dados!$C$42 -> 0.2 | C23: 3 | D23: =B23*C23 -> 0.6 | E23: =IF(OR(C23=0,C23=1,C23=3),"✓ Ok","⛔ Inválida") -> ✓ Ok | F23: =IF(OR(C23=0,C23=1),"⚠ Favor inserir justificativa da nota "&C23&" no campo JUSTIFICATIVAS","")
A24: =Dados!$B$43 -> Gerenciamento das Atividades Operacionais | B24: =Dados!$C$43 -> 0.3 | C24: 3 | D24: =B24*C24 -> 0.9 | E24: =IF(OR(C24=0,C24=1,C24=3),"✓ Ok","⛔ Inválida") -> ✓ Ok | F24: =IF(OR(C24=0,C24=1),"⚠ Favor inserir justificativa da nota "&C24&" no campo JUSTIFICATIVAS","")
A25: =Dados!$B$44 -> Atendimento às Solicitações | B25: =Dados!$C$44 -> 0.25 | C25: 3 | D25: =B25*C25 -> 0.75 | E25: =IF(OR(C25=0,C25=1,C25=3),"✓ Ok","⛔ Inválida") -> ✓ Ok | F25: =IF(OR(C25=0,C25=1),"⚠ Favor inserir justificativa da nota "&C25&" no campo JUSTIFICATIVAS","")
A26: =Dados!$B$45 -> Salários, Benefícios e Obrigações Trabalhistas (¹ Fiscal Adm.) | B26: =Dados!$C$45 -> 0.25 | C26: 3 | D26: =B26*C26 -> 0.75 | E26: =IF(OR(C26=0,C26=1,C26=3),"✓ Ok","⛔ Inválida") -> ✓ Ok | F26: =IF(OR(C26=0,C26=1),"⚠ Favor inserir justificativa da nota "&C26&" no campo JUSTIFICATIVAS","")
A27: TOTAL GRUPO 3 | B27: =SUM(B23:B26) -> 1 | D27: =SUM(D23:D26) -> 3
A28: NOTA FINAL (somatório dos Grupos 1, 2 e 3) | D28: =D16+D21+D27 -> 9 | E28: Conceito: | F28: =INDEX(Dados!$B$50:$B$55,MATCH(D28,Dados!$A$50:$A$55,1)) -> A | G28: (¹) Grupo 3 – Salários/Benefícios/Obrigações Trabalhistas: preenchido pelo Fiscal Administrativo
A30: POSTOS DE TRABALHO
A31: Item | B31: POSTO | C31: Qtde Contratada | D31: Valor Unit. Contratado (R$) | E31: Horas Contratadas | F31: Sem Cobertura (h) | G31: Valor da Hora Contratada (R$) | H31: Valor do Item após Descontos (R$) | I31: Mensal Contratado (R$)
A32: =IF(Dados!$A$12="","",Dados!$A$12) -> 1 | B32: =IF(Dados!$B$12="","",Dados!$B$12) -> Vigilante Diurno 12x36 (exemplo) | C32: =IF(Dados!$C$12="","",Dados!$C$12) -> 2 | D32: =IF(Dados!$D$12="","",Dados!$D$12) -> 5996.89 | E32: =IF(C32="","",C32*220) -> 440 | G32: =IF(C32="","",IF(C32>0,ROUNDDOWN(N(D32)/220,2),0)) -> 27.25 | H32: =IF(C32="","",IF(AND(C32>0,N(D32)>0),MAX(0,ROUNDDOWN((C32*N(D32)-G32*N(F32))/30*$F$75*$F$71,2)),0)) -> 11993.78 | I32: =IF(C32="","",ROUNDDOWN(C32*N(D32),2)) -> 11993.78
A33: =IF(Dados!$A$13="","",Dados!$A$13) | B33: =IF(Dados!$B$13="","",Dados!$B$13) | C33: =IF(Dados!$C$13="","",Dados!$C$13) | D33: =IF(Dados!$D$13="","",Dados!$D$13) | E33: =IF(C33="","",C33*220) | G33: =IF(C33="","",IF(C33>0,ROUNDDOWN(N(D33)/220,2),0)) | H33: =IF(C33="","",IF(AND(C33>0,N(D33)>0),MAX(0,ROUNDDOWN((C33*N(D33)-G33*N(F33))/30*$F$75*$F$71,2)),0)) | I33: =IF(C33="","",ROUNDDOWN(C33*N(D33),2))
A34: =IF(Dados!$A$14="","",Dados!$A$14) | B34: =IF(Dados!$B$14="","",Dados!$B$14) | C34: =IF(Dados!$C$14="","",Dados!$C$14) | D34: =IF(Dados!$D$14="","",Dados!$D$14) | E34: =IF(C34="","",C34*220) | G34: =IF(C34="","",IF(C34>0,ROUNDDOWN(N(D34)/220,2),0)) | H34: =IF(C34="","",IF(AND(C34>0,N(D34)>0),MAX(0,ROUNDDOWN((C34*N(D34)-G34*N(F34))/30*$F$75*$F$71,2)),0)) | I34: =IF(C34="","",ROUNDDOWN(C34*N(D34),2))
A35: =IF(Dados!$A$15="","",Dados!$A$15) | B35: =IF(Dados!$B$15="","",Dados!$B$15) | C35: =IF(Dados!$C$15="","",Dados!$C$15) | D35: =IF(Dados!$D$15="","",Dados!$D$15) | E35: =IF(C35="","",C35*220) | G35: =IF(C35="","",IF(C35>0,ROUNDDOWN(N(D35)/220,2),0)) | H35: =IF(C35="","",IF(AND(C35>0,N(D35)>0),MAX(0,ROUNDDOWN((C35*N(D35)-G35*N(F35))/30*$F$75*$F$71,2)),0)) | I35: =IF(C35="","",ROUNDDOWN(C35*N(D35),2))
A36: =IF(Dados!$A$16="","",Dados!$A$16) | B36: =IF(Dados!$B$16="","",Dados!$B$16) | C36: =IF(Dados!$C$16="","",Dados!$C$16) | D36: =IF(Dados!$D$16="","",Dados!$D$16) | E36: =IF(C36="","",C36*220) | G36: =IF(C36="","",IF(C36>0,ROUNDDOWN(N(D36)/220,2),0)) | H36: =IF(C36="","",IF(AND(C36>0,N(D36)>0),MAX(0,ROUNDDOWN((C36*N(D36)-G36*N(F36))/30*$F$75*$F$71,2)),0)) | I36: =IF(C36="","",ROUNDDOWN(C36*N(D36),2))
A37: =IF(Dados!$A$17="","",Dados!$A$17) | B37: =IF(Dados!$B$17="","",Dados!$B$17) | C37: =IF(Dados!$C$17="","",Dados!$C$17) | D37: =IF(Dados!$D$17="","",Dados!$D$17) | E37: =IF(C37="","",C37*220) | G37: =IF(C37="","",IF(C37>0,ROUNDDOWN(N(D37)/220,2),0)) | H37: =IF(C37="","",IF(AND(C37>0,N(D37)>0),MAX(0,ROUNDDOWN((C37*N(D37)-G37*N(F37))/30*$F$75*$F$71,2)),0)) | I37: =IF(C37="","",ROUNDDOWN(C37*N(D37),2))
A38: =IF(Dados!$A$18="","",Dados!$A$18) | B38: =IF(Dados!$B$18="","",Dados!$B$18) | C38: =IF(Dados!$C$18="","",Dados!$C$18) | D38: =IF(Dados!$D$18="","",Dados!$D$18) | E38: =IF(C38="","",C38*220) | G38: =IF(C38="","",IF(C38>0,ROUNDDOWN(N(D38)/220,2),0)) | H38: =IF(C38="","",IF(AND(C38>0,N(D38)>0),MAX(0,ROUNDDOWN((C38*N(D38)-G38*N(F38))/30*$F$75*$F$71,2)),0)) | I38: =IF(C38="","",ROUNDDOWN(C38*N(D38),2))
A39: =IF(Dados!$A$19="","",Dados!$A$19) | B39: =IF(Dados!$B$19="","",Dados!$B$19) | C39: =IF(Dados!$C$19="","",Dados!$C$19) | D39: =IF(Dados!$D$19="","",Dados!$D$19) | E39: =IF(C39="","",C39*220) | G39: =IF(C39="","",IF(C39>0,ROUNDDOWN(N(D39)/220,2),0)) | H39: =IF(C39="","",IF(AND(C39>0,N(D39)>0),MAX(0,ROUNDDOWN((C39*N(D39)-G39*N(F39))/30*$F$75*$F$71,2)),0)) | I39: =IF(C39="","",ROUNDDOWN(C39*N(D39),2))
A40: =IF(Dados!$A$20="","",Dados!$A$20) | B40: =IF(Dados!$B$20="","",Dados!$B$20) | C40: =IF(Dados!$C$20="","",Dados!$C$20) | D40: =IF(Dados!$D$20="","",Dados!$D$20) | E40: =IF(C40="","",C40*220) | G40: =IF(C40="","",IF(C40>0,ROUNDDOWN(N(D40)/220,2),0)) | H40: =IF(C40="","",IF(AND(C40>0,N(D40)>0),MAX(0,ROUNDDOWN((C40*N(D40)-G40*N(F40))/30*$F$75*$F$71,2)),0)) | I40: =IF(C40="","",ROUNDDOWN(C40*N(D40),2))
A41: =IF(Dados!$A$21="","",Dados!$A$21) | B41: =IF(Dados!$B$21="","",Dados!$B$21) | C41: =IF(Dados!$C$21="","",Dados!$C$21) | D41: =IF(Dados!$D$21="","",Dados!$D$21) | E41: =IF(C41="","",C41*220) | G41: =IF(C41="","",IF(C41>0,ROUNDDOWN(N(D41)/220,2),0)) | H41: =IF(C41="","",IF(AND(C41>0,N(D41)>0),MAX(0,ROUNDDOWN((C41*N(D41)-G41*N(F41))/30*$F$75*$F$71,2)),0)) | I41: =IF(C41="","",ROUNDDOWN(C41*N(D41),2))
A42: =IF(Dados!$A$22="","",Dados!$A$22) | B42: =IF(Dados!$B$22="","",Dados!$B$22) | C42: =IF(Dados!$C$22="","",Dados!$C$22) | D42: =IF(Dados!$D$22="","",Dados!$D$22) | E42: =IF(C42="","",C42*220) | G42: =IF(C42="","",IF(C42>0,ROUNDDOWN(N(D42)/220,2),0)) | H42: =IF(C42="","",IF(AND(C42>0,N(D42)>0),MAX(0,ROUNDDOWN((C42*N(D42)-G42*N(F42))/30*$F$75*$F$71,2)),0)) | I42: =IF(C42="","",ROUNDDOWN(C42*N(D42),2))
A43: =IF(Dados!$A$23="","",Dados!$A$23) | B43: =IF(Dados!$B$23="","",Dados!$B$23) | C43: =IF(Dados!$C$23="","",Dados!$C$23) | D43: =IF(Dados!$D$23="","",Dados!$D$23) | E43: =IF(C43="","",C43*220) | G43: =IF(C43="","",IF(C43>0,ROUNDDOWN(N(D43)/220,2),0)) | H43: =IF(C43="","",IF(AND(C43>0,N(D43)>0),MAX(0,ROUNDDOWN((C43*N(D43)-G43*N(F43))/30*$F$75*$F$71,2)),0)) | I43: =IF(C43="","",ROUNDDOWN(C43*N(D43),2))
A44: =IF(Dados!$A$24="","",Dados!$A$24) | B44: =IF(Dados!$B$24="","",Dados!$B$24) | C44: =IF(Dados!$C$24="","",Dados!$C$24) | D44: =IF(Dados!$D$24="","",Dados!$D$24) | E44: =IF(C44="","",C44*220) | G44: =IF(C44="","",IF(C44>0,ROUNDDOWN(N(D44)/220,2),0)) | H44: =IF(C44="","",IF(AND(C44>0,N(D44)>0),MAX(0,ROUNDDOWN((C44*N(D44)-G44*N(F44))/30*$F$75*$F$71,2)),0)) | I44: =IF(C44="","",ROUNDDOWN(C44*N(D44),2))
A45: =IF(Dados!$A$25="","",Dados!$A$25) | B45: =IF(Dados!$B$25="","",Dados!$B$25) | C45: =IF(Dados!$C$25="","",Dados!$C$25) | D45: =IF(Dados!$D$25="","",Dados!$D$25) | E45: =IF(C45="","",C45*220) | G45: =IF(C45="","",IF(C45>0,ROUNDDOWN(N(D45)/220,2),0)) | H45: =IF(C45="","",IF(AND(C45>0,N(D45)>0),MAX(0,ROUNDDOWN((C45*N(D45)-G45*N(F45))/30*$F$75*$F$71,2)),0)) | I45: =IF(C45="","",ROUNDDOWN(C45*N(D45),2))
A46: =IF(Dados!$A$26="","",Dados!$A$26) | B46: =IF(Dados!$B$26="","",Dados!$B$26) | C46: =IF(Dados!$C$26="","",Dados!$C$26) | D46: =IF(Dados!$D$26="","",Dados!$D$26) | E46: =IF(C46="","",C46*220) | G46: =IF(C46="","",IF(C46>0,ROUNDDOWN(N(D46)/220,2),0)) | H46: =IF(C46="","",IF(AND(C46>0,N(D46)>0),MAX(0,ROUNDDOWN((C46*N(D46)-G46*N(F46))/30*$F$75*$F$71,2)),0)) | I46: =IF(C46="","",ROUNDDOWN(C46*N(D46),2))
A47: TOTAIS | F47: =SUM(F32:F46) -> 0 | H47: =SUM(H32:H46) -> 11993.78 | I47: =SUM(I32:I46) -> 11993.78
A49: 📋 INSTRUMENTO DE COBRANÇA
A50: Item | B50: Posto | F50: Qtde Faturada | H50: Valor Unit. Faturado (R$)
A51: =IF(A32="","",A32) -> 1 | B51: =IF(B32="","",B32) -> Vigilante Diurno 12x36 (exemplo) | F51: =IF(C32="","",C32) -> 2 | H51: =IF(C32="","",IF(C32>0,ROUNDDOWN(H32/C32,2),0)) -> 5996.89
A52: =IF(A33="","",A33) | B52: =IF(B33="","",B33) | F52: =IF(C33="","",C33) | H52: =IF(C33="","",IF(C33>0,ROUNDDOWN(H33/C33,2),0))
A53: =IF(A34="","",A34) | B53: =IF(B34="","",B34) | F53: =IF(C34="","",C34) | H53: =IF(C34="","",IF(C34>0,ROUNDDOWN(H34/C34,2),0))
A54: =IF(A35="","",A35) | B54: =IF(B35="","",B35) | F54: =IF(C35="","",C35) | H54: =IF(C35="","",IF(C35>0,ROUNDDOWN(H35/C35,2),0))
A55: =IF(A36="","",A36) | B55: =IF(B36="","",B36) | F55: =IF(C36="","",C36) | H55: =IF(C36="","",IF(C36>0,ROUNDDOWN(H36/C36,2),0))
A56: =IF(A37="","",A37) | B56: =IF(B37="","",B37) | F56: =IF(C37="","",C37) | H56: =IF(C37="","",IF(C37>0,ROUNDDOWN(H37/C37,2),0))
A57: =IF(A38="","",A38) | B57: =IF(B38="","",B38) | F57: =IF(C38="","",C38) | H57: =IF(C38="","",IF(C38>0,ROUNDDOWN(H38/C38,2),0))
A58: =IF(A39="","",A39) | B58: =IF(B39="","",B39) | F58: =IF(C39="","",C39) | H58: =IF(C39="","",IF(C39>0,ROUNDDOWN(H39/C39,2),0))
A59: =IF(A40="","",A40) | B59: =IF(B40="","",B40) | F59: =IF(C40="","",C40) | H59: =IF(C40="","",IF(C40>0,ROUNDDOWN(H40/C40,2),0))
A60: =IF(A41="","",A41) | B60: =IF(B41="","",B41) | F60: =IF(C41="","",C41) | H60: =IF(C41="","",IF(C41>0,ROUNDDOWN(H41/C41,2),0))
A61: =IF(A42="","",A42) | B61: =IF(B42="","",B42) | F61: =IF(C42="","",C42) | H61: =IF(C42="","",IF(C42>0,ROUNDDOWN(H42/C42,2),0))
A62: =IF(A43="","",A43) | B62: =IF(B43="","",B43) | F62: =IF(C43="","",C43) | H62: =IF(C43="","",IF(C43>0,ROUNDDOWN(H43/C43,2),0))
... A65: =IF(A46="","",A46) | B65: =IF(B46="","",B46) | F65: =IF(C46="","",C46) | H65: =IF(C46="","",IF(C46>0,ROUNDDOWN(H46/C46,2),0))
A67: RESUMO FINANCEIRO
A68: Contratado Mensal – Total (R$) (Σ Qtde × Valor Unitário de todos os postos) | F68: =I47 -> 11993.78
A69: Nota Final Apurada | F69: =D28 -> 9
A70: Nota Atribuída pelo Avaliador (Conceito) | F70: =F28 -> A
A71: % do Faturamento a ser Liberado | F71: =INDEX(Dados!$C$50:$C$55,MATCH(D28,Dados!$A$50:$A$55,1)) -> 1
A72: Valor Glosado por QUALIDADE (R$) | F72: =ROUNDDOWN(I47-I47*$F$71,2) -> 0
A73: Número de Dias do Mês (calculado) | F73: =IF(ISNUMBER(B7),DAY(EOMONTH(B7,0)),30) -> 30
A74: Número de Dias Trabalhados no Mês | F74: =IF(ISNUMBER(B7),DAY(EOMONTH(B7,0)),30) -> 30 | H74: Campo de preenchimento: altere apenas em mês parcial (início/fim de contrato)
A75: Dias para Cálculo (mês cheio = 30 avos) | F75: =IF(N(F74)>=$F$73,30,MAX(0,N(F74))) -> 30
A76: Soma dos Itens após Descontos (R$) | F76: =H47 -> 11993.78
A77: VALOR APROVADO PARA PAGAMENTO (R$) (Σ Itens após Descontos + Total dos Reembolsos de Creche) | F77: =MAX(0,ROUNDDOWN(H47+F83,2)) -> 11993.78
A79: 🏫 REEMBOLSO DE CRECHE
A80: Valor Reembolso Creche Retido (R$) | F80: =Dados!$D30 -> 0 | H80: Campo de preenchimento
A81: Reembolsos Aprovados (quantidade) | H81: Campo de preenchimento
A82: Reembolso por dependente (R$) | F82: =Dados!$D31 -> 0 | H82: Campo de preenchimento
A83: Valor Total dos Reembolsos (R$) (Aprovados × Reembolso por dependente) | F83: =ROUNDDOWN(N(F81)*N(F82),2) -> 0
A84: Saldo de Reembolso (R$) (acumulado: saldo da aba anterior + Retido – Total) | F84: =ROUNDDOWN(P09!F84+N(F80)-N(F83),2) -> 0
A85: =IF(F84<0,"⚠ ATENÇÃO: Saldo negativo — será necessário ADITIVAR O CONTRATO PARA SUPORTAR A DESPESA!","")
A87: FAIXA DE AJUSTE DE PAGAMENTO
A88: Conceito | D88: % do Faturamento a ser Pago | G88: Nota Média Mensal Apurada
A89: =Dados!$B$55 -> A | D89: =Dados!$C$55 -> 1 | G89: =Dados!$D$55 -> Entre 9,00 e 8,10
A90: =Dados!$B$54 -> B | D90: =Dados!$C$54 -> 0.95 | G90: =Dados!$D$54 -> Entre 8,09 e 7,65
A91: =Dados!$B$53 -> C | D91: =Dados!$C$53 -> 0.9 | G91: =Dados!$D$53 -> Entre 7,64 e 6,75
A92: =Dados!$B$52 -> D | D92: =Dados!$C$52 -> 0.85 | G92: =Dados!$D$52 -> Entre 6,74 e 5,85
A93: =Dados!$B$51 -> E | D93: =Dados!$C$51 -> 0.8 | G93: =Dados!$D$51 -> Entre 5,84 e 5,40
A94: =Dados!$B$50 -> F | D94: =Dados!$C$50 -> 0.75 | G94: =Dados!$D$50 -> Abaixo de 5,40
A96: APROVAÇÃO E ASSINATURAS
A97: Fiscal Operacional | D97: Fiscal Administrativo (¹) | G97: Representante da Contratada | I97: Data da Aprovação
A100: Nome completo / Matrícula | D100: Nome completo / Matrícula | G100: Nome completo / Cargo | I100: dd/mm/aaaa
A102: 📝 JUSTIFICATIVAS (obrigatório para notas 0 e 1)
A107: =IF(COUNTIF(C13:C27,0)+COUNTIF(C13:C27,1)>0,"⚠ Existem notas 0 ou 1 nesta aba — a justificativa acima é OBRIGATÓRIA. Informe critério, nota e fundamentação.","Para cada nota 0 ou 1 informe: critério, nota atribuída e fundamentação.") -> Para cada nota 0 ou 1 informe: critério, nota atribuída e fundamentação.

Sheet P11
A1: UFRJ – PRÓ-REITORIA DE GESTÃO E GOVERNANÇA – PR6 | IMR
A2: INSTRUMENTO DE MEDIÇÃO DE RESULTADO
A3: =IF(Dados!$B$6="","",Dados!$B$6) -> Atualizado conforme Valor Unitário Contratado inicial
A5: CONTRATO Nº: | B5: =IF(Dados!$B$2="","",Dados!$B$2) -> 04/24 | E5: UNIDADE: | G5: =IF(Dados!$B$3="","",Dados!$B$3) -> CBAE
A6: CONTRATADA: | B6: =IF(Dados!$B$4="","",Dados!$B$4) -> Angels | E6: FISCAL OPERACIONAL: | G6: =IF(Dados!$B$5="","",Dados!$B$5)
A7: AVALIAÇÃO REFERENTE AO PERÍODO: | B7: =IF(Dados!$B$7="","(informe o período inicial na aba Dados)",EDATE(Dados!$B$7,10)) -> (informe o período inicial na aba Dados) | E7: PERÍODO (ABA) Nº: | G7: 11 de 60
A8: ⚠ Para notas 0 e 1 o campo JUSTIFICATIVAS (fim da aba) é de preenchimento obrigatório. | Contrato, Unidade, Contratada e Postos são compartilhados por todas as abas (aba Dados).
A10: AVALIAÇÃO DE DESEMPENHO
A11: Critério de Avaliação | B11: PESO (a) | C11: NOTA (b) (0, 1 ou 3) | D11: SUBTOTAL (c = a × b) | E11: Status | F11: Aviso de Justificativa
A12: ▶ GRUPO 1 – DESEMPENHO PROFISSIONAL
A13: =Dados!$B$36 -> Cumprimento das Atividades | B13: =Dados!$C$36 -> 0.4 | C13: 3 | D13: =B13*C13 -> 1.2 | E13: =IF(OR(C13=0,C13=1,C13=3),"✓ Ok","⛔ Inválida") -> ✓ Ok | F13: =IF(OR(C13=0,C13=1),"⚠ Favor inserir justificativa da nota "&C13&" no campo JUSTIFICATIVAS","")
A14: =Dados!$B$37 -> Qualificação / Atendimento ao Público / Postura | B14: =Dados!$C$37 -> 0.35 | C14: 3 | D14: =B14*C14 -> 1.05 | E14: =IF(OR(C14=0,C14=1,C14=3),"✓ Ok","⛔ Inválida") -> ✓ Ok | F14: =IF(OR(C14=0,C14=1),"⚠ Favor inserir justificativa da nota "&C14&" no campo JUSTIFICATIVAS","")
A15: =Dados!$B$38 -> Uniformes e Identificação | B15: =Dados!$C$38 -> 0.25 | C15: 3 | D15: =B15*C15 -> 0.75 | E15: =IF(OR(C15=0,C15=1,C15=3),"✓ Ok","⛔ Inválida") -> ✓ Ok | F15: =IF(OR(C15=0,C15=1),"⚠ Favor inserir justificativa da nota "&C15&" no campo JUSTIFICATIVAS","")
A16: TOTAL GRUPO 1 | B16: =SUM(B13:B15) -> 1 | D16: =SUM(D13:D15) -> 3
A17: ▶ GRUPO 2 – DESEMPENHO DAS ATIVIDADES
A18: =Dados!$B$39 -> Especificação Técnica dos Serviços | B18: =Dados!$C$39 -> 0.4 | C18: 3 | D18: =B18*C18 -> 1.2 | E18: =IF(OR(C18=0,C18=1,C18=3),"✓ Ok","⛔ Inválida") -> ✓ Ok | F18: =IF(OR(C18=0,C18=1),"⚠ Favor inserir justificativa da nota "&C18&" no campo JUSTIFICATIVAS","")
A19: =Dados!$B$40 -> Equipamentos e Acessórios | B19: =Dados!$C$40 -> 0.2 | C19: 3 | D19: =B19*C19 -> 0.6 | E19: =IF(OR(C19=0,C19=1,C19=3),"✓ Ok","⛔ Inválida") -> ✓ Ok | F19: =IF(OR(C19=0,C19=1),"⚠ Favor inserir justificativa da nota "&C19&" no campo JUSTIFICATIVAS","")
A20: =Dados!$B$41 -> Atendimento às Ocorrências | B20: =Dados!$C$41 -> 0.4 | C20: 3 | D20: =B20*C20 -> 1.2 | E20: =IF(OR(C20=0,C20=1,C20=3),"✓ Ok","⛔ Inválida") -> ✓ Ok | F20: =IF(OR(C20=0,C20=1),"⚠ Favor inserir justificativa da nota "&C20&" no campo JUSTIFICATIVAS","")
A21: TOTAL GRUPO 2 | B21: =SUM(B18:B20) -> 1 | D21: =SUM(D18:D20) -> 3
A22: ▶ GRUPO 3 – GERENCIAMENTO
A23: =Dados!$B$42 -> Periodicidade da Supervisão | B23: =Dados!$C$42 -> 0.2 | C23: 3 | D23: =B23*C23 -> 0.6 | E23: =IF(OR(C23=0,C23=1,C23=3),"✓ Ok","⛔ Inválida") -> ✓ Ok | F23: =IF(OR(C23=0,C23=1),"⚠ Favor inserir justificativa da nota "&C23&" no campo JUSTIFICATIVAS","")
A24: =Dados!$B$43 -> Gerenciamento das Atividades Operacionais | B24: =Dados!$C$43 -> 0.3 | C24: 3 | D24: =B24*C24 -> 0.9 | E24: =IF(OR(C24=0,C24=1,C24=3),"✓ Ok","⛔ Inválida") -> ✓ Ok | F24: =IF(OR(C24=0,C24=1),"⚠ Favor inserir justificativa da nota "&C24&" no campo JUSTIFICATIVAS","")
A25: =Dados!$B$44 -> Atendimento às Solicitações | B25: =Dados!$C$44 -> 0.25 | C25: 3 | D25: =B25*C25 -> 0.75 | E25: =IF(OR(C25=0,C25=1,C25=3),"✓ Ok","⛔ Inválida") -> ✓ Ok | F25: =IF(OR(C25=0,C25=1),"⚠ Favor inserir justificativa da nota "&C25&" no campo JUSTIFICATIVAS","")
A26: =Dados!$B$45 -> Salários, Benefícios e Obrigações Trabalhistas (¹ Fiscal Adm.) | B26: =Dados!$C$45 -> 0.25 | C26: 3 | D26: =B26*C26 -> 0.75 | E26: =IF(OR(C26=0,C26=1,C26=3),"✓ Ok","⛔ Inválida") -> ✓ Ok | F26: =IF(OR(C26=0,C26=1),"⚠ Favor inserir justificativa da nota "&C26&" no campo JUSTIFICATIVAS","")
A27: TOTAL GRUPO 3 | B27: =SUM(B23:B26) -> 1 | D27: =SUM(D23:D26) -> 3
A28: NOTA FINAL (somatório dos Grupos 1, 2 e 3) | D28: =D16+D21+D27 -> 9 | E28: Conceito: | F28: =INDEX(Dados!$B$50:$B$55,MATCH(D28,Dados!$A$50:$A$55,1)) -> A | G28: (¹) Grupo 3 – Salários/Benefícios/Obrigações Trabalhistas: preenchido pelo Fiscal Administrativo
A30: POSTOS DE TRABALHO
A31: Item | B31: POSTO | C31: Qtde Contratada | D31: Valor Unit. Contratado (R$) | E31: Horas Contratadas | F31: Sem Cobertura (h) | G31: Valor da Hora Contratada (R$) | H31: Valor do Item após Descontos (R$) | I31: Mensal Contratado (R$)
A32: =IF(Dados!$A$12="","",Dados!$A$12) -> 1 | B32: =IF(Dados!$B$12="","",Dados!$B$12) -> Vigilante Diurno 12x36 (exemplo) | C32: =IF(Dados!$C$12="","",Dados!$C$12) -> 2 | D32: =IF(Dados!$D$12="","",Dados!$D$12) -> 5996.89 | E32: =IF(C32="","",C32*220) -> 440 | G32: =IF(C32="","",IF(C32>0,ROUNDDOWN(N(D32)/220,2),0)) -> 27.25 | H32: =IF(C32="","",IF(AND(C32>0,N(D32)>0),MAX(0,ROUNDDOWN((C32*N(D32)-G32*N(F32))/30*$F$75*$F$71,2)),0)) -> 11993.78 | I32: =IF(C32="","",ROUNDDOWN(C32*N(D32),2)) -> 11993.78
A33: =IF(Dados!$A$13="","",Dados!$A$13) | B33: =IF(Dados!$B$13="","",Dados!$B$13) | C33: =IF(Dados!$C$13="","",Dados!$C$13) | D33: =IF(Dados!$D$13="","",Dados!$D$13) | E33: =IF(C33="","",C33*220) | G33: =IF(C33="","",IF(C33>0,ROUNDDOWN(N(D33)/220,2),0)) | H33: =IF(C33="","",IF(AND(C33>0,N(D33)>0),MAX(0,ROUNDDOWN((C33*N(D33)-G33*N(F33))/30*$F$75*$F$71,2)),0)) | I33: =IF(C33="","",ROUNDDOWN(C33*N(D33),2))
A34: =IF(Dados!$A$14="","",Dados!$A$14) | B34: =IF(Dados!$B$14="","",Dados!$B$14) | C34: =IF(Dados!$C$14="","",Dados!$C$14) | D34: =IF(Dados!$D$14="","",Dados!$D$14) | E34: =IF(C34="","",C34*220) | G34: =IF(C34="","",IF(C34>0,ROUNDDOWN(N(D34)/220,2),0)) | H34: =IF(C34="","",IF(AND(C34>0,N(D34)>0),MAX(0,ROUNDDOWN((C34*N(D34)-G34*N(F34))/30*$F$75*$F$71,2)),0)) | I34: =IF(C34="","",ROUNDDOWN(C34*N(D34),2))
A35: =IF(Dados!$A$15="","",Dados!$A$15) | B35: =IF(Dados!$B$15="","",Dados!$B$15) | C35: =IF(Dados!$C$15="","",Dados!$C$15) | D35: =IF(Dados!$D$15="","",Dados!$D$15) | E35: =IF(C35="","",C35*220) | G35: =IF(C35="","",IF(C35>0,ROUNDDOWN(N(D35)/220,2),0)) | H35: =IF(C35="","",IF(AND(C35>0,N(D35)>0),MAX(0,ROUNDDOWN((C35*N(D35)-G35*N(F35))/30*$F$75*$F$71,2)),0)) | I35: =IF(C35="","",ROUNDDOWN(C35*N(D35),2))
A36: =IF(Dados!$A$16="","",Dados!$A$16) | B36: =IF(Dados!$B$16="","",Dados!$B$16) | C36: =IF(Dados!$C$16="","",Dados!$C$16) | D36: =IF(Dados!$D$16="","",Dados!$D$16) | E36: =IF(C36="","",C36*220) | G36: =IF(C36="","",IF(C36>0,ROUNDDOWN(N(D36)/220,2),0)) | H36: =IF(C36="","",IF(AND(C36>0,N(D36)>0),MAX(0,ROUNDDOWN((C36*N(D36)-G36*N(F36))/30*$F$75*$F$71,2)),0)) | I36: =IF(C36="","",ROUNDDOWN(C36*N(D36),2))
A37: =IF(Dados!$A$17="","",Dados!$A$17) | B37: =IF(Dados!$B$17="","",Dados!$B$17) | C37: =IF(Dados!$C$17="","",Dados!$C$17) | D37: =IF(Dados!$D$17="","",Dados!$D$17) | E37: =IF(C37="","",C37*220) | G37: =IF(C37="","",IF(C37>0,ROUNDDOWN(N(D37)/220,2),0)) | H37: =IF(C37="","",IF(AND(C37>0,N(D37)>0),MAX(0,ROUNDDOWN((C37*N(D37)-G37*N(F37))/30*$F$75*$F$71,2)),0)) | I37: =IF(C37="","",ROUNDDOWN(C37*N(D37),2))
A38: =IF(Dados!$A$18="","",Dados!$A$18) | B38: =IF(Dados!$B$18="","",Dados!$B$18) | C38: =IF(Dados!$C$18="","",Dados!$C$18) | D38: =IF(Dados!$D$18="","",Dados!$D$18) | E38: =IF(C38="","",C38*220) | G38: =IF(C38="","",IF(C38>0,ROUNDDOWN(N(D38)/220,2),0)) | H38: =IF(C38="","",IF(AND(C38>0,N(D38)>0),MAX(0,ROUNDDOWN((C38*N(D38)-G38*N(F38))/30*$F$75*$F$71,2)),0)) | I38: =IF(C38="","",ROUNDDOWN(C38*N(D38),2))
A39: =IF(Dados!$A$19="","",Dados!$A$19) | B39: =IF(Dados!$B$19="","",Dados!$B$19) | C39: =IF(Dados!$C$19="","",Dados!$C$19) | D39: =IF(Dados!$D$19="","",Dados!$D$19) | E39: =IF(C39="","",C39*220) | G39: =IF(C39="","",IF(C39>0,ROUNDDOWN(N(D39)/220,2),0)) | H39: =IF(C39="","",IF(AND(C39>0,N(D39)>0),MAX(0,ROUNDDOWN((C39*N(D39)-G39*N(F39))/30*$F$75*$F$71,2)),0)) | I39: =IF(C39="","",ROUNDDOWN(C39*N(D39),2))
A40: =IF(Dados!$A$20="","",Dados!$A$20) | B40: =IF(Dados!$B$20="","",Dados!$B$20) | C40: =IF(Dados!$C$20="","",Dados!$C$20) | D40: =IF(Dados!$D$20="","",Dados!$D$20) | E40: =IF(C40="","",C40*220) | G40: =IF(C40="","",IF(C40>0,ROUNDDOWN(N(D40)/220,2),0)) | H40: =IF(C40="","",IF(AND(C40>0,N(D40)>0),MAX(0,ROUNDDOWN((C40*N(D40)-G40*N(F40))/30*$F$75*$F$71,2)),0)) | I40: =IF(C40="","",ROUNDDOWN(C40*N(D40),2))
A41: =IF(Dados!$A$21="","",Dados!$A$21) | B41: =IF(Dados!$B$21="","",Dados!$B$21) | C41: =IF(Dados!$C$21="","",Dados!$C$21) | D41: =IF(Dados!$D$21="","",Dados!$D$21) | E41: =IF(C41="","",C41*220) | G41: =IF(C41="","",IF(C41>0,ROUNDDOWN(N(D41)/220,2),0)) | H41: =IF(C41="","",IF(AND(C41>0,N(D41)>0),MAX(0,ROUNDDOWN((C41*N(D41)-G41*N(F41))/30*$F$75*$F$71,2)),0)) | I41: =IF(C41="","",ROUNDDOWN(C41*N(D41),2))
A42: =IF(Dados!$A$22="","",Dados!$A$22) | B42: =IF(Dados!$B$22="","",Dados!$B$22) | C42: =IF(Dados!$C$22="","",Dados!$C$22) | D42: =IF(Dados!$D$22="","",Dados!$D$22) | E42: =IF(C42="","",C42*220) | G42: =IF(C42="","",IF(C42>0,ROUNDDOWN(N(D42)/220,2),0)) | H42: =IF(C42="","",IF(AND(C42>0,N(D42)>0),MAX(0,ROUNDDOWN((C42*N(D42)-G42*N(F42))/30*$F$75*$F$71,2)),0)) | I42: =IF(C42="","",ROUNDDOWN(C42*N(D42),2))
A43: =IF(Dados!$A$23="","",Dados!$A$23) | B43: =IF(Dados!$B$23="","",Dados!$B$23) | C43: =IF(Dados!$C$23="","",Dados!$C$23) | D43: =IF(Dados!$D$23="","",Dados!$D$23) | E43: =IF(C43="","",C43*220) | G43: =IF(C43="","",IF(C43>0,ROUNDDOWN(N(D43)/220,2),0)) | H43: =IF(C43="","",IF(AND(C43>0,N(D43)>0),MAX(0,ROUNDDOWN((C43*N(D43)-G43*N(F43))/30*$F$75*$F$71,2)),0)) | I43: =IF(C43="","",ROUNDDOWN(C43*N(D43),2))
A44: =IF(Dados!$A$24="","",Dados!$A$24) | B44: =IF(Dados!$B$24="","",Dados!$B$24) | C44: =IF(Dados!$C$24="","",Dados!$C$24) | D44: =IF(Dados!$D$24="","",Dados!$D$24) | E44: =IF(C44="","",C44*220) | G44: =IF(C44="","",IF(C44>0,ROUNDDOWN(N(D44)/220,2),0)) | H44: =IF(C44="","",IF(AND(C44>0,N(D44)>0),MAX(0,ROUNDDOWN((C44*N(D44)-G44*N(F44))/30*$F$75*$F$71,2)),0)) | I44: =IF(C44="","",ROUNDDOWN(C44*N(D44),2))
A45: =IF(Dados!$A$25="","",Dados!$A$25) | B45: =IF(Dados!$B$25="","",Dados!$B$25) | C45: =IF(Dados!$C$25="","",Dados!$C$25) | D45: =IF(Dados!$D$25="","",Dados!$D$25) | E45: =IF(C45="","",C45*220) | G45: =IF(C45="","",IF(C45>0,ROUNDDOWN(N(D45)/220,2),0)) | H45: =IF(C45="","",IF(AND(C45>0,N(D45)>0),MAX(0,ROUNDDOWN((C45*N(D45)-G45*N(F45))/30*$F$75*$F$71,2)),0)) | I45: =IF(C45="","",ROUNDDOWN(C45*N(D45),2))
A46: =IF(Dados!$A$26="","",Dados!$A$26) | B46: =IF(Dados!$B$26="","",Dados!$B$26) | C46: =IF(Dados!$C$26="","",Dados!$C$26) | D46: =IF(Dados!$D$26="","",Dados!$D$26) | E46: =IF(C46="","",C46*220) | G46: =IF(C46="","",IF(C46>0,ROUNDDOWN(N(D46)/220,2),0)) | H46: =IF(C46="","",IF(AND(C46>0,N(D46)>0),MAX(0,ROUNDDOWN((C46*N(D46)-G46*N(F46))/30*$F$75*$F$71,2)),0)) | I46: =IF(C46="","",ROUNDDOWN(C46*N(D46),2))
A47: TOTAIS | F47: =SUM(F32:F46) -> 0 | H47: =SUM(H32:H46) -> 11993.78 | I47: =SUM(I32:I46) -> 11993.78
A49: 📋 INSTRUMENTO DE COBRANÇA
A50: Item | B50: Posto | F50: Qtde Faturada | H50: Valor Unit. Faturado (R$)
A51: =IF(A32="","",A32) -> 1 | B51: =IF(B32="","",B32) -> Vigilante Diurno 12x36 (exemplo) | F51: =IF(C32="","",C32) -> 2 | H51: =IF(C32="","",IF(C32>0,ROUNDDOWN(H32/C32,2),0)) -> 5996.89
A52: =IF(A33="","",A33) | B52: =IF(B33="","",B33) | F52: =IF(C33="","",C33) | H52: =IF(C33="","",IF(C33>0,ROUNDDOWN(H33/C33,2),0))
A53: =IF(A34="","",A34) | B53: =IF(B34="","",B34) | F53: =IF(C34="","",C34) | H53: =IF(C34="","",IF(C34>0,ROUNDDOWN(H34/C34,2),0))
A54: =IF(A35="","",A35) | B54: =IF(B35="","",B35) | F54: =IF(C35="","",C35) | H54: =IF(C35="","",IF(C35>0,ROUNDDOWN(H35/C35,2),0))
A55: =IF(A36="","",A36) | B55: =IF(B36="","",B36) | F55: =IF(C36="","",C36) | H55: =IF(C36="","",IF(C36>0,ROUNDDOWN(H36/C36,2),0))
A56: =IF(A37="","",A37) | B56: =IF(B37="","",B37) | F56: =IF(C37="","",C37) | H56: =IF(C37="","",IF(C37>0,ROUNDDOWN(H37/C37,2),0))
A57: =IF(A38="","",A38) | B57: =IF(B38="","",B38) | F57: =IF(C38="","",C38) | H57: =IF(C38="","",IF(C38>0,ROUNDDOWN(H38/C38,2),0))
A58: =IF(A39="","",A39) | B58: =IF(B39="","",B39) | F58: =IF(C39="","",C39) | H58: =IF(C39="","",IF(C39>0,ROUNDDOWN(H39/C39,2),0))
A59: =IF(A40="","",A40) | B59: =IF(B40="","",B40) | F59: =IF(C40="","",C40) | H59: =IF(C40="","",IF(C40>0,ROUNDDOWN(H40/C40,2),0))
A60: =IF(A41="","",A41) | B60: =IF(B41="","",B41) | F60: =IF(C41="","",C41) | H60: =IF(C41="","",IF(C41>0,ROUNDDOWN(H41/C41,2),0))
A61: =IF(A42="","",A42) | B61: =IF(B42="","",B42) | F61: =IF(C42="","",C42) | H61: =IF(C42="","",IF(C42>0,ROUNDDOWN(H42/C42,2),0))
A62: =IF(A43="","",A43) | B62: =IF(B43="","",B43) | F62: =IF(C43="","",C43) | H62: =IF(C43="","",IF(C43>0,ROUNDDOWN(H43/C43,2),0))
... A65: =IF(A46="","",A46) | B65: =IF(B46="","",B46) | F65: =IF(C46="","",C46) | H65: =IF(C46="","",IF(C46>0,ROUNDDOWN(H46/C46,2),0))
A67: RESUMO FINANCEIRO
A68: Contratado Mensal – Total (R$) (Σ Qtde × Valor Unitário de todos os postos) | F68: =I47 -> 11993.78
A69: Nota Final Apurada | F69: =D28 -> 9
A70: Nota Atribuída pelo Avaliador (Conceito) | F70: =F28 -> A
A71: % do Faturamento a ser Liberado | F71: =INDEX(Dados!$C$50:$C$55,MATCH(D28,Dados!$A$50:$A$55,1)) -> 1
A72: Valor Glosado por QUALIDADE (R$) | F72: =ROUNDDOWN(I47-I47*$F$71,2) -> 0
A73: Número de Dias do Mês (calculado) | F73: =IF(ISNUMBER(B7),DAY(EOMONTH(B7,0)),30) -> 30
A74: Número de Dias Trabalhados no Mês | F74: =IF(ISNUMBER(B7),DAY(EOMONTH(B7,0)),30) -> 30 | H74: Campo de preenchimento: altere apenas em mês parcial (início/fim de contrato)
A75: Dias para Cálculo (mês cheio = 30 avos) | F75: =IF(N(F74)>=$F$73,30,MAX(0,N(F74))) -> 30
A76: Soma dos Itens após Descontos (R$) | F76: =H47 -> 11993.78
A77: VALOR APROVADO PARA PAGAMENTO (R$) (Σ Itens após Descontos + Total dos Reembolsos de Creche) | F77: =MAX(0,ROUNDDOWN(H47+F83,2)) -> 11993.78
A79: 🏫 REEMBOLSO DE CRECHE
A80: Valor Reembolso Creche Retido (R$) | F80: =Dados!$D30 -> 0 | H80: Campo de preenchimento
A81: Reembolsos Aprovados (quantidade) | H81: Campo de preenchimento
A82: Reembolso por dependente (R$) | F82: =Dados!$D31 -> 0 | H82: Campo de preenchimento
A83: Valor Total dos Reembolsos (R$) (Aprovados × Reembolso por dependente) | F83: =ROUNDDOWN(N(F81)*N(F82),2) -> 0
A84: Saldo de Reembolso (R$) (acumulado: saldo da aba anterior + Retido – Total) | F84: =ROUNDDOWN(P10!F84+N(F80)-N(F83),2) -> 0
A85: =IF(F84<0,"⚠ ATENÇÃO: Saldo negativo — será necessário ADITIVAR O CONTRATO PARA SUPORTAR A DESPESA!","")
A87: FAIXA DE AJUSTE DE PAGAMENTO
A88: Conceito | D88: % do Faturamento a ser Pago | G88: Nota Média Mensal Apurada
A89: =Dados!$B$55 -> A | D89: =Dados!$C$55 -> 1 | G89: =Dados!$D$55 -> Entre 9,00 e 8,10
A90: =Dados!$B$54 -> B | D90: =Dados!$C$54 -> 0.95 | G90: =Dados!$D$54 -> Entre 8,09 e 7,65
A91: =Dados!$B$53 -> C | D91: =Dados!$C$53 -> 0.9 | G91: =Dados!$D$53 -> Entre 7,64 e 6,75
A92: =Dados!$B$52 -> D | D92: =Dados!$C$52 -> 0.85 | G92: =Dados!$D$52 -> Entre 6,74 e 5,85
A93: =Dados!$B$51 -> E | D93: =Dados!$C$51 -> 0.8 | G93: =Dados!$D$51 -> Entre 5,84 e 5,40
A94: =Dados!$B$50 -> F | D94: =Dados!$C$50 -> 0.75 | G94: =Dados!$D$50 -> Abaixo de 5,40
A96: APROVAÇÃO E ASSINATURAS
A97: Fiscal Operacional | D97: Fiscal Administrativo (¹) | G97: Representante da Contratada | I97: Data da Aprovação
A100: Nome completo / Matrícula | D100: Nome completo / Matrícula | G100: Nome completo / Cargo | I100: dd/mm/aaaa
A102: 📝 JUSTIFICATIVAS (obrigatório para notas 0 e 1)
A107: =IF(COUNTIF(C13:C27,0)+COUNTIF(C13:C27,1)>0,"⚠ Existem notas 0 ou 1 nesta aba — a justificativa acima é OBRIGATÓRIA. Informe critério, nota e fundamentação.","Para cada nota 0 ou 1 informe: critério, nota atribuída e fundamentação.") -> Para cada nota 0 ou 1 informe: critério, nota atribuída e fundamentação.

Sheet P12
A1: UFRJ – PRÓ-REITORIA DE GESTÃO E GOVERNANÇA – PR6 | IMR
A2: INSTRUMENTO DE MEDIÇÃO DE RESULTADO
A3: =IF(Dados!$B$6="","",Dados!$B$6) -> Atualizado conforme Valor Unitário Contratado inicial
A5: CONTRATO Nº: | B5: =IF(Dados!$B$2="","",Dados!$B$2) -> 04/24 | E5: UNIDADE: | G5: =IF(Dados!$B$3="","",Dados!$B$3) -> CBAE
A6: CONTRATADA: | B6: =IF(Dados!$B$4="","",Dados!$B$4) -> Angels | E6: FISCAL OPERACIONAL: | G6: =IF(Dados!$B$5="","",Dados!$B$5)
A7: AVALIAÇÃO REFERENTE AO PERÍODO: | B7: =IF(Dados!$B$7="","(informe o período inicial na aba Dados)",EDATE(Dados!$B$7,11)) -> (informe o período inicial na aba Dados) | E7: PERÍODO (ABA) Nº: | G7: 12 de 60
