Workbook

Sheet Resumo
B1: ANGEL'S 05/24 — MACAÉ — RESUMO DOS 60 MESES
B2: Cada mês tem sua aba. Valores calculados a partir das abas.
B3: Mês | C3: Posto (1º) | D3: Qtde | E3: Valor Unit. (R$) | F3: Dias | G3: Contratado Mensal (R$) | H3: Conceito | I3: % | J3: Valor Aprovado (R$)
B4: =HYPERLINK("#'Fevereiro 2024'!B1","Fevereiro 2024") | C4: ='Fevereiro 2024'!C42 | D4: ='Fevereiro 2024'!D42 | E4: ='Fevereiro 2024'!E42 | F4: ='Fevereiro 2024'!C37 | G4: ='Fevereiro 2024'!K49 | H4: ='Fevereiro 2024'!C33 | I4: ='Fevereiro 2024'!F33 | J4: ='Fevereiro 2024'!E66
B5: =HYPERLINK("#'Março 2024'!B1","Março 2024") | C5: ='Março 2024'!C42 | D5: ='Março 2024'!D42 | E5: ='Março 2024'!E42 | F5: ='Março 2024'!C37 | G5: ='Março 2024'!K49 | H5: ='Março 2024'!C33 | I5: ='Março 2024'!F33 | J5: ='Março 2024'!E66
B6: =HYPERLINK("#'Abril 2024'!B1","Abril 2024") | C6: ='Abril 2024'!C42 | D6: ='Abril 2024'!D42 | E6: ='Abril 2024'!E42 | F6: ='Abril 2024'!C37 | G6: ='Abril 2024'!K49 | H6: ='Abril 2024'!C33 | I6: ='Abril 2024'!F33 | J6: ='Abril 2024'!E66
B7: =HYPERLINK("#'Maio 2024'!B1","Maio 2024") | C7: ='Maio 2024'!C42 | D7: ='Maio 2024'!D42 | E7: ='Maio 2024'!E42 | F7: ='Maio 2024'!C37 | G7: ='Maio 2024'!K49 | H7: ='Maio 2024'!C33 | I7: ='Maio 2024'!F33 | J7: ='Maio 2024'!E66
B8: =HYPERLINK("#'Junho 2024'!B1","Junho 2024") | C8: ='Junho 2024'!C42 | D8: ='Junho 2024'!D42 | E8: ='Junho 2024'!E42 | F8: ='Junho 2024'!C37 | G8: ='Junho 2024'!K49 | H8: ='Junho 2024'!C33 | I8: ='Junho 2024'!F33 | J8: ='Junho 2024'!E66
B9: =HYPERLINK("#'Julho 2024'!B1","Julho 2024") | C9: ='Julho 2024'!C42 | D9: ='Julho 2024'!D42 | E9: ='Julho 2024'!E42 | F9: ='Julho 2024'!C37 | G9: ='Julho 2024'!K49 | H9: ='Julho 2024'!C33 | I9: ='Julho 2024'!F33 | J9: ='Julho 2024'!E66
B10: =HYPERLINK("#'Agosto 2024'!B1","Agosto 2024") | C10: ='Agosto 2024'!C42 | D10: ='Agosto 2024'!D42 | E10: ='Agosto 2024'!E42 | F10: ='Agosto 2024'!C37 | G10: ='Agosto 2024'!K49 | H10: ='Agosto 2024'!C33 | I10: ='Agosto 2024'!F33 | J10: ='Agosto 2024'!E66
B11: =HYPERLINK("#'Setembro 2024'!B1","Setembro 2024") | C11: ='Setembro 2024'!C42 | D11: ='Setembro 2024'!D42 | E11: ='Setembro 2024'!E42 | F11: ='Setembro 2024'!C37 | G11: ='Setembro 2024'!K49 | H11: ='Setembro 2024'!C33 | I11: ='Setembro 2024'!F33 | J11: ='Setembro 2024'!E66
B12: =HYPERLINK("#'Outubro 2024'!B1","Outubro 2024") | C12: ='Outubro 2024'!C42 | D12: ='Outubro 2024'!D42 | E12: ='Outubro 2024'!E42 | F12: ='Outubro 2024'!C37 | G12: ='Outubro 2024'!K49 | H12: ='Outubro 2024'!C33 | I12: ='Outubro 2024'!F33 | J12: ='Outubro 2024'!E66
B13: =HYPERLINK("#'Novembro 2024'!B1","Novembro 2024") | C13: ='Novembro 2024'!C42 | D13: ='Novembro 2024'!D42 | E13: ='Novembro 2024'!E42 | F13: ='Novembro 2024'!C37 | G13: ='Novembro 2024'!K49 | H13: ='Novembro 2024'!C33 | I13: ='Novembro 2024'!F33 | J13: ='Novembro 2024'!E66
B14: =HYPERLINK("#'Dezembro 2024'!B1","Dezembro 2024") | C14: ='Dezembro 2024'!C42 | D14: ='Dezembro 2024'!D42 | E14: ='Dezembro 2024'!E42 | F14: ='Dezembro 2024'!C37 | G14: ='Dezembro 2024'!K49 | H14: ='Dezembro 2024'!C33 | I14: ='Dezembro 2024'!F33 | J14: ='Dezembro 2024'!E66
B15: =HYPERLINK("#'Janeiro 2025'!B1","Janeiro 2025") | C15: ='Janeiro 2025'!C42 | D15: ='Janeiro 2025'!D42 | E15: ='Janeiro 2025'!E42 | F15: ='Janeiro 2025'!C37 | G15: ='Janeiro 2025'!K49 | H15: ='Janeiro 2025'!C33 | I15: ='Janeiro 2025'!F33 | J15: ='Janeiro 2025'!E66
B16: =HYPERLINK("#'Fevereiro 2025'!B1","Fevereiro 2025") | C16: ='Fevereiro 2025'!C42 | D16: ='Fevereiro 2025'!D42 | E16: ='Fevereiro 2025'!E42 | F16: ='Fevereiro 2025'!C37 | G16: ='Fevereiro 2025'!K49 | H16: ='Fevereiro 2025'!C33 | I16: ='Fevereiro 2025'!F33 | J16: ='Fevereiro 2025'!E66
B17: =HYPERLINK("#'Março 2025'!B1","Março 2025") | C17: ='Março 2025'!C42 | D17: ='Março 2025'!D42 | E17: ='Março 2025'!E42 | F17: ='Março 2025'!C37 | G17: ='Março 2025'!K49 | H17: ='Março 2025'!C33 | I17: ='Março 2025'!F33 | J17: ='Março 2025'!E66
B18: =HYPERLINK("#'Abril 2025'!B1","Abril 2025") | C18: ='Abril 2025'!C42 | D18: ='Abril 2025'!D42 | E18: ='Abril 2025'!E42 | F18: ='Abril 2025'!C37 | G18: ='Abril 2025'!K49 | H18: ='Abril 2025'!C33 | I18: ='Abril 2025'!F33 | J18: ='Abril 2025'!E66
B19: =HYPERLINK("#'Maio 2025'!B1","Maio 2025") | C19: ='Maio 2025'!C42 | D19: ='Maio 2025'!D42 | E19: ='Maio 2025'!E42 | F19: ='Maio 2025'!C37 | G19: ='Maio 2025'!K49 | H19: ='Maio 2025'!C33 | I19: ='Maio 2025'!F33 | J19: ='Maio 2025'!E66
B20: =HYPERLINK("#'Junho 2025'!B1","Junho 2025") | C20: ='Junho 2025'!C42 | D20: ='Junho 2025'!D42 | E20: ='Junho 2025'!E42 | F20: ='Junho 2025'!C37 | G20: ='Junho 2025'!K49 | H20: ='Junho 2025'!C33 | I20: ='Junho 2025'!F33 | J20: ='Junho 2025'!E66
B21: =HYPERLINK("#'Julho 2025'!B1","Julho 2025") | C21: ='Julho 2025'!C42 | D21: ='Julho 2025'!D42 | E21: ='Julho 2025'!E42 | F21: ='Julho 2025'!C37 | G21: ='Julho 2025'!K49 | H21: ='Julho 2025'!C33 | I21: ='Julho 2025'!F33 | J21: ='Julho 2025'!E66
B22: =HYPERLINK("#'Agosto 2025'!B1","Agosto 2025") | C22: ='Agosto 2025'!C42 | D22: ='Agosto 2025'!D42 | E22: ='Agosto 2025'!E42 | F22: ='Agosto 2025'!C37 | G22: ='Agosto 2025'!K49 | H22: ='Agosto 2025'!C33 | I22: ='Agosto 2025'!F33 | J22: ='Agosto 2025'!E66
B23: =HYPERLINK("#'Setembro 2025'!B1","Setembro 2025") | C23: ='Setembro 2025'!C42 | D23: ='Setembro 2025'!D42 | E23: ='Setembro 2025'!E42 | F23: ='Setembro 2025'!C37 | G23: ='Setembro 2025'!K49 | H23: ='Setembro 2025'!C33 | I23: ='Setembro 2025'!F33 | J23: ='Setembro 2025'!E66
B24: =HYPERLINK("#'Outubro 2025'!B1","Outubro 2025") | C24: ='Outubro 2025'!C42 | D24: ='Outubro 2025'!D42 | E24: ='Outubro 2025'!E42 | F24: ='Outubro 2025'!C37 | G24: ='Outubro 2025'!K49 | H24: ='Outubro 2025'!C33 | I24: ='Outubro 2025'!F33 | J24: ='Outubro 2025'!E66
B25: =HYPERLINK("#'Novembro 2025'!B1","Novembro 2025") | C25: ='Novembro 2025'!C42 | D25: ='Novembro 2025'!D42 | E25: ='Novembro 2025'!E42 | F25: ='Novembro 2025'!C37 | G25: ='Novembro 2025'!K49 | H25: ='Novembro 2025'!C33 | I25: ='Novembro 2025'!F33 | J25: ='Novembro 2025'!E66
B26: =HYPERLINK("#'Dezembro 2025'!B1","Dezembro 2025") | C26: ='Dezembro 2025'!C42 | D26: ='Dezembro 2025'!D42 | E26: ='Dezembro 2025'!E42 | F26: ='Dezembro 2025'!C37 | G26: ='Dezembro 2025'!K49 | H26: ='Dezembro 2025'!C33 | I26: ='Dezembro 2025'!F33 | J26: ='Dezembro 2025'!E66
B27: =HYPERLINK("#'Janeiro 2026'!B1","Janeiro 2026") | C27: ='Janeiro 2026'!C42 | D27: ='Janeiro 2026'!D42 | E27: ='Janeiro 2026'!E42 | F27: ='Janeiro 2026'!C37 | G27: ='Janeiro 2026'!K49 | H27: ='Janeiro 2026'!C33 | I27: ='Janeiro 2026'!F33 | J27: ='Janeiro 2026'!E66
B28: =HYPERLINK("#'Fevereiro 2026'!B1","Fevereiro 2026") | C28: ='Fevereiro 2026'!C42 | D28: ='Fevereiro 2026'!D42 | E28: ='Fevereiro 2026'!E42 | F28: ='Fevereiro 2026'!C37 | G28: ='Fevereiro 2026'!K49 | H28: ='Fevereiro 2026'!C33 | I28: ='Fevereiro 2026'!F33 | J28: ='Fevereiro 2026'!E66
B29: =HYPERLINK("#'Março 2026'!B1","Março 2026") | C29: ='Março 2026'!C42 | D29: ='Março 2026'!D42 | E29: ='Março 2026'!E42 | F29: ='Março 2026'!C37 | G29: ='Março 2026'!K49 | H29: ='Março 2026'!C33 | I29: ='Março 2026'!F33 | J29: ='Março 2026'!E66
B30: =HYPERLINK("#'Abril 2026'!B1","Abril 2026") | C30: ='Abril 2026'!C42 | D30: ='Abril 2026'!D42 | E30: ='Abril 2026'!E42 | F30: ='Abril 2026'!C37 | G30: ='Abril 2026'!K49 | H30: ='Abril 2026'!C33 | I30: ='Abril 2026'!F33 | J30: ='Abril 2026'!E66
B31: =HYPERLINK("#'Maio 2026'!B1","Maio 2026") | C31: ='Maio 2026'!C42 | D31: ='Maio 2026'!D42 | E31: ='Maio 2026'!E42 | F31: ='Maio 2026'!C37 | G31: ='Maio 2026'!K49 | H31: ='Maio 2026'!C33 | I31: ='Maio 2026'!F33 | J31: ='Maio 2026'!E66
B32: =HYPERLINK("#'Junho 2026'!B1","Junho 2026") | C32: ='Junho 2026'!C42 | D32: ='Junho 2026'!D42 | E32: ='Junho 2026'!E42 | F32: ='Junho 2026'!C37 | G32: ='Junho 2026'!K49 | H32: ='Junho 2026'!C33 | I32: ='Junho 2026'!F33 | J32: ='Junho 2026'!E66
B33: =HYPERLINK("#'Julho 2026'!B1","Julho 2026") | C33: ='Julho 2026'!C42 | D33: ='Julho 2026'!D42 | E33: ='Julho 2026'!E42 | F33: ='Julho 2026'!C37 | G33: ='Julho 2026'!K49 | H33: ='Julho 2026'!C33 | I33: ='Julho 2026'!F33 | J33: ='Julho 2026'!E66
B34: =HYPERLINK("#'Agosto 2026'!B1","Agosto 2026") | C34: ='Agosto 2026'!C42 | D34: ='Agosto 2026'!D42 | E34: ='Agosto 2026'!E42 | F34: ='Agosto 2026'!C37 | G34: ='Agosto 2026'!K49 | H34: ='Agosto 2026'!C33 | I34: ='Agosto 2026'!F33 | J34: ='Agosto 2026'!E66
B35: =HYPERLINK("#'Setembro 2026'!B1","Setembro 2026") | C35: ='Setembro 2026'!C42 | D35: ='Setembro 2026'!D42 | E35: ='Setembro 2026'!E42 | F35: ='Setembro 2026'!C37 | G35: ='Setembro 2026'!K49 | H35: ='Setembro 2026'!C33 | I35: ='Setembro 2026'!F33 | J35: ='Setembro 2026'!E66
B36: =HYPERLINK("#'Outubro 2026'!B1","Outubro 2026") | C36: ='Outubro 2026'!C42 | D36: ='Outubro 2026'!D42 | E36: ='Outubro 2026'!E42 | F36: ='Outubro 2026'!C37 | G36: ='Outubro 2026'!K49 | H36: ='Outubro 2026'!C33 | I36: ='Outubro 2026'!F33 | J36: ='Outubro 2026'!E66
B37: =HYPERLINK("#'Novembro 2026'!B1","Novembro 2026") | C37: ='Novembro 2026'!C42 | D37: ='Novembro 2026'!D42 | E37: ='Novembro 2026'!E42 | F37: ='Novembro 2026'!C37 | G37: ='Novembro 2026'!K49 | H37: ='Novembro 2026'!C33 | I37: ='Novembro 2026'!F33 | J37: ='Novembro 2026'!E66
B38: =HYPERLINK("#'Dezembro 2026'!B1","Dezembro 2026") | C38: ='Dezembro 2026'!C42 | D38: ='Dezembro 2026'!D42 | E38: ='Dezembro 2026'!E42 | F38: ='Dezembro 2026'!C37 | G38: ='Dezembro 2026'!K49 | H38: ='Dezembro 2026'!C33 | I38: ='Dezembro 2026'!F33 | J38: ='Dezembro 2026'!E66
B39: =HYPERLINK("#'Janeiro 2027'!B1","Janeiro 2027") | C39: ='Janeiro 2027'!C42 | D39: ='Janeiro 2027'!D42 | E39: ='Janeiro 2027'!E42 | F39: ='Janeiro 2027'!C37 | G39: ='Janeiro 2027'!K49 | H39: ='Janeiro 2027'!C33 | I39: ='Janeiro 2027'!F33 | J39: ='Janeiro 2027'!E66
B40: =HYPERLINK("#'Fevereiro 2027'!B1","Fevereiro 2027") | C40: ='Fevereiro 2027'!C42 | D40: ='Fevereiro 2027'!D42 | E40: ='Fevereiro 2027'!E42 | F40: ='Fevereiro 2027'!C37 | G40: ='Fevereiro 2027'!K49 | H40: ='Fevereiro 2027'!C33 | I40: ='Fevereiro 2027'!F33 | J40: ='Fevereiro 2027'!E66
B41: =HYPERLINK("#'Março 2027'!B1","Março 2027") | C41: ='Março 2027'!C42 | D41: ='Março 2027'!D42 | E41: ='Março 2027'!E42 | F41: ='Março 2027'!C37 | G41: ='Março 2027'!K49 | H41: ='Março 2027'!C33 | I41: ='Março 2027'!F33 | J41: ='Março 2027'!E66
B42: =HYPERLINK("#'Abril 2027'!B1","Abril 2027") | C42: ='Abril 2027'!C42 | D42: ='Abril 2027'!D42 | E42: ='Abril 2027'!E42 | F42: ='Abril 2027'!C37 | G42: ='Abril 2027'!K49 | H42: ='Abril 2027'!C33 | I42: ='Abril 2027'!F33 | J42: ='Abril 2027'!E66
B43: =HYPERLINK("#'Maio 2027'!B1","Maio 2027") | C43: ='Maio 2027'!C42 | D43: ='Maio 2027'!D42 | E43: ='Maio 2027'!E42 | F43: ='Maio 2027'!C37 | G43: ='Maio 2027'!K49 | H43: ='Maio 2027'!C33 | I43: ='Maio 2027'!F33 | J43: ='Maio 2027'!E66
B44: =HYPERLINK("#'Junho 2027'!B1","Junho 2027") | C44: ='Junho 2027'!C42 | D44: ='Junho 2027'!D42 | E44: ='Junho 2027'!E42 | F44: ='Junho 2027'!C37 | G44: ='Junho 2027'!K49 | H44: ='Junho 2027'!C33 | I44: ='Junho 2027'!F33 | J44: ='Junho 2027'!E66
B45: =HYPERLINK("#'Julho 2027'!B1","Julho 2027") | C45: ='Julho 2027'!C42 | D45: ='Julho 2027'!D42 | E45: ='Julho 2027'!E42 | F45: ='Julho 2027'!C37 | G45: ='Julho 2027'!K49 | H45: ='Julho 2027'!C33 | I45: ='Julho 2027'!F33 | J45: ='Julho 2027'!E66
B46: =HYPERLINK("#'Agosto 2027'!B1","Agosto 2027") | C46: ='Agosto 2027'!C42 | D46: ='Agosto 2027'!D42 | E46: ='Agosto 2027'!E42 | F46: ='Agosto 2027'!C37 | G46: ='Agosto 2027'!K49 | H46: ='Agosto 2027'!C33 | I46: ='Agosto 2027'!F33 | J46: ='Agosto 2027'!E66
B47: =HYPERLINK("#'Setembro 2027'!B1","Setembro 2027") | C47: ='Setembro 2027'!C42 | D47: ='Setembro 2027'!D42 | E47: ='Setembro 2027'!E42 | F47: ='Setembro 2027'!C37 | G47: ='Setembro 2027'!K49 | H47: ='Setembro 2027'!C33 | I47: ='Setembro 2027'!F33 | J47: ='Setembro 2027'!E66
B48: =HYPERLINK("#'Outubro 2027'!B1","Outubro 2027") | C48: ='Outubro 2027'!C42 | D48: ='Outubro 2027'!D42 | E48: ='Outubro 2027'!E42 | F48: ='Outubro 2027'!C37 | G48: ='Outubro 2027'!K49 | H48: ='Outubro 2027'!C33 | I48: ='Outubro 2027'!F33 | J48: ='Outubro 2027'!E66
B49: =HYPERLINK("#'Novembro 2027'!B1","Novembro 2027") | C49: ='Novembro 2027'!C42 | D49: ='Novembro 2027'!D42 | E49: ='Novembro 2027'!E42 | F49: ='Novembro 2027'!C37 | G49: ='Novembro 2027'!K49 | H49: ='Novembro 2027'!C33 | I49: ='Novembro 2027'!F33 | J49: ='Novembro 2027'!E66
B50: =HYPERLINK("#'Dezembro 2027'!B1","Dezembro 2027") | C50: ='Dezembro 2027'!C42 | D50: ='Dezembro 2027'!D42 | E50: ='Dezembro 2027'!E42 | F50: ='Dezembro 2027'!C37 | G50: ='Dezembro 2027'!K49 | H50: ='Dezembro 2027'!C33 | I50: ='Dezembro 2027'!F33 | J50: ='Dezembro 2027'!E66
B51: =HYPERLINK("#'Janeiro 2028'!B1","Janeiro 2028") | C51: ='Janeiro 2028'!C42 | D51: ='Janeiro 2028'!D42 | E51: ='Janeiro 2028'!E42 | F51: ='Janeiro 2028'!C37 | G51: ='Janeiro 2028'!K49 | H51: ='Janeiro 2028'!C33 | I51: ='Janeiro 2028'!F33 | J51: ='Janeiro 2028'!E66
B52: =HYPERLINK("#'Fevereiro 2028'!B1","Fevereiro 2028") | C52: ='Fevereiro 2028'!C42 | D52: ='Fevereiro 2028'!D42 | E52: ='Fevereiro 2028'!E42 | F52: ='Fevereiro 2028'!C37 | G52: ='Fevereiro 2028'!K49 | H52: ='Fevereiro 2028'!C33 | I52: ='Fevereiro 2028'!F33 | J52: ='Fevereiro 2028'!E66
B53: =HYPERLINK("#'Março 2028'!B1","Março 2028") | C53: ='Março 2028'!C42 | D53: ='Março 2028'!D42 | E53: ='Março 2028'!E42 | F53: ='Março 2028'!C37 | G53: ='Março 2028'!K49 | H53: ='Março 2028'!C33 | I53: ='Março 2028'!F33 | J53: ='Março 2028'!E66
B54: =HYPERLINK("#'Abril 2028'!B1","Abril 2028") | C54: ='Abril 2028'!C42 | D54: ='Abril 2028'!D42 | E54: ='Abril 2028'!E42 | F54: ='Abril 2028'!C37 | G54: ='Abril 2028'!K49 | H54: ='Abril 2028'!C33 | I54: ='Abril 2028'!F33 | J54: ='Abril 2028'!E66
B55: =HYPERLINK("#'Maio 2028'!B1","Maio 2028") | C55: ='Maio 2028'!C42 | D55: ='Maio 2028'!D42 | E55: ='Maio 2028'!E42 | F55: ='Maio 2028'!C37 | G55: ='Maio 2028'!K49 | H55: ='Maio 2028'!C33 | I55: ='Maio 2028'!F33 | J55: ='Maio 2028'!E66
B56: =HYPERLINK("#'Junho 2028'!B1","Junho 2028") | C56: ='Junho 2028'!C42 | D56: ='Junho 2028'!D42 | E56: ='Junho 2028'!E42 | F56: ='Junho 2028'!C37 | G56: ='Junho 2028'!K49 | H56: ='Junho 2028'!C33 | I56: ='Junho 2028'!F33 | J56: ='Junho 2028'!E66
B57: =HYPERLINK("#'Julho 2028'!B1","Julho 2028") | C57: ='Julho 2028'!C42 | D57: ='Julho 2028'!D42 | E57: ='Julho 2028'!E42 | F57: ='Julho 2028'!C37 | G57: ='Julho 2028'!K49 | H57: ='Julho 2028'!C33 | I57: ='Julho 2028'!F33 | J57: ='Julho 2028'!E66
B58: =HYPERLINK("#'Agosto 2028'!B1","Agosto 2028") | C58: ='Agosto 2028'!C42 | D58: ='Agosto 2028'!D42 | E58: ='Agosto 2028'!E42 | F58: ='Agosto 2028'!C37 | G58: ='Agosto 2028'!K49 | H58: ='Agosto 2028'!C33 | I58: ='Agosto 2028'!F33 | J58: ='Agosto 2028'!E66
B59: =HYPERLINK("#'Setembro 2028'!B1","Setembro 2028") | C59: ='Setembro 2028'!C42 | D59: ='Setembro 2028'!D42 | E59: ='Setembro 2028'!E42 | F59: ='Setembro 2028'!C37 | G59: ='Setembro 2028'!K49 | H59: ='Setembro 2028'!C33 | I59: ='Setembro 2028'!F33 | J59: ='Setembro 2028'!E66
B60: =HYPERLINK("#'Outubro 2028'!B1","Outubro 2028") | C60: ='Outubro 2028'!C42 | D60: ='Outubro 2028'!D42 | E60: ='Outubro 2028'!E42 | F60: ='Outubro 2028'!C37 | G60: ='Outubro 2028'!K49 | H60: ='Outubro 2028'!C33 | I60: ='Outubro 2028'!F33 | J60: ='Outubro 2028'!E66
B61: =HYPERLINK("#'Novembro 2028'!B1","Novembro 2028") | C61: ='Novembro 2028'!C42 | D61: ='Novembro 2028'!D42 | E61: ='Novembro 2028'!E42 | F61: ='Novembro 2028'!C37 | G61: ='Novembro 2028'!K49 | H61: ='Novembro 2028'!C33 | I61: ='Novembro 2028'!F33 | J61: ='Novembro 2028'!E66
B62: =HYPERLINK("#'Dezembro 2028'!B1","Dezembro 2028") | C62: ='Dezembro 2028'!C42 | D62: ='Dezembro 2028'!D42 | E62: ='Dezembro 2028'!E42 | F62: ='Dezembro 2028'!C37 | G62: ='Dezembro 2028'!K49 | H62: ='Dezembro 2028'!C33 | I62: ='Dezembro 2028'!F33 | J62: ='Dezembro 2028'!E66
B63: =HYPERLINK("#'Janeiro 2029'!B1","Janeiro 2029") | C63: ='Janeiro 2029'!C42 | D63: ='Janeiro 2029'!D42 | E63: ='Janeiro 2029'!E42 | F63: ='Janeiro 2029'!C37 | G63: ='Janeiro 2029'!K49 | H63: ='Janeiro 2029'!C33 | I63: ='Janeiro 2029'!F33 | J63: ='Janeiro 2029'!E66
B64: TOTAL | G64: =SUM(G4:G63) | J64: =SUM(J4:J63)

Sheet Fevereiro 2024
B1: UNIVERSIDADE FEDERAL DO RIO DE JANEIRO — PR-6
B3: INSTRUMENTO DE MEDIÇÃO DE RESULTADO (IMR)
B7: IDENTIFICAÇÃO
B8: CONTRATO Nº | C8: 05/24
B9: UNIDADE | C9: MACAÉ
B10: CONTRATADA | C10: ANGEL'S SEGURANÇA E VIGILÂNCIA - EM RECUPERAÇÃO JUDICIAL LTDA
B11: FISCAL OPERACIONAL
B12: PERÍODO DE REFERÊNCIA | C12: Fevereiro 2024
B14: AVALIAÇÃO DE DESEMPENHO
B15: Critério de Avaliação | C15: PESO (a) | D15: NOTA (b) (0,1,3) | E15: SUBTOTAL (c=a×b)
B16: ▶ GRUPO 1 – DESEMPENHO PROFISSIONAL
B17: Cumprimento das Atividades | C17: 0.4 | D17: 3 | E17: =C17*D17 | G17: =IF(OR(D17=0,D17=1),"Obrigatória justificativa no campo Justificativa e observações","")
B18: Qualificação / Atendimento ao Público / Postura | C18: 0.35 | D18: 3 | E18: =C18*D18 | G18: =IF(OR(D18=0,D18=1),"Obrigatória justificativa no campo Justificativa e observações","")
B19: Uniformes e Identificação | C19: 0.25 | D19: 3 | E19: =C19*D19 | G19: =IF(OR(D19=0,D19=1),"Obrigatória justificativa no campo Justificativa e observações","")
B20: TOTAL GRUPO 1 | C20: 1 | E20: =E17+E18+E19
B21: ▶ GRUPO 2 – DESEMPENHO DAS ATIVIDADES
B22: Especificação Técnica dos Serviços | C22: 0.4 | D22: 3 | E22: =C22*D22 | G22: =IF(OR(D22=0,D22=1),"Obrigatória justificativa no campo Justificativa e observações","")
B23: Equipamentos e Acessórios | C23: 0.2 | D23: 3 | E23: =C23*D23 | G23: =IF(OR(D23=0,D23=1),"Obrigatória justificativa no campo Justificativa e observações","")
B24: Atendimento às Ocorrências | C24: 0.4 | D24: 3 | E24: =C24*D24 | G24: =IF(OR(D24=0,D24=1),"Obrigatória justificativa no campo Justificativa e observações","")
B25: TOTAL GRUPO 2 | C25: 1 | E25: =E22+E23+E24
B26: ▶ GRUPO 3 – GERENCIAMENTO
B27: Periodicidade da Supervisão | C27: 0.2 | D27: 3 | E27: =C27*D27 | G27: =IF(OR(D27=0,D27=1),"Obrigatória justificativa no campo Justificativa e observações","")
B28: Gerenciamento das Atividades Operacionais | C28: 0.3 | D28: 3 | E28: =C28*D28 | G28: =IF(OR(D28=0,D28=1),"Obrigatória justificativa no campo Justificativa e observações","")
B29: Atendimento às Solicitações | C29: 0.25 | D29: 3 | E29: =C29*D29 | G29: =IF(OR(D29=0,D29=1),"Obrigatória justificativa no campo Justificativa e observações","")
B30: Salários, Benefícios e Obrigações Trabalhistas | C30: 0.25 | D30: 3 | E30: =C30*D30 | G30: =IF(OR(D30=0,D30=1),"Obrigatória justificativa no campo Justificativa e observações","")
B31: TOTAL GRUPO 3 | C31: 1 | E31: =E27+E28+E29+E30
B32: NOTA FINAL (G1+G2+G3) | E32: =E20+E25+E31
B33: CONCEITO | C33: =IF(E32>=8.1,"A",IF(E32>=7.65,"B",IF(E32>=6.75,"C",IF(E32>=5.85,"D",IF(E32>=5.4,"E","F"))))) | E33: % a pagar | F33: =IF(C33="A",1,IF(C33="B",0.95,IF(C33="C",0.9,IF(C33="D",0.85,IF(C33="E",0.8,0.75)))))
B35: PARÂMETROS (base 30 avos)
B36: Dias no mês (calendário) | C36: 29
B37: Nº de Dias Trabalhados | C37: 29
B38: Dias para cálculo (base 30) | C38: =IF(C37>=C36,30,MIN(C37,C36))
B40: POSTOS DE TRABALHO
B41: Item | C41: POSTO | D41: Qtde Contratada | E41: Valor Unit. (R$) | F41: Horas | G41: Sem Cob. (h) | H41: Valor Hora (R$) | I41: Valor após Descontos (R$) | K41: (aux) Mensal
B42: 1 | C42: Vigilância armada de 12x36 horas diurnas de Segunda Feira a Domingo | D42: 4 | E42: 5677.75 | F42: =IF(N(D42)>0,D42*220,0) | H42: =IF(N(D42)>0,ROUNDDOWN(E42/220,2),0) | I42: =IF(AND(N(D42)>0,N(E42)>0),MAX(0,ROUNDDOWN((D42*E42-H42*N(G42))/30*C38*F33,2)),0) | K42: =ROUNDDOWN(N(D42)*N(E42),2)
B43: 2 | C43: Vigilância armada de 12x36 horas noturnas de Segunda Feira a Domingo | D43: 12 | E43: 6228.99 | F43: =IF(N(D43)>0,D43*220,0) | H43: =IF(N(D43)>0,ROUNDDOWN(E43/220,2),0) | I43: =IF(AND(N(D43)>0,N(E43)>0),MAX(0,ROUNDDOWN((D43*E43-H43*N(G43))/30*C38*F33,2)),0) | K43: =ROUNDDOWN(N(D43)*N(E43),2)
B44: 3 | C44: Vigilância desarmada de 12x36 horas diurnas de Segunda Feira a Domingo | D44: 18 | E44: 5672.89 | F44: =IF(N(D44)>0,D44*220,0) | H44: =IF(N(D44)>0,ROUNDDOWN(E44/220,2),0) | I44: =IF(AND(N(D44)>0,N(E44)>0),MAX(0,ROUNDDOWN((D44*E44-H44*N(G44))/30*C38*F33,2)),0) | K44: =ROUNDDOWN(N(D44)*N(E44),2)
B45: 4 | C45: Vigilância desarmada de 12x36 horas noturnas de Segunda Feira a Domingo | D45: 10 | E45: 6224.09 | F45: =IF(N(D45)>0,D45*220,0) | H45: =IF(N(D45)>0,ROUNDDOWN(E45/220,2),0) | I45: =IF(AND(N(D45)>0,N(E45)>0),MAX(0,ROUNDDOWN((D45*E45-H45*N(G45))/30*C38*F33,2)),0) | K45: =ROUNDDOWN(N(D45)*N(E45),2)
B46: 5 | C46: Vigilância desarmada de 44h (8:48 horas) diurnas de Segunda Feira a Sexta | D46: 1 | E46: 6019.58 | F46: =IF(N(D46)>0,D46*220,0) | H46: =IF(N(D46)>0,ROUNDDOWN(E46/220,2),0) | I46: =IF(AND(N(D46)>0,N(E46)>0),MAX(0,ROUNDDOWN((D46*E46-H46*N(G46))/30*C38*F33,2)),0) | K46: =ROUNDDOWN(N(D46)*N(E46),2)
B47: 6 | C47: Vigilância desarmada de 12x36 horas diurnas de Segunda Feira a Domingo COM INTRAJORNADA | D47: 2 | E47: 6064.91 | F47: =IF(N(D47)>0,D47*220,0) | H47: =IF(N(D47)>0,ROUNDDOWN(E47/220,2),0) | I47: =IF(AND(N(D47)>0,N(E47)>0),MAX(0,ROUNDDOWN((D47*E47-H47*N(G47))/30*C38*F33,2)),0) | K47: =ROUNDDOWN(N(D47)*N(E47),2)
B48: 7 | C48: Vigilância desarmada de 12x36 horas noturnas de Segunda Feira a Domingo COM INTRAJORNADA | D48: 2 | E48: 6654.1 | F48: =IF(N(D48)>0,D48*220,0) | H48: =IF(N(D48)>0,ROUNDDOWN(E48/220,2),0) | I48: =IF(AND(N(D48)>0,N(E48)>0),MAX(0,ROUNDDOWN((D48*E48-H48*N(G48))/30*C38*F33,2)),0) | K48: =ROUNDDOWN(N(D48)*N(E48),2)
B49: TOTAIS | D49: =SUM(D42:D48) | E49: ◀ Qtde contratada | I49: =SUM(I42:I48) | K49: =SUM(K42:K48)
B51: INSTRUMENTO DE COBRANÇA
B52: Item | C52: Posto | D52: Qtde Fat. | E52: Valor Unit. Faturado (R$)
B53: =B42 | C53: =C42 | D53: =N(D42) | E53: =IF(N(D42)>0,ROUNDDOWN(I42/D42,2),0)
B54: =B43 | C54: =C43 | D54: =N(D43) | E54: =IF(N(D43)>0,ROUNDDOWN(I43/D43,2),0)
B55: =B44 | C55: =C44 | D55: =N(D44) | E55: =IF(N(D44)>0,ROUNDDOWN(I44/D44,2),0)
B56: =B45 | C56: =C45 | D56: =N(D45) | E56: =IF(N(D45)>0,ROUNDDOWN(I45/D45,2),0)
B57: =B46 | C57: =C46 | D57: =N(D46) | E57: =IF(N(D46)>0,ROUNDDOWN(I46/D46,2),0)
B58: =B47 | C58: =C47 | D58: =N(D47) | E58: =IF(N(D47)>0,ROUNDDOWN(I47/D47,2),0)
B59: =B48 | C59: =C48 | D59: =N(D48) | E59: =IF(N(D48)>0,ROUNDDOWN(I48/D48,2),0)
B61: RESUMO FINANCEIRO
B62: Contratado Mensal – Total (R$) | E62: =K49
B63: Conceito | E63: =C33
B64: % do Faturamento a ser Liberado | E64: =F33
B65: Valor Glosado por QUALIDADE (R$) | E65: =ROUNDDOWN(K49-K49*F33,2)
B66: Valor Aprovado para Pagamento (R$) | E66: =MAX(0,ROUNDDOWN(I49+E82,2))
B68: FAIXA DE AJUSTE
B69: Conceito | C69: % a Pagar | E69: Nota Média
B70: A | C70: 100% | E70: 9,00–8,10
B71: B | C71: 95% | E71: 8,09–7,65
B72: C | C72: 90% | E72: 7,64–6,75
B73: D | C73: 85% | E73: 6,74–5,85
B74: E | C74: 80% | E74: 5,84–5,40
B75: F | C75: 75% | E75: < 5,40
B77: REEMBOLSO DE CRECHE
B78: Valor estimado unitário (R$) | E78: 0
B79: Valor Reembolso Creche Retido (R$) (estimado × qtde contratada) | E79: =ROUNDDOWN(E78*D49,2)
B80: Reembolsos Aprovados (quantidade)
B81: Reembolso por dependente (R$) | E81: 526.64
B82: Valor Total dos Reembolsos (R$) (Aprovados × Reembolso por dependente) | E82: =ROUNDDOWN(E80*E81,2)
B83: Saldo do mês anterior (R$) | E83: 0
B84: Saldo de Reembolso (R$) (Saldo anterior + Retido − Total) | E84: =E83+E79-E82
B85: =IF(E84<0,"⚠ Saldo negativo — se houver mais de uma unidade favor somar o saldo de todas; se permanecer negativo, aditivar o contrato.","")
B88: JUSTIFICATIVAS E OBSERVAÇÕES

Sheet Março 2024
B1: UNIVERSIDADE FEDERAL DO RIO DE JANEIRO — PR-6
B3: INSTRUMENTO DE MEDIÇÃO DE RESULTADO (IMR)
B7: IDENTIFICAÇÃO
B8: CONTRATO Nº | C8: 05/24
B9: UNIDADE | C9: MACAÉ
B10: CONTRATADA | C10: ANGEL'S SEGURANÇA E VIGILÂNCIA - EM RECUPERAÇÃO JUDICIAL LTDA
B11: FISCAL OPERACIONAL
B12: PERÍODO DE REFERÊNCIA | C12: Março 2024
B14: AVALIAÇÃO DE DESEMPENHO
B15: Critério de Avaliação | C15: PESO (a) | D15: NOTA (b) (0,1,3) | E15: SUBTOTAL (c=a×b)
B16: ▶ GRUPO 1 – DESEMPENHO PROFISSIONAL
B17: Cumprimento das Atividades | C17: 0.4 | D17: 3 | E17: =C17*D17 | G17: =IF(OR(D17=0,D17=1),"Obrigatória justificativa no campo Justificativa e observações","")
B18: Qualificação / Atendimento ao Público / Postura | C18: 0.35 | D18: 3 | E18: =C18*D18 | G18: =IF(OR(D18=0,D18=1),"Obrigatória justificativa no campo Justificativa e observações","")
B19: Uniformes e Identificação | C19: 0.25 | D19: 3 | E19: =C19*D19 | G19: =IF(OR(D19=0,D19=1),"Obrigatória justificativa no campo Justificativa e observações","")
B20: TOTAL GRUPO 1 | C20: 1 | E20: =E17+E18+E19
B21: ▶ GRUPO 2 – DESEMPENHO DAS ATIVIDADES
B22: Especificação Técnica dos Serviços | C22: 0.4 | D22: 3 | E22: =C22*D22 | G22: =IF(OR(D22=0,D22=1),"Obrigatória justificativa no campo Justificativa e observações","")
B23: Equipamentos e Acessórios | C23: 0.2 | D23: 3 | E23: =C23*D23 | G23: =IF(OR(D23=0,D23=1),"Obrigatória justificativa no campo Justificativa e observações","")
B24: Atendimento às Ocorrências | C24: 0.4 | D24: 3 | E24: =C24*D24 | G24: =IF(OR(D24=0,D24=1),"Obrigatória justificativa no campo Justificativa e observações","")
B25: TOTAL GRUPO 2 | C25: 1 | E25: =E22+E23+E24
B26: ▶ GRUPO 3 – GERENCIAMENTO
B27: Periodicidade da Supervisão | C27: 0.2 | D27: 3 | E27: =C27*D27 | G27: =IF(OR(D27=0,D27=1),"Obrigatória justificativa no campo Justificativa e observações","")
B28: Gerenciamento das Atividades Operacionais | C28: 0.3 | D28: 3 | E28: =C28*D28 | G28: =IF(OR(D28=0,D28=1),"Obrigatória justificativa no campo Justificativa e observações","")
B29: Atendimento às Solicitações | C29: 0.25 | D29: 3 | E29: =C29*D29 | G29: =IF(OR(D29=0,D29=1),"Obrigatória justificativa no campo Justificativa e observações","")
B30: Salários, Benefícios e Obrigações Trabalhistas | C30: 0.25 | D30: 3 | E30: =C30*D30 | G30: =IF(OR(D30=0,D30=1),"Obrigatória justificativa no campo Justificativa e observações","")
B31: TOTAL GRUPO 3 | C31: 1 | E31: =E27+E28+E29+E30
B32: NOTA FINAL (G1+G2+G3) | E32: =E20+E25+E31
B33: CONCEITO | C33: =IF(E32>=8.1,"A",IF(E32>=7.65,"B",IF(E32>=6.75,"C",IF(E32>=5.85,"D",IF(E32>=5.4,"E","F"))))) | E33: % a pagar | F33: =IF(C33="A",1,IF(C33="B",0.95,IF(C33="C",0.9,IF(C33="D",0.85,IF(C33="E",0.8,0.75)))))
B35: PARÂMETROS (base 30 avos)
B36: Dias no mês (calendário) | C36: 30
B37: Nº de Dias Trabalhados | C37: 30
B38: Dias para cálculo (base 30) | C38: =IF(C37>=C36,30,MIN(C37,C36))
B40: POSTOS DE TRABALHO
B41: Item | C41: POSTO | D41: Qtde Contratada | E41: Valor Unit. (R$) | F41: Horas | G41: Sem Cob. (h) | H41: Valor Hora (R$) | I41: Valor após Descontos (R$) | K41: (aux) Mensal
B42: 1 | C42: Vigilância armada de 12x36 horas diurnas de Segunda Feira a Domingo | D42: 4 | E42: 5677.75 | F42: =IF(N(D42)>0,D42*220,0) | H42: =IF(N(D42)>0,ROUNDDOWN(E42/220,2),0) | I42: =IF(AND(N(D42)>0,N(E42)>0),MAX(0,ROUNDDOWN((D42*E42-H42*N(G42))/30*C38*F33,2)),0) | K42: =ROUNDDOWN(N(D42)*N(E42),2)
B43: 2 | C43: Vigilância armada de 12x36 horas noturnas de Segunda Feira a Domingo | D43: 12 | E43: 6228.99 | F43: =IF(N(D43)>0,D43*220,0) | H43: =IF(N(D43)>0,ROUNDDOWN(E43/220,2),0) | I43: =IF(AND(N(D43)>0,N(E43)>0),MAX(0,ROUNDDOWN((D43*E43-H43*N(G43))/30*C38*F33,2)),0) | K43: =ROUNDDOWN(N(D43)*N(E43),2)
B44: 3 | C44: Vigilância desarmada de 12x36 horas diurnas de Segunda Feira a Domingo | D44: 18 | E44: 5672.89 | F44: =IF(N(D44)>0,D44*220,0) | H44: =IF(N(D44)>0,ROUNDDOWN(E44/220,2),0) | I44: =IF(AND(N(D44)>0,N(E44)>0),MAX(0,ROUNDDOWN((D44*E44-H44*N(G44))/30*C38*F33,2)),0) | K44: =ROUNDDOWN(N(D44)*N(E44),2)
B45: 4 | C45: Vigilância desarmada de 12x36 horas noturnas de Segunda Feira a Domingo | D45: 10 | E45: 6224.09 | F45: =IF(N(D45)>0,D45*220,0) | H45: =IF(N(D45)>0,ROUNDDOWN(E45/220,2),0) | I45: =IF(AND(N(D45)>0,N(E45)>0),MAX(0,ROUNDDOWN((D45*E45-H45*N(G45))/30*C38*F33,2)),0) | K45: =ROUNDDOWN(N(D45)*N(E45),2)
B46: 5 | C46: Vigilância desarmada de 44h (8:48 horas) diurnas de Segunda Feira a Sexta | D46: 1 | E46: 6019.58 | F46: =IF(N(D46)>0,D46*220,0) | H46: =IF(N(D46)>0,ROUNDDOWN(E46/220,2),0) | I46: =IF(AND(N(D46)>0,N(E46)>0),MAX(0,ROUNDDOWN((D46*E46-H46*N(G46))/30*C38*F33,2)),0) | K46: =ROUNDDOWN(N(D46)*N(E46),2)
B47: 6 | C47: Vigilância desarmada de 12x36 horas diurnas de Segunda Feira a Domingo COM INTRAJORNADA | D47: 2 | E47: 6064.91 | F47: =IF(N(D47)>0,D47*220,0) | H47: =IF(N(D47)>0,ROUNDDOWN(E47/220,2),0) | I47: =IF(AND(N(D47)>0,N(E47)>0),MAX(0,ROUNDDOWN((D47*E47-H47*N(G47))/30*C38*F33,2)),0) | K47: =ROUNDDOWN(N(D47)*N(E47),2)
B48: 7 | C48: Vigilância desarmada de 12x36 horas noturnas de Segunda Feira a Domingo COM INTRAJORNADA | D48: 2 | E48: 6654.1 | F48: =IF(N(D48)>0,D48*220,0) | H48: =IF(N(D48)>0,ROUNDDOWN(E48/220,2),0) | I48: =IF(AND(N(D48)>0,N(E48)>0),MAX(0,ROUNDDOWN((D48*E48-H48*N(G48))/30*C38*F33,2)),0) | K48: =ROUNDDOWN(N(D48)*N(E48),2)
B49: TOTAIS | D49: =SUM(D42:D48) | E49: ◀ Qtde contratada | I49: =SUM(I42:I48) | K49: =SUM(K42:K48)
B51: INSTRUMENTO DE COBRANÇA
B52: Item | C52: Posto | D52: Qtde Fat. | E52: Valor Unit. Faturado (R$)
B53: =B42 | C53: =C42 | D53: =N(D42) | E53: =IF(N(D42)>0,ROUNDDOWN(I42/D42,2),0)
B54: =B43 | C54: =C43 | D54: =N(D43) | E54: =IF(N(D43)>0,ROUNDDOWN(I43/D43,2),0)
B55: =B44 | C55: =C44 | D55: =N(D44) | E55: =IF(N(D44)>0,ROUNDDOWN(I44/D44,2),0)
B56: =B45 | C56: =C45 | D56: =N(D45) | E56: =IF(N(D45)>0,ROUNDDOWN(I45/D45,2),0)
B57: =B46 | C57: =C46 | D57: =N(D46) | E57: =IF(N(D46)>0,ROUNDDOWN(I46/D46,2),0)
B58: =B47 | C58: =C47 | D58: =N(D47) | E58: =IF(N(D47)>0,ROUNDDOWN(I47/D47,2),0)
B59: =B48 | C59: =C48 | D59: =N(D48) | E59: =IF(N(D48)>0,ROUNDDOWN(I48/D48,2),0)
B61: RESUMO FINANCEIRO
B62: Contratado Mensal – Total (R$) | E62: =K49
B63: Conceito | E63: =C33
B64: % do Faturamento a ser Liberado | E64: =F33
B65: Valor Glosado por QUALIDADE (R$) | E65: =ROUNDDOWN(K49-K49*F33,2)
B66: Valor Aprovado para Pagamento (R$) | E66: =MAX(0,ROUNDDOWN(I49+E82,2))
B68: FAIXA DE AJUSTE
B69: Conceito | C69: % a Pagar | E69: Nota Média
B70: A | C70: 100% | E70: 9,00–8,10
B71: B | C71: 95% | E71: 8,09–7,65
B72: C | C72: 90% | E72: 7,64–6,75
B73: D | C73: 85% | E73: 6,74–5,85
B74: E | C74: 80% | E74: 5,84–5,40
B75: F | C75: 75% | E75: < 5,40
B77: REEMBOLSO DE CRECHE
B78: Valor estimado unitário (R$) | E78: 0
B79: Valor Reembolso Creche Retido (R$) (estimado × qtde contratada) | E79: =ROUNDDOWN(E78*D49,2)
B80: Reembolsos Aprovados (quantidade)
B81: Reembolso por dependente (R$) | E81: 526.64
B82: Valor Total dos Reembolsos (R$) (Aprovados × Reembolso por dependente) | E82: =ROUNDDOWN(E80*E81,2)
B83: Saldo do mês anterior (R$) | E83: ='Fevereiro 2024'!E84
B84: Saldo de Reembolso (R$) (Saldo anterior + Retido − Total) | E84: =E83+E79-E82
B85: =IF(E84<0,"⚠ Saldo negativo — se houver mais de uma unidade favor somar o saldo de todas; se permanecer negativo, aditivar o contrato.","")
B88: JUSTIFICATIVAS E OBSERVAÇÕES

Sheet Abril 2024
B1: UNIVERSIDADE FEDERAL DO RIO DE JANEIRO — PR-6
B3: INSTRUMENTO DE MEDIÇÃO DE RESULTADO (IMR)
B7: IDENTIFICAÇÃO
B8: CONTRATO Nº | C8: 05/24
B9: UNIDADE | C9: MACAÉ
B10: CONTRATADA | C10: ANGEL'S SEGURANÇA E VIGILÂNCIA - EM RECUPERAÇÃO JUDICIAL LTDA
B11: FISCAL OPERACIONAL
B12: PERÍODO DE REFERÊNCIA | C12: Abril 2024
B14: AVALIAÇÃO DE DESEMPENHO
B15: Critério de Avaliação | C15: PESO (a) | D15: NOTA (b) (0,1,3) | E15: SUBTOTAL (c=a×b)
B16: ▶ GRUPO 1 – DESEMPENHO PROFISSIONAL
B17: Cumprimento das Atividades | C17: 0.4 | D17: 3 | E17: =C17*D17 | G17: =IF(OR(D17=0,D17=1),"Obrigatória justificativa no campo Justificativa e observações","")
B18: Qualificação / Atendimento ao Público / Postura | C18: 0.35 | D18: 3 | E18: =C18*D18 | G18: =IF(OR(D18=0,D18=1),"Obrigatória justificativa no campo Justificativa e observações","")
B19: Uniformes e Identificação | C19: 0.25 | D19: 3 | E19: =C19*D19 | G19: =IF(OR(D19=0,D19=1),"Obrigatória justificativa no campo Justificativa e observações","")
B20: TOTAL GRUPO 1 | C20: 1 | E20: =E17+E18+E19
B21: ▶ GRUPO 2 – DESEMPENHO DAS ATIVIDADES
B22: Especificação Técnica dos Serviços | C22: 0.4 | D22: 3 | E22: =C22*D22 | G22: =IF(OR(D22=0,D22=1),"Obrigatória justificativa no campo Justificativa e observações","")
B23: Equipamentos e Acessórios | C23: 0.2 | D23: 3 | E23: =C23*D23 | G23: =IF(OR(D23=0,D23=1),"Obrigatória justificativa no campo Justificativa e observações","")
B24: Atendimento às Ocorrências | C24: 0.4 | D24: 3 | E24: =C24*D24 | G24: =IF(OR(D24=0,D24=1),"Obrigatória justificativa no campo Justificativa e observações","")
B25: TOTAL GRUPO 2 | C25: 1 | E25: =E22+E23+E24
B26: ▶ GRUPO 3 – GERENCIAMENTO
B27: Periodicidade da Supervisão | C27: 0.2 | D27: 3 | E27: =C27*D27 | G27: =IF(OR(D27=0,D27=1),"Obrigatória justificativa no campo Justificativa e observações","")
B28: Gerenciamento das Atividades Operacionais | C28: 0.3 | D28: 3 | E28: =C28*D28 | G28: =IF(OR(D28=0,D28=1),"Obrigatória justificativa no campo Justificativa e observações","")
B29: Atendimento às Solicitações | C29: 0.25 | D29: 3 | E29: =C29*D29 | G29: =IF(OR(D29=0,D29=1),"Obrigatória justificativa no campo Justificativa e observações","")
B30: Salários, Benefícios e Obrigações Trabalhistas | C30: 0.25 | D30: 3 | E30: =C30*D30 | G30: =IF(OR(D30=0,D30=1),"Obrigatória justificativa no campo Justificativa e observações","")
B31: TOTAL GRUPO 3 | C31: 1 | E31: =E27+E28+E29+E30
B32: NOTA FINAL (G1+G2+G3) | E32: =E20+E25+E31
B33: CONCEITO | C33: =IF(E32>=8.1,"A",IF(E32>=7.65,"B",IF(E32>=6.75,"C",IF(E32>=5.85,"D",IF(E32>=5.4,"E","F"))))) | E33: % a pagar | F33: =IF(C33="A",1,IF(C33="B",0.95,IF(C33="C",0.9,IF(C33="D",0.85,IF(C33="E",0.8,0.75)))))
B35: PARÂMETROS (base 30 avos)
B36: Dias no mês (calendário) | C36: 30
B37: Nº de Dias Trabalhados | C37: 30
B38: Dias para cálculo (base 30) | C38: =IF(C37>=C36,30,MIN(C37,C36))
B40: POSTOS DE TRABALHO
B41: Item | C41: POSTO | D41: Qtde Contratada | E41: Valor Unit. (R$) | F41: Horas | G41: Sem Cob. (h) | H41: Valor Hora (R$) | I41: Valor após Descontos (R$) | K41: (aux) Mensal
B42: 1 | C42: Vigilância armada de 12x36 horas diurnas de Segunda Feira a Domingo | D42: 4 | E42: 5677.75 | F42: =IF(N(D42)>0,D42*220,0) | H42: =IF(N(D42)>0,ROUNDDOWN(E42/220,2),0) | I42: =IF(AND(N(D42)>0,N(E42)>0),MAX(0,ROUNDDOWN((D42*E42-H42*N(G42))/30*C38*F33,2)),0) | K42: =ROUNDDOWN(N(D42)*N(E42),2)
B43: 2 | C43: Vigilância armada de 12x36 horas noturnas de Segunda Feira a Domingo | D43: 12 | E43: 6228.99 | F43: =IF(N(D43)>0,D43*220,0) | H43: =IF(N(D43)>0,ROUNDDOWN(E43/220,2),0) | I43: =IF(AND(N(D43)>0,N(E43)>0),MAX(0,ROUNDDOWN((D43*E43-H43*N(G43))/30*C38*F33,2)),0) | K43: =ROUNDDOWN(N(D43)*N(E43),2)
B44: 3 | C44: Vigilância desarmada de 12x36 horas diurnas de Segunda Feira a Domingo | D44: 18 | E44: 5672.89 | F44: =IF(N(D44)>0,D44*220,0) | H44: =IF(N(D44)>0,ROUNDDOWN(E44/220,2),0) | I44: =IF(AND(N(D44)>0,N(E44)>0),MAX(0,ROUNDDOWN((D44*E44-H44*N(G44))/30*C38*F33,2)),0) | K44: =ROUNDDOWN(N(D44)*N(E44),2)
B45: 4 | C45: Vigilância desarmada de 12x36 horas noturnas de Segunda Feira a Domingo | D45: 10 | E45: 6224.09 | F45: =IF(N(D45)>0,D45*220,0) | H45: =IF(N(D45)>0,ROUNDDOWN(E45/220,2),0) | I45: =IF(AND(N(D45)>0,N(E45)>0),MAX(0,ROUNDDOWN((D45*E45-H45*N(G45))/30*C38*F33,2)),0) | K45: =ROUNDDOWN(N(D45)*N(E45),2)
B46: 5 | C46: Vigilância desarmada de 44h (8:48 horas) diurnas de Segunda Feira a Sexta | D46: 1 | E46: 6019.58 | F46: =IF(N(D46)>0,D46*220,0) | H46: =IF(N(D46)>0,ROUNDDOWN(E46/220,2),0) | I46: =IF(AND(N(D46)>0,N(E46)>0),MAX(0,ROUNDDOWN((D46*E46-H46*N(G46))/30*C38*F33,2)),0) | K46: =ROUNDDOWN(N(D46)*N(E46),2)
B47: 6 | C47: Vigilância desarmada de 12x36 horas diurnas de Segunda Feira a Domingo COM INTRAJORNADA | D47: 2 | E47: 6064.91 | F47: =IF(N(D47)>0,D47*220,0) | H47: =IF(N(D47)>0,ROUNDDOWN(E47/220,2),0) | I47: =IF(AND(N(D47)>0,N(E47)>0),MAX(0,ROUNDDOWN((D47*E47-H47*N(G47))/30*C38*F33,2)),0) | K47: =ROUNDDOWN(N(D47)*N(E47),2)
B48: 7 | C48: Vigilância desarmada de 12x36 horas noturnas de Segunda Feira a Domingo COM INTRAJORNADA | D48: 2 | E48: 6654.1 | F48: =IF(N(D48)>0,D48*220,0) | H48: =IF(N(D48)>0,ROUNDDOWN(E48/220,2),0) | I48: =IF(AND(N(D48)>0,N(E48)>0),MAX(0,ROUNDDOWN((D48*E48-H48*N(G48))/30*C38*F33,2)),0) | K48: =ROUNDDOWN(N(D48)*N(E48),2)
B49: TOTAIS | D49: =SUM(D42:D48) | E49: ◀ Qtde contratada | I49: =SUM(I42:I48) | K49: =SUM(K42:K48)
B51: INSTRUMENTO DE COBRANÇA
B52: Item | C52: Posto | D52: Qtde Fat. | E52: Valor Unit. Faturado (R$)
B53: =B42 | C53: =C42 | D53: =N(D42) | E53: =IF(N(D42)>0,ROUNDDOWN(I42/D42,2),0)
B54: =B43 | C54: =C43 | D54: =N(D43) | E54: =IF(N(D43)>0,ROUNDDOWN(I43/D43,2),0)
B55: =B44 | C55: =C44 | D55: =N(D44) | E55: =IF(N(D44)>0,ROUNDDOWN(I44/D44,2),0)
B56: =B45 | C56: =C45 | D56: =N(D45) | E56: =IF(N(D45)>0,ROUNDDOWN(I45/D45,2),0)
B57: =B46 | C57: =C46 | D57: =N(D46) | E57: =IF(N(D46)>0,ROUNDDOWN(I46/D46,2),0)
B58: =B47 | C58: =C47 | D58: =N(D47) | E58: =IF(N(D47)>0,ROUNDDOWN(I47/D47,2),0)
B59: =B48 | C59: =C48 | D59: =N(D48) | E59: =IF(N(D48)>0,ROUNDDOWN(I48/D48,2),0)
B61: RESUMO FINANCEIRO
B62: Contratado Mensal – Total (R$) | E62: =K49
B63: Conceito | E63: =C33
B64: % do Faturamento a ser Liberado | E64: =F33
B65: Valor Glosado por QUALIDADE (R$) | E65: =ROUNDDOWN(K49-K49*F33,2)
B66: Valor Aprovado para Pagamento (R$) | E66: =MAX(0,ROUNDDOWN(I49+E82,2))
B68: FAIXA DE AJUSTE
B69: Conceito | C69: % a Pagar | E69: Nota Média
B70: A | C70: 100% | E70: 9,00–8,10
B71: B | C71: 95% | E71: 8,09–7,65
B72: C | C72: 90% | E72: 7,64–6,75
B73: D | C73: 85% | E73: 6,74–5,85
B74: E | C74: 80% | E74: 5,84–5,40
B75: F | C75: 75% | E75: < 5,40
B77: REEMBOLSO DE CRECHE
B78: Valor estimado unitário (R$) | E78: 0
B79: Valor Reembolso Creche Retido (R$) (estimado × qtde contratada) | E79: =ROUNDDOWN(E78*D49,2)
B80: Reembolsos Aprovados (quantidade)
B81: Reembolso por dependente (R$) | E81: 526.64
B82: Valor Total dos Reembolsos (R$) (Aprovados × Reembolso por dependente) | E82: =ROUNDDOWN(E80*E81,2)
B83: Saldo do mês anterior (R$) | E83: ='Março 2024'!E84
B84: Saldo de Reembolso (R$) (Saldo anterior + Retido − Total) | E84: =E83+E79-E82
B85: =IF(E84<0,"⚠ Saldo negativo — se houver mais de uma unidade favor somar o saldo de todas; se permanecer negativo, aditivar o contrato.","")
B88: JUSTIFICATIVAS E OBSERVAÇÕES

Sheet Maio 2024
B1: UNIVERSIDADE FEDERAL DO RIO DE JANEIRO — PR-6
B3: INSTRUMENTO DE MEDIÇÃO DE RESULTADO (IMR)
B7: IDENTIFICAÇÃO
B8: CONTRATO Nº | C8: 05/24
B9: UNIDADE | C9: MACAÉ
B10: CONTRATADA | C10: ANGEL'S SEGURANÇA E VIGILÂNCIA - EM RECUPERAÇÃO JUDICIAL LTDA
B11: FISCAL OPERACIONAL
B12: PERÍODO DE REFERÊNCIA | C12: Maio 2024
B14: AVALIAÇÃO DE DESEMPENHO
B15: Critério de Avaliação | C15: PESO (a) | D15: NOTA (b) (0,1,3) | E15: SUBTOTAL (c=a×b)
B16: ▶ GRUPO 1 – DESEMPENHO PROFISSIONAL
B17: Cumprimento das Atividades | C17: 0.4 | D17: 3 | E17: =C17*D17 | G17: =IF(OR(D17=0,D17=1),"Obrigatória justificativa no campo Justificativa e observações","")
B18: Qualificação / Atendimento ao Público / Postura | C18: 0.35 | D18: 3 | E18: =C18*D18 | G18: =IF(OR(D18=0,D18=1),"Obrigatória justificativa no campo Justificativa e observações","")
B19: Uniformes e Identificação | C19: 0.25 | D19: 3 | E19: =C19*D19 | G19: =IF(OR(D19=0,D19=1),"Obrigatória justificativa no campo Justificativa e observações","")
B20: TOTAL GRUPO 1 | C20: 1 | E20: =E17+E18+E19
B21: ▶ GRUPO 2 – DESEMPENHO DAS ATIVIDADES
B22: Especificação Técnica dos Serviços | C22: 0.4 | D22: 3 | E22: =C22*D22 | G22: =IF(OR(D22=0,D22=1),"Obrigatória justificativa no campo Justificativa e observações","")
B23: Equipamentos e Acessórios | C23: 0.2 | D23: 3 | E23: =C23*D23 | G23: =IF(OR(D23=0,D23=1),"Obrigatória justificativa no campo Justificativa e observações","")
B24: Atendimento às Ocorrências | C24: 0.4 | D24: 3 | E24: =C24*D24 | G24: =IF(OR(D24=0,D24=1),"Obrigatória justificativa no campo Justificativa e observações","")
B25: TOTAL GRUPO 2 | C25: 1 | E25: =E22+E23+E24
B26: ▶ GRUPO 3 – GERENCIAMENTO
B27: Periodicidade da Supervisão | C27: 0.2 | D27: 3 | E27: =C27*D27 | G27: =IF(OR(D27=0,D27=1),"Obrigatória justificativa no campo Justificativa e observações","")
B28: Gerenciamento das Atividades Operacionais | C28: 0.3 | D28: 3 | E28: =C28*D28 | G28: =IF(OR(D28=0,D28=1),"Obrigatória justificativa no campo Justificativa e observações","")
B29: Atendimento às Solicitações | C29: 0.25 | D29: 3 | E29: =C29*D29 | G29: =IF(OR(D29=0,D29=1),"Obrigatória justificativa no campo Justificativa e observações","")
B30: Salários, Benefícios e Obrigações Trabalhistas | C30: 0.25 | D30: 3 | E30: =C30*D30 | G30: =IF(OR(D30=0,D30=1),"Obrigatória justificativa no campo Justificativa e observações","")
B31: TOTAL GRUPO 3 | C31: 1 | E31: =E27+E28+E29+E30
B32: NOTA FINAL (G1+G2+G3) | E32: =E20+E25+E31
B33: CONCEITO | C33: =IF(E32>=8.1,"A",IF(E32>=7.65,"B",IF(E32>=6.75,"C",IF(E32>=5.85,"D",IF(E32>=5.4,"E","F"))))) | E33: % a pagar | F33: =IF(C33="A",1,IF(C33="B",0.95,IF(C33="C",0.9,IF(C33="D",0.85,IF(C33="E",0.8,0.75)))))
B35: PARÂMETROS (base 30 avos)
B36: Dias no mês (calendário) | C36: 30
B37: Nº de Dias Trabalhados | C37: 30
B38: Dias para cálculo (base 30) | C38: =IF(C37>=C36,30,MIN(C37,C36))
B40: POSTOS DE TRABALHO
B41: Item | C41: POSTO | D41: Qtde Contratada | E41: Valor Unit. (R$) | F41: Horas | G41: Sem Cob. (h) | H41: Valor Hora (R$) | I41: Valor após Descontos (R$) | K41: (aux) Mensal
B42: 1 | C42: Vigilância armada de 12x36 horas diurnas de Segunda Feira a Domingo | D42: 4 | E42: 5677.75 | F42: =IF(N(D42)>0,D42*220,0) | H42: =IF(N(D42)>0,ROUNDDOWN(E42/220,2),0) | I42: =IF(AND(N(D42)>0,N(E42)>0),MAX(0,ROUNDDOWN((D42*E42-H42*N(G42))/30*C38*F33,2)),0) | K42: =ROUNDDOWN(N(D42)*N(E42),2)
B43: 2 | C43: Vigilância armada de 12x36 horas noturnas de Segunda Feira a Domingo | D43: 12 | E43: 6228.99 | F43: =IF(N(D43)>0,D43*220,0) | H43: =IF(N(D43)>0,ROUNDDOWN(E43/220,2),0) | I43: =IF(AND(N(D43)>0,N(E43)>0),MAX(0,ROUNDDOWN((D43*E43-H43*N(G43))/30*C38*F33,2)),0) | K43: =ROUNDDOWN(N(D43)*N(E43),2)
B44: 3 | C44: Vigilância desarmada de 12x36 horas diurnas de Segunda Feira a Domingo | D44: 18 | E44: 5672.89 | F44: =IF(N(D44)>0,D44*220,0) | H44: =IF(N(D44)>0,ROUNDDOWN(E44/220,2),0) | I44: =IF(AND(N(D44)>0,N(E44)>0),MAX(0,ROUNDDOWN((D44*E44-H44*N(G44))/30*C38*F33,2)),0) | K44: =ROUNDDOWN(N(D44)*N(E44),2)
B45: 4 | C45: Vigilância desarmada de 12x36 horas noturnas de Segunda Feira a Domingo | D45: 10 | E45: 6224.09 | F45: =IF(N(D45)>0,D45*220,0) | H45: =IF(N(D45)>0,ROUNDDOWN(E45/220,2),0) | I45: =IF(AND(N(D45)>0,N(E45)>0),MAX(0,ROUNDDOWN((D45*E45-H45*N(G45))/30*C38*F33,2)),0) | K45: =ROUNDDOWN(N(D45)*N(E45),2)
B46: 5 | C46: Vigilância desarmada de 44h (8:48 horas) diurnas de Segunda Feira a Sexta | D46: 1 | E46: 6019.58 | F46: =IF(N(D46)>0,D46*220,0) | H46: =IF(N(D46)>0,ROUNDDOWN(E46/220,2),0) | I46: =IF(AND(N(D46)>0,N(E46)>0),MAX(0,ROUNDDOWN((D46*E46-H46*N(G46))/30*C38*F33,2)),0) | K46: =ROUNDDOWN(N(D46)*N(E46),2)
B47: 6 | C47: Vigilância desarmada de 12x36 horas diurnas de Segunda Feira a Domingo COM INTRAJORNADA | D47: 2 | E47: 6064.91 | F47: =IF(N(D47)>0,D47*220,0) | H47: =IF(N(D47)>0,ROUNDDOWN(E47/220,2),0) | I47: =IF(AND(N(D47)>0,N(E47)>0),MAX(0,ROUNDDOWN((D47*E47-H47*N(G47))/30*C38*F33,2)),0) | K47: =ROUNDDOWN(N(D47)*N(E47),2)
B48: 7 | C48: Vigilância desarmada de 12x36 horas noturnas de Segunda Feira a Domingo COM INTRAJORNADA | D48: 2 | E48: 6654.1 | F48: =IF(N(D48)>0,D48*220,0) | H48: =IF(N(D48)>0,ROUNDDOWN(E48/220,2),0) | I48: =IF(AND(N(D48)>0,N(E48)>0),MAX(0,ROUNDDOWN((D48*E48-H48*N(G48))/30*C38*F33,2)),0) | K48: =ROUNDDOWN(N(D48)*N(E48),2)
B49: TOTAIS | D49: =SUM(D42:D48) | E49: ◀ Qtde contratada | I49: =SUM(I42:I48) | K49: =SUM(K42:K48)
B51: INSTRUMENTO DE COBRANÇA
B52: Item | C52: Posto | D52: Qtde Fat. | E52: Valor Unit. Faturado (R$)
B53: =B42 | C53: =C42 | D53: =N(D42) | E53: =IF(N(D42)>0,ROUNDDOWN(I42/D42,2),0)
B54: =B43 | C54: =C43 | D54: =N(D43) | E54: =IF(N(D43)>0,ROUNDDOWN(I43/D43,2),0)
B55: =B44 | C55: =C44 | D55: =N(D44) | E55: =IF(N(D44)>0,ROUNDDOWN(I44/D44,2),0)
B56: =B45 | C56: =C45 | D56: =N(D45) | E56: =IF(N(D45)>0,ROUNDDOWN(I45/D45,2),0)
B57: =B46 | C57: =C46 | D57: =N(D46) | E57: =IF(N(D46)>0,ROUNDDOWN(I46/D46,2),0)
B58: =B47 | C58: =C47 | D58: =N(D47) | E58: =IF(N(D47)>0,ROUNDDOWN(I47/D47,2),0)
B59: =B48 | C59: =C48 | D59: =N(D48) | E59: =IF(N(D48)>0,ROUNDDOWN(I48/D48,2),0)
B61: RESUMO FINANCEIRO
B62: Contratado Mensal – Total (R$) | E62: =K49
B63: Conceito | E63: =C33
B64: % do Faturamento a ser Liberado | E64: =F33
B65: Valor Glosado por QUALIDADE (R$) | E65: =ROUNDDOWN(K49-K49*F33,2)
B66: Valor Aprovado para Pagamento (R$) | E66: =MAX(0,ROUNDDOWN(I49+E82,2))
B68: FAIXA DE AJUSTE
B69: Conceito | C69: % a Pagar | E69: Nota Média
B70: A | C70: 100% | E70: 9,00–8,10
B71: B | C71: 95% | E71: 8,09–7,65
B72: C | C72: 90% | E72: 7,64–6,75
B73: D | C73: 85% | E73: 6,74–5,85
B74: E | C74: 80% | E74: 5,84–5,40
B75: F | C75: 75% | E75: < 5,40
B77: REEMBOLSO DE CRECHE
B78: Valor estimado unitário (R$) | E78: 0
B79: Valor Reembolso Creche Retido (R$) (estimado × qtde contratada) | E79: =ROUNDDOWN(E78*D49,2)
B80: Reembolsos Aprovados (quantidade)
B81: Reembolso por dependente (R$) | E81: 526.64
B82: Valor Total dos Reembolsos (R$) (Aprovados × Reembolso por dependente) | E82: =ROUNDDOWN(E80*E81,2)
B83: Saldo do mês anterior (R$) | E83: ='Abril 2024'!E84
B84: Saldo de Reembolso (R$) (Saldo anterior + Retido − Total) | E84: =E83+E79-E82
B85: =IF(E84<0,"⚠ Saldo negativo — se houver mais de uma unidade favor somar o saldo de todas; se permanecer negativo, aditivar o contrato.","")
B88: JUSTIFICATIVAS E OBSERVAÇÕES

Sheet Junho 2024
B1: UNIVERSIDADE FEDERAL DO RIO DE JANEIRO — PR-6
B3: INSTRUMENTO DE MEDIÇÃO DE RESULTADO (IMR)
B7: IDENTIFICAÇÃO
B8: CONTRATO Nº | C8: 05/24
B9: UNIDADE | C9: MACAÉ
B10: CONTRATADA | C10: ANGEL'S SEGURANÇA E VIGILÂNCIA - EM RECUPERAÇÃO JUDICIAL LTDA
B11: FISCAL OPERACIONAL
B12: PERÍODO DE REFERÊNCIA | C12: Junho 2024
B14: AVALIAÇÃO DE DESEMPENHO
B15: Critério de Avaliação | C15: PESO (a) | D15: NOTA (b) (0,1,3) | E15: SUBTOTAL (c=a×b)
B16: ▶ GRUPO 1 – DESEMPENHO PROFISSIONAL
B17: Cumprimento das Atividades | C17: 0.4 | D17: 3 | E17: =C17*D17 | G17: =IF(OR(D17=0,D17=1),"Obrigatória justificativa no campo Justificativa e observações","")
B18: Qualificação / Atendimento ao Público / Postura | C18: 0.35 | D18: 3 | E18: =C18*D18 | G18: =IF(OR(D18=0,D18=1),"Obrigatória justificativa no campo Justificativa e observações","")
B19: Uniformes e Identificação | C19: 0.25 | D19: 3 | E19: =C19*D19 | G19: =IF(OR(D19=0,D19=1),"Obrigatória justificativa no campo Justificativa e observações","")
B20: TOTAL GRUPO 1 | C20: 1 | E20: =E17+E18+E19
B21: ▶ GRUPO 2 – DESEMPENHO DAS ATIVIDADES
B22: Especificação Técnica dos Serviços | C22: 0.4 | D22: 3 | E22: =C22*D22 | G22: =IF(OR(D22=0,D22=1),"Obrigatória justificativa no campo Justificativa e observações","")
B23: Equipamentos e Acessórios | C23: 0.2 | D23: 3 | E23: =C23*D23 | G23: =IF(OR(D23=0,D23=1),"Obrigatória justificativa no campo Justificativa e observações","")
B24: Atendimento às Ocorrências | C24: 0.4 | D24: 3 | E24: =C24*D24 | G24: =IF(OR(D24=0,D24=1),"Obrigatória justificativa no campo Justificativa e observações","")
B25: TOTAL GRUPO 2 | C25: 1 | E25: =E22+E23+E24
B26: ▶ GRUPO 3 – GERENCIAMENTO
B27: Periodicidade da Supervisão | C27: 0.2 | D27: 3 | E27: =C27*D27 | G27: =IF(OR(D27=0,D27=1),"Obrigatória justificativa no campo Justificativa e observações","")
B28: Gerenciamento das Atividades Operacionais | C28: 0.3 | D28: 3 | E28: =C28*D28 | G28: =IF(OR(D28=0,D28=1),"Obrigatória justificativa no campo Justificativa e observações","")
B29: Atendimento às Solicitações | C29: 0.25 | D29: 3 | E29: =C29*D29 | G29: =IF(OR(D29=0,D29=1),"Obrigatória justificativa no campo Justificativa e observações","")
B30: Salários, Benefícios e Obrigações Trabalhistas | C30: 0.25 | D30: 3 | E30: =C30*D30 | G30: =IF(OR(D30=0,D30=1),"Obrigatória justificativa no campo Justificativa e observações","")
B31: TOTAL GRUPO 3 | C31: 1 | E31: =E27+E28+E29+E30
B32: NOTA FINAL (G1+G2+G3) | E32: =E20+E25+E31
B33: CONCEITO | C33: =IF(E32>=8.1,"A",IF(E32>=7.65,"B",IF(E32>=6.75,"C",IF(E32>=5.85,"D",IF(E32>=5.4,"E","F"))))) | E33: % a pagar | F33: =IF(C33="A",1,IF(C33="B",0.95,IF(C33="C",0.9,IF(C33="D",0.85,IF(C33="E",0.8,0.75)))))
B35: PARÂMETROS (base 30 avos)
B36: Dias no mês (calendário) | C36: 30
B37: Nº de Dias Trabalhados | C37: 30
B38: Dias para cálculo (base 30) | C38: =IF(C37>=C36,30,MIN(C37,C36))
B40: POSTOS DE TRABALHO
B41: Item | C41: POSTO | D41: Qtde Contratada | E41: Valor Unit. (R$) | F41: Horas | G41: Sem Cob. (h) | H41: Valor Hora (R$) | I41: Valor após Descontos (R$) | K41: (aux) Mensal
B42: 1 | C42: Vigilância armada de 12x36 horas diurnas de Segunda Feira a Domingo | D42: 4 | E42: 5677.75 | F42: =IF(N(D42)>0,D42*220,0) | H42: =IF(N(D42)>0,ROUNDDOWN(E42/220,2),0) | I42: =IF(AND(N(D42)>0,N(E42)>0),MAX(0,ROUNDDOWN((D42*E42-H42*N(G42))/30*C38*F33,2)),0) | K42: =ROUNDDOWN(N(D42)*N(E42),2)
B43: 2 | C43: Vigilância armada de 12x36 horas noturnas de Segunda Feira a Domingo | D43: 12 | E43: 6228.99 | F43: =IF(N(D43)>0,D43*220,0) | H43: =IF(N(D43)>0,ROUNDDOWN(E43/220,2),0) | I43: =IF(AND(N(D43)>0,N(E43)>0),MAX(0,ROUNDDOWN((D43*E43-H43*N(G43))/30*C38*F33,2)),0) | K43: =ROUNDDOWN(N(D43)*N(E43),2)
B44: 3 | C44: Vigilância desarmada de 12x36 horas diurnas de Segunda Feira a Domingo | D44: 18 | E44: 5672.89 | F44: =IF(N(D44)>0,D44*220,0) | H44: =IF(N(D44)>0,ROUNDDOWN(E44/220,2),0) | I44: =IF(AND(N(D44)>0,N(E44)>0),MAX(0,ROUNDDOWN((D44*E44-H44*N(G44))/30*C38*F33,2)),0) | K44: =ROUNDDOWN(N(D44)*N(E44),2)
B45: 4 | C45: Vigilância desarmada de 12x36 horas noturnas de Segunda Feira a Domingo | D45: 10 | E45: 6224.09 | F45: =IF(N(D45)>0,D45*220,0) | H45: =IF(N(D45)>0,ROUNDDOWN(E45/220,2),0) | I45: =IF(AND(N(D45)>0,N(E45)>0),MAX(0,ROUNDDOWN((D45*E45-H45*N(G45))/30*C38*F33,2)),0) | K45: =ROUNDDOWN(N(D45)*N(E45),2)
B46: 5 | C46: Vigilância desarmada de 44h (8:48 horas) diurnas de Segunda Feira a Sexta | D46: 1 | E46: 6019.58 | F46: =IF(N(D46)>0,D46*220,0) | H46: =IF(N(D46)>0,ROUNDDOWN(E46/220,2),0) | I46: =IF(AND(N(D46)>0,N(E46)>0),MAX(0,ROUNDDOWN((D46*E46-H46*N(G46))/30*C38*F33,2)),0) | K46: =ROUNDDOWN(N(D46)*N(E46),2)
B47: 6 | C47: Vigilância desarmada de 12x36 horas diurnas de Segunda Feira a Domingo COM INTRAJORNADA | D47: 2 | E47: 6064.91 | F47: =IF(N(D47)>0,D47*220,0) | H47: =IF(N(D47)>0,ROUNDDOWN(E47/220,2),0) | I47: =IF(AND(N(D47)>0,N(E47)>0),MAX(0,ROUNDDOWN((D47*E47-H47*N(G47))/30*C38*F33,2)),0) | K47: =ROUNDDOWN(N(D47)*N(E47),2)
B48: 7 | C48: Vigilância desarmada de 12x36 horas noturnas de Segunda Feira a Domingo COM INTRAJORNADA | D48: 2 | E48: 6654.1 | F48: =IF(N(D48)>0,D48*220,0) | H48: =IF(N(D48)>0,ROUNDDOWN(E48/220,2),0) | I48: =IF(AND(N(D48)>0,N(E48)>0),MAX(0,ROUNDDOWN((D48*E48-H48*N(G48))/30*C38*F33,2)),0) | K48: =ROUNDDOWN(N(D48)*N(E48),2)
B49: TOTAIS | D49: =SUM(D42:D48) | E49: ◀ Qtde contratada | I49: =SUM(I42:I48) | K49: =SUM(K42:K48)
B51: INSTRUMENTO DE COBRANÇA
B52: Item | C52: Posto | D52: Qtde Fat. | E52: Valor Unit. Faturado (R$)
B53: =B42 | C53: =C42 | D53: =N(D42) | E53: =IF(N(D42)>0,ROUNDDOWN(I42/D42,2),0)
B54: =B43 | C54: =C43 | D54: =N(D43) | E54: =IF(N(D43)>0,ROUNDDOWN(I43/D43,2),0)
B55: =B44 | C55: =C44 | D55: =N(D44) | E55: =IF(N(D44)>0,ROUNDDOWN(I44/D44,2),0)
B56: =B45 | C56: =C45 | D56: =N(D45) | E56: =IF(N(D45)>0,ROUNDDOWN(I45/D45,2),0)
B57: =B46 | C57: =C46 | D57: =N(D46) | E57: =IF(N(D46)>0,ROUNDDOWN(I46/D46,2),0)
B58: =B47 | C58: =C47 | D58: =N(D47) | E58: =IF(N(D47)>0,ROUNDDOWN(I47/D47,2),0)
B59: =B48 | C59: =C48 | D59: =N(D48) | E59: =IF(N(D48)>0,ROUNDDOWN(I48/D48,2),0)
B61: RESUMO FINANCEIRO
B62: Contratado Mensal – Total (R$) | E62: =K49
B63: Conceito | E63: =C33
B64: % do Faturamento a ser Liberado | E64: =F33
B65: Valor Glosado por QUALIDADE (R$) | E65: =ROUNDDOWN(K49-K49*F33,2)
B66: Valor Aprovado para Pagamento (R$) | E66: =MAX(0,ROUNDDOWN(I49+E82,2))
B68: FAIXA DE AJUSTE
B69: Conceito | C69: % a Pagar | E69: Nota Média
B70: A | C70: 100% | E70: 9,00–8,10
B71: B | C71: 95% | E71: 8,09–7,65
B72: C | C72: 90% | E72: 7,64–6,75
B73: D | C73: 85% | E73: 6,74–5,85
B74: E | C74: 80% | E74: 5,84–5,40
B75: F | C75: 75% | E75: < 5,40
B77: REEMBOLSO DE CRECHE
B78: Valor estimado unitário (R$) | E78: 0
B79: Valor Reembolso Creche Retido (R$) (estimado × qtde contratada) | E79: =ROUNDDOWN(E78*D49,2)
B80: Reembolsos Aprovados (quantidade)
B81: Reembolso por dependente (R$) | E81: 526.64
B82: Valor Total dos Reembolsos (R$) (Aprovados × Reembolso por dependente) | E82: =ROUNDDOWN(E80*E81,2)
B83: Saldo do mês anterior (R$) | E83: ='Maio 2024'!E84
B84: Saldo de Reembolso (R$) (Saldo anterior + Retido − Total) | E84: =E83+E79-E82
B85: =IF(E84<0,"⚠ Saldo negativo — se houver mais de uma unidade favor somar o saldo de todas; se permanecer negativo, aditivar o contrato.","")
B88: JUSTIFICATIVAS E OBSERVAÇÕES

Sheet Julho 2024
B1: UNIVERSIDADE FEDERAL DO RIO DE JANEIRO — PR-6
B3: INSTRUMENTO DE MEDIÇÃO DE RESULTADO (IMR)
B7: IDENTIFICAÇÃO
B8: CONTRATO Nº | C8: 05/24
B9: UNIDADE | C9: MACAÉ
B10: CONTRATADA | C10: ANGEL'S SEGURANÇA E VIGILÂNCIA - EM RECUPERAÇÃO JUDICIAL LTDA
B11: FISCAL OPERACIONAL
B12: PERÍODO DE REFERÊNCIA | C12: Julho 2024
B14: AVALIAÇÃO DE DESEMPENHO
B15: Critério de Avaliação | C15: PESO (a) | D15: NOTA (b) (0,1,3) | E15: SUBTOTAL (c=a×b)
B16: ▶ GRUPO 1 – DESEMPENHO PROFISSIONAL
B17: Cumprimento das Atividades | C17: 0.4 | D17: 3 | E17: =C17*D17 | G17: =IF(OR(D17=0,D17=1),"Obrigatória justificativa no campo Justificativa e observações","")
B18: Qualificação / Atendimento ao Público / Postura | C18: 0.35 | D18: 3 | E18: =C18*D18 | G18: =IF(OR(D18=0,D18=1),"Obrigatória justificativa no campo Justificativa e observações","")
B19: Uniformes e Identificação | C19: 0.25 | D19: 3 | E19: =C19*D19 | G19: =IF(OR(D19=0,D19=1),"Obrigatória justificativa no campo Justificativa e observações","")
B20: TOTAL GRUPO 1 | C20: 1 | E20: =E17+E18+E19
B21: ▶ GRUPO 2 – DESEMPENHO DAS ATIVIDADES
B22: Especificação Técnica dos Serviços | C22: 0.4 | D22: 3 | E22: =C22*D22 | G22: =IF(OR(D22=0,D22=1),"Obrigatória justificativa no campo Justificativa e observações","")
B23: Equipamentos e Acessórios | C23: 0.2 | D23: 3 | E23: =C23*D23 | G23: =IF(OR(D23=0,D23=1),"Obrigatória justificativa no campo Justificativa e observações","")
B24: Atendimento às Ocorrências | C24: 0.4 | D24: 3 | E24: =C24*D24 | G24: =IF(OR(D24=0,D24=1),"Obrigatória justificativa no campo Justificativa e observações","")
B25: TOTAL GRUPO 2 | C25: 1 | E25: =E22+E23+E24
B26: ▶ GRUPO 3 – GERENCIAMENTO
B27: Periodicidade da Supervisão | C27: 0.2 | D27: 3 | E27: =C27*D27 | G27: =IF(OR(D27=0,D27=1),"Obrigatória justificativa no campo Justificativa e observações","")
B28: Gerenciamento das Atividades Operacionais | C28: 0.3 | D28: 3 | E28: =C28*D28 | G28: =IF(OR(D28=0,D28=1),"Obrigatória justificativa no campo Justificativa e observações","")
B29: Atendimento às Solicitações | C29: 0.25 | D29: 3 | E29: =C29*D29 | G29: =IF(OR(D29=0,D29=1),"Obrigatória justificativa no campo Justificativa e observações","")
B30: Salários, Benefícios e Obrigações Trabalhistas | C30: 0.25 | D30: 3 | E30: =C30*D30 | G30: =IF(OR(D30=0,D30=1),"Obrigatória justificativa no campo Justificativa e observações","")
B31: TOTAL GRUPO 3 | C31: 1 | E31: =E27+E28+E29+E30
B32: NOTA FINAL (G1+G2+G3) | E32: =E20+E25+E31
B33: CONCEITO | C33: =IF(E32>=8.1,"A",IF(E32>=7.65,"B",IF(E32>=6.75,"C",IF(E32>=5.85,"D",IF(E32>=5.4,"E","F"))))) | E33: % a pagar | F33: =IF(C33="A",1,IF(C33="B",0.95,IF(C33="C",0.9,IF(C33="D",0.85,IF(C33="E",0.8,0.75)))))
B35: PARÂMETROS (base 30 avos)
B36: Dias no mês (calendário) | C36: 30
B37: Nº de Dias Trabalhados | C37: 30
B38: Dias para cálculo (base 30) | C38: =IF(C37>=C36,30,MIN(C37,C36))
B40: POSTOS DE TRABALHO
B41: Item | C41: POSTO | D41: Qtde Contratada | E41: Valor Unit. (R$) | F41: Horas | G41: Sem Cob. (h) | H41: Valor Hora (R$) | I41: Valor após Descontos (R$) | K41: (aux) Mensal
B42: 1 | C42: Vigilância armada de 12x36 horas diurnas de Segunda Feira a Domingo | D42: 4 | E42: 5677.75 | F42: =IF(N(D42)>0,D42*220,0) | H42: =IF(N(D42)>0,ROUNDDOWN(E42/220,2),0) | I42: =IF(AND(N(D42)>0,N(E42)>0),MAX(0,ROUNDDOWN((D42*E42-H42*N(G42))/30*C38*F33,2)),0) | K42: =ROUNDDOWN(N(D42)*N(E42),2)
B43: 2 | C43: Vigilância armada de 12x36 horas noturnas de Segunda Feira a Domingo | D43: 12 | E43: 6228.99 | F43: =IF(N(D43)>0,D43*220,0) | H43: =IF(N(D43)>0,ROUNDDOWN(E43/220,2),0) | I43: =IF(AND(N(D43)>0,N(E43)>0),MAX(0,ROUNDDOWN((D43*E43-H43*N(G43))/30*C38*F33,2)),0) | K43: =ROUNDDOWN(N(D43)*N(E43),2)
B44: 3 | C44: Vigilância desarmada de 12x36 horas diurnas de Segunda Feira a Domingo | D44: 18 | E44: 5672.89 | F44: =IF(N(D44)>0,D44*220,0) | H44: =IF(N(D44)>0,ROUNDDOWN(E44/220,2),0) | I44: =IF(AND(N(D44)>0,N(E44)>0),MAX(0,ROUNDDOWN((D44*E44-H44*N(G44))/30*C38*F33,2)),0) | K44: =ROUNDDOWN(N(D44)*N(E44),2)
B45: 4 | C45: Vigilância desarmada de 12x36 horas noturnas de Segunda Feira a Domingo | D45: 10 | E45: 6224.09 | F45: =IF(N(D45)>0,D45*220,0) | H45: =IF(N(D45)>0,ROUNDDOWN(E45/220,2),0) | I45: =IF(AND(N(D45)>0,N(E45)>0),MAX(0,ROUNDDOWN((D45*E45-H45*N(G45))/30*C38*F33,2)),0) | K45: =ROUNDDOWN(N(D45)*N(E45),2)
B46: 5 | C46: Vigilância desarmada de 44h (8:48 horas) diurnas de Segunda Feira a Sexta | D46: 1 | E46: 6019.58 | F46: =IF(N(D46)>0,D46*220,0) | H46: =IF(N(D46)>0,ROUNDDOWN(E46/220,2),0) | I46: =IF(AND(N(D46)>0,N(E46)>0),MAX(0,ROUNDDOWN((D46*E46-H46*N(G46))/30*C38*F33,2)),0) | K46: =ROUNDDOWN(N(D46)*N(E46),2)
B47: 6 | C47: Vigilância desarmada de 12x36 horas diurnas de Segunda Feira a Domingo COM INTRAJORNADA | D47: 2 | E47: 6064.91 | F47: =IF(N(D47)>0,D47*220,0) | H47: =IF(N(D47)>0,ROUNDDOWN(E47/220,2),0) | I47: =IF(AND(N(D47)>0,N(E47)>0),MAX(0,ROUNDDOWN((D47*E47-H47*N(G47))/30*C38*F33,2)),0) | K47: =ROUNDDOWN(N(D47)*N(E47),2)
B48: 7 | C48: Vigilância desarmada de 12x36 horas noturnas de Segunda Feira a Domingo COM INTRAJORNADA | D48: 2 | E48: 6654.1 | F48: =IF(N(D48)>0,D48*220,0) | H48: =IF(N(D48)>0,ROUNDDOWN(E48/220,2),0) | I48: =IF(AND(N(D48)>0,N(E48)>0),MAX(0,ROUNDDOWN((D48*E48-H48*N(G48))/30*C38*F33,2)),0) | K48: =ROUNDDOWN(N(D48)*N(E48),2)
B49: TOTAIS | D49: =SUM(D42:D48) | E49: ◀ Qtde contratada | I49: =SUM(I42:I48) | K49: =SUM(K42:K48)
B51: INSTRUMENTO DE COBRANÇA
B52: Item | C52: Posto | D52: Qtde Fat. | E52: Valor Unit. Faturado (R$)
B53: =B42 | C53: =C42 | D53: =N(D42) | E53: =IF(N(D42)>0,ROUNDDOWN(I42/D42,2),0)
B54: =B43 | C54: =C43 | D54: =N(D43) | E54: =IF(N(D43)>0,ROUNDDOWN(I43/D43,2),0)
B55: =B44 | C55: =C44 | D55: =N(D44) | E55: =IF(N(D44)>0,ROUNDDOWN(I44/D44,2),0)
B56: =B45 | C56: =C45 | D56: =N(D45) | E56: =IF(N(D45)>0,ROUNDDOWN(I45/D45,2),0)
B57: =B46 | C57: =C46 | D57: =N(D46) | E57: =IF(N(D46)>0,ROUNDDOWN(I46/D46,2),0)
B58: =B47 | C58: =C47 | D58: =N(D47) | E58: =IF(N(D47)>0,ROUNDDOWN(I47/D47,2),0)
B59: =B48 | C59: =C48 | D59: =N(D48) | E59: =IF(N(D48)>0,ROUNDDOWN(I48/D48,2),0)
B61: RESUMO FINANCEIRO
B62: Contratado Mensal – Total (R$) | E62: =K49
B63: Conceito | E63: =C33
B64: % do Faturamento a ser Liberado | E64: =F33
B65: Valor Glosado por QUALIDADE (R$) | E65: =ROUNDDOWN(K49-K49*F33,2)
B66: Valor Aprovado para Pagamento (R$) | E66: =MAX(0,ROUNDDOWN(I49+E82,2))
B68: FAIXA DE AJUSTE
B69: Conceito | C69: % a Pagar | E69: Nota Média
B70: A | C70: 100% | E70: 9,00–8,10
B71: B | C71: 95% | E71: 8,09–7,65
B72: C | C72: 90% | E72: 7,64–6,75
B73: D | C73: 85% | E73: 6,74–5,85
B74: E | C74: 80% | E74: 5,84–5,40
B75: F | C75: 75% | E75: < 5,40
B77: REEMBOLSO DE CRECHE
B78: Valor estimado unitário (R$) | E78: 0
B79: Valor Reembolso Creche Retido (R$) (estimado × qtde contratada) | E79: =ROUNDDOWN(E78*D49,2)
B80: Reembolsos Aprovados (quantidade)
B81: Reembolso por dependente (R$) | E81: 526.64
B82: Valor Total dos Reembolsos (R$) (Aprovados × Reembolso por dependente) | E82: =ROUNDDOWN(E80*E81,2)
B83: Saldo do mês anterior (R$) | E83: ='Junho 2024'!E84
B84: Saldo de Reembolso (R$) (Saldo anterior + Retido − Total) | E84: =E83+E79-E82
B85: =IF(E84<0,"⚠ Saldo negativo — se houver mais de uma unidade favor somar o saldo de todas; se permanecer negativo, aditivar o contrato.","")
B88: JUSTIFICATIVAS E OBSERVAÇÕES

Sheet Agosto 2024
B1: UNIVERSIDADE FEDERAL DO RIO DE JANEIRO — PR-6
B3: INSTRUMENTO DE MEDIÇÃO DE RESULTADO (IMR)
B7: IDENTIFICAÇÃO
B8: CONTRATO Nº | C8: 05/24
B9: UNIDADE | C9: MACAÉ
B10: CONTRATADA | C10: ANGEL'S SEGURANÇA E VIGILÂNCIA - EM RECUPERAÇÃO JUDICIAL LTDA
B11: FISCAL OPERACIONAL
B12: PERÍODO DE REFERÊNCIA | C12: Agosto 2024
B14: AVALIAÇÃO DE DESEMPENHO
B15: Critério de Avaliação | C15: PESO (a) | D15: NOTA (b) (0,1,3) | E15: SUBTOTAL (c=a×b)
B16: ▶ GRUPO 1 – DESEMPENHO PROFISSIONAL
B17: Cumprimento das Atividades | C17: 0.4 | D17: 3 | E17: =C17*D17 | G17: =IF(OR(D17=0,D17=1),"Obrigatória justificativa no campo Justificativa e observações","")
B18: Qualificação / Atendimento ao Público / Postura | C18: 0.35 | D18: 3 | E18: =C18*D18 | G18: =IF(OR(D18=0,D18=1),"Obrigatória justificativa no campo Justificativa e observações","")
B19: Uniformes e Identificação | C19: 0.25 | D19: 3 | E19: =C19*D19 | G19: =IF(OR(D19=0,D19=1),"Obrigatória justificativa no campo Justificativa e observações","")
B20: TOTAL GRUPO 1 | C20: 1 | E20: =E17+E18+E19
B21: ▶ GRUPO 2 – DESEMPENHO DAS ATIVIDADES
B22: Especificação Técnica dos Serviços | C22: 0.4 | D22: 3 | E22: =C22*D22 | G22: =IF(OR(D22=0,D22=1),"Obrigatória justificativa no campo Justificativa e observações","")
B23: Equipamentos e Acessórios | C23: 0.2 | D23: 3 | E23: =C23*D23 | G23: =IF(OR(D23=0,D23=1),"Obrigatória justificativa no campo Justificativa e observações","")
B24: Atendimento às Ocorrências | C24: 0.4 | D24: 3 | E24: =C24*D24 | G24: =IF(OR(D24=0,D24=1),"Obrigatória justificativa no campo Justificativa e observações","")
B25: TOTAL GRUPO 2 | C25: 1 | E25: =E22+E23+E24
B26: ▶ GRUPO 3 – GERENCIAMENTO
B27: Periodicidade da Supervisão | C27: 0.2 | D27: 3 | E27: =C27*D27 | G27: =IF(OR(D27=0,D27=1),"Obrigatória justificativa no campo Justificativa e observações","")
B28: Gerenciamento das Atividades Operacionais | C28: 0.3 | D28: 3 | E28: =C28*D28 | G28: =IF(OR(D28=0,D28=1),"Obrigatória justificativa no campo Justificativa e observações","")
B29: Atendimento às Solicitações | C29: 0.25 | D29: 3 | E29: =C29*D29 | G29: =IF(OR(D29=0,D29=1),"Obrigatória justificativa no campo Justificativa e observações","")
B30: Salários, Benefícios e Obrigações Trabalhistas | C30: 0.25 | D30: 3 | E30: =C30*D30 | G30: =IF(OR(D30=0,D30=1),"Obrigatória justificativa no campo Justificativa e observações","")
B31: TOTAL GRUPO 3 | C31: 1 | E31: =E27+E28+E29+E30
B32: NOTA FINAL (G1+G2+G3) | E32: =E20+E25+E31
B33: CONCEITO | C33: =IF(E32>=8.1,"A",IF(E32>=7.65,"B",IF(E32>=6.75,"C",IF(E32>=5.85,"D",IF(E32>=5.4,"E","F"))))) | E33: % a pagar | F33: =IF(C33="A",1,IF(C33="B",0.95,IF(C33="C",0.9,IF(C33="D",0.85,IF(C33="E",0.8,0.75)))))
B35: PARÂMETROS (base 30 avos)
B36: Dias no mês (calendário) | C36: 30
B37: Nº de Dias Trabalhados | C37: 30
B38: Dias para cálculo (base 30) | C38: =IF(C37>=C36,30,MIN(C37,C36))
B40: POSTOS DE TRABALHO
B41: Item | C41: POSTO | D41: Qtde Contratada | E41: Valor Unit. (R$) | F41: Horas | G41: Sem Cob. (h) | H41: Valor Hora (R$) | I41: Valor após Descontos (R$) | K41: (aux) Mensal
B42: 1 | C42: Vigilância armada de 12x36 horas diurnas de Segunda Feira a Domingo | D42: 4 | E42: 5677.75 | F42: =IF(N(D42)>0,D42*220,0) | H42: =IF(N(D42)>0,ROUNDDOWN(E42/220,2),0) | I42: =IF(AND(N(D42)>0,N(E42)>0),MAX(0,ROUNDDOWN((D42*E42-H42*N(G42))/30*C38*F33,2)),0) | K42: =ROUNDDOWN(N(D42)*N(E42),2)
B43: 2 | C43: Vigilância armada de 12x36 horas noturnas de Segunda Feira a Domingo | D43: 12 | E43: 6228.99 | F43: =IF(N(D43)>0,D43*220,0) | H43: =IF(N(D43)>0,ROUNDDOWN(E43/220,2),0) | I43: =IF(AND(N(D43)>0,N(E43)>0),MAX(0,ROUNDDOWN((D43*E43-H43*N(G43))/30*C38*F33,2)),0) | K43: =ROUNDDOWN(N(D43)*N(E43),2)
B44: 3 | C44: Vigilância desarmada de 12x36 horas diurnas de Segunda Feira a Domingo | D44: 18 | E44: 5672.89 | F44: =IF(N(D44)>0,D44*220,0) | H44: =IF(N(D44)>0,ROUNDDOWN(E44/220,2),0) | I44: =IF(AND(N(D44)>0,N(E44)>0),MAX(0,ROUNDDOWN((D44*E44-H44*N(G44))/30*C38*F33,2)),0) | K44: =ROUNDDOWN(N(D44)*N(E44),2)
B45: 4 | C45: Vigilância desarmada de 12x36 horas noturnas de Segunda Feira a Domingo | D45: 10 | E45: 6224.09 | F45: =IF(N(D45)>0,D45*220,0) | H45: =IF(N(D45)>0,ROUNDDOWN(E45/220,2),0) | I45: =IF(AND(N(D45)>0,N(E45)>0),MAX(0,ROUNDDOWN((D45*E45-H45*N(G45))/30*C38*F33,2)),0) | K45: =ROUNDDOWN(N(D45)*N(E45),2)
B46: 5 | C46: Vigilância desarmada de 44h (8:48 horas) diurnas de Segunda Feira a Sexta | D46: 1 | E46: 6019.58 | F46: =IF(N(D46)>0,D46*220,0) | H46: =IF(N(D46)>0,ROUNDDOWN(E46/220,2),0) | I46: =IF(AND(N(D46)>0,N(E46)>0),MAX(0,ROUNDDOWN((D46*E46-H46*N(G46))/30*C38*F33,2)),0) | K46: =ROUNDDOWN(N(D46)*N(E46),2)
B47: 6 | C47: Vigilância desarmada de 12x36 horas diurnas de Segunda Feira a Domingo COM INTRAJORNADA | D47: 2 | E47: 6064.91 | F47: =IF(N(D47)>0,D47*220,0) | H47: =IF(N(D47)>0,ROUNDDOWN(E47/220,2),0) | I47: =IF(AND(N(D47)>0,N(E47)>0),MAX(0,ROUNDDOWN((D47*E47-H47*N(G47))/30*C38*F33,2)),0) | K47: =ROUNDDOWN(N(D47)*N(E47),2)
B48: 7 | C48: Vigilância desarmada de 12x36 horas noturnas de Segunda Feira a Domingo COM INTRAJORNADA | D48: 2 | E48: 6654.1 | F48: =IF(N(D48)>0,D48*220,0) | H48: =IF(N(D48)>0,ROUNDDOWN(E48/220,2),0) | I48: =IF(AND(N(D48)>0,N(E48)>0),MAX(0,ROUNDDOWN((D48*E48-H48*N(G48))/30*C38*F33,2)),0) | K48: =ROUNDDOWN(N(D48)*N(E48),2)
B49: TOTAIS | D49: =SUM(D42:D48) | E49: ◀ Qtde contratada | I49: =SUM(I42:I48) | K49: =SUM(K42:K48)
B51: INSTRUMENTO DE COBRANÇA
B52: Item | C52: Posto | D52: Qtde Fat. | E52: Valor Unit. Faturado (R$)
B53: =B42 | C53: =C42 | D53: =N(D42) | E53: =IF(N(D42)>0,ROUNDDOWN(I42/D42,2),0)
B54: =B43 | C54: =C43 | D54: =N(D43) | E54: =IF(N(D43)>0,ROUNDDOWN(I43/D43,2),0)
B55: =B44 | C55: =C44 | D55: =N(D44) | E55: =IF(N(D44)>0,ROUNDDOWN(I44/D44,2),0)
B56: =B45 | C56: =C45 | D56: =N(D45) | E56: =IF(N(D45)>0,ROUNDDOWN(I45/D45,2),0)
B57: =B46 | C57: =C46 | D57: =N(D46) | E57: =IF(N(D46)>0,ROUNDDOWN(I46/D46,2),0)
B58: =B47 | C58: =C47 | D58: =N(D47) | E58: =IF(N(D47)>0,ROUNDDOWN(I47/D47,2),0)
B59: =B48 | C59: =C48 | D59: =N(D48) | E59: =IF(N(D48)>0,ROUNDDOWN(I48/D48,2),0)
B61: RESUMO FINANCEIRO
B62: Contratado Mensal – Total (R$) | E62: =K49
B63: Conceito | E63: =C33
B64: % do Faturamento a ser Liberado | E64: =F33
B65: Valor Glosado por QUALIDADE (R$) | E65: =ROUNDDOWN(K49-K49*F33,2)
B66: Valor Aprovado para Pagamento (R$) | E66: =MAX(0,ROUNDDOWN(I49+E82,2))
B68: FAIXA DE AJUSTE
B69: Conceito | C69: % a Pagar | E69: Nota Média
B70: A | C70: 100% | E70: 9,00–8,10
B71: B | C71: 95% | E71: 8,09–7,65
B72: C | C72: 90% | E72: 7,64–6,75
B73: D | C73: 85% | E73: 6,74–5,85
B74: E | C74: 80% | E74: 5,84–5,40
B75: F | C75: 75% | E75: < 5,40
B77: REEMBOLSO DE CRECHE
B78: Valor estimado unitário (R$) | E78: 0
B79: Valor Reembolso Creche Retido (R$) (estimado × qtde contratada) | E79: =ROUNDDOWN(E78*D49,2)
B80: Reembolsos Aprovados (quantidade)
B81: Reembolso por dependente (R$) | E81: 526.64
B82: Valor Total dos Reembolsos (R$) (Aprovados × Reembolso por dependente) | E82: =ROUNDDOWN(E80*E81,2)
B83: Saldo do mês anterior (R$) | E83: ='Julho 2024'!E84
B84: Saldo de Reembolso (R$) (Saldo anterior + Retido − Total) | E84: =E83+E79-E82
B85: =IF(E84<0,"⚠ Saldo negativo — se houver mais de uma unidade favor somar o saldo de todas; se permanecer negativo, aditivar o contrato.","")
B88: JUSTIFICATIVAS E OBSERVAÇÕES

Sheet Setembro 2024
B1: UNIVERSIDADE FEDERAL DO RIO DE JANEIRO — PR-6
B3: INSTRUMENTO DE MEDIÇÃO DE RESULTADO (IMR)
B7: IDENTIFICAÇÃO
B8: CONTRATO Nº | C8: 05/24
B9: UNIDADE | C9: MACAÉ
B10: CONTRATADA | C10: ANGEL'S SEGURANÇA E VIGILÂNCIA - EM RECUPERAÇÃO JUDICIAL LTDA
B11: FISCAL OPERACIONAL
B12: PERÍODO DE REFERÊNCIA | C12: Setembro 2024
B14: AVALIAÇÃO DE DESEMPENHO
B15: Critério de Avaliação | C15: PESO (a) | D15: NOTA (b) (0,1,3) | E15: SUBTOTAL (c=a×b)
B16: ▶ GRUPO 1 – DESEMPENHO PROFISSIONAL
B17: Cumprimento das Atividades | C17: 0.4 | D17: 3 | E17: =C17*D17 | G17: =IF(OR(D17=0,D17=1),"Obrigatória justificativa no campo Justificativa e observações","")
B18: Qualificação / Atendimento ao Público / Postura | C18: 0.35 | D18: 3 | E18: =C18*D18 | G18: =IF(OR(D18=0,D18=1),"Obrigatória justificativa no campo Justificativa e observações","")
B19: Uniformes e Identificação | C19: 0.25 | D19: 3 | E19: =C19*D19 | G19: =IF(OR(D19=0,D19=1),"Obrigatória justificativa no campo Justificativa e observações","")
B20: TOTAL GRUPO 1 | C20: 1 | E20: =E17+E18+E19
B21: ▶ GRUPO 2 – DESEMPENHO DAS ATIVIDADES
B22: Especificação Técnica dos Serviços | C22: 0.4 | D22: 3 | E22: =C22*D22 | G22: =IF(OR(D22=0,D22=1),"Obrigatória justificativa no campo Justificativa e observações","")
B23: Equipamentos e Acessórios | C23: 0.2 | D23: 3 | E23: =C23*D23 | G23: =IF(OR(D23=0,D23=1),"Obrigatória justificativa no campo Justificativa e observações","")
B24: Atendimento às Ocorrências | C24: 0.4 | D24: 3 | E24: =C24*D24 | G24: =IF(OR(D24=0,D24=1),"Obrigatória justificativa no campo Justificativa e observações","")
B25: TOTAL GRUPO 2 | C25: 1 | E25: =E22+E23+E24
B26: ▶ GRUPO 3 – GERENCIAMENTO
B27: Periodicidade da Supervisão | C27: 0.2 | D27: 3 | E27: =C27*D27 | G27: =IF(OR(D27=0,D27=1),"Obrigatória justificativa no campo Justificativa e observações","")
B28: Gerenciamento das Atividades Operacionais | C28: 0.3 | D28: 3 | E28: =C28*D28 | G28: =IF(OR(D28=0,D28=1),"Obrigatória justificativa no campo Justificativa e observações","")
B29: Atendimento às Solicitações | C29: 0.25 | D29: 3 | E29: =C29*D29 | G29: =IF(OR(D29=0,D29=1),"Obrigatória justificativa no campo Justificativa e observações","")
B30: Salários, Benefícios e Obrigações Trabalhistas | C30: 0.25 | D30: 3 | E30: =C30*D30 | G30: =IF(OR(D30=0,D30=1),"Obrigatória justificativa no campo Justificativa e observações","")
B31: TOTAL GRUPO 3 | C31: 1 | E31: =E27+E28+E29+E30
B32: NOTA FINAL (G1+G2+G3) | E32: =E20+E25+E31
B33: CONCEITO | C33: =IF(E32>=8.1,"A",IF(E32>=7.65,"B",IF(E32>=6.75,"C",IF(E32>=5.85,"D",IF(E32>=5.4,"E","F"))))) | E33: % a pagar | F33: =IF(C33="A",1,IF(C33="B",0.95,IF(C33="C",0.9,IF(C33="D",0.85,IF(C33="E",0.8,0.75)))))
B35: PARÂMETROS (base 30 avos)
B36: Dias no mês (calendário) | C36: 30
B37: Nº de Dias Trabalhados | C37: 30
B38: Dias para cálculo (base 30) | C38: =IF(C37>=C36,30,MIN(C37,C36))
B40: POSTOS DE TRABALHO
B41: Item | C41: POSTO | D41: Qtde Contratada | E41: Valor Unit. (R$) | F41: Horas | G41: Sem Cob. (h) | H41: Valor Hora (R$) | I41: Valor após Descontos (R$) | K41: (aux) Mensal
B42: 1 | C42: Vigilância armada de 12x36 horas diurnas de Segunda Feira a Domingo | D42: 4 | E42: 5677.75 | F42: =IF(N(D42)>0,D42*220,0) | H42: =IF(N(D42)>0,ROUNDDOWN(E42/220,2),0) | I42: =IF(AND(N(D42)>0,N(E42)>0),MAX(0,ROUNDDOWN((D42*E42-H42*N(G42))/30*C38*F33,2)),0) | K42: =ROUNDDOWN(N(D42)*N(E42),2)
B43: 2 | C43: Vigilância armada de 12x36 horas noturnas de Segunda Feira a Domingo | D43: 12 | E43: 6228.99 | F43: =IF(N(D43)>0,D43*220,0) | H43: =IF(N(D43)>0,ROUNDDOWN(E43/220,2),0) | I43: =IF(AND(N(D43)>0,N(E43)>0),MAX(0,ROUNDDOWN((D43*E43-H43*N(G43))/30*C38*F33,2)),0) | K43: =ROUNDDOWN(N(D43)*N(E43),2)
B44: 3 | C44: Vigilância desarmada de 12x36 horas diurnas de Segunda Feira a Domingo | D44: 18 | E44: 5672.89 | F44: =IF(N(D44)>0,D44*220,0) | H44: =IF(N(D44)>0,ROUNDDOWN(E44/220,2),0) | I44: =IF(AND(N(D44)>0,N(E44)>0),MAX(0,ROUNDDOWN((D44*E44-H44*N(G44))/30*C38*F33,2)),0) | K44: =ROUNDDOWN(N(D44)*N(E44),2)
B45: 4 | C45: Vigilância desarmada de 12x36 horas noturnas de Segunda Feira a Domingo | D45: 10 | E45: 6224.09 | F45: =IF(N(D45)>0,D45*220,0) | H45: =IF(N(D45)>0,ROUNDDOWN(E45/220,2),0) | I45: =IF(AND(N(D45)>0,N(E45)>0),MAX(0,ROUNDDOWN((D45*E45-H45*N(G45))/30*C38*F33,2)),0) | K45: =ROUNDDOWN(N(D45)*N(E45),2)
B46: 5 | C46: Vigilância desarmada de 44h (8:48 horas) diurnas de Segunda Feira a Sexta | D46: 1 | E46: 6019.58 | F46: =IF(N(D46)>0,D46*220,0) | H46: =IF(N(D46)>0,ROUNDDOWN(E46/220,2),0) | I46: =IF(AND(N(D46)>0,N(E46)>0),MAX(0,ROUNDDOWN((D46*E46-H46*N(G46))/30*C38*F33,2)),0) | K46: =ROUNDDOWN(N(D46)*N(E46),2)
B47: 6 | C47: Vigilância desarmada de 12x36 horas diurnas de Segunda Feira a Domingo COM INTRAJORNADA | D47: 2 | E47: 6064.91 | F47: =IF(N(D47)>0,D47*220,0) | H47: =IF(N(D47)>0,ROUNDDOWN(E47/220,2),0) | I47: =IF(AND(N(D47)>0,N(E47)>0),MAX(0,ROUNDDOWN((D47*E47-H47*N(G47))/30*C38*F33,2)),0) | K47: =ROUNDDOWN(N(D47)*N(E47),2)
B48: 7 | C48: Vigilância desarmada de 12x36 horas noturnas de Segunda Feira a Domingo COM INTRAJORNADA | D48: 2 | E48: 6654.1 | F48: =IF(N(D48)>0,D48*220,0) | H48: =IF(N(D48)>0,ROUNDDOWN(E48/220,2),0) | I48: =IF(AND(N(D48)>0,N(E48)>0),MAX(0,ROUNDDOWN((D48*E48-H48*N(G48))/30*C38*F33,2)),0) | K48: =ROUNDDOWN(N(D48)*N(E48),2)
B49: TOTAIS | D49: =SUM(D42:D48) | E49: ◀ Qtde contratada | I49: =SUM(I42:I48) | K49: =SUM(K42:K48)
B51: INSTRUMENTO DE COBRANÇA
B52: Item | C52: Posto | D52: Qtde Fat. | E52: Valor Unit. Faturado (R$)
B53: =B42 | C53: =C42 | D53: =N(D42) | E53: =IF(N(D42)>0,ROUNDDOWN(I42/D42,2),0)
B54: =B43 | C54: =C43 | D54: =N(D43) | E54: =IF(N(D43)>0,ROUNDDOWN(I43/D43,2),0)
B55: =B44 | C55: =C44 | D55: =N(D44) | E55: =IF(N(D44)>0,ROUNDDOWN(I44/D44,2),0)
B56: =B45 | C56: =C45 | D56: =N(D45) | E56: =IF(N(D45)>0,ROUNDDOWN(I45/D45,2),0)
B57: =B46 | C57: =C46 | D57: =N(D46) | E57: =IF(N(D46)>0,ROUNDDOWN(I46/D46,2),0)
B58: =B47 | C58: =C47 | D58: =N(D47) | E58: =IF(N(D47)>0,ROUNDDOWN(I47/D47,2),0)
B59: =B48 | C59: =C48 | D59: =N(D48) | E59: =IF(N(D48)>0,ROUNDDOWN(I48/D48,2),0)
B61: RESUMO FINANCEIRO
B62: Contratado Mensal – Total (R$) | E62: =K49
B63: Conceito | E63: =C33
B64: % do Faturamento a ser Liberado | E64: =F33
B65: Valor Glosado por QUALIDADE (R$) | E65: =ROUNDDOWN(K49-K49*F33,2)
B66: Valor Aprovado para Pagamento (R$) | E66: =MAX(0,ROUNDDOWN(I49+E82,2))
B68: FAIXA DE AJUSTE
B69: Conceito | C69: % a Pagar | E69: Nota Média
B70: A | C70: 100% | E70: 9,00–8,10
B71: B | C71: 95% | E71: 8,09–7,65
B72: C | C72: 90% | E72: 7,64–6,75
B73: D | C73: 85% | E73: 6,74–5,85
B74: E | C74: 80% | E74: 5,84–5,40
B75: F | C75: 75% | E75: < 5,40
B77: REEMBOLSO DE CRECHE
B78: Valor estimado unitário (R$) | E78: 0
B79: Valor Reembolso Creche Retido (R$) (estimado × qtde contratada) | E79: =ROUNDDOWN(E78*D49,2)
B80: Reembolsos Aprovados (quantidade)
B81: Reembolso por dependente (R$) | E81: 526.64
B82: Valor Total dos Reembolsos (R$) (Aprovados × Reembolso por dependente) | E82: =ROUNDDOWN(E80*E81,2)
B83: Saldo do mês anterior (R$) | E83: ='Agosto 2024'!E84
B84: Saldo de Reembolso (R$) (Saldo anterior + Retido − Total) | E84: =E83+E79-E82
B85: =IF(E84<0,"⚠ Saldo negativo — se houver mais de uma unidade favor somar o saldo de todas; se permanecer negativo, aditivar o contrato.","")
B88: JUSTIFICATIVAS E OBSERVAÇÕES

Sheet Outubro 2024
B1: UNIVERSIDADE FEDERAL DO RIO DE JANEIRO — PR-6
B3: INSTRUMENTO DE MEDIÇÃO DE RESULTADO (IMR)
B7: IDENTIFICAÇÃO
B8: CONTRATO Nº | C8: 05/24
B9: UNIDADE | C9: MACAÉ
B10: CONTRATADA | C10: ANGEL'S SEGURANÇA E VIGILÂNCIA - EM RECUPERAÇÃO JUDICIAL LTDA
B11: FISCAL OPERACIONAL
B12: PERÍODO DE REFERÊNCIA | C12: Outubro 2024
B14: AVALIAÇÃO DE DESEMPENHO
B15: Critério de Avaliação | C15: PESO (a) | D15: NOTA (b) (0,1,3) | E15: SUBTOTAL (c=a×b)
B16: ▶ GRUPO 1 – DESEMPENHO PROFISSIONAL
B17: Cumprimento das Atividades | C17: 0.4 | D17: 3 | E17: =C17*D17 | G17: =IF(OR(D17=0,D17=1),"Obrigatória justificativa no campo Justificativa e observações","")
B18: Qualificação / Atendimento ao Público / Postura | C18: 0.35 | D18: 3 | E18: =C18*D18 | G18: =IF(OR(D18=0,D18=1),"Obrigatória justificativa no campo Justificativa e observações","")
B19: Uniformes e Identificação | C19: 0.25 | D19: 3 | E19: =C19*D19 | G19: =IF(OR(D19=0,D19=1),"Obrigatória justificativa no campo Justificativa e observações","")
B20: TOTAL GRUPO 1 | C20: 1 | E20: =E17+E18+E19
B21: ▶ GRUPO 2 – DESEMPENHO DAS ATIVIDADES
B22: Especificação Técnica dos Serviços | C22: 0.4 | D22: 3 | E22: =C22*D22 | G22: =IF(OR(D22=0,D22=1),"Obrigatória justificativa no campo Justificativa e observações","")
B23: Equipamentos e Acessórios | C23: 0.2 | D23: 3 | E23: =C23*D23 | G23: =IF(OR(D23=0,D23=1),"Obrigatória justificativa no campo Justificativa e observações","")
B24: Atendimento às Ocorrências | C24: 0.4 | D24: 3 | E24: =C24*D24 | G24: =IF(OR(D24=0,D24=1),"Obrigatória justificativa no campo Justificativa e observações","")
B25: TOTAL GRUPO 2 | C25: 1 | E25: =E22+E23+E24
B26: ▶ GRUPO 3 – GERENCIAMENTO
B27: Periodicidade da Supervisão | C27: 0.2 | D27: 3 | E27: =C27*D27 | G27: =IF(OR(D27=0,D27=1),"Obrigatória justificativa no campo Justificativa e observações","")
B28: Gerenciamento das Atividades Operacionais | C28: 0.3 | D28: 3 | E28: =C28*D28 | G28: =IF(OR(D28=0,D28=1),"Obrigatória justificativa no campo Justificativa e observações","")
B29: Atendimento às Solicitações | C29: 0.25 | D29: 3 | E29: =C29*D29 | G29: =IF(OR(D29=0,D29=1),"Obrigatória justificativa no campo Justificativa e observações","")
B30: Salários, Benefícios e Obrigações Trabalhistas | C30: 0.25 | D30: 3 | E30: =C30*D30 | G30: =IF(OR(D30=0,D30=1),"Obrigatória justificativa no campo Justificativa e observações","")
B31: TOTAL GRUPO 3 | C31: 1 | E31: =E27+E28+E29+E30
B32: NOTA FINAL (G1+G2+G3) | E32: =E20+E25+E31
B33: CONCEITO | C33: =IF(E32>=8.1,"A",IF(E32>=7.65,"B",IF(E32>=6.75,"C",IF(E32>=5.85,"D",IF(E32>=5.4,"E","F"))))) | E33: % a pagar | F33: =IF(C33="A",1,IF(C33="B",0.95,IF(C33="C",0.9,IF(C33="D",0.85,IF(C33="E",0.8,0.75)))))
B35: PARÂMETROS (base 30 avos)
B36: Dias no mês (calendário) | C36: 30
B37: Nº de Dias Trabalhados | C37: 30
B38: Dias para cálculo (base 30) | C38: =IF(C37>=C36,30,MIN(C37,C36))
B40: POSTOS DE TRABALHO
B41: Item | C41: POSTO | D41: Qtde Contratada | E41: Valor Unit. (R$) | F41: Horas | G41: Sem Cob. (h) | H41: Valor Hora (R$) | I41: Valor após Descontos (R$) | K41: (aux) Mensal
B42: 1 | C42: Vigilância armada de 12x36 horas diurnas de Segunda Feira a Domingo | D42: 4 | E42: 5677.75 | F42: =IF(N(D42)>0,D42*220,0) | H42: =IF(N(D42)>0,ROUNDDOWN(E42/220,2),0) | I42: =IF(AND(N(D42)>0,N(E42)>0),MAX(0,ROUNDDOWN((D42*E42-H42*N(G42))/30*C38*F33,2)),0) | K42: =ROUNDDOWN(N(D42)*N(E42),2)
B43: 2 | C43: Vigilância armada de 12x36 horas noturnas de Segunda Feira a Domingo | D43: 12 | E43: 6228.99 | F43: =IF(N(D43)>0,D43*220,0) | H43: =IF(N(D43)>0,ROUNDDOWN(E43/220,2),0) | I43: =IF(AND(N(D43)>0,N(E43)>0),MAX(0,ROUNDDOWN((D43*E43-H43*N(G43))/30*C38*F33,2)),0) | K43: =ROUNDDOWN(N(D43)*N(E43),2)
B44: 3 | C44: Vigilância desarmada de 12x36 horas diurnas de Segunda Feira a Domingo | D44: 18 | E44: 5672.89 | F44: =IF(N(D44)>0,D44*220,0) | H44: =IF(N(D44)>0,ROUNDDOWN(E44/220,2),0) | I44: =IF(AND(N(D44)>0,N(E44)>0),MAX(0,ROUNDDOWN((D44*E44-H44*N(G44))/30*C38*F33,2)),0) | K44: =ROUNDDOWN(N(D44)*N(E44),2)
B45: 4 | C45: Vigilância desarmada de 12x36 horas noturnas de Segunda Feira a Domingo | D45: 10 | E45: 6224.09 | F45: =IF(N(D45)>0,D45*220,0) | H45: =IF(N(D45)>0,ROUNDDOWN(E45/220,2),0) | I45: =IF(AND(N(D45)>0,N(E45)>0),MAX(0,ROUNDDOWN((D45*E45-H45*N(G45))/30*C38*F33,2)),0) | K45: =ROUNDDOWN(N(D45)*N(E45),2)
B46: 5 | C46: Vigilância desarmada de 44h (8:48 horas) diurnas de Segunda Feira a Sexta | D46: 1 | E46: 6019.58 | F46: =IF(N(D46)>0,D46*220,0) | H46: =IF(N(D46)>0,ROUNDDOWN(E46/220,2),0) | I46: =IF(AND(N(D46)>0,N(E46)>0),MAX(0,ROUNDDOWN((D46*E46-H46*N(G46))/30*C38*F33,2)),0) | K46: =ROUNDDOWN(N(D46)*N(E46),2)
B47: 6 | C47: Vigilância desarmada de 12x36 horas diurnas de Segunda Feira a Domingo COM INTRAJORNADA | D47: 2 | E47: 6064.91 | F47: =IF(N(D47)>0,D47*220,0) | H47: =IF(N(D47)>0,ROUNDDOWN(E47/220,2),0) | I47: =IF(AND(N(D47)>0,N(E47)>0),MAX(0,ROUNDDOWN((D47*E47-H47*N(G47))/30*C38*F33,2)),0) | K47: =ROUNDDOWN(N(D47)*N(E47),2)
B48: 7 | C48: Vigilância desarmada de 12x36 horas noturnas de Segunda Feira a Domingo COM INTRAJORNADA | D48: 2 | E48: 6654.1 | F48: =IF(N(D48)>0,D48*220,0) | H48: =IF(N(D48)>0,ROUNDDOWN(E48/220,2),0) | I48: =IF(AND(N(D48)>0,N(E48)>0),MAX(0,ROUNDDOWN((D48*E48-H48*N(G48))/30*C38*F33,2)),0) | K48: =ROUNDDOWN(N(D48)*N(E48),2)
B49: TOTAIS | D49: =SUM(D42:D48) | E49: ◀ Qtde contratada | I49: =SUM(I42:I48) | K49: =SUM(K42:K48)
B51: INSTRUMENTO DE COBRANÇA
B52: Item | C52: Posto | D52: Qtde Fat. | E52: Valor Unit. Faturado (R$)
B53: =B42 | C53: =C42 | D53: =N(D42) | E53: =IF(N(D42)>0,ROUNDDOWN(I42/D42,2),0)
B54: =B43 | C54: =C43 | D54: =N(D43) | E54: =IF(N(D43)>0,ROUNDDOWN(I43/D43,2),0)
B55: =B44 | C55: =C44 | D55: =N(D44) | E55: =IF(N(D44)>0,ROUNDDOWN(I44/D44,2),0)
B56: =B45 | C56: =C45 | D56: =N(D45) | E56: =IF(N(D45)>0,ROUNDDOWN(I45/D45,2),0)
B57: =B46 | C57: =C46 | D57: =N(D46) | E57: =IF(N(D46)>0,ROUNDDOWN(I46/D46,2),0)
B58: =B47 | C58: =C47 | D58: =N(D47) | E58: =IF(N(D47)>0,ROUNDDOWN(I47/D47,2),0)
B59: =B48 | C59: =C48 | D59: =N(D48) | E59: =IF(N(D48)>0,ROUNDDOWN(I48/D48,2),0)
B61: RESUMO FINANCEIRO
B62: Contratado Mensal – Total (R$) | E62: =K49
B63: Conceito | E63: =C33
B64: % do Faturamento a ser Liberado | E64: =F33
B65: Valor Glosado por QUALIDADE (R$) | E65: =ROUNDDOWN(K49-K49*F33,2)
B66: Valor Aprovado para Pagamento (R$) | E66: =MAX(0,ROUNDDOWN(I49+E82,2))
B68: FAIXA DE AJUSTE
B69: Conceito | C69: % a Pagar | E69: Nota Média
B70: A | C70: 100% | E70: 9,00–8,10
B71: B | C71: 95% | E71: 8,09–7,65
B72: C | C72: 90% | E72: 7,64–6,75
B73: D | C73: 85% | E73: 6,74–5,85
B74: E | C74: 80% | E74: 5,84–5,40
B75: F | C75: 75% | E75: < 5,40
B77: REEMBOLSO DE CRECHE
B78: Valor estimado unitário (R$) | E78: 0
B79: Valor Reembolso Creche Retido (R$) (estimado × qtde contratada) | E79: =ROUNDDOWN(E78*D49,2)
B80: Reembolsos Aprovados (quantidade)
B81: Reembolso por dependente (R$) | E81: 526.64
B82: Valor Total dos Reembolsos (R$) (Aprovados × Reembolso por dependente) | E82: =ROUNDDOWN(E80*E81,2)
B83: Saldo do mês anterior (R$) | E83: ='Setembro 2024'!E84
B84: Saldo de Reembolso (R$) (Saldo anterior + Retido − Total) | E84: =E83+E79-E82
B85: =IF(E84<0,"⚠ Saldo negativo — se houver mais de uma unidade favor somar o saldo de todas; se permanecer negativo, aditivar o contrato.","")
B88: JUSTIFICATIVAS E OBSERVAÇÕES

Sheet Novembro 2024
B1: UNIVERSIDADE FEDERAL DO RIO DE JANEIRO — PR-6
B3: INSTRUMENTO DE MEDIÇÃO DE RESULTADO (IMR)
B7: IDENTIFICAÇÃO
B8: CONTRATO Nº | C8: 05/24
B9: UNIDADE | C9: MACAÉ
B10: CONTRATADA | C10: ANGEL'S SEGURANÇA E VIGILÂNCIA - EM RECUPERAÇÃO JUDICIAL LTDA
B11: FISCAL OPERACIONAL
B12: PERÍODO DE REFERÊNCIA | C12: Novembro 2024
B14: AVALIAÇÃO DE DESEMPENHO
B15: Critério de Avaliação | C15: PESO (a) | D15: NOTA (b) (0,1,3) | E15: SUBTOTAL (c=a×b)
B16: ▶ GRUPO 1 – DESEMPENHO PROFISSIONAL
B17: Cumprimento das Atividades | C17: 0.4 | D17: 3 | E17: =C17*D17 | G17: =IF(OR(D17=0,D17=1),"Obrigatória justificativa no campo Justificativa e observações","")
B18: Qualificação / Atendimento ao Público / Postura | C18: 0.35 | D18: 3 | E18: =C18*D18 | G18: =IF(OR(D18=0,D18=1),"Obrigatória justificativa no campo Justificativa e observações","")
B19: Uniformes e Identificação | C19: 0.25 | D19: 3 | E19: =C19*D19 | G19: =IF(OR(D19=0,D19=1),"Obrigatória justificativa no campo Justificativa e observações","")
B20: TOTAL GRUPO 1 | C20: 1 | E20: =E17+E18+E19
B21: ▶ GRUPO 2 – DESEMPENHO DAS ATIVIDADES
B22: Especificação Técnica dos Serviços | C22: 0.4 | D22: 3 | E22: =C22*D22 | G22: =IF(OR(D22=0,D22=1),"Obrigatória justificativa no campo Justificativa e observações","")
B23: Equipamentos e Acessórios | C23: 0.2 | D23: 3 | E23: =C23*D23 | G23: =IF(OR(D23=0,D23=1),"Obrigatória justificativa no campo Justificativa e observações","")
B24: Atendimento às Ocorrências | C24: 0.4 | D24: 3 | E24: =C24*D24 | G24: =IF(OR(D24=0,D24=1),"Obrigatória justificativa no campo Justificativa e observações","")
B25: TOTAL GRUPO 2 | C25: 1 | E25: =E22+E23+E24
B26: ▶ GRUPO 3 – GERENCIAMENTO
B27: Periodicidade da Supervisão | C27: 0.2 | D27: 3 | E27: =C27*D27 | G27: =IF(OR(D27=0,D27=1),"Obrigatória justificativa no campo Justificativa e observações","")
B28: Gerenciamento das Atividades Operacionais | C28: 0.3 | D28: 3 | E28: =C28*D28 | G28: =IF(OR(D28=0,D28=1),"Obrigatória justificativa no campo Justificativa e observações","")
B29: Atendimento às Solicitações | C29: 0.25 | D29: 3 | E29: =C29*D29 | G29: =IF(OR(D29=0,D29=1),"Obrigatória justificativa no campo Justificativa e observações","")
B30: Salários, Benefícios e Obrigações Trabalhistas | C30: 0.25 | D30: 3 | E30: =C30*D30 | G30: =IF(OR(D30=0,D30=1),"Obrigatória justificativa no campo Justificativa e observações","")
B31: TOTAL GRUPO 3 | C31: 1 | E31: =E27+E28+E29+E30
B32: NOTA FINAL (G1+G2+G3) | E32: =E20+E25+E31
B33: CONCEITO | C33: =IF(E32>=8.1,"A",IF(E32>=7.65,"B",IF(E32>=6.75,"C",IF(E32>=5.85,"D",IF(E32>=5.4,"E","F"))))) | E33: % a pagar | F33: =IF(C33="A",1,IF(C33="B",0.95,IF(C33="C",0.9,IF(C33="D",0.85,IF(C33="E",0.8,0.75)))))
B35: PARÂMETROS (base 30 avos)
B36: Dias no mês (calendário) | C36: 30
B37: Nº de Dias Trabalhados | C37: 30
B38: Dias para cálculo (base 30) | C38: =IF(C37>=C36,30,MIN(C37,C36))
B40: POSTOS DE TRABALHO
B41: Item | C41: POSTO | D41: Qtde Contratada | E41: Valor Unit. (R$) | F41: Horas | G41: Sem Cob. (h) | H41: Valor Hora (R$) | I41: Valor após Descontos (R$) | K41: (aux) Mensal
B42: 1 | C42: Vigilância armada de 12x36 horas diurnas de Segunda Feira a Domingo | D42: 4 | E42: 5677.75 | F42: =IF(N(D42)>0,D42*220,0) | H42: =IF(N(D42)>0,ROUNDDOWN(E42/220,2),0) | I42: =IF(AND(N(D42)>0,N(E42)>0),MAX(0,ROUNDDOWN((D42*E42-H42*N(G42))/30*C38*F33,2)),0) | K42: =ROUNDDOWN(N(D42)*N(E42),2)
B43: 2 | C43: Vigilância armada de 12x36 horas noturnas de Segunda Feira a Domingo | D43: 12 | E43: 6228.99 | F43: =IF(N(D43)>0,D43*220,0) | H43: =IF(N(D43)>0,ROUNDDOWN(E43/220,2),0) | I43: =IF(AND(N(D43)>0,N(E43)>0),MAX(0,ROUNDDOWN((D43*E43-H43*N(G43))/30*C38*F33,2)),0) | K43: =ROUNDDOWN(N(D43)*N(E43),2)
B44: 3 | C44: Vigilância desarmada de 12x36 horas diurnas de Segunda Feira a Domingo | D44: 18 | E44: 5672.89 | F44: =IF(N(D44)>0,D44*220,0) | H44: =IF(N(D44)>0,ROUNDDOWN(E44/220,2),0) | I44: =IF(AND(N(D44)>0,N(E44)>0),MAX(0,ROUNDDOWN((D44*E44-H44*N(G44))/30*C38*F33,2)),0) | K44: =ROUNDDOWN(N(D44)*N(E44),2)
B45: 4 | C45: Vigilância desarmada de 12x36 horas noturnas de Segunda Feira a Domingo | D45: 10 | E45: 6224.09 | F45: =IF(N(D45)>0,D45*220,0) | H45: =IF(N(D45)>0,ROUNDDOWN(E45/220,2),0) | I45: =IF(AND(N(D45)>0,N(E45)>0),MAX(0,ROUNDDOWN((D45*E45-H45*N(G45))/30*C38*F33,2)),0) | K45: =ROUNDDOWN(N(D45)*N(E45),2)
B46: 5 | C46: Vigilância desarmada de 44h (8:48 horas) diurnas de Segunda Feira a Sexta | D46: 1 | E46: 6019.58 | F46: =IF(N(D46)>0,D46*220,0) | H46: =IF(N(D46)>0,ROUNDDOWN(E46/220,2),0) | I46: =IF(AND(N(D46)>0,N(E46)>0),MAX(0,ROUNDDOWN((D46*E46-H46*N(G46))/30*C38*F33,2)),0) | K46: =ROUNDDOWN(N(D46)*N(E46),2)
B47: 6 | C47: Vigilância desarmada de 12x36 horas diurnas de Segunda Feira a Domingo COM INTRAJORNADA | D47: 2 | E47: 6064.91 | F47: =IF(N(D47)>0,D47*220,0) | H47: =IF(N(D47)>0,ROUNDDOWN(E47/220,2),0) | I47: =IF(AND(N(D47)>0,N(E47)>0),MAX(0,ROUNDDOWN((D47*E47-H47*N(G47))/30*C38*F33,2)),0) | K47: =ROUNDDOWN(N(D47)*N(E47),2)
B48: 7 | C48: Vigilância desarmada de 12x36 horas noturnas de Segunda Feira a Domingo COM INTRAJORNADA | D48: 2 | E48: 6654.1 | F48: =IF(N(D48)>0,D48*220,0) | H48: =IF(N(D48)>0,ROUNDDOWN(E48/220,2),0) | I48: =IF(AND(N(D48)>0,N(E48)>0),MAX(0,ROUNDDOWN((D48*E48-H48*N(G48))/30*C38*F33,2)),0) | K48: =ROUNDDOWN(N(D48)*N(E48),2)
B49: TOTAIS | D49: =SUM(D42:D48) | E49: ◀ Qtde contratada | I49: =SUM(I42:I48) | K49: =SUM(K42:K48)
B51: INSTRUMENTO DE COBRANÇA
B52: Item | C52: Posto | D52: Qtde Fat. | E52: Valor Unit. Faturado (R$)
B53: =B42 | C53: =C42 | D53: =N(D42) | E53: =IF(N(D42)>0,ROUNDDOWN(I42/D42,2),0)
B54: =B43 | C54: =C43 | D54: =N(D43) | E54: =IF(N(D43)>0,ROUNDDOWN(I43/D43,2),0)
B55: =B44 | C55: =C44 | D55: =N(D44) | E55: =IF(N(D44)>0,ROUNDDOWN(I44/D44,2),0)
B56: =B45 | C56: =C45 | D56: =N(D45) | E56: =IF(N(D45)>0,ROUNDDOWN(I45/D45,2),0)
B57: =B46 | C57: =C46 | D57: =N(D46) | E57: =IF(N(D46)>0,ROUNDDOWN(I46/D46,2),0)
B58: =B47 | C58: =C47 | D58: =N(D47) | E58: =IF(N(D47)>0,ROUNDDOWN(I47/D47,2),0)
B59: =B48 | C59: =C48 | D59: =N(D48) | E59: =IF(N(D48)>0,ROUNDDOWN(I48/D48,2),0)
B61: RESUMO FINANCEIRO
B62: Contratado Mensal – Total (R$) | E62: =K49
B63: Conceito | E63: =C33
B64: % do Faturamento a ser Liberado | E64: =F33
B65: Valor Glosado por QUALIDADE (R$) | E65: =ROUNDDOWN(K49-K49*F33,2)
B66: Valor Aprovado para Pagamento (R$) | E66: =MAX(0,ROUNDDOWN(I49+E82,2))
B68: FAIXA DE AJUSTE
B69: Conceito | C69: % a Pagar | E69: Nota Média
B70: A | C70: 100% | E70: 9,00–8,10
B71: B | C71: 95% | E71: 8,09–7,65
B72: C | C72: 90% | E72: 7,64–6,75
B73: D | C73: 85% | E73: 6,74–5,85
B74: E | C74: 80% | E74: 5,84–5,40
B75: F | C75: 75% | E75: < 5,40
B77: REEMBOLSO DE CRECHE
B78: Valor estimado unitário (R$) | E78: 0
B79: Valor Reembolso Creche Retido (R$) (estimado × qtde contratada) | E79: =ROUNDDOWN(E78*D49,2)
B80: Reembolsos Aprovados (quantidade)
B81: Reembolso por dependente (R$) | E81: 526.64
B82: Valor Total dos Reembolsos (R$) (Aprovados × Reembolso por dependente) | E82: =ROUNDDOWN(E80*E81,2)
B83: Saldo do mês anterior (R$) | E83: ='Outubro 2024'!E84
B84: Saldo de Reembolso (R$) (Saldo anterior + Retido − Total) | E84: =E83+E79-E82
B85: =IF(E84<0,"⚠ Saldo negativo — se houver mais de uma unidade favor somar o saldo de todas; se permanecer negativo, aditivar o contrato.","")
B88: JUSTIFICATIVAS E OBSERVAÇÕES

Sheet Dezembro 2024
B1: UNIVERSIDADE FEDERAL DO RIO DE JANEIRO — PR-6
B3: INSTRUMENTO DE MEDIÇÃO DE RESULTADO (IMR)
B7: IDENTIFICAÇÃO
B8: CONTRATO Nº | C8: 05/24
B9: UNIDADE | C9: MACAÉ
B10: CONTRATADA | C10: ANGEL'S SEGURANÇA E VIGILÂNCIA - EM RECUPERAÇÃO JUDICIAL LTDA
B11: FISCAL OPERACIONAL
B12: PERÍODO DE REFERÊNCIA | C12: Dezembro 2024
B14: AVALIAÇÃO DE DESEMPENHO
B15: Critério de Avaliação | C15: PESO (a) | D15: NOTA (b) (0,1,3) | E15: SUBTOTAL (c=a×b)
B16: ▶ GRUPO 1 – DESEMPENHO PROFISSIONAL
B17: Cumprimento das Atividades | C17: 0.4 | D17: 3 | E17: =C17*D17 | G17: =IF(OR(D17=0,D17=1),"Obrigatória justificativa no campo Justificativa e observações","")
B18: Qualificação / Atendimento ao Público / Postura | C18: 0.35 | D18: 3 | E18: =C18*D18 | G18: =IF(OR(D18=0,D18=1),"Obrigatória justificativa no campo Justificativa e observações","")
B19: Uniformes e Identificação | C19: 0.25 | D19: 3 | E19: =C19*D19 | G19: =IF(OR(D19=0,D19=1),"Obrigatória justificativa no campo Justificativa e observações","")
B20: TOTAL GRUPO 1 | C20: 1 | E20: =E17+E18+E19
B21: ▶ GRUPO 2 – DESEMPENHO DAS ATIVIDADES
B22: Especificação Técnica dos Serviços | C22: 0.4 | D22: 3 | E22: =C22*D22 | G22: =IF(OR(D22=0,D22=1),"Obrigatória justificativa no campo Justificativa e observações","")
B23: Equipamentos e Acessórios | C23: 0.2 | D23: 3 | E23: =C23*D23 | G23: =IF(OR(D23=0,D23=1),"Obrigatória justificativa no campo Justificativa e observações","")
B24: Atendimento às Ocorrências | C24: 0.4 | D24: 3 | E24: =C24*D24 | G24: =IF(OR(D24=0,D24=1),"Obrigatória justificativa no campo Justificativa e observações","")
B25: TOTAL GRUPO 2 | C25: 1 | E25: =E22+E23+E24
B26: ▶ GRUPO 3 – GERENCIAMENTO
B27: Periodicidade da Supervisão | C27: 0.2 | D27: 3 | E27: =C27*D27 | G27: =IF(OR(D27=0,D27=1),"Obrigatória justificativa no campo Justificativa e observações","")
B28: Gerenciamento das Atividades Operacionais | C28: 0.3 | D28: 3 | E28: =C28*D28 | G28: =IF(OR(D28=0,D28=1),"Obrigatória justificativa no campo Justificativa e observações","")
B29: Atendimento às Solicitações | C29: 0.25 | D29: 3 | E29: =C29*D29 | G29: =IF(OR(D29=0,D29=1),"Obrigatória justificativa no campo Justificativa e observações","")
B30: Salários, Benefícios e Obrigações Trabalhistas | C30: 0.25 | D30: 3 | E30: =C30*D30 | G30: =IF(OR(D30=0,D30=1),"Obrigatória justificativa no campo Justificativa e observações","")
B31: TOTAL GRUPO 3 | C31: 1 | E31: =E27+E28+E29+E30
B32: NOTA FINAL (G1+G2+G3) | E32: =E20+E25+E31
B33: CONCEITO | C33: =IF(E32>=8.1,"A",IF(E32>=7.65,"B",IF(E32>=6.75,"C",IF(E32>=5.85,"D",IF(E32>=5.4,"E","F"))))) | E33: % a pagar | F33: =IF(C33="A",1,IF(C33="B",0.95,IF(C33="C",0.9,IF(C33="D",0.85,IF(C33="E",0.8,0.75)))))
B35: PARÂMETROS (base 30 avos)
B36: Dias no mês (calendário) | C36: 30
B37: Nº de Dias Trabalhados | C37: 30
B38: Dias para cálculo (base 30) | C38: =IF(C37>=C36,30,MIN(C37,C36))
B40: POSTOS DE TRABALHO
B41: Item | C41: POSTO | D41: Qtde Contratada | E41: Valor Unit. (R$) | F41: Horas | G41: Sem Cob. (h) | H41: Valor Hora (R$) | I41: Valor após Descontos (R$) | K41: (aux) Mensal
B42: 1 | C42: Vigilância armada de 12x36 horas diurnas de Segunda Feira a Domingo | D42: 4 | E42: 5677.75 | F42: =IF(N(D42)>0,D42*220,0) | H42: =IF(N(D42)>0,ROUNDDOWN(E42/220,2),0) | I42: =IF(AND(N(D42)>0,N(E42)>0),MAX(0,ROUNDDOWN((D42*E42-H42*N(G42))/30*C38*F33,2)),0) | K42: =ROUNDDOWN(N(D42)*N(E42),2)
B43: 2 | C43: Vigilância armada de 12x36 horas noturnas de Segunda Feira a Domingo | D43: 12 | E43: 6228.99 | F43: =IF(N(D43)>0,D43*220,0) | H43: =IF(N(D43)>0,ROUNDDOWN(E43/220,2),0) | I43: =IF(AND(N(D43)>0,N(E43)>0),MAX(0,ROUNDDOWN((D43*E43-H43*N(G43))/30*C38*F33,2)),0) | K43: =ROUNDDOWN(N(D43)*N(E43),2)
B44: 3 | C44: Vigilância desarmada de 12x36 horas diurnas de Segunda Feira a Domingo | D44: 18 | E44: 5672.89 | F44: =IF(N(D44)>0,D44*220,0) | H44: =IF(N(D44)>0,ROUNDDOWN(E44/220,2),0) | I44: =IF(AND(N(D44)>0,N(E44)>0),MAX(0,ROUNDDOWN((D44*E44-H44*N(G44))/30*C38*F33,2)),0) | K44: =ROUNDDOWN(N(D44)*N(E44),2)
B45: 4 | C45: Vigilância desarmada de 12x36 horas noturnas de Segunda Feira a Domingo | D45: 10 | E45: 6224.09 | F45: =IF(N(D45)>0,D45*220,0) | H45: =IF(N(D45)>0,ROUNDDOWN(E45/220,2),0) | I45: =IF(AND(N(D45)>0,N(E45)>0),MAX(0,ROUNDDOWN((D45*E45-H45*N(G45))/30*C38*F33,2)),0) | K45: =ROUNDDOWN(N(D45)*N(E45),2)
B46: 5 | C46: Vigilância desarmada de 44h (8:48 horas) diurnas de Segunda Feira a Sexta | D46: 1 | E46: 6019.58 | F46: =IF(N(D46)>0,D46*220,0) | H46: =IF(N(D46)>0,ROUNDDOWN(E46/220,2),0) | I46: =IF(AND(N(D46)>0,N(E46)>0),MAX(0,ROUNDDOWN((D46*E46-H46*N(G46))/30*C38*F33,2)),0) | K46: =ROUNDDOWN(N(D46)*N(E46),2)
B47: 6 | C47: Vigilância desarmada de 12x36 horas diurnas de Segunda Feira a Domingo COM INTRAJORNADA | D47: 2 | E47: 6064.91 | F47: =IF(N(D47)>0,D47*220,0) | H47: =IF(N(D47)>0,ROUNDDOWN(E47/220,2),0) | I47: =IF(AND(N(D47)>0,N(E47)>0),MAX(0,ROUNDDOWN((D47*E47-H47*N(G47))/30*C38*F33,2)),0) | K47: =ROUNDDOWN(N(D47)*N(E47),2)
B48: 7 | C48: Vigilância desarmada de 12x36 horas noturnas de Segunda Feira a Domingo COM INTRAJORNADA | D48: 2 | E48: 6654.1 | F48: =IF(N(D48)>0,D48*220,0) | H48: =IF(N(D48)>0,ROUNDDOWN(E48/220,2),0) | I48: =IF(AND(N(D48)>0,N(E48)>0),MAX(0,ROUNDDOWN((D48*E48-H48*N(G48))/30*C38*F33,2)),0) | K48: =ROUNDDOWN(N(D48)*N(E48),2)
B49: TOTAIS | D49: =SUM(D42:D48) | E49: ◀ Qtde contratada | I49: =SUM(I42:I48) | K49: =SUM(K42:K48)
B51: INSTRUMENTO DE COBRANÇA
B52: Item | C52: Posto | D52: Qtde Fat. | E52: Valor Unit. Faturado (R$)
B53: =B42 | C53: =C42 | D53: =N(D42) | E53: =IF(N(D42)>0,ROUNDDOWN(I42/D42,2),0)
B54: =B43 | C54: =C43 | D54: =N(D43) | E54: =IF(N(D43)>0,ROUNDDOWN(I43/D43,2),0)
B55: =B44 | C55: =C44 | D55: =N(D44) | E55: =IF(N(D44)>0,ROUNDDOWN(I44/D44,2),0)
B56: =B45 | C56: =C45 | D56: =N(D45) | E56: =IF(N(D45)>0,ROUNDDOWN(I45/D45,2),0)
B57: =B46 | C57: =C46 | D57: =N(D46) | E57: =IF(N(D46)>0,ROUNDDOWN(I46/D46,2),0)
B58: =B47 | C58: =C47 | D58: =N(D47) | E58: =IF(N(D47)>0,ROUNDDOWN(I47/D47,2),0)
B59: =B48 | C59: =C48 | D59: =N(D48) | E59: =IF(N(D48)>0,ROUNDDOWN(I48/D48,2),0)
B61: RESUMO FINANCEIRO
B62: Contratado Mensal – Total (R$) | E62: =K49
B63: Conceito | E63: =C33
B64: % do Faturamento a ser Liberado | E64: =F33
B65: Valor Glosado por QUALIDADE (R$) | E65: =ROUNDDOWN(K49-K49*F33,2)
B66: Valor Aprovado para Pagamento (R$) | E66: =MAX(0,ROUNDDOWN(I49+E82,2))
B68: FAIXA DE AJUSTE
B69: Conceito | C69: % a Pagar | E69: Nota Média
B70: A | C70: 100% | E70: 9,00–8,10
B71: B | C71: 95% | E71: 8,09–7,65
B72: C | C72: 90% | E72: 7,64–6,75
B73: D | C73: 85% | E73: 6,74–5,85
B74: E | C74: 80% | E74: 5,84–5,40
B75: F | C75: 75% | E75: < 5,40
B77: REEMBOLSO DE CRECHE
B78: Valor estimado unitário (R$) | E78: 0
B79: Valor Reembolso Creche Retido (R$) (estimado × qtde contratada) | E79: =ROUNDDOWN(E78*D49,2)
B80: Reembolsos Aprovados (quantidade)
B81: Reembolso por dependente (R$) | E81: 526.64
B82: Valor Total dos Reembolsos (R$) (Aprovados × Reembolso por dependente) | E82: =ROUNDDOWN(E80*E81,2)
B83: Saldo do mês anterior (R$) | E83: ='Novembro 2024'!E84
B84: Saldo de Reembolso (R$) (Saldo anterior + Retido − Total) | E84: =E83+E79-E82
B85: =IF(E84<0,"⚠ Saldo negativo — se houver mais de uma unidade favor somar o saldo de todas; se permanecer negativo, aditivar o contrato.","")
B88: JUSTIFICATIVAS E OBSERVAÇÕES

Sheet Janeiro 2025
B1: UNIVERSIDADE FEDERAL DO RIO DE JANEIRO — PR-6
B3: INSTRUMENTO DE MEDIÇÃO DE RESULTADO (IMR)
B7: IDENTIFICAÇÃO
B8: CONTRATO Nº | C8: 05/24
B9: UNIDADE | C9: MACAÉ
B10: CONTRATADA | C10: ANGEL'S SEGURANÇA E VIGILÂNCIA - EM RECUPERAÇÃO JUDICIAL LTDA
B11: FISCAL OPERACIONAL
B12: PERÍODO DE REFERÊNCIA | C12: Janeiro 2025
B14: AVALIAÇÃO DE DESEMPENHO
B15: Critério de Avaliação | C15: PESO (a) | D15: NOTA (b) (0,1,3) | E15: SUBTOTAL (c=a×b)
B16: ▶ GRUPO 1 – DESEMPENHO PROFISSIONAL
B17: Cumprimento das Atividades | C17: 0.4 | D17: 3 | E17: =C17*D17 | G17: =IF(OR(D17=0,D17=1),"Obrigatória justificativa no campo Justificativa e observações","")
B18: Qualificação / Atendimento ao Público / Postura | C18: 0.35 | D18: 3 | E18: =C18*D18 | G18: =IF(OR(D18=0,D18=1),"Obrigatória justificativa no campo Justificativa e observações","")
B19: Uniformes e Identificação | C19: 0.25 | D19: 3 | E19: =C19*D19 | G19: =IF(OR(D19=0,D19=1),"Obrigatória justificativa no campo Justificativa e observações","")
B20: TOTAL GRUPO 1 | C20: 1 | E20: =E17+E18+E19
B21: ▶ GRUPO 2 – DESEMPENHO DAS ATIVIDADES
B22: Especificação Técnica dos Serviços | C22: 0.4 | D22: 3 | E22: =C22*D22 | G22: =IF(OR(D22=0,D22=1),"Obrigatória justificativa no campo Justificativa e observações","")
B23: Equipamentos e Acessórios | C23: 0.2 | D23: 3 | E23: =C23*D23 | G23: =IF(OR(D23=0,D23=1),"Obrigatória justificativa no campo Justificativa e observações","")
B24: Atendimento às Ocorrências | C24: 0.4 | D24: 3 | E24: =C24*D24 | G24: =IF(OR(D24=0,D24=1),"Obrigatória justificativa no campo Justificativa e observações","")
B25: TOTAL GRUPO 2 | C25: 1 | E25: =E22+E23+E24
B26: ▶ GRUPO 3 – GERENCIAMENTO
B27: Periodicidade da Supervisão | C27: 0.2 | D27: 3 | E27: =C27*D27 | G27: =IF(OR(D27=0,D27=1),"Obrigatória justificativa no campo Justificativa e observações","")
B28: Gerenciamento das Atividades Operacionais | C28: 0.3 | D28: 3 | E28: =C28*D28 | G28: =IF(OR(D28=0,D28=1),"Obrigatória justificativa no campo Justificativa e observações","")
B29: Atendimento às Solicitações | C29: 0.25 | D29: 3 | E29: =C29*D29 | G29: =IF(OR(D29=0,D29=1),"Obrigatória justificativa no campo Justificativa e observações","")
B30: Salários, Benefícios e Obrigações Trabalhistas | C30: 0.25 | D30: 3 | E30: =C30*D30 | G30: =IF(OR(D30=0,D30=1),"Obrigatória justificativa no campo Justificativa e observações","")
B31: TOTAL GRUPO 3 | C31: 1 | E31: =E27+E28+E29+E30
B32: NOTA FINAL (G1+G2+G3) | E32: =E20+E25+E31
B33: CONCEITO | C33: =IF(E32>=8.1,"A",IF(E32>=7.65,"B",IF(E32>=6.75,"C",IF(E32>=5.85,"D",IF(E32>=5.4,"E","F"))))) | E33: % a pagar | F33: =IF(C33="A",1,IF(C33="B",0.95,IF(C33="C",0.9,IF(C33="D",0.85,IF(C33="E",0.8,0.75)))))
B35: PARÂMETROS (base 30 avos)
B36: Dias no mês (calendário) | C36: 30
B37: Nº de Dias Trabalhados | C37: 30
B38: Dias para cálculo (base 30) | C38: =IF(C37>=C36,30,MIN(C37,C36))
B40: POSTOS DE TRABALHO
B41: Item | C41: POSTO | D41: Qtde Contratada | E41: Valor Unit. (R$) | F41: Horas | G41: Sem Cob. (h) | H41: Valor Hora (R$) | I41: Valor após Descontos (R$) | K41: (aux) Mensal
B42: 1 | C42: Vigilância armada de 12x36 horas diurnas de Segunda Feira a Domingo | D42: 4 | E42: 5677.75 | F42: =IF(N(D42)>0,D42*220,0) | H42: =IF(N(D42)>0,ROUNDDOWN(E42/220,2),0) | I42: =IF(AND(N(D42)>0,N(E42)>0),MAX(0,ROUNDDOWN((D42*E42-H42*N(G42))/30*C38*F33,2)),0) | K42: =ROUNDDOWN(N(D42)*N(E42),2)
B43: 2 | C43: Vigilância armada de 12x36 horas noturnas de Segunda Feira a Domingo | D43: 12 | E43: 6228.99 | F43: =IF(N(D43)>0,D43*220,0) | H43: =IF(N(D43)>0,ROUNDDOWN(E43/220,2),0) | I43: =IF(AND(N(D43)>0,N(E43)>0),MAX(0,ROUNDDOWN((D43*E43-H43*N(G43))/30*C38*F33,2)),0) | K43: =ROUNDDOWN(N(D43)*N(E43),2)
B44: 3 | C44: Vigilância desarmada de 12x36 horas diurnas de Segunda Feira a Domingo | D44: 18 | E44: 5672.89 | F44: =IF(N(D44)>0,D44*220,0) | H44: =IF(N(D44)>0,ROUNDDOWN(E44/220,2),0) | I44: =IF(AND(N(D44)>0,N(E44)>0),MAX(0,ROUNDDOWN((D44*E44-H44*N(G44))/30*C38*F33,2)),0) | K44: =ROUNDDOWN(N(D44)*N(E44),2)
B45: 4 | C45: Vigilância desarmada de 12x36 horas noturnas de Segunda Feira a Domingo | D45: 10 | E45: 6224.09 | F45: =IF(N(D45)>0,D45*220,0) | H45: =IF(N(D45)>0,ROUNDDOWN(E45/220,2),0) | I45: =IF(AND(N(D45)>0,N(E45)>0),MAX(0,ROUNDDOWN((D45*E45-H45*N(G45))/30*C38*F33,2)),0) | K45: =ROUNDDOWN(N(D45)*N(E45),2)
B46: 5 | C46: Vigilância desarmada de 44h (8:48 horas) diurnas de Segunda Feira a Sexta | D46: 1 | E46: 6019.58 | F46: =IF(N(D46)>0,D46*220,0) | H46: =IF(N(D46)>0,ROUNDDOWN(E46/220,2),0) | I46: =IF(AND(N(D46)>0,N(E46)>0),MAX(0,ROUNDDOWN((D46*E46-H46*N(G46))/30*C38*F33,2)),0) | K46: =ROUNDDOWN(N(D46)*N(E46),2)
B47: 6 | C47: Vigilância desarmada de 12x36 horas diurnas de Segunda Feira a Domingo COM INTRAJORNADA | D47: 2 | E47: 6064.91 | F47: =IF(N(D47)>0,D47*220,0) | H47: =IF(N(D47)>0,ROUNDDOWN(E47/220,2),0) | I47: =IF(AND(N(D47)>0,N(E47)>0),MAX(0,ROUNDDOWN((D47*E47-H47*N(G47))/30*C38*F33,2)),0) | K47: =ROUNDDOWN(N(D47)*N(E47),2)
B48: 7 | C48: Vigilância desarmada de 12x36 horas noturnas de Segunda Feira a Domingo COM INTRAJORNADA | D48: 2 | E48: 6654.1 | F48: =IF(N(D48)>0,D48*220,0) | H48: =IF(N(D48)>0,ROUNDDOWN(E48/220,2),0) | I48: =IF(AND(N(D48)>0,N(E48)>0),MAX(0,ROUNDDOWN((D48*E48-H48*N(G48))/30*C38*F33,2)),0) | K48: =ROUNDDOWN(N(D48)*N(E48),2)
B49: TOTAIS | D49: =SUM(D42:D48) | E49: ◀ Qtde contratada | I49: =SUM(I42:I48) | K49: =SUM(K42:K48)
B51: INSTRUMENTO DE COBRANÇA
B52: Item | C52: Posto | D52: Qtde Fat. | E52: Valor Unit. Faturado (R$)
B53: =B42 | C53: =C42 | D53: =N(D42) | E53: =IF(N(D42)>0,ROUNDDOWN(I42/D42,2),0)
B54: =B43 | C54: =C43 | D54: =N(D43) | E54: =IF(N(D43)>0,ROUNDDOWN(I43/D43,2),0)
B55: =B44 | C55: =C44 | D55: =N(D44) | E55: =IF(N(D44)>0,ROUNDDOWN(I44/D44,2),0)
B56: =B45 | C56: =C45 | D56: =N(D45) | E56: =IF(N(D45)>0,ROUNDDOWN(I45/D45,2),0)
B57: =B46 | C57: =C46 | D57: =N(D46) | E57: =IF(N(D46)>0,ROUNDDOWN(I46/D46,2),0)
B58: =B47 | C58: =C47 | D58: =N(D47) | E58: =IF(N(D47)>0,ROUNDDOWN(I47/D47,2),0)
B59: =B48 | C59: =C48 | D59: =N(D48) | E59: =IF(N(D48)>0,ROUNDDOWN(I48/D48,2),0)
B61: RESUMO FINANCEIRO
B62: Contratado Mensal – Total (R$) | E62: =K49
B63: Conceito | E63: =C33
B64: % do Faturamento a ser Liberado | E64: =F33
B65: Valor Glosado por QUALIDADE (R$) | E65: =ROUNDDOWN(K49-K49*F33,2)
B66: Valor Aprovado para Pagamento (R$) | E66: =MAX(0,ROUNDDOWN(I49+E82,2))
B68: FAIXA DE AJUSTE
B69: Conceito | C69: % a Pagar | E69: Nota Média
B70: A | C70: 100% | E70: 9,00–8,10
B71: B | C71: 95% | E71: 8,09–7,65
B72: C | C72: 90% | E72: 7,64–6,75
B73: D | C73: 85% | E73: 6,74–5,85
B74: E | C74: 80% | E74: 5,84–5,40
B75: F | C75: 75% | E75: < 5,40
B77: REEMBOLSO DE CRECHE
B78: Valor estimado unitário (R$) | E78: 0
B79: Valor Reembolso Creche Retido (R$) (estimado × qtde contratada) | E79: =ROUNDDOWN(E78*D49,2)
B80: Reembolsos Aprovados (quantidade)
B81: Reembolso por dependente (R$) | E81: 526.64
B82: Valor Total dos Reembolsos (R$) (Aprovados × Reembolso por dependente) | E82: =ROUNDDOWN(E80*E81,2)
B83: Saldo do mês anterior (R$) | E83: ='Dezembro 2024'!E84
B84: Saldo de Reembolso (R$) (Saldo anterior + Retido − Total) | E84: =E83+E79-E82
B85: =IF(E84<0,"⚠ Saldo negativo — se houver mais de uma unidade favor somar o saldo de todas; se permanecer negativo, aditivar o contrato.","")
B88: JUSTIFICATIVAS E OBSERVAÇÕES

Sheet Fevereiro 2025
B1: UNIVERSIDADE FEDERAL DO RIO DE JANEIRO — PR-6
B3: INSTRUMENTO DE MEDIÇÃO DE RESULTADO (IMR)
B7: IDENTIFICAÇÃO
B8: CONTRATO Nº | C8: 05/24
B9: UNIDADE | C9: MACAÉ
B10: CONTRATADA | C10: ANGEL'S SEGURANÇA E VIGILÂNCIA - EM RECUPERAÇÃO JUDICIAL LTDA
B11: FISCAL OPERACIONAL
B12: PERÍODO DE REFERÊNCIA | C12: Fevereiro 2025
B14: AVALIAÇÃO DE DESEMPENHO
B15: Critério de Avaliação | C15: PESO (a) | D15: NOTA (b) (0,1,3) | E15: SUBTOTAL (c=a×b)
B16: ▶ GRUPO 1 – DESEMPENHO PROFISSIONAL
B17: Cumprimento das Atividades | C17: 0.4 | D17: 3 | E17: =C17*D17 | G17: =IF(OR(D17=0,D17=1),"Obrigatória justificativa no campo Justificativa e observações","")
B18: Qualificação / Atendimento ao Público / Postura | C18: 0.35 | D18: 3 | E18: =C18*D18 | G18: =IF(OR(D18=0,D18=1),"Obrigatória justificativa no campo Justificativa e observações","")
B19: Uniformes e Identificação | C19: 0.25 | D19: 3 | E19: =C19*D19 | G19: =IF(OR(D19=0,D19=1),"Obrigatória justificativa no campo Justificativa e observações","")
B20: TOTAL GRUPO 1 | C20: 1 | E20: =E17+E18+E19
B21: ▶ GRUPO 2 – DESEMPENHO DAS ATIVIDADES
B22: Especificação Técnica dos Serviços | C22: 0.4 | D22: 3 | E22: =C22*D22 | G22: =IF(OR(D22=0,D22=1),"Obrigatória justificativa no campo Justificativa e observações","")
B23: Equipamentos e Acessórios | C23: 0.2 | D23: 3 | E23: =C23*D23 | G23: =IF(OR(D23=0,D23=1),"Obrigatória justificativa no campo Justificativa e observações","")
B24: Atendimento às Ocorrências | C24: 0.4 | D24: 3 | E24: =C24*D24 | G24: =IF(OR(D24=0,D24=1),"Obrigatória justificativa no campo Justificativa e observações","")
B25: TOTAL GRUPO 2 | C25: 1 | E25: =E22+E23+E24
B26: ▶ GRUPO 3 – GERENCIAMENTO
B27: Periodicidade da Supervisão | C27: 0.2 | D27: 3 | E27: =C27*D27 | G27: =IF(OR(D27=0,D27=1),"Obrigatória justificativa no campo Justificativa e observações","")
B28: Gerenciamento das Atividades Operacionais | C28: 0.3 | D28: 3 | E28: =C28*D28 | G28: =IF(OR(D28=0,D28=1),"Obrigatória justificativa no campo Justificativa e observações","")
B29: Atendimento às Solicitações | C29: 0.25 | D29: 3 | E29: =C29*D29 | G29: =IF(OR(D29=0,D29=1),"Obrigatória justificativa no campo Justificativa e observações","")
B30: Salários, Benefícios e Obrigações Trabalhistas | C30: 0.25 | D30: 3 | E30: =C30*D30 | G30: =IF(OR(D30=0,D30=1),"Obrigatória justificativa no campo Justificativa e observações","")
B31: TOTAL GRUPO 3 | C31: 1 | E31: =E27+E28+E29+E30
B32: NOTA FINAL (G1+G2+G3) | E32: =E20+E25+E31
B33: CONCEITO | C33: =IF(E32>=8.1,"A",IF(E32>=7.65,"B",IF(E32>=6.75,"C",IF(E32>=5.85,"D",IF(E32>=5.4,"E","F"))))) | E33: % a pagar | F33: =IF(C33="A",1,IF(C33="B",0.95,IF(C33="C",0.9,IF(C33="D",0.85,IF(C33="E",0.8,0.75)))))
B35: PARÂMETROS (base 30 avos)
B36: Dias no mês (calendário) | C36: 30
B37: Nº de Dias Trabalhados | C37: 30
B38: Dias para cálculo (base 30) | C38: =IF(C37>=C36,30,MIN(C37,C36))
B40: POSTOS DE TRABALHO
B41: Item | C41: POSTO | D41: Qtde Contratada | E41: Valor Unit. (R$) | F41: Horas | G41: Sem Cob. (h) | H41: Valor Hora (R$) | I41: Valor após Descontos (R$) | K41: (aux) Mensal
B42: 1 | C42: Vigilância armada de 12x36 horas diurnas de Segunda Feira a Domingo | D42: 4 | E42: 5677.75 | F42: =IF(N(D42)>0,D42*220,0) | H42: =IF(N(D42)>0,ROUNDDOWN(E42/220,2),0) | I42: =IF(AND(N(D42)>0,N(E42)>0),MAX(0,ROUNDDOWN((D42*E42-H42*N(G42))/30*C38*F33,2)),0) | K42: =ROUNDDOWN(N(D42)*N(E42),2)
B43: 2 | C43: Vigilância armada de 12x36 horas noturnas de Segunda Feira a Domingo | D43: 12 | E43: 6228.99 | F43: =IF(N(D43)>0,D43*220,0) | H43: =IF(N(D43)>0,ROUNDDOWN(E43/220,2),0) | I43: =IF(AND(N(D43)>0,N(E43)>0),MAX(0,ROUNDDOWN((D43*E43-H43*N(G43))/30*C38*F33,2)),0) | K43: =ROUNDDOWN(N(D43)*N(E43),2)
B44: 3 | C44: Vigilância desarmada de 12x36 horas diurnas de Segunda Feira a Domingo | D44: 18 | E44: 5672.89 | F44: =IF(N(D44)>0,D44*220,0) | H44: =IF(N(D44)>0,ROUNDDOWN(E44/220,2),0) | I44: =IF(AND(N(D44)>0,N(E44)>0),MAX(0,ROUNDDOWN((D44*E44-H44*N(G44))/30*C38*F33,2)),0) | K44: =ROUNDDOWN(N(D44)*N(E44),2)
B45: 4 | C45: Vigilância desarmada de 12x36 horas noturnas de Segunda Feira a Domingo | D45: 10 | E45: 6224.09 | F45: =IF(N(D45)>0,D45*220,0) | H45: =IF(N(D45)>0,ROUNDDOWN(E45/220,2),0) | I45: =IF(AND(N(D45)>0,N(E45)>0),MAX(0,ROUNDDOWN((D45*E45-H45*N(G45))/30*C38*F33,2)),0) | K45: =ROUNDDOWN(N(D45)*N(E45),2)
B46: 5 | C46: Vigilância desarmada de 44h (8:48 horas) diurnas de Segunda Feira a Sexta | D46: 1 | E46: 6019.58 | F46: =IF(N(D46)>0,D46*220,0) | H46: =IF(N(D46)>0,ROUNDDOWN(E46/220,2),0) | I46: =IF(AND(N(D46)>0,N(E46)>0),MAX(0,ROUNDDOWN((D46*E46-H46*N(G46))/30*C38*F33,2)),0) | K46: =ROUNDDOWN(N(D46)*N(E46),2)
B47: 6 | C47: Vigilância desarmada de 12x36 horas diurnas de Segunda Feira a Domingo COM INTRAJORNADA | D47: 2 | E47: 6064.91 | F47: =IF(N(D47)>0,D47*220,0) | H47: =IF(N(D47)>0,ROUNDDOWN(E47/220,2),0) | I47: =IF(AND(N(D47)>0,N(E47)>0),MAX(0,ROUNDDOWN((D47*E47-H47*N(G47))/30*C38*F33,2)),0) | K47: =ROUNDDOWN(N(D47)*N(E47),2)
B48: 7 | C48: Vigilância desarmada de 12x36 horas noturnas de Segunda Feira a Domingo COM INTRAJORNADA | D48: 2 | E48: 6654.1 | F48: =IF(N(D48)>0,D48*220,0) | H48: =IF(N(D48)>0,ROUNDDOWN(E48/220,2),0) | I48: =IF(AND(N(D48)>0,N(E48)>0),MAX(0,ROUNDDOWN((D48*E48-H48*N(G48))/30*C38*F33,2)),0) | K48: =ROUNDDOWN(N(D48)*N(E48),2)
B49: TOTAIS | D49: =SUM(D42:D48) | E49: ◀ Qtde contratada | I49: =SUM(I42:I48) | K49: =SUM(K42:K48)
B51: INSTRUMENTO DE COBRANÇA
B52: Item | C52: Posto | D52: Qtde Fat. | E52: Valor Unit. Faturado (R$)
B53: =B42 | C53: =C42 | D53: =N(D42) | E53: =IF(N(D42)>0,ROUNDDOWN(I42/D42,2),0)
B54: =B43 | C54: =C43 | D54: =N(D43) | E54: =IF(N(D43)>0,ROUNDDOWN(I43/D43,2),0)
B55: =B44 | C55: =C44 | D55: =N(D44) | E55: =IF(N(D44)>0,ROUNDDOWN(I44/D44,2),0)
B56: =B45 | C56: =C45 | D56: =N(D45) | E56: =IF(N(D45)>0,ROUNDDOWN(I45/D45,2),0)
B57: =B46 | C57: =C46 | D57: =N(D46) | E57: =IF(N(D46)>0,ROUNDDOWN(I46/D46,2),0)
B58: =B47 | C58: =C47 | D58: =N(D47) | E58: =IF(N(D47)>0,ROUNDDOWN(I47/D47,2),0)
B59: =B48 | C59: =C48 | D59: =N(D48) | E59: =IF(N(D48)>0,ROUNDDOWN(I48/D48,2),0)
B61: RESUMO FINANCEIRO
B62: Contratado Mensal – Total (R$) | E62: =K49
B63: Conceito | E63: =C33
B64: % do Faturamento a ser Liberado | E64: =F33
B65: Valor Glosado por QUALIDADE (R$) | E65: =ROUNDDOWN(K49-K49*F33,2)
B66: Valor Aprovado para Pagamento (R$) | E66: =MAX(0,ROUNDDOWN(I49+E82,2))
B68: FAIXA DE AJUSTE
B69: Conceito | C69: % a Pagar | E69: Nota Média
B70: A | C70: 100% | E70: 9,00–8,10
B71: B | C71: 95% | E71: 8,09–7,65
B72: C | C72: 90% | E72: 7,64–6,75
B73: D | C73: 85% | E73: 6,74–5,85
B74: E | C74: 80% | E74: 5,84–5,40
B75: F | C75: 75% | E75: < 5,40
B77: REEMBOLSO DE CRECHE
B78: Valor estimado unitário (R$) | E78: 0
B79: Valor Reembolso Creche Retido (R$) (estimado × qtde contratada) | E79: =ROUNDDOWN(E78*D49,2)
B80: Reembolsos Aprovados (quantidade)
B81: Reembolso por dependente (R$) | E81: 526.64
B82: Valor Total dos Reembolsos (R$) (Aprovados × Reembolso por dependente) | E82: =ROUNDDOWN(E80*E81,2)
B83: Saldo do mês anterior (R$) | E83: ='Janeiro 2025'!E84
B84: Saldo de Reembolso (R$) (Saldo anterior + Retido − Total) | E84: =E83+E79-E82
B85: =IF(E84<0,"⚠ Saldo negativo — se houver mais de uma unidade favor somar o saldo de todas; se permanecer negativo, aditivar o contrato.","")
B88: JUSTIFICATIVAS E OBSERVAÇÕES

Sheet Março 2025
B1: UNIVERSIDADE FEDERAL DO RIO DE JANEIRO — PR-6
B3: INSTRUMENTO DE MEDIÇÃO DE RESULTADO (IMR)
B7: IDENTIFICAÇÃO
B8: CONTRATO Nº | C8: 05/24
B9: UNIDADE | C9: MACAÉ
B10: CONTRATADA | C10: ANGEL'S SEGURANÇA E VIGILÂNCIA - EM RECUPERAÇÃO JUDICIAL LTDA
B11: FISCAL OPERACIONAL
B12: PERÍODO DE REFERÊNCIA | C12: Março 2025
B14: AVALIAÇÃO DE DESEMPENHO
B15: Critério de Avaliação | C15: PESO (a) | D15: NOTA (b) (0,1,3) | E15: SUBTOTAL (c=a×b)
B16: ▶ GRUPO 1 – DESEMPENHO PROFISSIONAL
B17: Cumprimento das Atividades | C17: 0.4 | D17: 3 | E17: =C17*D17 | G17: =IF(OR(D17=0,D17=1),"Obrigatória justificativa no campo Justificativa e observações","")
B18: Qualificação / Atendimento ao Público / Postura | C18: 0.35 | D18: 3 | E18: =C18*D18 | G18: =IF(OR(D18=0,D18=1),"Obrigatória justificativa no campo Justificativa e observações","")
B19: Uniformes e Identificação | C19: 0.25 | D19: 3 | E19: =C19*D19 | G19: =IF(OR(D19=0,D19=1),"Obrigatória justificativa no campo Justificativa e observações","")
B20: TOTAL GRUPO 1 | C20: 1 | E20: =E17+E18+E19
B21: ▶ GRUPO 2 – DESEMPENHO DAS ATIVIDADES
B22: Especificação Técnica dos Serviços | C22: 0.4 | D22: 3 | E22: =C22*D22 | G22: =IF(OR(D22=0,D22=1),"Obrigatória justificativa no campo Justificativa e observações","")
B23: Equipamentos e Acessórios | C23: 0.2 | D23: 3 | E23: =C23*D23 | G23: =IF(OR(D23=0,D23=1),"Obrigatória justificativa no campo Justificativa e observações","")
B24: Atendimento às Ocorrências | C24: 0.4 | D24: 3 | E24: =C24*D24 | G24: =IF(OR(D24=0,D24=1),"Obrigatória justificativa no campo Justificativa e observações","")
B25: TOTAL GRUPO 2 | C25: 1 | E25: =E22+E23+E24
B26: ▶ GRUPO 3 – GERENCIAMENTO
B27: Periodicidade da Supervisão | C27: 0.2 | D27: 3 | E27: =C27*D27 | G27: =IF(OR(D27=0,D27=1),"Obrigatória justificativa no campo Justificativa e observações","")
B28: Gerenciamento das Atividades Operacionais | C28: 0.3 | D28: 3 | E28: =C28*D28 | G28: =IF(OR(D28=0,D28=1),"Obrigatória justificativa no campo Justificativa e observações","")
B29: Atendimento às Solicitações | C29: 0.25 | D29: 3 | E29: =C29*D29 | G29: =IF(OR(D29=0,D29=1),"Obrigatória justificativa no campo Justificativa e observações","")
B30: Salários, Benefícios e Obrigações Trabalhistas | C30: 0.25 | D30: 3 | E30: =C30*D30 | G30: =IF(OR(D30=0,D30=1),"Obrigatória justificativa no campo Justificativa e observações","")
B31: TOTAL GRUPO 3 | C31: 1 | E31: =E27+E28+E29+E30
B32: NOTA FINAL (G1+G2+G3) | E32: =E20+E25+E31
B33: CONCEITO | C33: =IF(E32>=8.1,"A",IF(E32>=7.65,"B",IF(E32>=6.75,"C",IF(E32>=5.85,"D",IF(E32>=5.4,"E","F"))))) | E33: % a pagar | F33: =IF(C33="A",1,IF(C33="B",0.95,IF(C33="C",0.9,IF(C33="D",0.85,IF(C33="E",0.8,0.75)))))
B35: PARÂMETROS (base 30 avos)
B36: Dias no mês (calendário) | C36: 30
B37: Nº de Dias Trabalhados | C37: 30
B38: Dias para cálculo (base 30) | C38: =IF(C37>=C36,30,MIN(C37,C36))
B40: POSTOS DE TRABALHO
B41: Item | C41: POSTO | D41: Qtde Contratada | E41: Valor Unit. (R$) | F41: Horas | G41: Sem Cob. (h) | H41: Valor Hora (R$) | I41: Valor após Descontos (R$) | K41: (aux) Mensal
B42: 1 | C42: Vigilância armada de 12x36 horas diurnas de Segunda Feira a Domingo | D42: 4 | E42: 5677.75 | F42: =IF(N(D42)>0,D42*220,0) | H42: =IF(N(D42)>0,ROUNDDOWN(E42/220,2),0) | I42: =IF(AND(N(D42)>0,N(E42)>0),MAX(0,ROUNDDOWN((D42*E42-H42*N(G42))/30*C38*F33,2)),0) | K42: =ROUNDDOWN(N(D42)*N(E42),2)
B43: 2 | C43: Vigilância armada de 12x36 horas noturnas de Segunda Feira a Domingo | D43: 12 | E43: 6228.99 | F43: =IF(N(D43)>0,D43*220,0) | H43: =IF(N(D43)>0,ROUNDDOWN(E43/220,2),0) | I43: =IF(AND(N(D43)>0,N(E43)>0),MAX(0,ROUNDDOWN((D43*E43-H43*N(G43))/30*C38*F33,2)),0) | K43: =ROUNDDOWN(N(D43)*N(E43),2)
B44: 3 | C44: Vigilância desarmada de 12x36 horas diurnas de Segunda Feira a Domingo | D44: 18 | E44: 5672.89 | F44: =IF(N(D44)>0,D44*220,0) | H44: =IF(N(D44)>0,ROUNDDOWN(E44/220,2),0) | I44: =IF(AND(N(D44)>0,N(E44)>0),MAX(0,ROUNDDOWN((D44*E44-H44*N(G44))/30*C38*F33,2)),0) | K44: =ROUNDDOWN(N(D44)*N(E44),2)
B45: 4 | C45: Vigilância desarmada de 12x36 horas noturnas de Segunda Feira a Domingo | D45: 10 | E45: 6224.09 | F45: =IF(N(D45)>0,D45*220,0) | H45: =IF(N(D45)>0,ROUNDDOWN(E45/220,2),0) | I45: =IF(AND(N(D45)>0,N(E45)>0),MAX(0,ROUNDDOWN((D45*E45-H45*N(G45))/30*C38*F33,2)),0) | K45: =ROUNDDOWN(N(D45)*N(E45),2)
B46: 5 | C46: Vigilância desarmada de 44h (8:48 horas) diurnas de Segunda Feira a Sexta | D46: 1 | E46: 6019.58 | F46: =IF(N(D46)>0,D46*220,0) | H46: =IF(N(D46)>0,ROUNDDOWN(E46/220,2),0) | I46: =IF(AND(N(D46)>0,N(E46)>0),MAX(0,ROUNDDOWN((D46*E46-H46*N(G46))/30*C38*F33,2)),0) | K46: =ROUNDDOWN(N(D46)*N(E46),2)
B47: 6 | C47: Vigilância desarmada de 12x36 horas diurnas de Segunda Feira a Domingo COM INTRAJORNADA | D47: 2 | E47: 6064.91 | F47: =IF(N(D47)>0,D47*220,0) | H47: =IF(N(D47)>0,ROUNDDOWN(E47/220,2),0) | I47: =IF(AND(N(D47)>0,N(E47)>0),MAX(0,ROUNDDOWN((D47*E47-H47*N(G47))/30*C38*F33,2)),0) | K47: =ROUNDDOWN(N(D47)*N(E47),2)
B48: 7 | C48: Vigilância desarmada de 12x36 horas noturnas de Segunda Feira a Domingo COM INTRAJORNADA | D48: 2 | E48: 6654.1 | F48: =IF(N(D48)>0,D48*220,0) | H48: =IF(N(D48)>0,ROUNDDOWN(E48/220,2),0) | I48: =IF(AND(N(D48)>0,N(E48)>0),MAX(0,ROUNDDOWN((D48*E48-H48*N(G48))/30*C38*F33,2)),0) | K48: =ROUNDDOWN(N(D48)*N(E48),2)
B49: TOTAIS | D49: =SUM(D42:D48) | E49: ◀ Qtde contratada | I49: =SUM(I42:I48) | K49: =SUM(K42:K48)
B51: INSTRUMENTO DE COBRANÇA
B52: Item | C52: Posto | D52: Qtde Fat. | E52: Valor Unit. Faturado (R$)
B53: =B42 | C53: =C42 | D53: =N(D42) | E53: =IF(N(D42)>0,ROUNDDOWN(I42/D42,2),0)
B54: =B43 | C54: =C43 | D54: =N(D43) | E54: =IF(N(D43)>0,ROUNDDOWN(I43/D43,2),0)
B55: =B44 | C55: =C44 | D55: =N(D44) | E55: =IF(N(D44)>0,ROUNDDOWN(I44/D44,2),0)
B56: =B45 | C56: =C45 | D56: =N(D45) | E56: =IF(N(D45)>0,ROUNDDOWN(I45/D45,2),0)
B57: =B46 | C57: =C46 | D57: =N(D46) | E57: =IF(N(D46)>0,ROUNDDOWN(I46/D46,2),0)
B58: =B47 | C58: =C47 | D58: =N(D47) | E58: =IF(N(D47)>0,ROUNDDOWN(I47/D47,2),0)
B59: =B48 | C59: =C48 | D59: =N(D48) | E59: =IF(N(D48)>0,ROUNDDOWN(I48/D48,2),0)
B61: RESUMO FINANCEIRO
B62: Contratado Mensal – Total (R$) | E62: =K49
B63: Conceito | E63: =C33
B64: % do Faturamento a ser Liberado | E64: =F33
B65: Valor Glosado por QUALIDADE (R$) | E65: =ROUNDDOWN(K49-K49*F33,2)
B66: Valor Aprovado para Pagamento (R$) | E66: =MAX(0,ROUNDDOWN(I49+E82,2))
B68: FAIXA DE AJUSTE
B69: Conceito | C69: % a Pagar | E69: Nota Média
B70: A | C70: 100% | E70: 9,00–8,10
B71: B | C71: 95% | E71: 8,09–7,65
B72: C | C72: 90% | E72: 7,64–6,75
B73: D | C73: 85% | E73: 6,74–5,85
B74: E | C74: 80% | E74: 5,84–5,40
B75: F | C75: 75% | E75: < 5,40
B77: REEMBOLSO DE CRECHE
B78: Valor estimado unitário (R$) | E78: 0
B79: Valor Reembolso Creche Retido (R$) (estimado × qtde contratada) | E79: =ROUNDDOWN(E78*D49,2)
B80: Reembolsos Aprovados (quantidade)
B81: Reembolso por dependente (R$) | E81: 526.64
B82: Valor Total dos Reembolsos (R$) (Aprovados × Reembolso por dependente) | E82: =ROUNDDOWN(E80*E81,2)
B83: Saldo do mês anterior (R$) | E83: ='Fevereiro 2025'!E84
B84: Saldo de Reembolso (R$) (Saldo anterior + Retido − Total) | E84: =E83+E79-E82
B85: =IF(E84<0,"⚠ Saldo negativo — se houver mais de uma unidade favor somar o saldo de todas; se permanecer negativo, aditivar o contrato.","")
B88: JUSTIFICATIVAS E OBSERVAÇÕES

Sheet Abril 2025
B1: UNIVERSIDADE FEDERAL DO RIO DE JANEIRO — PR-6
B3: INSTRUMENTO DE MEDIÇÃO DE RESULTADO (IMR)
B7: IDENTIFICAÇÃO
B8: CONTRATO Nº | C8: 05/24
B9: UNIDADE | C9: MACAÉ
B10: CONTRATADA | C10: ANGEL'S SEGURANÇA E VIGILÂNCIA - EM RECUPERAÇÃO JUDICIAL LTDA
B11: FISCAL OPERACIONAL
B12: PERÍODO DE REFERÊNCIA | C12: Abril 2025
B14: AVALIAÇÃO DE DESEMPENHO
B15: Critério de Avaliação | C15: PESO (a) | D15: NOTA (b) (0,1,3) | E15: SUBTOTAL (c=a×b)
B16: ▶ GRUPO 1 – DESEMPENHO PROFISSIONAL
B17: Cumprimento das Atividades | C17: 0.4 | D17: 3 | E17: =C17*D17 | G17: =IF(OR(D17=0,D17=1),"Obrigatória justificativa no campo Justificativa e observações","")
B18: Qualificação / Atendimento ao Público / Postura | C18: 0.35 | D18: 3 | E18: =C18*D18 | G18: =IF(OR(D18=0,D18=1),"Obrigatória justificativa no campo Justificativa e observações","")
B19: Uniformes e Identificação | C19: 0.25 | D19: 3 | E19: =C19*D19 | G19: =IF(OR(D19=0,D19=1),"Obrigatória justificativa no campo Justificativa e observações","")
B20: TOTAL GRUPO 1 | C20: 1 | E20: =E17+E18+E19
B21: ▶ GRUPO 2 – DESEMPENHO DAS ATIVIDADES
B22: Especificação Técnica dos Serviços | C22: 0.4 | D22: 3 | E22: =C22*D22 | G22: =IF(OR(D22=0,D22=1),"Obrigatória justificativa no campo Justificativa e observações","")
B23: Equipamentos e Acessórios | C23: 0.2 | D23: 3 | E23: =C23*D23 | G23: =IF(OR(D23=0,D23=1),"Obrigatória justificativa no campo Justificativa e observações","")
B24: Atendimento às Ocorrências | C24: 0.4 | D24: 3 | E24: =C24*D24 | G24: =IF(OR(D24=0,D24=1),"Obrigatória justificativa no campo Justificativa e observações","")
B25: TOTAL GRUPO 2 | C25: 1 | E25: =E22+E23+E24
B26: ▶ GRUPO 3 – GERENCIAMENTO
B27: Periodicidade da Supervisão | C27: 0.2 | D27: 3 | E27: =C27*D27 | G27: =IF(OR(D27=0,D27=1),"Obrigatória justificativa no campo Justificativa e observações","")
B28: Gerenciamento das Atividades Operacionais | C28: 0.3 | D28: 3 | E28: =C28*D28 | G28: =IF(OR(D28=0,D28=1),"Obrigatória justificativa no campo Justificativa e observações","")
B29: Atendimento às Solicitações | C29: 0.25 | D29: 3 | E29: =C29*D29 | G29: =IF(OR(D29=0,D29=1),"Obrigatória justificativa no campo Justificativa e observações","")
B30: Salários, Benefícios e Obrigações Trabalhistas | C30: 0.25 | D30: 3 | E30: =C30*D30 | G30: =IF(OR(D30=0,D30=1),"Obrigatória justificativa no campo Justificativa e observações","")
B31: TOTAL GRUPO 3 | C31: 1 | E31: =E27+E28+E29+E30
B32: NOTA FINAL (G1+G2+G3) | E32: =E20+E25+E31
B33: CONCEITO | C33: =IF(E32>=8.1,"A",IF(E32>=7.65,"B",IF(E32>=6.75,"C",IF(E32>=5.85,"D",IF(E32>=5.4,"E","F"))))) | E33: % a pagar | F33: =IF(C33="A",1,IF(C33="B",0.95,IF(C33="C",0.9,IF(C33="D",0.85,IF(C33="E",0.8,0.75)))))
B35: PARÂMETROS (base 30 avos)
B36: Dias no mês (calendário) | C36: 30
B37: Nº de Dias Trabalhados | C37: 30
B38: Dias para cálculo (base 30) | C38: =IF(C37>=C36,30,MIN(C37,C36))
B40: POSTOS DE TRABALHO
B41: Item | C41: POSTO | D41: Qtde Contratada | E41: Valor Unit. (R$) | F41: Horas | G41: Sem Cob. (h) | H41: Valor Hora (R$) | I41: Valor após Descontos (R$) | K41: (aux) Mensal
B42: 1 | C42: Vigilância armada de 12x36 horas diurnas de Segunda Feira a Domingo | D42: 4 | E42: 5677.75 | F42: =IF(N(D42)>0,D42*220,0) | H42: =IF(N(D42)>0,ROUNDDOWN(E42/220,2),0) | I42: =IF(AND(N(D42)>0,N(E42)>0),MAX(0,ROUNDDOWN((D42*E42-H42*N(G42))/30*C38*F33,2)),0) | K42: =ROUNDDOWN(N(D42)*N(E42),2)
B43: 2 | C43: Vigilância armada de 12x36 horas noturnas de Segunda Feira a Domingo | D43: 12 | E43: 6228.99 | F43: =IF(N(D43)>0,D43*220,0) | H43: =IF(N(D43)>0,ROUNDDOWN(E43/220,2),0) | I43: =IF(AND(N(D43)>0,N(E43)>0),MAX(0,ROUNDDOWN((D43*E43-H43*N(G43))/30*C38*F33,2)),0) | K43: =ROUNDDOWN(N(D43)*N(E43),2)
B44: 3 | C44: Vigilância desarmada de 12x36 horas diurnas de Segunda Feira a Domingo | D44: 18 | E44: 5672.89 | F44: =IF(N(D44)>0,D44*220,0) | H44: =IF(N(D44)>0,ROUNDDOWN(E44/220,2),0) | I44: =IF(AND(N(D44)>0,N(E44)>0),MAX(0,ROUNDDOWN((D44*E44-H44*N(G44))/30*C38*F33,2)),0) | K44: =ROUNDDOWN(N(D44)*N(E44),2)
B45: 4 | C45: Vigilância desarmada de 12x36 horas noturnas de Segunda Feira a Domingo | D45: 10 | E45: 6224.09 | F45: =IF(N(D45)>0,D45*220,0) | H45: =IF(N(D45)>0,ROUNDDOWN(E45/220,2),0) | I45: =IF(AND(N(D45)>0,N(E45)>0),MAX(0,ROUNDDOWN((D45*E45-H45*N(G45))/30*C38*F33,2)),0) | K45: =ROUNDDOWN(N(D45)*N(E45),2)
B46: 5 | C46: Vigilância desarmada de 44h (8:48 horas) diurnas de Segunda Feira a Sexta | D46: 1 | E46: 6019.58 | F46: =IF(N(D46)>0,D46*220,0) | H46: =IF(N(D46)>0,ROUNDDOWN(E46/220,2),0) | I46: =IF(AND(N(D46)>0,N(E46)>0),MAX(0,ROUNDDOWN((D46*E46-H46*N(G46))/30*C38*F33,2)),0) | K46: =ROUNDDOWN(N(D46)*N(E46),2)
B47: 6 | C47: Vigilância desarmada de 12x36 horas diurnas de Segunda Feira a Domingo COM INTRAJORNADA | D47: 2 | E47: 6064.91 | F47: =IF(N(D47)>0,D47*220,0) | H47: =IF(N(D47)>0,ROUNDDOWN(E47/220,2),0) | I47: =IF(AND(N(D47)>0,N(E47)>0),MAX(0,ROUNDDOWN((D47*E47-H47*N(G47))/30*C38*F33,2)),0) | K47: =ROUNDDOWN(N(D47)*N(E47),2)
B48: 7 | C48: Vigilância desarmada de 12x36 horas noturnas de Segunda Feira a Domingo COM INTRAJORNADA | D48: 2 | E48: 6654.1 | F48: =IF(N(D48)>0,D48*220,0) | H48: =IF(N(D48)>0,ROUNDDOWN(E48/220,2),0) | I48: =IF(AND(N(D48)>0,N(E48)>0),MAX(0,ROUNDDOWN((D48*E48-H48*N(G48))/30*C38*F33,2)),0) | K48: =ROUNDDOWN(N(D48)*N(E48),2)
B49: TOTAIS | D49: =SUM(D42:D48) | E49: ◀ Qtde contratada | I49: =SUM(I42:I48) | K49: =SUM(K42:K48)
B51: INSTRUMENTO DE COBRANÇA
B52: Item | C52: Posto | D52: Qtde Fat. | E52: Valor Unit. Faturado (R$)
B53: =B42 | C53: =C42 | D53: =N(D42) | E53: =IF(N(D42)>0,ROUNDDOWN(I42/D42,2),0)
B54: =B43 | C54: =C43 | D54: =N(D43) | E54: =IF(N(D43)>0,ROUNDDOWN(I43/D43,2),0)
B55: =B44 | C55: =C44 | D55: =N(D44) | E55: =IF(N(D44)>0,ROUNDDOWN(I44/D44,2),0)
B56: =B45 | C56: =C45 | D56: =N(D45) | E56: =IF(N(D45)>0,ROUNDDOWN(I45/D45,2),0)
B57: =B46 | C57: =C46 | D57: =N(D46) | E57: =IF(N(D46)>0,ROUNDDOWN(I46/D46,2),0)
B58: =B47 | C58: =C47 | D58: =N(D47) | E58: =IF(N(D47)>0,ROUNDDOWN(I47/D47,2),0)
B59: =B48 | C59: =C48 | D59: =N(D48) | E59: =IF(N(D48)>0,ROUNDDOWN(I48/D48,2),0)
B61: RESUMO FINANCEIRO
B62: Contratado Mensal – Total (R$) | E62: =K49
B63: Conceito | E63: =C33
B64: % do Faturamento a ser Liberado | E64: =F33
B65: Valor Glosado por QUALIDADE (R$) | E65: =ROUNDDOWN(K49-K49*F33,2)
B66: Valor Aprovado para Pagamento (R$) | E66: =MAX(0,ROUNDDOWN(I49+E82,2))
B68: FAIXA DE AJUSTE
B69: Conceito | C69: % a Pagar | E69: Nota Média
B70: A | C70: 100% | E70: 9,00–8,10
B71: B | C71: 95% | E71: 8,09–7,65
B72: C | C72: 90% | E72: 7,64–6,75
B73: D | C73: 85% | E73: 6,74–5,85
B74: E | C74: 80% | E74: 5,84–5,40
B75: F | C75: 75% | E75: < 5,40
B77: REEMBOLSO DE CRECHE
B78: Valor estimado unitário (R$) | E78: 0
B79: Valor Reembolso Creche Retido (R$) (estimado × qtde contratada) | E79: =ROUNDDOWN(E78*D49,2)
B80: Reembolsos Aprovados (quantidade)
B81: Reembolso por dependente (R$) | E81: 526.64
B82: Valor Total dos Reembolsos (R$) (Aprovados × Reembolso por dependente) | E82: =ROUNDDOWN(E80*E81,2)
B83: Saldo do mês anterior (R$) | E83: ='Março 2025'!E84
B84: Saldo de Reembolso (R$) (Saldo anterior + Retido − Total) | E84: =E83+E79-E82
B85: =IF(E84<0,"⚠ Saldo negativo — se houver mais de uma unidade favor somar o saldo de todas; se permanecer negativo, aditivar o contrato.","")
B88: JUSTIFICATIVAS E OBSERVAÇÕES

Sheet Maio 2025
B1: UNIVERSIDADE FEDERAL DO RIO DE JANEIRO — PR-6
B3: INSTRUMENTO DE MEDIÇÃO DE RESULTADO (IMR)
B7: IDENTIFICAÇÃO
B8: CONTRATO Nº | C8: 05/24
B9: UNIDADE | C9: MACAÉ
B10: CONTRATADA | C10: ANGEL'S SEGURANÇA E VIGILÂNCIA - EM RECUPERAÇÃO JUDICIAL LTDA
B11: FISCAL OPERACIONAL
B12: PERÍODO DE REFERÊNCIA | C12: Maio 2025
B14: AVALIAÇÃO DE DESEMPENHO
B15: Critério de Avaliação | C15: PESO (a) | D15: NOTA (b) (0,1,3) | E15: SUBTOTAL (c=a×b)
B16: ▶ GRUPO 1 – DESEMPENHO PROFISSIONAL
B17: Cumprimento das Atividades | C17: 0.4 | D17: 3 | E17: =C17*D17 | G17: =IF(OR(D17=0,D17=1),"Obrigatória justificativa no campo Justificativa e observações","")
B18: Qualificação / Atendimento ao Público / Postura | C18: 0.35 | D18: 3 | E18: =C18*D18 | G18: =IF(OR(D18=0,D18=1),"Obrigatória justificativa no campo Justificativa e observações","")
B19: Uniformes e Identificação | C19: 0.25 | D19: 3 | E19: =C19*D19 | G19: =IF(OR(D19=0,D19=1),"Obrigatória justificativa no campo Justificativa e observações","")
B20: TOTAL GRUPO 1 | C20: 1 | E20: =E17+E18+E19
B21: ▶ GRUPO 2 – DESEMPENHO DAS ATIVIDADES
B22: Especificação Técnica dos Serviços | C22: 0.4 | D22: 3 | E22: =C22*D22 | G22: =IF(OR(D22=0,D22=1),"Obrigatória justificativa no campo Justificativa e observações","")
B23: Equipamentos e Acessórios | C23: 0.2 | D23: 3 | E23: =C23*D23 | G23: =IF(OR(D23=0,D23=1),"Obrigatória justificativa no campo Justificativa e observações","")
B24: Atendimento às Ocorrências | C24: 0.4 | D24: 3 | E24: =C24*D24 | G24: =IF(OR(D24=0,D24=1),"Obrigatória justificativa no campo Justificativa e observações","")
B25: TOTAL GRUPO 2 | C25: 1 | E25: =E22+E23+E24
B26: ▶ GRUPO 3 – GERENCIAMENTO
B27: Periodicidade da Supervisão | C27: 0.2 | D27: 3 | E27: =C27*D27 | G27: =IF(OR(D27=0,D27=1),"Obrigatória justificativa no campo Justificativa e observações","")
B28: Gerenciamento das Atividades Operacionais | C28: 0.3 | D28: 3 | E28: =C28*D28 | G28: =IF(OR(D28=0,D28=1),"Obrigatória justificativa no campo Justificativa e observações","")
B29: Atendimento às Solicitações | C29: 0.25 | D29: 3 | E29: =C29*D29 | G29: =IF(OR(D29=0,D29=1),"Obrigatória justificativa no campo Justificativa e observações","")
B30: Salários, Benefícios e Obrigações Trabalhistas | C30: 0.25 | D30: 3 | E30: =C30*D30 | G30: =IF(OR(D30=0,D30=1),"Obrigatória justificativa no campo Justificativa e observações","")
B31: TOTAL GRUPO 3 | C31: 1 | E31: =E27+E28+E29+E30
B32: NOTA FINAL (G1+G2+G3) | E32: =E20+E25+E31
B33: CONCEITO | C33: =IF(E32>=8.1,"A",IF(E32>=7.65,"B",IF(E32>=6.75,"C",IF(E32>=5.85,"D",IF(E32>=5.4,"E","F"))))) | E33: % a pagar | F33: =IF(C33="A",1,IF(C33="B",0.95,IF(C33="C",0.9,IF(C33="D",0.85,IF(C33="E",0.8,0.75)))))
B35: PARÂMETROS (base 30 avos)
B36: Dias no mês (calendário) | C36: 30
B37: Nº de Dias Trabalhados | C37: 30
B38: Dias para cálculo (base 30) | C38: =IF(C37>=C36,30,MIN(C37,C36))
B40: POSTOS DE TRABALHO
B41: Item | C41: POSTO | D41: Qtde Contratada | E41: Valor Unit. (R$) | F41: Horas | G41: Sem Cob. (h) | H41: Valor Hora (R$) | I41: Valor após Descontos (R$) | K41: (aux) Mensal
B42: 1 | C42: Vigilância armada de 12x36 horas diurnas de Segunda Feira a Domingo | D42: 4 | E42: 5677.75 | F42: =IF(N(D42)>0,D42*220,0) | H42: =IF(N(D42)>0,ROUNDDOWN(E42/220,2),0) | I42: =IF(AND(N(D42)>0,N(E42)>0),MAX(0,ROUNDDOWN((D42*E42-H42*N(G42))/30*C38*F33,2)),0) | K42: =ROUNDDOWN(N(D42)*N(E42),2)
B43: 2 | C43: Vigilância armada de 12x36 horas noturnas de Segunda Feira a Domingo | D43: 12 | E43: 6228.99 | F43: =IF(N(D43)>0,D43*220,0) | H43: =IF(N(D43)>0,ROUNDDOWN(E43/220,2),0) | I43: =IF(AND(N(D43)>0,N(E43)>0),MAX(0,ROUNDDOWN((D43*E43-H43*N(G43))/30*C38*F33,2)),0) | K43: =ROUNDDOWN(N(D43)*N(E43),2)
B44: 3 | C44: Vigilância desarmada de 12x36 horas diurnas de Segunda Feira a Domingo | D44: 18 | E44: 5672.89 | F44: =IF(N(D44)>0,D44*220,0) | H44: =IF(N(D44)>0,ROUNDDOWN(E44/220,2),0) | I44: =IF(AND(N(D44)>0,N(E44)>0),MAX(0,ROUNDDOWN((D44*E44-H44*N(G44))/30*C38*F33,2)),0) | K44: =ROUNDDOWN(N(D44)*N(E44),2)
B45: 4 | C45: Vigilância desarmada de 12x36 horas noturnas de Segunda Feira a Domingo | D45: 10 | E45: 6224.09 | F45: =IF(N(D45)>0,D45*220,0) | H45: =IF(N(D45)>0,ROUNDDOWN(E45/220,2),0) | I45: =IF(AND(N(D45)>0,N(E45)>0),MAX(0,ROUNDDOWN((D45*E45-H45*N(G45))/30*C38*F33,2)),0) | K45: =ROUNDDOWN(N(D45)*N(E45),2)
B46: 5 | C46: Vigilância desarmada de 44h (8:48 horas) diurnas de Segunda Feira a Sexta | D46: 1 | E46: 6019.58 | F46: =IF(N(D46)>0,D46*220,0) | H46: =IF(N(D46)>0,ROUNDDOWN(E46/220,2),0) | I46: =IF(AND(N(D46)>0,N(E46)>0),MAX(0,ROUNDDOWN((D46*E46-H46*N(G46))/30*C38*F33,2)),0) | K46: =ROUNDDOWN(N(D46)*N(E46),2)
B47: 6 | C47: Vigilância desarmada de 12x36 horas diurnas de Segunda Feira a Domingo COM INTRAJORNADA | D47: 2 | E47: 6064.91 | F47: =IF(N(D47)>0,D47*220,0) | H47: =IF(N(D47)>0,ROUNDDOWN(E47/220,2),0) | I47: =IF(AND(N(D47)>0,N(E47)>0),MAX(0,ROUNDDOWN((D47*E47-H47*N(G47))/30*C38*F33,2)),0) | K47: =ROUNDDOWN(N(D47)*N(E47),2)
B48: 7 | C48: Vigilância desarmada de 12x36 horas noturnas de Segunda Feira a Domingo COM INTRAJORNADA | D48: 2 | E48: 6654.1 | F48: =IF(N(D48)>0,D48*220,0) | H48: =IF(N(D48)>0,ROUNDDOWN(E48/220,2),0) | I48: =IF(AND(N(D48)>0,N(E48)>0),MAX(0,ROUNDDOWN((D48*E48-H48*N(G48))/30*C38*F33,2)),0) | K48: =ROUNDDOWN(N(D48)*N(E48),2)
B49: TOTAIS | D49: =SUM(D42:D48) | E49: ◀ Qtde contratada | I49: =SUM(I42:I48) | K49: =SUM(K42:K48)
B51: INSTRUMENTO DE COBRANÇA
B52: Item | C52: Posto | D52: Qtde Fat. | E52: Valor Unit. Faturado (R$)
B53: =B42 | C53: =C42 | D53: =N(D42) | E53: =IF(N(D42)>0,ROUNDDOWN(I42/D42,2),0)
B54: =B43 | C54: =C43 | D54: =N(D43) | E54: =IF(N(D43)>0,ROUNDDOWN(I43/D43,2),0)
B55: =B44 | C55: =C44 | D55: =N(D44) | E55: =IF(N(D44)>0,ROUNDDOWN(I44/D44,2),0)
B56: =B45 | C56: =C45 | D56: =N(D45) | E56: =IF(N(D45)>0,ROUNDDOWN(I45/D45,2),0)
B57: =B46 | C57: =C46 | D57: =N(D46) | E57: =IF(N(D46)>0,ROUNDDOWN(I46/D46,2),0)
B58: =B47 | C58: =C47 | D58: =N(D47) | E58: =IF(N(D47)>0,ROUNDDOWN(I47/D47,2),0)
B59: =B48 | C59: =C48 | D59: =N(D48) | E59: =IF(N(D48)>0,ROUNDDOWN(I48/D48,2),0)
B61: RESUMO FINANCEIRO
B62: Contratado Mensal – Total (R$) | E62: =K49
B63: Conceito | E63: =C33
B64: % do Faturamento a ser Liberado | E64: =F33
B65: Valor Glosado por QUALIDADE (R$) | E65: =ROUNDDOWN(K49-K49*F33,2)
B66: Valor Aprovado para Pagamento (R$) | E66: =MAX(0,ROUNDDOWN(I49+E82,2))
B68: FAIXA DE AJUSTE
B69: Conceito | C69: % a Pagar | E69: Nota Média
B70: A | C70: 100% | E70: 9,00–8,10
B71: B | C71: 95% | E71: 8,09–7,65
B72: C | C72: 90% | E72: 7,64–6,75
B73: D | C73: 85% | E73: 6,74–5,85
B74: E | C74: 80% | E74: 5,84–5,40
B75: F | C75: 75% | E75: < 5,40
B77: REEMBOLSO DE CRECHE
B78: Valor estimado unitário (R$) | E78: 0
B79: Valor Reembolso Creche Retido (R$) (estimado × qtde contratada) | E79: =ROUNDDOWN(E78*D49,2)
B80: Reembolsos Aprovados (quantidade)
B81: Reembolso por dependente (R$) | E81: 526.64
B82: Valor Total dos Reembolsos (R$) (Aprovados × Reembolso por dependente) | E82: =ROUNDDOWN(E80*E81,2)
B83: Saldo do mês anterior (R$) | E83: ='Abril 2025'!E84
B84: Saldo de Reembolso (R$) (Saldo anterior + Retido − Total) | E84: =E83+E79-E82
B85: =IF(E84<0,"⚠ Saldo negativo — se houver mais de uma unidade favor somar o saldo de todas; se permanecer negativo, aditivar o contrato.","")
B88: JUSTIFICATIVAS E OBSERVAÇÕES

Sheet Junho 2025
B1: UNIVERSIDADE FEDERAL DO RIO DE JANEIRO — PR-6
B3: INSTRUMENTO DE MEDIÇÃO DE RESULTADO (IMR)
B7: IDENTIFICAÇÃO
B8: CONTRATO Nº | C8: 05/24
B9: UNIDADE | C9: MACAÉ
B10: CONTRATADA | C10: ANGEL'S SEGURANÇA E VIGILÂNCIA - EM RECUPERAÇÃO JUDICIAL LTDA
B11: FISCAL OPERACIONAL
B12: PERÍODO DE REFERÊNCIA | C12: Junho 2025
B14: AVALIAÇÃO DE DESEMPENHO
B15: Critério de Avaliação | C15: PESO (a) | D15: NOTA (b) (0,1,3) | E15: SUBTOTAL (c=a×b)
B16: ▶ GRUPO 1 – DESEMPENHO PROFISSIONAL
B17: Cumprimento das Atividades | C17: 0.4 | D17: 3 | E17: =C17*D17 | G17: =IF(OR(D17=0,D17=1),"Obrigatória justificativa no campo Justificativa e observações","")
B18: Qualificação / Atendimento ao Público / Postura | C18: 0.35 | D18: 3 | E18: =C18*D18 | G18: =IF(OR(D18=0,D18=1),"Obrigatória justificativa no campo Justificativa e observações","")
B19: Uniformes e Identificação | C19: 0.25 | D19: 3 | E19: =C19*D19 | G19: =IF(OR(D19=0,D19=1),"Obrigatória justificativa no campo Justificativa e observações","")
B20: TOTAL GRUPO 1 | C20: 1 | E20: =E17+E18+E19
B21: ▶ GRUPO 2 – DESEMPENHO DAS ATIVIDADES
B22: Especificação Técnica dos Serviços | C22: 0.4 | D22: 3 | E22: =C22*D22 | G22: =IF(OR(D22=0,D22=1),"Obrigatória justificativa no campo Justificativa e observações","")
B23: Equipamentos e Acessórios | C23: 0.2 | D23: 3 | E23: =C23*D23 | G23: =IF(OR(D23=0,D23=1),"Obrigatória justificativa no campo Justificativa e observações","")
B24: Atendimento às Ocorrências | C24: 0.4 | D24: 3 | E24: =C24*D24 | G24: =IF(OR(D24=0,D24=1),"Obrigatória justificativa no campo Justificativa e observações","")
B25: TOTAL GRUPO 2 | C25: 1 | E25: =E22+E23+E24
B26: ▶ GRUPO 3 – GERENCIAMENTO
B27: Periodicidade da Supervisão | C27: 0.2 | D27: 3 | E27: =C27*D27 | G27: =IF(OR(D27=0,D27=1),"Obrigatória justificativa no campo Justificativa e observações","")
B28: Gerenciamento das Atividades Operacionais | C28: 0.3 | D28: 3 | E28: =C28*D28 | G28: =IF(OR(D28=0,D28=1),"Obrigatória justificativa no campo Justificativa e observações","")
B29: Atendimento às Solicitações | C29: 0.25 | D29: 3 | E29: =C29*D29 | G29: =IF(OR(D29=0,D29=1),"Obrigatória justificativa no campo Justificativa e observações","")
B30: Salários, Benefícios e Obrigações Trabalhistas | C30: 0.25 | D30: 3 | E30: =C30*D30 | G30: =IF(OR(D30=0,D30=1),"Obrigatória justificativa no campo Justificativa e observações","")
B31: TOTAL GRUPO 3 | C31: 1 | E31: =E27+E28+E29+E30
B32: NOTA FINAL (G1+G2+G3) | E32: =E20+E25+E31
B33: CONCEITO | C33: =IF(E32>=8.1,"A",IF(E32>=7.65,"B",IF(E32>=6.75,"C",IF(E32>=5.85,"D",IF(E32>=5.4,"E","F"))))) | E33: % a pagar | F33: =IF(C33="A",1,IF(C33="B",0.95,IF(C33="C",0.9,IF(C33="D",0.85,IF(C33="E",0.8,0.75)))))
B35: PARÂMETROS (base 30 avos)
B36: Dias no mês (calendário) | C36: 30
B37: Nº de Dias Trabalhados | C37: 30
B38: Dias para cálculo (base 30) | C38: =IF(C37>=C36,30,MIN(C37,C36))
B40: POSTOS DE TRABALHO
B41: Item | C41: POSTO | D41: Qtde Contratada | E41: Valor Unit. (R$) | F41: Horas | G41: Sem Cob. (h) | H41: Valor Hora (R$) | I41: Valor após Descontos (R$) | K41: (aux) Mensal
B42: 1 | C42: Vigilância armada de 12x36 horas diurnas de Segunda Feira a Domingo | D42: 4 | E42: 5677.75 | F42: =IF(N(D42)>0,D42*220,0) | H42: =IF(N(D42)>0,ROUNDDOWN(E42/220,2),0) | I42: =IF(AND(N(D42)>0,N(E42)>0),MAX(0,ROUNDDOWN((D42*E42-H42*N(G42))/30*C38*F33,2)),0) | K42: =ROUNDDOWN(N(D42)*N(E42),2)
B43: 2 | C43: Vigilância armada de 12x36 horas noturnas de Segunda Feira a Domingo | D43: 12 | E43: 6228.99 | F43: =IF(N(D43)>0,D43*220,0) | H43: =IF(N(D43)>0,ROUNDDOWN(E43/220,2),0) | I43: =IF(AND(N(D43)>0,N(E43)>0),MAX(0,ROUNDDOWN((D43*E43-H43*N(G43))/30*C38*F33,2)),0) | K43: =ROUNDDOWN(N(D43)*N(E43),2)
B44: 3 | C44: Vigilância desarmada de 12x36 horas diurnas de Segunda Feira a Domingo | D44: 18 | E44: 5672.89 | F44: =IF(N(D44)>0,D44*220,0) | H44: =IF(N(D44)>0,ROUNDDOWN(E44/220,2),0) | I44: =IF(AND(N(D44)>0,N(E44)>0),MAX(0,ROUNDDOWN((D44*E44-H44*N(G44))/30*C38*F33,2)),0) | K44: =ROUNDDOWN(N(D44)*N(E44),2)
B45: 4 | C45: Vigilância desarmada de 12x36 horas noturnas de Segunda Feira a Domingo | D45: 10 | E45: 6224.09 | F45: =IF(N(D45)>0,D45*220,0) | H45: =IF(N(D45)>0,ROUNDDOWN(E45/220,2),0) | I45: =IF(AND(N(D45)>0,N(E45)>0),MAX(0,ROUNDDOWN((D45*E45-H45*N(G45))/30*C38*F33,2)),0) | K45: =ROUNDDOWN(N(D45)*N(E45),2)
B46: 5 | C46: Vigilância desarmada de 44h (8:48 horas) diurnas de Segunda Feira a Sexta | D46: 1 | E46: 6019.58 | F46: =IF(N(D46)>0,D46*220,0) | H46: =IF(N(D46)>0,ROUNDDOWN(E46/220,2),0) | I46: =IF(AND(N(D46)>0,N(E46)>0),MAX(0,ROUNDDOWN((D46*E46-H46*N(G46))/30*C38*F33,2)),0) | K46: =ROUNDDOWN(N(D46)*N(E46),2)
B47: 6 | C47: Vigilância desarmada de 12x36 horas diurnas de Segunda Feira a Domingo COM INTRAJORNADA | D47: 2 | E47: 6064.91 | F47: =IF(N(D47)>0,D47*220,0) | H47: =IF(N(D47)>0,ROUNDDOWN(E47/220,2),0) | I47: =IF(AND(N(D47)>0,N(E47)>0),MAX(0,ROUNDDOWN((D47*E47-H47*N(G47))/30*C38*F33,2)),0) | K47: =ROUNDDOWN(N(D47)*N(E47),2)
B48: 7 | C48: Vigilância desarmada de 12x36 horas noturnas de Segunda Feira a Domingo COM INTRAJORNADA | D48: 2 | E48: 6654.1 | F48: =IF(N(D48)>0,D48*220,0) | H48: =IF(N(D48)>0,ROUNDDOWN(E48/220,2),0) | I48: =IF(AND(N(D48)>0,N(E48)>0),MAX(0,ROUNDDOWN((D48*E48-H48*N(G48))/30*C38*F33,2)),0) | K48: =ROUNDDOWN(N(D48)*N(E48),2)
B49: TOTAIS | D49: =SUM(D42:D48) | E49: ◀ Qtde contratada | I49: =SUM(I42:I48) | K49: =SUM(K42:K48)
B51: INSTRUMENTO DE COBRANÇA
B52: Item | C52: Posto | D52: Qtde Fat. | E52: Valor Unit. Faturado (R$)
B53: =B42 | C53: =C42 | D53: =N(D42) | E53: =IF(N(D42)>0,ROUNDDOWN(I42/D42,2),0)
B54: =B43 | C54: =C43 | D54: =N(D43) | E54: =IF(N(D43)>0,ROUNDDOWN(I43/D43,2),0)
B55: =B44 | C55: =C44 | D55: =N(D44) | E55: =IF(N(D44)>0,ROUNDDOWN(I44/D44,2),0)
B56: =B45 | C56: =C45 | D56: =N(D45) | E56: =IF(N(D45)>0,ROUNDDOWN(I45/D45,2),0)
B57: =B46 | C57: =C46 | D57: =N(D46) | E57: =IF(N(D46)>0,ROUNDDOWN(I46/D46,2),0)
B58: =B47 | C58: =C47 | D58: =N(D47) | E58: =IF(N(D47)>0,ROUNDDOWN(I47/D47,2),0)
B59: =B48 | C59: =C48 | D59: =N(D48) | E59: =IF(N(D48)>0,ROUNDDOWN(I48/D48,2),0)
B61: RESUMO FINANCEIRO
B62: Contratado Mensal – Total (R$) | E62: =K49
B63: Conceito | E63: =C33
B64: % do Faturamento a ser Liberado | E64: =F33
B65: Valor Glosado por QUALIDADE (R$) | E65: =ROUNDDOWN(K49-K49*F33,2)
B66: Valor Aprovado para Pagamento (R$) | E66: =MAX(0,ROUNDDOWN(I49+E82,2))
B68: FAIXA DE AJUSTE
B69: Conceito | C69: % a Pagar | E69: Nota Média
B70: A | C70: 100% | E70: 9,00–8,10
B71: B | C71: 95% | E71: 8,09–7,65
B72: C | C72: 90% | E72: 7,64–6,75
B73: D | C73: 85% | E73: 6,74–5,85
B74: E | C74: 80% | E74: 5,84–5,40
B75: F | C75: 75% | E75: < 5,40
B77: REEMBOLSO DE CRECHE
B78: Valor estimado unitário (R$) | E78: 0
B79: Valor Reembolso Creche Retido (R$) (estimado × qtde contratada) | E79: =ROUNDDOWN(E78*D49,2)
B80: Reembolsos Aprovados (quantidade)
B81: Reembolso por dependente (R$) | E81: 526.64
B82: Valor Total dos Reembolsos (R$) (Aprovados × Reembolso por dependente) | E82: =ROUNDDOWN(E80*E81,2)
B83: Saldo do mês anterior (R$) | E83: ='Maio 2025'!E84
B84: Saldo de Reembolso (R$) (Saldo anterior + Retido − Total) | E84: =E83+E79-E82
B85: =IF(E84<0,"⚠ Saldo negativo — se houver mais de uma unidade favor somar o saldo de todas; se permanecer negativo, aditivar o contrato.","")
B88: JUSTIFICATIVAS E OBSERVAÇÕES

Sheet Julho 2025
B1: UNIVERSIDADE FEDERAL DO RIO DE JANEIRO — PR-6
B3: INSTRUMENTO DE MEDIÇÃO DE RESULTADO (IMR)
B7: IDENTIFICAÇÃO
B8: CONTRATO Nº | C8: 05/24
B9: UNIDADE | C9: MACAÉ
B10: CONTRATADA | C10: ANGEL'S SEGURANÇA E VIGILÂNCIA - EM RECUPERAÇÃO JUDICIAL LTDA
B11: FISCAL OPERACIONAL
B12: PERÍODO DE REFERÊNCIA | C12: Julho 2025
B14: AVALIAÇÃO DE DESEMPENHO
B15: Critério de Avaliação | C15: PESO (a) | D15: NOTA (b) (0,1,3) | E15: SUBTOTAL (c=a×b)
B16: ▶ GRUPO 1 – DESEMPENHO PROFISSIONAL
B17: Cumprimento das Atividades | C17: 0.4 | D17: 3 | E17: =C17*D17 | G17: =IF(OR(D17=0,D17=1),"Obrigatória justificativa no campo Justificativa e observações","")
B18: Qualificação / Atendimento ao Público / Postura | C18: 0.35 | D18: 3 | E18: =C18*D18 | G18: =IF(OR(D18=0,D18=1),"Obrigatória justificativa no campo Justificativa e observações","")
B19: Uniformes e Identificação | C19: 0.25 | D19: 3 | E19: =C19*D19 | G19: =IF(OR(D19=0,D19=1),"Obrigatória justificativa no campo Justificativa e observações","")
B20: TOTAL GRUPO 1 | C20: 1 | E20: =E17+E18+E19
B21: ▶ GRUPO 2 – DESEMPENHO DAS ATIVIDADES
B22: Especificação Técnica dos Serviços | C22: 0.4 | D22: 3 | E22: =C22*D22 | G22: =IF(OR(D22=0,D22=1),"Obrigatória justificativa no campo Justificativa e observações","")
B23: Equipamentos e Acessórios | C23: 0.2 | D23: 3 | E23: =C23*D23 | G23: =IF(OR(D23=0,D23=1),"Obrigatória justificativa no campo Justificativa e observações","")
B24: Atendimento às Ocorrências | C24: 0.4 | D24: 3 | E24: =C24*D24 | G24: =IF(OR(D24=0,D24=1),"Obrigatória justificativa no campo Justificativa e observações","")
B25: TOTAL GRUPO 2 | C25: 1 | E25: =E22+E23+E24
B26: ▶ GRUPO 3 – GERENCIAMENTO
B27: Periodicidade da Supervisão | C27: 0.2 | D27: 3 | E27: =C27*D27 | G27: =IF(OR(D27=0,D27=1),"Obrigatória justificativa no campo Justificativa e observações","")
B28: Gerenciamento das Atividades Operacionais | C28: 0.3 | D28: 3 | E28: =C28*D28 | G28: =IF(OR(D28=0,D28=1),"Obrigatória justificativa no campo Justificativa e observações","")
B29: Atendimento às Solicitações | C29: 0.25 | D29: 3 | E29: =C29*D29 | G29: =IF(OR(D29=0,D29=1),"Obrigatória justificativa no campo Justificativa e observações","")
B30: Salários, Benefícios e Obrigações Trabalhistas | C30: 0.25 | D30: 3 | E30: =C30*D30 | G30: =IF(OR(D30=0,D30=1),"Obrigatória justificativa no campo Justificativa e observações","")
B31: TOTAL GRUPO 3 | C31: 1 | E31: =E27+E28+E29+E30
B32: NOTA FINAL (G1+G2+G3) | E32: =E20+E25+E31
B33: CONCEITO | C33: =IF(E32>=8.1,"A",IF(E32>=7.65,"B",IF(E32>=6.75,"C",IF(E32>=5.85,"D",IF(E32>=5.4,"E","F"))))) | E33: % a pagar | F33: =IF(C33="A",1,IF(C33="B",0.95,IF(C33="C",0.9,IF(C33="D",0.85,IF(C33="E",0.8,0.75)))))
B35: PARÂMETROS (base 30 avos)
B36: Dias no mês (calendário) | C36: 30
B37: Nº de Dias Trabalhados | C37: 30
B38: Dias para cálculo (base 30) | C38: =IF(C37>=C36,30,MIN(C37,C36))
B40: POSTOS DE TRABALHO
B41: Item | C41: POSTO | D41: Qtde Contratada | E41: Valor Unit. (R$) | F41: Horas | G41: Sem Cob. (h) | H41: Valor Hora (R$) | I41: Valor após Descontos (R$) | K41: (aux) Mensal
B42: 1 | C42: Vigilância armada de 12x36 horas diurnas de Segunda Feira a Domingo | D42: 4 | E42: 5677.75 | F42: =IF(N(D42)>0,D42*220,0) | H42: =IF(N(D42)>0,ROUNDDOWN(E42/220,2),0) | I42: =IF(AND(N(D42)>0,N(E42)>0),MAX(0,ROUNDDOWN((D42*E42-H42*N(G42))/30*C38*F33,2)),0) | K42: =ROUNDDOWN(N(D42)*N(E42),2)
B43: 2 | C43: Vigilância armada de 12x36 horas noturnas de Segunda Feira a Domingo | D43: 12 | E43: 6228.99 | F43: =IF(N(D43)>0,D43*220,0) | H43: =IF(N(D43)>0,ROUNDDOWN(E43/220,2),0) | I43: =IF(AND(N(D43)>0,N(E43)>0),MAX(0,ROUNDDOWN((D43*E43-H43*N(G43))/30*C38*F33,2)),0) | K43: =ROUNDDOWN(N(D43)*N(E43),2)
B44: 3 | C44: Vigilância desarmada de 12x36 horas diurnas de Segunda Feira a Domingo | D44: 18 | E44: 5672.89 | F44: =IF(N(D44)>0,D44*220,0) | H44: =IF(N(D44)>0,ROUNDDOWN(E44/220,2),0) | I44: =IF(AND(N(D44)>0,N(E44)>0),MAX(0,ROUNDDOWN((D44*E44-H44*N(G44))/30*C38*F33,2)),0) | K44: =ROUNDDOWN(N(D44)*N(E44),2)
B45: 4 | C45: Vigilância desarmada de 12x36 horas noturnas de Segunda Feira a Domingo | D45: 10 | E45: 6224.09 | F45: =IF(N(D45)>0,D45*220,0) | H45: =IF(N(D45)>0,ROUNDDOWN(E45/220,2),0) | I45: =IF(AND(N(D45)>0,N(E45)>0),MAX(0,ROUNDDOWN((D45*E45-H45*N(G45))/30*C38*F33,2)),0) | K45: =ROUNDDOWN(N(D45)*N(E45),2)
B46: 5 | C46: Vigilância desarmada de 44h (8:48 horas) diurnas de Segunda Feira a Sexta | D46: 1 | E46: 6019.58 | F46: =IF(N(D46)>0,D46*220,0) | H46: =IF(N(D46)>0,ROUNDDOWN(E46/220,2),0) | I46: =IF(AND(N(D46)>0,N(E46)>0),MAX(0,ROUNDDOWN((D46*E46-H46*N(G46))/30*C38*F33,2)),0) | K46: =ROUNDDOWN(N(D46)*N(E46),2)
B47: 6 | C47: Vigilância desarmada de 12x36 horas diurnas de Segunda Feira a Domingo COM INTRAJORNADA | D47: 2 | E47: 6064.91 | F47: =IF(N(D47)>0,D47*220,0) | H47: =IF(N(D47)>0,ROUNDDOWN(E47/220,2),0) | I47: =IF(AND(N(D47)>0,N(E47)>0),MAX(0,ROUNDDOWN((D47*E47-H47*N(G47))/30*C38*F33,2)),0) | K47: =ROUNDDOWN(N(D47)*N(E47),2)
B48: 7 | C48: Vigilância desarmada de 12x36 horas noturnas de Segunda Feira a Domingo COM INTRAJORNADA | D48: 2 | E48: 6654.1 | F48: =IF(N(D48)>0,D48*220,0) | H48: =IF(N(D48)>0,ROUNDDOWN(E48/220,2),0) | I48: =IF(AND(N(D48)>0,N(E48)>0),MAX(0,ROUNDDOWN((D48*E48-H48*N(G48))/30*C38*F33,2)),0) | K48: =ROUNDDOWN(N(D48)*N(E48),2)
B49: TOTAIS | D49: =SUM(D42:D48) | E49: ◀ Qtde contratada | I49: =SUM(I42:I48) | K49: =SUM(K42:K48)
B51: INSTRUMENTO DE COBRANÇA
B52: Item | C52: Posto | D52: Qtde Fat. | E52: Valor Unit. Faturado (R$)
B53: =B42 | C53: =C42 | D53: =N(D42) | E53: =IF(N(D42)>0,ROUNDDOWN(I42/D42,2),0)
B54: =B43 | C54: =C43 | D54: =N(D43) | E54: =IF(N(D43)>0,ROUNDDOWN(I43/D43,2),0)
B55: =B44 | C55: =C44 | D55: =N(D44) | E55: =IF(N(D44)>0,ROUNDDOWN(I44/D44,2),0)
B56: =B45 | C56: =C45 | D56: =N(D45) | E56: =IF(N(D45)>0,ROUNDDOWN(I45/D45,2),0)
B57: =B46 | C57: =C46 | D57: =N(D46) | E57: =IF(N(D46)>0,ROUNDDOWN(I46/D46,2),0)
B58: =B47 | C58: =C47 | D58: =N(D47) | E58: =IF(N(D47)>0,ROUNDDOWN(I47/D47,2),0)
B59: =B48 | C59: =C48 | D59: =N(D48) | E59: =IF(N(D48)>0,ROUNDDOWN(I48/D48,2),0)
B61: RESUMO FINANCEIRO
B62: Contratado Mensal – Total (R$) | E62: =K49
B63: Conceito | E63: =C33
B64: % do Faturamento a ser Liberado | E64: =F33
B65: Valor Glosado por QUALIDADE (R$) | E65: =ROUNDDOWN(K49-K49*F33,2)
B66: Valor Aprovado para Pagamento (R$) | E66: =MAX(0,ROUNDDOWN(I49+E82,2))
B68: FAIXA DE AJUSTE
B69: Conceito | C69: % a Pagar | E69: Nota Média
B70: A | C70: 100% | E70: 9,00–8,10
B71: B | C71: 95% | E71: 8,09–7,65
B72: C | C72: 90% | E72: 7,64–6,75
B73: D | C73: 85% | E73: 6,74–5,85
B74: E | C74: 80% | E74: 5,84–5,40
B75: F | C75: 75% | E75: < 5,40
B77: REEMBOLSO DE CRECHE
B78: Valor estimado unitário (R$) | E78: 0
B79: Valor Reembolso Creche Retido (R$) (estimado × qtde contratada) | E79: =ROUNDDOWN(E78*D49,2)
B80: Reembolsos Aprovados (quantidade)
B81: Reembolso por dependente (R$) | E81: 526.64
B82: Valor Total dos Reembolsos (R$) (Aprovados × Reembolso por dependente) | E82: =ROUNDDOWN(E80*E81,2)
B83: Saldo do mês anterior (R$) | E83: ='Junho 2025'!E84
B84: Saldo de Reembolso (R$) (Saldo anterior + Retido − Total) | E84: =E83+E79-E82
B85: =IF(E84<0,"⚠ Saldo negativo — se houver mais de uma unidade favor somar o saldo de todas; se permanecer negativo, aditivar o contrato.","")
B88: JUSTIFICATIVAS E OBSERVAÇÕES

Sheet Agosto 2025
B1: UNIVERSIDADE FEDERAL DO RIO DE JANEIRO — PR-6
B3: INSTRUMENTO DE MEDIÇÃO DE RESULTADO (IMR)
B7: IDENTIFICAÇÃO
B8: CONTRATO Nº | C8: 05/24
B9: UNIDADE | C9: MACAÉ
B10: CONTRATADA | C10: ANGEL'S SEGURANÇA E VIGILÂNCIA - EM RECUPERAÇÃO JUDICIAL LTDA
B11: FISCAL OPERACIONAL
B12: PERÍODO DE REFERÊNCIA | C12: Agosto 2025
B14: AVALIAÇÃO DE DESEMPENHO
B15: Critério de Avaliação | C15: PESO (a) | D15: NOTA (b) (0,1,3) | E15: SUBTOTAL (c=a×b)
B16: ▶ GRUPO 1 – DESEMPENHO PROFISSIONAL
B17: Cumprimento das Atividades | C17: 0.4 | D17: 3 | E17: =C17*D17 | G17: =IF(OR(D17=0,D17=1),"Obrigatória justificativa no campo Justificativa e observações","")
B18: Qualificação / Atendimento ao Público / Postura | C18: 0.35 | D18: 3 | E18: =C18*D18 | G18: =IF(OR(D18=0,D18=1),"Obrigatória justificativa no campo Justificativa e observações","")
B19: Uniformes e Identificação | C19: 0.25 | D19: 3 | E19: =C19*D19 | G19: =IF(OR(D19=0,D19=1),"Obrigatória justificativa no campo Justificativa e observações","")
B20: TOTAL GRUPO 1 | C20: 1 | E20: =E17+E18+E19
B21: ▶ GRUPO 2 – DESEMPENHO DAS ATIVIDADES
B22: Especificação Técnica dos Serviços | C22: 0.4 | D22: 3 | E22: =C22*D22 | G22: =IF(OR(D22=0,D22=1),"Obrigatória justificativa no campo Justificativa e observações","")
B23: Equipamentos e Acessórios | C23: 0.2 | D23: 3 | E23: =C23*D23 | G23: =IF(OR(D23=0,D23=1),"Obrigatória justificativa no campo Justificativa e observações","")
B24: Atendimento às Ocorrências | C24: 0.4 | D24: 3 | E24: =C24*D24 | G24: =IF(OR(D24=0,D24=1),"Obrigatória justificativa no campo Justificativa e observações","")
B25: TOTAL GRUPO 2 | C25: 1 | E25: =E22+E23+E24
B26: ▶ GRUPO 3 – GERENCIAMENTO
B27: Periodicidade da Supervisão | C27: 0.2 | D27: 3 | E27: =C27*D27 | G27: =IF(OR(D27=0,D27=1),"Obrigatória justificativa no campo Justificativa e observações","")
B28: Gerenciamento das Atividades Operacionais | C28: 0.3 | D28: 3 | E28: =C28*D28 | G28: =IF(OR(D28=0,D28=1),"Obrigatória justificativa no campo Justificativa e observações","")
B29: Atendimento às Solicitações | C29: 0.25 | D29: 3 | E29: =C29*D29 | G29: =IF(OR(D29=0,D29=1),"Obrigatória justificativa no campo Justificativa e observações","")
B30: Salários, Benefícios e Obrigações Trabalhistas | C30: 0.25 | D30: 3 | E30: =C30*D30 | G30: =IF(OR(D30=0,D30=1),"Obrigatória justificativa no campo Justificativa e observações","")
B31: TOTAL GRUPO 3 | C31: 1 | E31: =E27+E28+E29+E30
B32: NOTA FINAL (G1+G2+G3) | E32: =E20+E25+E31
B33: CONCEITO | C33: =IF(E32>=8.1,"A",IF(E32>=7.65,"B",IF(E32>=6.75,"C",IF(E32>=5.85,"D",IF(E32>=5.4,"E","F"))))) | E33: % a pagar | F33: =IF(C33="A",1,IF(C33="B",0.95,IF(C33="C",0.9,IF(C33="D",0.85,IF(C33="E",0.8,0.75)))))
B35: PARÂMETROS (base 30 avos)
B36: Dias no mês (calendário) | C36: 30
B37: Nº de Dias Trabalhados | C37: 30
B38: Dias para cálculo (base 30) | C38: =IF(C37>=C36,30,MIN(C37,C36))
B40: POSTOS DE TRABALHO
B41: Item | C41: POSTO | D41: Qtde Contratada | E41: Valor Unit. (R$) | F41: Horas | G41: Sem Cob. (h) | H41: Valor Hora (R$) | I41: Valor após Descontos (R$) | K41: (aux) Mensal
B42: 1 | C42: Vigilância armada de 12x36 horas diurnas de Segunda Feira a Domingo | D42: 4 | E42: 5677.75 | F42: =IF(N(D42)>0,D42*220,0) | H42: =IF(N(D42)>0,ROUNDDOWN(E42/220,2),0) | I42: =IF(AND(N(D42)>0,N(E42)>0),MAX(0,ROUNDDOWN((D42*E42-H42*N(G42))/30*C38*F33,2)),0) | K42: =ROUNDDOWN(N(D42)*N(E42),2)
B43: 2 | C43: Vigilância armada de 12x36 horas noturnas de Segunda Feira a Domingo | D43: 12 | E43: 6228.99 | F43: =IF(N(D43)>0,D43*220,0) | H43: =IF(N(D43)>0,ROUNDDOWN(E43/220,2),0) | I43: =IF(AND(N(D43)>0,N(E43)>0),MAX(0,ROUNDDOWN((D43*E43-H43*N(G43))/30*C38*F33,2)),0) | K43: =ROUNDDOWN(N(D43)*N(E43),2)
B44: 3 | C44: Vigilância desarmada de 12x36 horas diurnas de Segunda Feira a Domingo | D44: 18 | E44: 5672.89 | F44: =IF(N(D44)>0,D44*220,0) | H44: =IF(N(D44)>0,ROUNDDOWN(E44/220,2),0) | I44: =IF(AND(N(D44)>0,N(E44)>0),MAX(0,ROUNDDOWN((D44*E44-H44*N(G44))/30*C38*F33,2)),0) | K44: =ROUNDDOWN(N(D44)*N(E44),2)
B45: 4 | C45: Vigilância desarmada de 12x36 horas noturnas de Segunda Feira a Domingo | D45: 10 | E45: 6224.09 | F45: =IF(N(D45)>0,D45*220,0) | H45: =IF(N(D45)>0,ROUNDDOWN(E45/220,2),0) | I45: =IF(AND(N(D45)>0,N(E45)>0),MAX(0,ROUNDDOWN((D45*E45-H45*N(G45))/30*C38*F33,2)),0) | K45: =ROUNDDOWN(N(D45)*N(E45),2)
B46: 5 | C46: Vigilância desarmada de 44h (8:48 horas) diurnas de Segunda Feira a Sexta | D46: 1 | E46: 6019.58 | F46: =IF(N(D46)>0,D46*220,0) | H46: =IF(N(D46)>0,ROUNDDOWN(E46/220,2),0) | I46: =IF(AND(N(D46)>0,N(E46)>0),MAX(0,ROUNDDOWN((D46*E46-H46*N(G46))/30*C38*F33,2)),0) | K46: =ROUNDDOWN(N(D46)*N(E46),2)
B47: 6 | C47: Vigilância desarmada de 12x36 horas diurnas de Segunda Feira a Domingo COM INTRAJORNADA | D47: 2 | E47: 6064.91 | F47: =IF(N(D47)>0,D47*220,0) | H47: =IF(N(D47)>0,ROUNDDOWN(E47/220,2),0) | I47: =IF(AND(N(D47)>0,N(E47)>0),MAX(0,ROUNDDOWN((D47*E47-H47*N(G47))/30*C38*F33,2)),0) | K47: =ROUNDDOWN(N(D47)*N(E47),2)
B48: 7 | C48: Vigilância desarmada de 12x36 horas noturnas de Segunda Feira a Domingo COM INTRAJORNADA | D48: 2 | E48: 6654.1 | F48: =IF(N(D48)>0,D48*220,0) | H48: =IF(N(D48)>0,ROUNDDOWN(E48/220,2),0) | I48: =IF(AND(N(D48)>0,N(E48)>0),MAX(0,ROUNDDOWN((D48*E48-H48*N(G48))/30*C38*F33,2)),0) | K48: =ROUNDDOWN(N(D48)*N(E48),2)
B49: TOTAIS | D49: =SUM(D42:D48) | E49: ◀ Qtde contratada | I49: =SUM(I42:I48) | K49: =SUM(K42:K48)
B51: INSTRUMENTO DE COBRANÇA
B52: Item | C52: Posto | D52: Qtde Fat. | E52: Valor Unit. Faturado (R$)
B53: =B42 | C53: =C42 | D53: =N(D42) | E53: =IF(N(D42)>0,ROUNDDOWN(I42/D42,2),0)
B54: =B43 | C54: =C43 | D54: =N(D43) | E54: =IF(N(D43)>0,ROUNDDOWN(I43/D43,2),0)
B55: =B44 | C55: =C44 | D55: =N(D44) | E55: =IF(N(D44)>0,ROUNDDOWN(I44/D44,2),0)
B56: =B45 | C56: =C45 | D56: =N(D45) | E56: =IF(N(D45)>0,ROUNDDOWN(I45/D45,2),0)
B57: =B46 | C57: =C46 | D57: =N(D46) | E57: =IF(N(D46)>0,ROUNDDOWN(I46/D46,2),0)
B58: =B47 | C58: =C47 | D58: =N(D47) | E58: =IF(N(D47)>0,ROUNDDOWN(I47/D47,2),0)
B59: =B48 | C59: =C48 | D59: =N(D48) | E59: =IF(N(D48)>0,ROUNDDOWN(I48/D48,2),0)
B61: RESUMO FINANCEIRO
B62: Contratado Mensal – Total (R$) | E62: =K49
B63: Conceito | E63: =C33
B64: % do Faturamento a ser Liberado | E64: =F33
B65: Valor Glosado por QUALIDADE (R$) | E65: =ROUNDDOWN(K49-K49*F33,2)
B66: Valor Aprovado para Pagamento (R$) | E66: =MAX(0,ROUNDDOWN(I49+E82,2))
B68: FAIXA DE AJUSTE
B69: Conceito | C69: % a Pagar | E69: Nota Média
B70: A | C70: 100% | E70: 9,00–8,10
B71: B | C71: 95% | E71: 8,09–7,65
B72: C | C72: 90% | E72: 7,64–6,75
B73: D | C73: 85% | E73: 6,74–5,85
B74: E | C74: 80% | E74: 5,84–5,40
B75: F | C75: 75% | E75: < 5,40
B77: REEMBOLSO DE CRECHE
B78: Valor estimado unitário (R$) | E78: 0
B79: Valor Reembolso Creche Retido (R$) (estimado × qtde contratada) | E79: =ROUNDDOWN(E78*D49,2)
B80: Reembolsos Aprovados (quantidade)
B81: Reembolso por dependente (R$) | E81: 526.64
B82: Valor Total dos Reembolsos (R$) (Aprovados × Reembolso por dependente) | E82: =ROUNDDOWN(E80*E81,2)
B83: Saldo do mês anterior (R$) | E83: ='Julho 2025'!E84
B84: Saldo de Reembolso (R$) (Saldo anterior + Retido − Total) | E84: =E83+E79-E82
B85: =IF(E84<0,"⚠ Saldo negativo — se houver mais de uma unidade favor somar o saldo de todas; se permanecer negativo, aditivar o contrato.","")
B88: JUSTIFICATIVAS E OBSERVAÇÕES

Sheet Setembro 2025
B1: UNIVERSIDADE FEDERAL DO RIO DE JANEIRO — PR-6
B3: INSTRUMENTO DE MEDIÇÃO DE RESULTADO (IMR)
B7: IDENTIFICAÇÃO
B8: CONTRATO Nº | C8: 05/24
B9: UNIDADE | C9: MACAÉ
B10: CONTRATADA | C10: ANGEL'S SEGURANÇA E VIGILÂNCIA - EM RECUPERAÇÃO JUDICIAL LTDA
B11: FISCAL OPERACIONAL
B12: PERÍODO DE REFERÊNCIA | C12: Setembro 2025
B14: AVALIAÇÃO DE DESEMPENHO
B15: Critério de Avaliação | C15: PESO (a) | D15: NOTA (b) (0,1,3) | E15: SUBTOTAL (c=a×b)
B16: ▶ GRUPO 1 – DESEMPENHO PROFISSIONAL
B17: Cumprimento das Atividades | C17: 0.4 | D17: 3 | E17: =C17*D17 | G17: =IF(OR(D17=0,D17=1),"Obrigatória justificativa no campo Justificativa e observações","")
B18: Qualificação / Atendimento ao Público / Postura | C18: 0.35 | D18: 3 | E18: =C18*D18 | G18: =IF(OR(D18=0,D18=1),"Obrigatória justificativa no campo Justificativa e observações","")
B19: Uniformes e Identificação | C19: 0.25 | D19: 3 | E19: =C19*D19 | G19: =IF(OR(D19=0,D19=1),"Obrigatória justificativa no campo Justificativa e observações","")
B20: TOTAL GRUPO 1 | C20: 1 | E20: =E17+E18+E19
B21: ▶ GRUPO 2 – DESEMPENHO DAS ATIVIDADES
B22: Especificação Técnica dos Serviços | C22: 0.4 | D22: 3 | E22: =C22*D22 | G22: =IF(OR(D22=0,D22=1),"Obrigatória justificativa no campo Justificativa e observações","")
B23: Equipamentos e Acessórios | C23: 0.2 | D23: 3 | E23: =C23*D23 | G23: =IF(OR(D23=0,D23=1),"Obrigatória justificativa no campo Justificativa e observações","")
B24: Atendimento às Ocorrências | C24: 0.4 | D24: 3 | E24: =C24*D24 | G24: =IF(OR(D24=0,D24=1),"Obrigatória justificativa no campo Justificativa e observações","")
B25: TOTAL GRUPO 2 | C25: 1 | E25: =E22+E23+E24
B26: ▶ GRUPO 3 – GERENCIAMENTO
B27: Periodicidade da Supervisão | C27: 0.2 | D27: 3 | E27: =C27*D27 | G27: =IF(OR(D27=0,D27=1),"Obrigatória justificativa no campo Justificativa e observações","")
B28: Gerenciamento das Atividades Operacionais | C28: 0.3 | D28: 3 | E28: =C28*D28 | G28: =IF(OR(D28=0,D28=1),"Obrigatória justificativa no campo Justificativa e observações","")
B29: Atendimento às Solicitações | C29: 0.25 | D29: 3 | E29: =C29*D29 | G29: =IF(OR(D29=0,D29=1),"Obrigatória justificativa no campo Justificativa e observações","")
B30: Salários, Benefícios e Obrigações Trabalhistas | C30: 0.25 | D30: 3 | E30: =C30*D30 | G30: =IF(OR(D30=0,D30=1),"Obrigatória justificativa no campo Justificativa e observações","")
B31: TOTAL GRUPO 3 | C31: 1 | E31: =E27+E28+E29+E30
B32: NOTA FINAL (G1+G2+G3) | E32: =E20+E25+E31
B33: CONCEITO | C33: =IF(E32>=8.1,"A",IF(E32>=7.65,"B",IF(E32>=6.75,"C",IF(E32>=5.85,"D",IF(E32>=5.4,"E","F"))))) | E33: % a pagar | F33: =IF(C33="A",1,IF(C33="B",0.95,IF(C33="C",0.9,IF(C33="D",0.85,IF(C33="E",0.8,0.75)))))
B35: PARÂMETROS (base 30 avos)
B36: Dias no mês (calendário) | C36: 30
B37: Nº de Dias Trabalhados | C37: 30
B38: Dias para cálculo (base 30) | C38: =IF(C37>=C36,30,MIN(C37,C36))
B40: POSTOS DE TRABALHO
B41: Item | C41: POSTO | D41: Qtde Contratada | E41: Valor Unit. (R$) | F41: Horas | G41: Sem Cob. (h) | H41: Valor Hora (R$) | I41: Valor após Descontos (R$) | K41: (aux) Mensal
B42: 1 | C42: Vigilância armada de 12x36 horas diurnas de Segunda Feira a Domingo | D42: 4 | E42: 5677.75 | F42: =IF(N(D42)>0,D42*220,0) | H42: =IF(N(D42)>0,ROUNDDOWN(E42/220,2),0) | I42: =IF(AND(N(D42)>0,N(E42)>0),MAX(0,ROUNDDOWN((D42*E42-H42*N(G42))/30*C38*F33,2)),0) | K42: =ROUNDDOWN(N(D42)*N(E42),2)
B43: 2 | C43: Vigilância armada de 12x36 horas noturnas de Segunda Feira a Domingo | D43: 12 | E43: 6228.99 | F43: =IF(N(D43)>0,D43*220,0) | H43: =IF(N(D43)>0,ROUNDDOWN(E43/220,2),0) | I43: =IF(AND(N(D43)>0,N(E43)>0),MAX(0,ROUNDDOWN((D43*E43-H43*N(G43))/30*C38*F33,2)),0) | K43: =ROUNDDOWN(N(D43)*N(E43),2)
B44: 3 | C44: Vigilância desarmada de 12x36 horas diurnas de Segunda Feira a Domingo | D44: 18 | E44: 5672.89 | F44: =IF(N(D44)>0,D44*220,0) | H44: =IF(N(D44)>0,ROUNDDOWN(E44/220,2),0) | I44: =IF(AND(N(D44)>0,N(E44)>0),MAX(0,ROUNDDOWN((D44*E44-H44*N(G44))/30*C38*F33,2)),0) | K44: =ROUNDDOWN(N(D44)*N(E44),2)
B45: 4 | C45: Vigilância desarmada de 12x36 horas noturnas de Segunda Feira a Domingo | D45: 10 | E45: 6224.09 | F45: =IF(N(D45)>0,D45*220,0) | H45: =IF(N(D45)>0,ROUNDDOWN(E45/220,2),0) | I45: =IF(AND(N(D45)>0,N(E45)>0),MAX(0,ROUNDDOWN((D45*E45-H45*N(G45))/30*C38*F33,2)),0) | K45: =ROUNDDOWN(N(D45)*N(E45),2)
B46: 5 | C46: Vigilância desarmada de 44h (8:48 horas) diurnas de Segunda Feira a Sexta | D46: 1 | E46: 6019.58 | F46: =IF(N(D46)>0,D46*220,0) | H46: =IF(N(D46)>0,ROUNDDOWN(E46/220,2),0) | I46: =IF(AND(N(D46)>0,N(E46)>0),MAX(0,ROUNDDOWN((D46*E46-H46*N(G46))/30*C38*F33,2)),0) | K46: =ROUNDDOWN(N(D46)*N(E46),2)
B47: 6 | C47: Vigilância desarmada de 12x36 horas diurnas de Segunda Feira a Domingo COM INTRAJORNADA | D47: 2 | E47: 6064.91 | F47: =IF(N(D47)>0,D47*220,0) | H47: =IF(N(D47)>0,ROUNDDOWN(E47/220,2),0) | I47: =IF(AND(N(D47)>0,N(E47)>0),MAX(0,ROUNDDOWN((D47*E47-H47*N(G47))/30*C38*F33,2)),0) | K47: =ROUNDDOWN(N(D47)*N(E47),2)
B48: 7 | C48: Vigilância desarmada de 12x36 horas noturnas de Segunda Feira a Domingo COM INTRAJORNADA | D48: 2 | E48: 6654.1 | F48: =IF(N(D48)>0,D48*220,0) | H48: =IF(N(D48)>0,ROUNDDOWN(E48/220,2),0) | I48: =IF(AND(N(D48)>0,N(E48)>0),MAX(0,ROUNDDOWN((D48*E48-H48*N(G48))/30*C38*F33,2)),0) | K48: =ROUNDDOWN(N(D48)*N(E48),2)
B49: TOTAIS | D49: =SUM(D42:D48) | E49: ◀ Qtde contratada | I49: =SUM(I42:I48) | K49: =SUM(K42:K48)
B51: INSTRUMENTO DE COBRANÇA
B52: Item | C52: Posto | D52: Qtde Fat. | E52: Valor Unit. Faturado (R$)
B53: =B42 | C53: =C42 | D53: =N(D42) | E53: =IF(N(D42)>0,ROUNDDOWN(I42/D42,2),0)
B54: =B43 | C54: =C43 | D54: =N(D43) | E54: =IF(N(D43)>0,ROUNDDOWN(I43/D43,2),0)
B55: =B44 | C55: =C44 | D55: =N(D44) | E55: =IF(N(D44)>0,ROUNDDOWN(I44/D44,2),0)
B56: =B45 | C56: =C45 | D56: =N(D45) | E56: =IF(N(D45)>0,ROUNDDOWN(I45/D45,2),0)
B57: =B46 | C57: =C46 | D57: =N(D46) | E57: =IF(N(D46)>0,ROUNDDOWN(I46/D46,2),0)
B58: =B47 | C58: =C47 | D58: =N(D47) | E58: =IF(N(D47)>0,ROUNDDOWN(I47/D47,2),0)
B59: =B48 | C59: =C48 | D59: =N(D48) | E59: =IF(N(D48)>0,ROUNDDOWN(I48/D48,2),0)
B61: RESUMO FINANCEIRO
B62: Contratado Mensal – Total (R$) | E62: =K49
B63: Conceito | E63: =C33
B64: % do Faturamento a ser Liberado | E64: =F33
B65: Valor Glosado por QUALIDADE (R$) | E65: =ROUNDDOWN(K49-K49*F33,2)
B66: Valor Aprovado para Pagamento (R$) | E66: =MAX(0,ROUNDDOWN(I49+E82,2))
B68: FAIXA DE AJUSTE
B69: Conceito | C69: % a Pagar | E69: Nota Média
B70: A | C70: 100% | E70: 9,00–8,10
B71: B | C71: 95% | E71: 8,09–7,65
B72: C | C72: 90% | E72: 7,64–6,75
B73: D | C73: 85% | E73: 6,74–5,85
B74: E | C74: 80% | E74: 5,84–5,40
B75: F | C75: 75% | E75: < 5,40
B77: REEMBOLSO DE CRECHE
B78: Valor estimado unitário (R$) | E78: 0
B79: Valor Reembolso Creche Retido (R$) (estimado × qtde contratada) | E79: =ROUNDDOWN(E78*D49,2)
B80: Reembolsos Aprovados (quantidade)
B81: Reembolso por dependente (R$) | E81: 526.64
B82: Valor Total dos Reembolsos (R$) (Aprovados × Reembolso por dependente) | E82: =ROUNDDOWN(E80*E81,2)
B83: Saldo do mês anterior (R$) | E83: ='Agosto 2025'!E84
B84: Saldo de Reembolso (R$) (Saldo anterior + Retido − Total) | E84: =E83+E79-E82
B85: =IF(E84<0,"⚠ Saldo negativo — se houver mais de uma unidade favor somar o saldo de todas; se permanecer negativo, aditivar o contrato.","")
B88: JUSTIFICATIVAS E OBSERVAÇÕES

Sheet Outubro 2025
B1: UNIVERSIDADE FEDERAL DO RIO DE JANEIRO — PR-6
B3: INSTRUMENTO DE MEDIÇÃO DE RESULTADO (IMR)
B7: IDENTIFICAÇÃO
B8: CONTRATO Nº | C8: 05/24
B9: UNIDADE | C9: MACAÉ
B10: CONTRATADA | C10: ANGEL'S SEGURANÇA E VIGILÂNCIA - EM RECUPERAÇÃO JUDICIAL LTDA
B11: FISCAL OPERACIONAL
B12: PERÍODO DE REFERÊNCIA | C12: Outubro 2025
B14: AVALIAÇÃO DE DESEMPENHO
B15: Critério de Avaliação | C15: PESO (a) | D15: NOTA (b) (0,1,3) | E15: SUBTOTAL (c=a×b)
B16: ▶ GRUPO 1 – DESEMPENHO PROFISSIONAL
B17: Cumprimento das Atividades | C17: 0.4 | D17: 3 | E17: =C17*D17 | G17: =IF(OR(D17=0,D17=1),"Obrigatória justificativa no campo Justificativa e observações","")
B18: Qualificação / Atendimento ao Público / Postura | C18: 0.35 | D18: 3 | E18: =C18*D18 | G18: =IF(OR(D18=0,D18=1),"Obrigatória justificativa no campo Justificativa e observações","")
B19: Uniformes e Identificação | C19: 0.25 | D19: 3 | E19: =C19*D19 | G19: =IF(OR(D19=0,D19=1),"Obrigatória justificativa no campo Justificativa e observações","")
B20: TOTAL GRUPO 1 | C20: 1 | E20: =E17+E18+E19
B21: ▶ GRUPO 2 – DESEMPENHO DAS ATIVIDADES
B22: Especificação Técnica dos Serviços | C22: 0.4 | D22: 3 | E22: =C22*D22 | G22: =IF(OR(D22=0,D22=1),"Obrigatória justificativa no campo Justificativa e observações","")
B23: Equipamentos e Acessórios | C23: 0.2 | D23: 3 | E23: =C23*D23 | G23: =IF(OR(D23=0,D23=1),"Obrigatória justificativa no campo Justificativa e observações","")
B24: Atendimento às Ocorrências | C24: 0.4 | D24: 3 | E24: =C24*D24 | G24: =IF(OR(D24=0,D24=1),"Obrigatória justificativa no campo Justificativa e observações","")
B25: TOTAL GRUPO 2 | C25: 1 | E25: =E22+E23+E24
B26: ▶ GRUPO 3 – GERENCIAMENTO
B27: Periodicidade da Supervisão | C27: 0.2 | D27: 3 | E27: =C27*D27 | G27: =IF(OR(D27=0,D27=1),"Obrigatória justificativa no campo Justificativa e observações","")
B28: Gerenciamento das Atividades Operacionais | C28: 0.3 | D28: 3 | E28: =C28*D28 | G28: =IF(OR(D28=0,D28=1),"Obrigatória justificativa no campo Justificativa e observações","")
B29: Atendimento às Solicitações | C29: 0.25 | D29: 3 | E29: =C29*D29 | G29: =IF(OR(D29=0,D29=1),"Obrigatória justificativa no campo Justificativa e observações","")
B30: Salários, Benefícios e Obrigações Trabalhistas | C30: 0.25 | D30: 3 | E30: =C30*D30 | G30: =IF(OR(D30=0,D30=1),"Obrigatória justificativa no campo Justificativa e observações","")
B31: TOTAL GRUPO 3 | C31: 1 | E31: =E27+E28+E29+E30
B32: NOTA FINAL (G1+G2+G3) | E32: =E20+E25+E31
B33: CONCEITO | C33: =IF(E32>=8.1,"A",IF(E32>=7.65,"B",IF(E32>=6.75,"C",IF(E32>=5.85,"D",IF(E32>=5.4,"E","F"))))) | E33: % a pagar | F33: =IF(C33="A",1,IF(C33="B",0.95,IF(C33="C",0.9,IF(C33="D",0.85,IF(C33="E",0.8,0.75)))))
B35: PARÂMETROS (base 30 avos)
B36: Dias no mês (calendário) | C36: 30
B37: Nº de Dias Trabalhados | C37: 30
B38: Dias para cálculo (base 30) | C38: =IF(C37>=C36,30,MIN(C37,C36))
B40: POSTOS DE TRABALHO
B41: Item | C41: POSTO | D41: Qtde Contratada | E41: Valor Unit. (R$) | F41: Horas | G41: Sem Cob. (h) | H41: Valor Hora (R$) | I41: Valor após Descontos (R$) | K41: (aux) Mensal
B42: 1 | C42: Vigilância armada de 12x36 horas diurnas de Segunda Feira a Domingo | D42: 4 | E42: 5677.75 | F42: =IF(N(D42)>0,D42*220,0) | H42: =IF(N(D42)>0,ROUNDDOWN(E42/220,2),0) | I42: =IF(AND(N(D42)>0,N(E42)>0),MAX(0,ROUNDDOWN((D42*E42-H42*N(G42))/30*C38*F33,2)),0) | K42: =ROUNDDOWN(N(D42)*N(E42),2)
B43: 2 | C43: Vigilância armada de 12x36 horas noturnas de Segunda Feira a Domingo | D43: 12 | E43: 6228.99 | F43: =IF(N(D43)>0,D43*220,0) | H43: =IF(N(D43)>0,ROUNDDOWN(E43/220,2),0) | I43: =IF(AND(N(D43)>0,N(E43)>0),MAX(0,ROUNDDOWN((D43*E43-H43*N(G43))/30*C38*F33,2)),0) | K43: =ROUNDDOWN(N(D43)*N(E43),2)
B44: 3 | C44: Vigilância desarmada de 12x36 horas diurnas de Segunda Feira a Domingo | D44: 18 | E44: 5672.89 | F44: =IF(N(D44)>0,D44*220,0) | H44: =IF(N(D44)>0,ROUNDDOWN(E44/220,2),0) | I44: =IF(AND(N(D44)>0,N(E44)>0),MAX(0,ROUNDDOWN((D44*E44-H44*N(G44))/30*C38*F33,2)),0) | K44: =ROUNDDOWN(N(D44)*N(E44),2)
B45: 4 | C45: Vigilância desarmada de 12x36 horas noturnas de Segunda Feira a Domingo | D45: 10 | E45: 6224.09 | F45: =IF(N(D45)>0,D45*220,0) | H45: =IF(N(D45)>0,ROUNDDOWN(E45/220,2),0) | I45: =IF(AND(N(D45)>0,N(E45)>0),MAX(0,ROUNDDOWN((D45*E45-H45*N(G45))/30*C38*F33,2)),0) | K45: =ROUNDDOWN(N(D45)*N(E45),2)
B46: 5 | C46: Vigilância desarmada de 44h (8:48 horas) diurnas de Segunda Feira a Sexta | D46: 1 | E46: 6019.58 | F46: =IF(N(D46)>0,D46*220,0) | H46: =IF(N(D46)>0,ROUNDDOWN(E46/220,2),0) | I46: =IF(AND(N(D46)>0,N(E46)>0),MAX(0,ROUNDDOWN((D46*E46-H46*N(G46))/30*C38*F33,2)),0) | K46: =ROUNDDOWN(N(D46)*N(E46),2)
B47: 6 | C47: Vigilância desarmada de 12x36 horas diurnas de Segunda Feira a Domingo COM INTRAJORNADA | D47: 2 | E47: 6064.91 | F47: =IF(N(D47)>0,D47*220,0) | H47: =IF(N(D47)>0,ROUNDDOWN(E47/220,2),0) | I47: =IF(AND(N(D47)>0,N(E47)>0),MAX(0,ROUNDDOWN((D47*E47-H47*N(G47))/30*C38*F33,2)),0) | K47: =ROUNDDOWN(N(D47)*N(E47),2)
B48: 7 | C48: Vigilância desarmada de 12x36 horas noturnas de Segunda Feira a Domingo COM INTRAJORNADA | D48: 2 | E48: 6654.1 | F48: =IF(N(D48)>0,D48*220,0) | H48: =IF(N(D48)>0,ROUNDDOWN(E48/220,2),0) | I48: =IF(AND(N(D48)>0,N(E48)>0),MAX(0,ROUNDDOWN((D48*E48-H48*N(G48))/30*C38*F33,2)),0) | K48: =ROUNDDOWN(N(D48)*N(E48),2)
B49: TOTAIS | D49: =SUM(D42:D48) | E49: ◀ Qtde contratada | I49: =SUM(I42:I48) | K49: =SUM(K42:K48)
B51: INSTRUMENTO DE COBRANÇA
B52: Item | C52: Posto | D52: Qtde Fat. | E52: Valor Unit. Faturado (R$)
B53: =B42 | C53: =C42 | D53: =N(D42) | E53: =IF(N(D42)>0,ROUNDDOWN(I42/D42,2),0)
B54: =B43 | C54: =C43 | D54: =N(D43) | E54: =IF(N(D43)>0,ROUNDDOWN(I43/D43,2),0)
B55: =B44 | C55: =C44 | D55: =N(D44) | E55: =IF(N(D44)>0,ROUNDDOWN(I44/D44,2),0)
B56: =B45 | C56: =C45 | D56: =N(D45) | E56: =IF(N(D45)>0,ROUNDDOWN(I45/D45,2),0)
B57: =B46 | C57: =C46 | D57: =N(D46) | E57: =IF(N(D46)>0,ROUNDDOWN(I46/D46,2),0)
B58: =B47 | C58: =C47 | D58: =N(D47) | E58: =IF(N(D47)>0,ROUNDDOWN(I47/D47,2),0)
B59: =B48 | C59: =C48 | D59: =N(D48) | E59: =IF(N(D48)>0,ROUNDDOWN(I48/D48,2),0)
B61: RESUMO FINANCEIRO
B62: Contratado Mensal – Total (R$) | E62: =K49
B63: Conceito | E63: =C33
B64: % do Faturamento a ser Liberado | E64: =F33
B65: Valor Glosado por QUALIDADE (R$) | E65: =ROUNDDOWN(K49-K49*F33,2)
B66: Valor Aprovado para Pagamento (R$) | E66: =MAX(0,ROUNDDOWN(I49+E82,2))
B68: FAIXA DE AJUSTE
B69: Conceito | C69: % a Pagar | E69: Nota Média
B70: A | C70: 100% | E70: 9,00–8,10
B71: B | C71: 95% | E71: 8,09–7,65
B72: C | C72: 90% | E72: 7,64–6,75
B73: D | C73: 85% | E73: 6,74–5,85
B74: E | C74: 80% | E74: 5,84–5,40
B75: F | C75: 75% | E75: < 5,40
B77: REEMBOLSO DE CRECHE
B78: Valor estimado unitário (R$) | E78: 0
B79: Valor Reembolso Creche Retido (R$) (estimado × qtde contratada) | E79: =ROUNDDOWN(E78*D49,2)
B80: Reembolsos Aprovados (quantidade)
B81: Reembolso por dependente (R$) | E81: 526.64
B82: Valor Total dos Reembolsos (R$) (Aprovados × Reembolso por dependente) | E82: =ROUNDDOWN(E80*E81,2)
B83: Saldo do mês anterior (R$) | E83: ='Setembro 2025'!E84
B84: Saldo de Reembolso (R$) (Saldo anterior + Retido − Total) | E84: =E83+E79-E82
B85: =IF(E84<0,"⚠ Saldo negativo — se houver mais de uma unidade favor somar o saldo de todas; se permanecer negativo, aditivar o contrato.","")
B88: JUSTIFICATIVAS E OBSERVAÇÕES

Sheet Novembro 2025
B1: UNIVERSIDADE FEDERAL DO RIO DE JANEIRO — PR-6
B3: INSTRUMENTO DE MEDIÇÃO DE RESULTADO (IMR)
B7: IDENTIFICAÇÃO
B8: CONTRATO Nº | C8: 05/24
B9: UNIDADE | C9: MACAÉ
B10: CONTRATADA | C10: ANGEL'S SEGURANÇA E VIGILÂNCIA - EM RECUPERAÇÃO JUDICIAL LTDA
B11: FISCAL OPERACIONAL
B12: PERÍODO DE REFERÊNCIA | C12: Novembro 2025
B14: AVALIAÇÃO DE DESEMPENHO
B15: Critério de Avaliação | C15: PESO (a) | D15: NOTA (b) (0,1,3) | E15: SUBTOTAL (c=a×b)
B16: ▶ GRUPO 1 – DESEMPENHO PROFISSIONAL
B17: Cumprimento das Atividades | C17: 0.4 | D17: 3 | E17: =C17*D17 | G17: =IF(OR(D17=0,D17=1),"Obrigatória justificativa no campo Justificativa e observações","")
B18: Qualificação / Atendimento ao Público / Postura | C18: 0.35 | D18: 3 | E18: =C18*D18 | G18: =IF(OR(D18=0,D18=1),"Obrigatória justificativa no campo Justificativa e observações","")
B19: Uniformes e Identificação | C19: 0.25 | D19: 3 | E19: =C19*D19 | G19: =IF(OR(D19=0,D19=1),"Obrigatória justificativa no campo Justificativa e observações","")
B20: TOTAL GRUPO 1 | C20: 1 | E20: =E17+E18+E19
B21: ▶ GRUPO 2 – DESEMPENHO DAS ATIVIDADES
B22: Especificação Técnica dos Serviços | C22: 0.4 | D22: 3 | E22: =C22*D22 | G22: =IF(OR(D22=0,D22=1),"Obrigatória justificativa no campo Justificativa e observações","")
B23: Equipamentos e Acessórios | C23: 0.2 | D23: 3 | E23: =C23*D23 | G23: =IF(OR(D23=0,D23=1),"Obrigatória justificativa no campo Justificativa e observações","")
B24: Atendimento às Ocorrências | C24: 0.4 | D24: 3 | E24: =C24*D24 | G24: =IF(OR(D24=0,D24=1),"Obrigatória justificativa no campo Justificativa e observações","")
B25: TOTAL GRUPO 2 | C25: 1 | E25: =E22+E23+E24
B26: ▶ GRUPO 3 – GERENCIAMENTO
B27: Periodicidade da Supervisão | C27: 0.2 | D27: 3 | E27: =C27*D27 | G27: =IF(OR(D27=0,D27=1),"Obrigatória justificativa no campo Justificativa e observações","")
B28: Gerenciamento das Atividades Operacionais | C28: 0.3 | D28: 3 | E28: =C28*D28 | G28: =IF(OR(D28=0,D28=1),"Obrigatória justificativa no campo Justificativa e observações","")
B29: Atendimento às Solicitações | C29: 0.25 | D29: 3 | E29: =C29*D29 | G29: =IF(OR(D29=0,D29=1),"Obrigatória justificativa no campo Justificativa e observações","")
B30: Salários, Benefícios e Obrigações Trabalhistas | C30: 0.25 | D30: 3 | E30: =C30*D30 | G30: =IF(OR(D30=0,D30=1),"Obrigatória justificativa no campo Justificativa e observações","")
B31: TOTAL GRUPO 3 | C31: 1 | E31: =E27+E28+E29+E30
B32: NOTA FINAL (G1+G2+G3) | E32: =E20+E25+E31
B33: CONCEITO | C33: =IF(E32>=8.1,"A",IF(E32>=7.65,"B",IF(E32>=6.75,"C",IF(E32>=5.85,"D",IF(E32>=5.4,"E","F"))))) | E33: % a pagar | F33: =IF(C33="A",1,IF(C33="B",0.95,IF(C33="C",0.9,IF(C33="D",0.85,IF(C33="E",0.8,0.75)))))
B35: PARÂMETROS (base 30 avos)
B36: Dias no mês (calendário) | C36: 30
B37: Nº de Dias Trabalhados | C37: 30
B38: Dias para cálculo (base 30) | C38: =IF(C37>=C36,30,MIN(C37,C36))
B40: POSTOS DE TRABALHO
B41: Item | C41: POSTO | D41: Qtde Contratada | E41: Valor Unit. (R$) | F41: Horas | G41: Sem Cob. (h) | H41: Valor Hora (R$) | I41: Valor após Descontos (R$) | K41: (aux) Mensal
B42: 1 | C42: Vigilância armada de 12x36 horas diurnas de Segunda Feira a Domingo | D42: 4 | E42: 5677.75 | F42: =IF(N(D42)>0,D42*220,0) | H42: =IF(N(D42)>0,ROUNDDOWN(E42/220,2),0) | I42: =IF(AND(N(D42)>0,N(E42)>0),MAX(0,ROUNDDOWN((D42*E42-H42*N(G42))/30*C38*F33,2)),0) | K42: =ROUNDDOWN(N(D42)*N(E42),2)
B43: 2 | C43: Vigilância armada de 12x36 horas noturnas de Segunda Feira a Domingo | D43: 12 | E43: 6228.99 | F43: =IF(N(D43)>0,D43*220,0) | H43: =IF(N(D43)>0,ROUNDDOWN(E43/220,2),0) | I43: =IF(AND(N(D43)>0,N(E43)>0),MAX(0,ROUNDDOWN((D43*E43-H43*N(G43))/30*C38*F33,2)),0) | K43: =ROUNDDOWN(N(D43)*N(E43),2)
B44: 3 | C44: Vigilância desarmada de 12x36 horas diurnas de Segunda Feira a Domingo | D44: 18 | E44: 5672.89 | F44: =IF(N(D44)>0,D44*220,0) | H44: =IF(N(D44)>0,ROUNDDOWN(E44/220,2),0) | I44: =IF(AND(N(D44)>0,N(E44)>0),MAX(0,ROUNDDOWN((D44*E44-H44*N(G44))/30*C38*F33,2)),0) | K44: =ROUNDDOWN(N(D44)*N(E44),2)
B45: 4 | C45: Vigilância desarmada de 12x36 horas noturnas de Segunda Feira a Domingo | D45: 10 | E45: 6224.09 | F45: =IF(N(D45)>0,D45*220,0) | H45: =IF(N(D45)>0,ROUNDDOWN(E45/220,2),0) | I45: =IF(AND(N(D45)>0,N(E45)>0),MAX(0,ROUNDDOWN((D45*E45-H45*N(G45))/30*C38*F33,2)),0) | K45: =ROUNDDOWN(N(D45)*N(E45),2)
B46: 5 | C46: Vigilância desarmada de 44h (8:48 horas) diurnas de Segunda Feira a Sexta | D46: 1 | E46: 6019.58 | F46: =IF(N(D46)>0,D46*220,0) | H46: =IF(N(D46)>0,ROUNDDOWN(E46/220,2),0) | I46: =IF(AND(N(D46)>0,N(E46)>0),MAX(0,ROUNDDOWN((D46*E46-H46*N(G46))/30*C38*F33,2)),0) | K46: =ROUNDDOWN(N(D46)*N(E46),2)
B47: 6 | C47: Vigilância desarmada de 12x36 horas diurnas de Segunda Feira a Domingo COM INTRAJORNADA | D47: 2 | E47: 6064.91 | F47: =IF(N(D47)>0,D47*220,0) | H47: =IF(N(D47)>0,ROUNDDOWN(E47/220,2),0) | I47: =IF(AND(N(D47)>0,N(E47)>0),MAX(0,ROUNDDOWN((D47*E47-H47*N(G47))/30*C38*F33,2)),0) | K47: =ROUNDDOWN(N(D47)*N(E47),2)
B48: 7 | C48: Vigilância desarmada de 12x36 horas noturnas de Segunda Feira a Domingo COM INTRAJORNADA | D48: 2 | E48: 6654.1 | F48: =IF(N(D48)>0,D48*220,0) | H48: =IF(N(D48)>0,ROUNDDOWN(E48/220,2),0) | I48: =IF(AND(N(D48)>0,N(E48)>0),MAX(0,ROUNDDOWN((D48*E48-H48*N(G48))/30*C38*F33,2)),0) | K48: =ROUNDDOWN(N(D48)*N(E48),2)
B49: TOTAIS | D49: =SUM(D42:D48) | E49: ◀ Qtde contratada | I49: =SUM(I42:I48) | K49: =SUM(K42:K48)
B51: INSTRUMENTO DE COBRANÇA
B52: Item | C52: Posto | D52: Qtde Fat. | E52: Valor Unit. Faturado (R$)
B53: =B42 | C53: =C42 | D53: =N(D42) | E53: =IF(N(D42)>0,ROUNDDOWN(I42/D42,2),0)
B54: =B43 | C54: =C43 | D54: =N(D43) | E54: =IF(N(D43)>0,ROUNDDOWN(I43/D43,2),0)
B55: =B44 | C55: =C44 | D55: =N(D44) | E55: =IF(N(D44)>0,ROUNDDOWN(I44/D44,2),0)
B56: =B45 | C56: =C45 | D56: =N(D45) | E56: =IF(N(D45)>0,ROUNDDOWN(I45/D45,2),0)
B57: =B46 | C57: =C46 | D57: =N(D46) | E57: =IF(N(D46)>0,ROUNDDOWN(I46/D46,2),0)
B58: =B47 | C58: =C47 | D58: =N(D47) | E58: =IF(N(D47)>0,ROUNDDOWN(I47/D47,2),0)
B59: =B48 | C59: =C48 | D59: =N(D48) | E59: =IF(N(D48)>0,ROUNDDOWN(I48/D48,2),0)
B61: RESUMO FINANCEIRO
B62: Contratado Mensal – Total (R$) | E62: =K49
B63: Conceito | E63: =C33
B64: % do Faturamento a ser Liberado | E64: =F33
B65: Valor Glosado por QUALIDADE (R$) | E65: =ROUNDDOWN(K49-K49*F33,2)
B66: Valor Aprovado para Pagamento (R$) | E66: =MAX(0,ROUNDDOWN(I49+E82,2))
B68: FAIXA DE AJUSTE
B69: Conceito | C69: % a Pagar | E69: Nota Média
B70: A | C70: 100% | E70: 9,00–8,10
B71: B | C71: 95% | E71: 8,09–7,65
B72: C | C72: 90% | E72: 7,64–6,75
B73: D | C73: 85% | E73: 6,74–5,85
B74: E | C74: 80% | E74: 5,84–5,40
B75: F | C75: 75% | E75: < 5,40
B77: REEMBOLSO DE CRECHE
B78: Valor estimado unitário (R$) | E78: 0
B79: Valor Reembolso Creche Retido (R$) (estimado × qtde contratada) | E79: =ROUNDDOWN(E78*D49,2)
B80: Reembolsos Aprovados (quantidade)
B81: Reembolso por dependente (R$) | E81: 526.64
B82: Valor Total dos Reembolsos (R$) (Aprovados × Reembolso por dependente) | E82: =ROUNDDOWN(E80*E81,2)
B83: Saldo do mês anterior (R$) | E83: ='Outubro 2025'!E84
B84: Saldo de Reembolso (R$) (Saldo anterior + Retido − Total) | E84: =E83+E79-E82
B85: =IF(E84<0,"⚠ Saldo negativo — se houver mais de uma unidade favor somar o saldo de todas; se permanecer negativo, aditivar o contrato.","")
B88: JUSTIFICATIVAS E OBSERVAÇÕES

Sheet Dezembro 2025
B1: UNIVERSIDADE FEDERAL DO RIO DE JANEIRO — PR-6
B3: INSTRUMENTO DE MEDIÇÃO DE RESULTADO (IMR)
B7: IDENTIFICAÇÃO
B8: CONTRATO Nº | C8: 05/24
B9: UNIDADE | C9: MACAÉ
B10: CONTRATADA | C10: ANGEL'S SEGURANÇA E VIGILÂNCIA - EM RECUPERAÇÃO JUDICIAL LTDA
B11: FISCAL OPERACIONAL
B12: PERÍODO DE REFERÊNCIA | C12: Dezembro 2025
B14: AVALIAÇÃO DE DESEMPENHO
B15: Critério de Avaliação | C15: PESO (a) | D15: NOTA (b) (0,1,3) | E15: SUBTOTAL (c=a×b)
B16: ▶ GRUPO 1 – DESEMPENHO PROFISSIONAL
B17: Cumprimento das Atividades | C17: 0.4 | D17: 3 | E17: =C17*D17 | G17: =IF(OR(D17=0,D17=1),"Obrigatória justificativa no campo Justificativa e observações","")
B18: Qualificação / Atendimento ao Público / Postura | C18: 0.35 | D18: 3 | E18: =C18*D18 | G18: =IF(OR(D18=0,D18=1),"Obrigatória justificativa no campo Justificativa e observações","")
B19: Uniformes e Identificação | C19: 0.25 | D19: 3 | E19: =C19*D19 | G19: =IF(OR(D19=0,D19=1),"Obrigatória justificativa no campo Justificativa e observações","")
B20: TOTAL GRUPO 1 | C20: 1 | E20: =E17+E18+E19
B21: ▶ GRUPO 2 – DESEMPENHO DAS ATIVIDADES
B22: Especificação Técnica dos Serviços | C22: 0.4 | D22: 3 | E22: =C22*D22 | G22: =IF(OR(D22=0,D22=1),"Obrigatória justificativa no campo Justificativa e observações","")
B23: Equipamentos e Acessórios | C23: 0.2 | D23: 3 | E23: =C23*D23 | G23: =IF(OR(D23=0,D23=1),"Obrigatória justificativa no campo Justificativa e observações","")
B24: Atendimento às Ocorrências | C24: 0.4 | D24: 3 | E24: =C24*D24 | G24: =IF(OR(D24=0,D24=1),"Obrigatória justificativa no campo Justificativa e observações","")
B25: TOTAL GRUPO 2 | C25: 1 | E25: =E22+E23+E24
B26: ▶ GRUPO 3 – GERENCIAMENTO
B27: Periodicidade da Supervisão | C27: 0.2 | D27: 3 | E27: =C27*D27 | G27: =IF(OR(D27=0,D27=1),"Obrigatória justificativa no campo Justificativa e observações","")
B28: Gerenciamento das Atividades Operacionais | C28: 0.3 | D28: 3 | E28: =C28*D28 | G28: =IF(OR(D28=0,D28=1),"Obrigatória justificativa no campo Justificativa e observações","")
B29: Atendimento às Solicitações | C29: 0.25 | D29: 3 | E29: =C29*D29 | G29: =IF(OR(D29=0,D29=1),"Obrigatória justificativa no campo Justificativa e observações","")
B30: Salários, Benefícios e Obrigações Trabalhistas | C30: 0.25 | D30: 3 | E30: =C30*D30 | G30: =IF(OR(D30=0,D30=1),"Obrigatória justificativa no campo Justificativa e observações","")
B31: TOTAL GRUPO 3 | C31: 1 | E31: =E27+E28+E29+E30
B32: NOTA FINAL (G1+G2+G3) | E32: =E20+E25+E31
B33: CONCEITO | C33: =IF(E32>=8.1,"A",IF(E32>=7.65,"B",IF(E32>=6.75,"C",IF(E32>=5.85,"D",IF(E32>=5.4,"E","F"))))) | E33: % a pagar | F33: =IF(C33="A",1,IF(C33="B",0.95,IF(C33="C",0.9,IF(C33="D",0.85,IF(C33="E",0.8,0.75)))))
B35: PARÂMETROS (base 30 avos)
B36: Dias no mês (calendário) | C36: 30
B37: Nº de Dias Trabalhados | C37: 30
B38: Dias para cálculo (base 30) | C38: =IF(C37>=C36,30,MIN(C37,C36))
B40: POSTOS DE TRABALHO
B41: Item | C41: POSTO | D41: Qtde Contratada | E41: Valor Unit. (R$) | F41: Horas | G41: Sem Cob. (h) | H41: Valor Hora (R$) | I41: Valor após Descontos (R$) | K41: (aux) Mensal
B42: 1 | C42: Vigilância armada de 12x36 horas diurnas de Segunda Feira a Domingo | D42: 4 | E42: 5677.75 | F42: =IF(N(D42)>0,D42*220,0) | H42: =IF(N(D42)>0,ROUNDDOWN(E42/220,2),0) | I42: =IF(AND(N(D42)>0,N(E42)>0),MAX(0,ROUNDDOWN((D42*E42-H42*N(G42))/30*C38*F33,2)),0) | K42: =ROUNDDOWN(N(D42)*N(E42),2)
B43: 2 | C43: Vigilância armada de 12x36 horas noturnas de Segunda Feira a Domingo | D43: 12 | E43: 6228.99 | F43: =IF(N(D43)>0,D43*220,0) | H43: =IF(N(D43)>0,ROUNDDOWN(E43/220,2),0) | I43: =IF(AND(N(D43)>0,N(E43)>0),MAX(0,ROUNDDOWN((D43*E43-H43*N(G43))/30*C38*F33,2)),0) | K43: =ROUNDDOWN(N(D43)*N(E43),2)
B44: 3 | C44: Vigilância desarmada de 12x36 horas diurnas de Segunda Feira a Domingo | D44: 18 | E44: 5672.89 | F44: =IF(N(D44)>0,D44*220,0) | H44: =IF(N(D44)>0,ROUNDDOWN(E44/220,2),0) | I44: =IF(AND(N(D44)>0,N(E44)>0),MAX(0,ROUNDDOWN((D44*E44-H44*N(G44))/30*C38*F33,2)),0) | K44: =ROUNDDOWN(N(D44)*N(E44),2)
B45: 4 | C45: Vigilância desarmada de 12x36 horas noturnas de Segunda Feira a Domingo | D45: 10 | E45: 6224.09 | F45: =IF(N(D45)>0,D45*220,0) | H45: =IF(N(D45)>0,ROUNDDOWN(E45/220,2),0) | I45: =IF(AND(N(D45)>0,N(E45)>0),MAX(0,ROUNDDOWN((D45*E45-H45*N(G45))/30*C38*F33,2)),0) | K45: =ROUNDDOWN(N(D45)*N(E45),2)
B46: 5 | C46: Vigilância desarmada de 44h (8:48 horas) diurnas de Segunda Feira a Sexta | D46: 1 | E46: 6019.58 | F46: =IF(N(D46)>0,D46*220,0) | H46: =IF(N(D46)>0,ROUNDDOWN(E46/220,2),0) | I46: =IF(AND(N(D46)>0,N(E46)>0),MAX(0,ROUNDDOWN((D46*E46-H46*N(G46))/30*C38*F33,2)),0) | K46: =ROUNDDOWN(N(D46)*N(E46),2)
B47: 6 | C47: Vigilância desarmada de 12x36 horas diurnas de Segunda Feira a Domingo COM INTRAJORNADA | D47: 2 | E47: 6064.91 | F47: =IF(N(D47)>0,D47*220,0) | H47: =IF(N(D47)>0,ROUNDDOWN(E47/220,2),0) | I47: =IF(AND(N(D47)>0,N(E47)>0),MAX(0,ROUNDDOWN((D47*E47-H47*N(G47))/30*C38*F33,2)),0) | K47: =ROUNDDOWN(N(D47)*N(E47),2)
B48: 7 | C48: Vigilância desarmada de 12x36 horas noturnas de Segunda Feira a Domingo COM INTRAJORNADA | D48: 2 | E48: 6654.1 | F48: =IF(N(D48)>0,D48*220,0) | H48: =IF(N(D48)>0,ROUNDDOWN(E48/220,2),0) | I48: =IF(AND(N(D48)>0,N(E48)>0),MAX(0,ROUNDDOWN((D48*E48-H48*N(G48))/30*C38*F33,2)),0) | K48: =ROUNDDOWN(N(D48)*N(E48),2)
B49: TOTAIS | D49: =SUM(D42:D48) | E49: ◀ Qtde contratada | I49: =SUM(I42:I48) | K49: =SUM(K42:K48)
B51: INSTRUMENTO DE COBRANÇA
B52: Item | C52: Posto | D52: Qtde Fat. | E52: Valor Unit. Faturado (R$)
B53: =B42 | C53: =C42 | D53: =N(D42) | E53: =IF(N(D42)>0,ROUNDDOWN(I42/D42,2),0)
B54: =B43 | C54: =C43 | D54: =N(D43) | E54: =IF(N(D43)>0,ROUNDDOWN(I43/D43,2),0)
B55: =B44 | C55: =C44 | D55: =N(D44) | E55: =IF(N(D44)>0,ROUNDDOWN(I44/D44,2),0)
B56: =B45 | C56: =C45 | D56: =N(D45) | E56: =IF(N(D45)>0,ROUNDDOWN(I45/D45,2),0)
B57: =B46 | C57: =C46 | D57: =N(D46) | E57: =IF(N(D46)>0,ROUNDDOWN(I46/D46,2),0)
B58: =B47 | C58: =C47 | D58: =N(D47) | E58: =IF(N(D47)>0,ROUNDDOWN(I47/D47,2),0)
B59: =B48 | C59: =C48 | D59: =N(D48) | E59: =IF(N(D48)>0,ROUNDDOWN(I48/D48,2),0)
B61: RESUMO FINANCEIRO
B62: Contratado Mensal – Total (R$) | E62: =K49
B63: Conceito | E63: =C33
B64: % do Faturamento a ser Liberado | E64: =F33
B65: Valor Glosado por QUALIDADE (R$) | E65: =ROUNDDOWN(K49-K49*F33,2)
B66: Valor Aprovado para Pagamento (R$) | E66: =MAX(0,ROUNDDOWN(I49+E82,2))
B68: FAIXA DE AJUSTE
B69: Conceito | C69: % a Pagar | E69: Nota Média
B70: A | C70: 100% | E70: 9,00–8,10
B71: B | C71: 95% | E71: 8,09–7,65
B72: C | C72: 90% | E72: 7,64–6,75
B73: D | C73: 85% | E73: 6,74–5,85
B74: E | C74: 80% | E74: 5,84–5,40
B75: F | C75: 75% | E75: < 5,40
B77: REEMBOLSO DE CRECHE
B78: Valor estimado unitário (R$) | E78: 0
B79: Valor Reembolso Creche Retido (R$) (estimado × qtde contratada) | E79: =ROUNDDOWN(E78*D49,2)
B80: Reembolsos Aprovados (quantidade)
B81: Reembolso por dependente (R$) | E81: 526.64
B82: Valor Total dos Reembolsos (R$) (Aprovados × Reembolso por dependente) | E82: =ROUNDDOWN(E80*E81,2)
B83: Saldo do mês anterior (R$) | E83: ='Novembro 2025'!E84
B84: Saldo de Reembolso (R$) (Saldo anterior + Retido − Total) | E84: =E83+E79-E82
B85: =IF(E84<0,"⚠ Saldo negativo — se houver mais de uma unidade favor somar o saldo de todas; se permanecer negativo, aditivar o contrato.","")
B88: JUSTIFICATIVAS E OBSERVAÇÕES

Sheet Janeiro 2026
B1: UNIVERSIDADE FEDERAL DO RIO DE JANEIRO — PR-6
B3: INSTRUMENTO DE MEDIÇÃO DE RESULTADO (IMR)
B7: IDENTIFICAÇÃO
B8: CONTRATO Nº | C8: 05/24
B9: UNIDADE | C9: MACAÉ
B10: CONTRATADA | C10: ANGEL'S SEGURANÇA E VIGILÂNCIA - EM RECUPERAÇÃO JUDICIAL LTDA
B11: FISCAL OPERACIONAL
B12: PERÍODO DE REFERÊNCIA | C12: Janeiro 2026
B14: AVALIAÇÃO DE DESEMPENHO
B15: Critério de Avaliação | C15: PESO (a) | D15: NOTA (b) (0,1,3) | E15: SUBTOTAL (c=a×b)
B16: ▶ GRUPO 1 – DESEMPENHO PROFISSIONAL
B17: Cumprimento das Atividades | C17: 0.4 | D17: 3 | E17: =C17*D17 | G17: =IF(OR(D17=0,D17=1),"Obrigatória justificativa no campo Justificativa e observações","")
B18: Qualificação / Atendimento ao Público / Postura | C18: 0.35 | D18: 3 | E18: =C18*D18 | G18: =IF(OR(D18=0,D18=1),"Obrigatória justificativa no campo Justificativa e observações","")
B19: Uniformes e Identificação | C19: 0.25 | D19: 3 | E19: =C19*D19 | G19: =IF(OR(D19=0,D19=1),"Obrigatória justificativa no campo Justificativa e observações","")
B20: TOTAL GRUPO 1 | C20: 1 | E20: =E17+E18+E19
B21: ▶ GRUPO 2 – DESEMPENHO DAS ATIVIDADES
B22: Especificação Técnica dos Serviços | C22: 0.4 | D22: 3 | E22: =C22*D22 | G22: =IF(OR(D22=0,D22=1),"Obrigatória justificativa no campo Justificativa e observações","")
B23: Equipamentos e Acessórios | C23: 0.2 | D23: 3 | E23: =C23*D23 | G23: =IF(OR(D23=0,D23=1),"Obrigatória justificativa no campo Justificativa e observações","")
B24: Atendimento às Ocorrências | C24: 0.4 | D24: 3 | E24: =C24*D24 | G24: =IF(OR(D24=0,D24=1),"Obrigatória justificativa no campo Justificativa e observações","")
B25: TOTAL GRUPO 2 | C25: 1 | E25: =E22+E23+E24
B26: ▶ GRUPO 3 – GERENCIAMENTO
B27: Periodicidade da Supervisão | C27: 0.2 | D27: 3 | E27: =C27*D27 | G27: =IF(OR(D27=0,D27=1),"Obrigatória justificativa no campo Justificativa e observações","")
B28: Gerenciamento das Atividades Operacionais | C28: 0.3 | D28: 3 | E28: =C28*D28 | G28: =IF(OR(D28=0,D28=1),"Obrigatória justificativa no campo Justificativa e observações","")
B29: Atendimento às Solicitações | C29: 0.25 | D29: 3 | E29: =C29*D29 | G29: =IF(OR(D29=0,D29=1),"Obrigatória justificativa no campo Justificativa e observações","")
B30: Salários, Benefícios e Obrigações Trabalhistas | C30: 0.25 | D30: 3 | E30: =C30*D30 | G30: =IF(OR(D30=0,D30=1),"Obrigatória justificativa no campo Justificativa e observações","")
B31: TOTAL GRUPO 3 | C31: 1 | E31: =E27+E28+E29+E30
B32: NOTA FINAL (G1+G2+G3) | E32: =E20+E25+E31
B33: CONCEITO | C33: =IF(E32>=8.1,"A",IF(E32>=7.65,"B",IF(E32>=6.75,"C",IF(E32>=5.85,"D",IF(E32>=5.4,"E","F"))))) | E33: % a pagar | F33: =IF(C33="A",1,IF(C33="B",0.95,IF(C33="C",0.9,IF(C33="D",0.85,IF(C33="E",0.8,0.75)))))
B35: PARÂMETROS (base 30 avos)
B36: Dias no mês (calendário) | C36: 30
B37: Nº de Dias Trabalhados | C37: 30
B38: Dias para cálculo (base 30) | C38: =IF(C37>=C36,30,MIN(C37,C36))
B40: POSTOS DE TRABALHO
B41: Item | C41: POSTO | D41: Qtde Contratada | E41: Valor Unit. (R$) | F41: Horas | G41: Sem Cob. (h) | H41: Valor Hora (R$) | I41: Valor após Descontos (R$) | K41: (aux) Mensal
B42: 1 | C42: Vigilância armada de 12x36 horas diurnas de Segunda Feira a Domingo | D42: 4 | E42: 5677.75 | F42: =IF(N(D42)>0,D42*220,0) | H42: =IF(N(D42)>0,ROUNDDOWN(E42/220,2),0) | I42: =IF(AND(N(D42)>0,N(E42)>0),MAX(0,ROUNDDOWN((D42*E42-H42*N(G42))/30*C38*F33,2)),0) | K42: =ROUNDDOWN(N(D42)*N(E42),2)
B43: 2 | C43: Vigilância armada de 12x36 horas noturnas de Segunda Feira a Domingo | D43: 12 | E43: 6228.99 | F43: =IF(N(D43)>0,D43*220,0) | H43: =IF(N(D43)>0,ROUNDDOWN(E43/220,2),0) | I43: =IF(AND(N(D43)>0,N(E43)>0),MAX(0,ROUNDDOWN((D43*E43-H43*N(G43))/30*C38*F33,2)),0) | K43: =ROUNDDOWN(N(D43)*N(E43),2)
B44: 3 | C44: Vigilância desarmada de 12x36 horas diurnas de Segunda Feira a Domingo | D44: 18 | E44: 5672.89 | F44: =IF(N(D44)>0,D44*220,0) | H44: =IF(N(D44)>0,ROUNDDOWN(E44/220,2),0) | I44: =IF(AND(N(D44)>0,N(E44)>0),MAX(0,ROUNDDOWN((D44*E44-H44*N(G44))/30*C38*F33,2)),0) | K44: =ROUNDDOWN(N(D44)*N(E44),2)
B45: 4 | C45: Vigilância desarmada de 12x36 horas noturnas de Segunda Feira a Domingo | D45: 10 | E45: 6224.09 | F45: =IF(N(D45)>0,D45*220,0) | H45: =IF(N(D45)>0,ROUNDDOWN(E45/220,2),0) | I45: =IF(AND(N(D45)>0,N(E45)>0),MAX(0,ROUNDDOWN((D45*E45-H45*N(G45))/30*C38*F33,2)),0) | K45: =ROUNDDOWN(N(D45)*N(E45),2)
B46: 5 | C46: Vigilância desarmada de 44h (8:48 horas) diurnas de Segunda Feira a Sexta | D46: 1 | E46: 6019.58 | F46: =IF(N(D46)>0,D46*220,0) | H46: =IF(N(D46)>0,ROUNDDOWN(E46/220,2),0) | I46: =IF(AND(N(D46)>0,N(E46)>0),MAX(0,ROUNDDOWN((D46*E46-H46*N(G46))/30*C38*F33,2)),0) | K46: =ROUNDDOWN(N(D46)*N(E46),2)
B47: 6 | C47: Vigilância desarmada de 12x36 horas diurnas de Segunda Feira a Domingo COM INTRAJORNADA | D47: 2 | E47: 6064.91 | F47: =IF(N(D47)>0,D47*220,0) | H47: =IF(N(D47)>0,ROUNDDOWN(E47/220,2),0) | I47: =IF(AND(N(D47)>0,N(E47)>0),MAX(0,ROUNDDOWN((D47*E47-H47*N(G47))/30*C38*F33,2)),0) | K47: =ROUNDDOWN(N(D47)*N(E47),2)
B48: 7 | C48: Vigilância desarmada de 12x36 horas noturnas de Segunda Feira a Domingo COM INTRAJORNADA | D48: 2 | E48: 6654.1 | F48: =IF(N(D48)>0,D48*220,0) | H48: =IF(N(D48)>0,ROUNDDOWN(E48/220,2),0) | I48: =IF(AND(N(D48)>0,N(E48)>0),MAX(0,ROUNDDOWN((D48*E48-H48*N(G48))/30*C38*F33,2)),0) | K48: =ROUNDDOWN(N(D48)*N(E48),2)
B49: TOTAIS | D49: =SUM(D42:D48) | E49: ◀ Qtde contratada | I49: =SUM(I42:I48) | K49: =SUM(K42:K48)
B51: INSTRUMENTO DE COBRANÇA
B52: Item | C52: Posto | D52: Qtde Fat. | E52: Valor Unit. Faturado (R$)
B53: =B42 | C53: =C42 | D53: =N(D42) | E53: =IF(N(D42)>0,ROUNDDOWN(I42/D42,2),0)
B54: =B43 | C54: =C43 | D54: =N(D43) | E54: =IF(N(D43)>0,ROUNDDOWN(I43/D43,2),0)
B55: =B44 | C55: =C44 | D55: =N(D44) | E55: =IF(N(D44)>0,ROUNDDOWN(I44/D44,2),0)
B56: =B45 | C56: =C45 | D56: =N(D45) | E56: =IF(N(D45)>0,ROUNDDOWN(I45/D45,2),0)
B57: =B46 | C57: =C46 | D57: =N(D46) | E57: =IF(N(D46)>0,ROUNDDOWN(I46/D46,2),0)
B58: =B47 | C58: =C47 | D58: =N(D47) | E58: =IF(N(D47)>0,ROUNDDOWN(I47/D47,2),0)
B59: =B48 | C59: =C48 | D59: =N(D48) | E59: =IF(N(D48)>0,ROUNDDOWN(I48/D48,2),0)
B61: RESUMO FINANCEIRO
B62: Contratado Mensal – Total (R$) | E62: =K49
B63: Conceito | E63: =C33
B64: % do Faturamento a ser Liberado | E64: =F33
B65: Valor Glosado por QUALIDADE (R$) | E65: =ROUNDDOWN(K49-K49*F33,2)
B66: Valor Aprovado para Pagamento (R$) | E66: =MAX(0,ROUNDDOWN(I49+E82,2))
B68: FAIXA DE AJUSTE
B69: Conceito | C69: % a Pagar | E69: Nota Média
B70: A | C70: 100% | E70: 9,00–8,10
B71: B | C71: 95% | E71: 8,09–7,65
B72: C | C72: 90% | E72: 7,64–6,75
B73: D | C73: 85% | E73: 6,74–5,85
B74: E | C74: 80% | E74: 5,84–5,40
B75: F | C75: 75% | E75: < 5,40
B77: REEMBOLSO DE CRECHE
B78: Valor estimado unitário (R$) | E78: 0
B79: Valor Reembolso Creche Retido (R$) (estimado × qtde contratada) | E79: =ROUNDDOWN(E78*D49,2)
B80: Reembolsos Aprovados (quantidade)
B81: Reembolso por dependente (R$) | E81: 526.64
B82: Valor Total dos Reembolsos (R$) (Aprovados × Reembolso por dependente) | E82: =ROUNDDOWN(E80*E81,2)
B83: Saldo do mês anterior (R$) | E83: ='Dezembro 2025'!E84
B84: Saldo de Reembolso (R$) (Saldo anterior + Retido − Total) | E84: =E83+E79-E82
B85: =IF(E84<0,"⚠ Saldo negativo — se houver mais de uma unidade favor somar o saldo de todas; se permanecer negativo, aditivar o contrato.","")
B88: JUSTIFICATIVAS E OBSERVAÇÕES

Sheet Fevereiro 2026
B1: UNIVERSIDADE FEDERAL DO RIO DE JANEIRO — PR-6
B3: INSTRUMENTO DE MEDIÇÃO DE RESULTADO (IMR)
B7: IDENTIFICAÇÃO
B8: CONTRATO Nº | C8: 05/24
B9: UNIDADE | C9: MACAÉ
B10: CONTRATADA | C10: ANGEL'S SEGURANÇA E VIGILÂNCIA - EM RECUPERAÇÃO JUDICIAL LTDA
B11: FISCAL OPERACIONAL
B12: PERÍODO DE REFERÊNCIA | C12: Fevereiro 2026
B14: AVALIAÇÃO DE DESEMPENHO
B15: Critério de Avaliação | C15: PESO (a) | D15: NOTA (b) (0,1,3) | E15: SUBTOTAL (c=a×b)
B16: ▶ GRUPO 1 – DESEMPENHO PROFISSIONAL
B17: Cumprimento das Atividades | C17: 0.4 | D17: 3 | E17: =C17*D17 | G17: =IF(OR(D17=0,D17=1),"Obrigatória justificativa no campo Justificativa e observações","")
B18: Qualificação / Atendimento ao Público / Postura | C18: 0.35 | D18: 3 | E18: =C18*D18 | G18: =IF(OR(D18=0,D18=1),"Obrigatória justificativa no campo Justificativa e observações","")
B19: Uniformes e Identificação | C19: 0.25 | D19: 3 | E19: =C19*D19 | G19: =IF(OR(D19=0,D19=1),"Obrigatória justificativa no campo Justificativa e observações","")
B20: TOTAL GRUPO 1 | C20: 1 | E20: =E17+E18+E19
B21: ▶ GRUPO 2 – DESEMPENHO DAS ATIVIDADES
B22: Especificação Técnica dos Serviços | C22: 0.4 | D22: 3 | E22: =C22*D22 | G22: =IF(OR(D22=0,D22=1),"Obrigatória justificativa no campo Justificativa e observações","")
B23: Equipamentos e Acessórios | C23: 0.2 | D23: 3 | E23: =C23*D23 | G23: =IF(OR(D23=0,D23=1),"Obrigatória justificativa no campo Justificativa e observações","")
B24: Atendimento às Ocorrências | C24: 0.4 | D24: 3 | E24: =C24*D24 | G24: =IF(OR(D24=0,D24=1),"Obrigatória justificativa no campo Justificativa e observações","")
B25: TOTAL GRUPO 2 | C25: 1 | E25: =E22+E23+E24
B26: ▶ GRUPO 3 – GERENCIAMENTO
B27: Periodicidade da Supervisão | C27: 0.2 | D27: 3 | E27: =C27*D27 | G27: =IF(OR(D27=0,D27=1),"Obrigatória justificativa no campo Justificativa e observações","")
B28: Gerenciamento das Atividades Operacionais | C28: 0.3 | D28: 3 | E28: =C28*D28 | G28: =IF(OR(D28=0,D28=1),"Obrigatória justificativa no campo Justificativa e observações","")
B29: Atendimento às Solicitações | C29: 0.25 | D29: 3 | E29: =C29*D29 | G29: =IF(OR(D29=0,D29=1),"Obrigatória justificativa no campo Justificativa e observações","")
B30: Salários, Benefícios e Obrigações Trabalhistas | C30: 0.25 | D30: 3 | E30: =C30*D30 | G30: =IF(OR(D30=0,D30=1),"Obrigatória justificativa no campo Justificativa e observações","")
B31: TOTAL GRUPO 3 | C31: 1 | E31: =E27+E28+E29+E30
B32: NOTA FINAL (G1+G2+G3) | E32: =E20+E25+E31
B33: CONCEITO | C33: =IF(E32>=8.1,"A",IF(E32>=7.65,"B",IF(E32>=6.75,"C",IF(E32>=5.85,"D",IF(E32>=5.4,"E","F"))))) | E33: % a pagar | F33: =IF(C33="A",1,IF(C33="B",0.95,IF(C33="C",0.9,IF(C33="D",0.85,IF(C33="E",0.8,0.75)))))
B35: PARÂMETROS (base 30 avos)
B36: Dias no mês (calendário) | C36: 30
B37: Nº de Dias Trabalhados | C37: 30
B38: Dias para cálculo (base 30) | C38: =IF(C37>=C36,30,MIN(C37,C36))
B40: POSTOS DE TRABALHO
B41: Item | C41: POSTO | D41: Qtde Contratada | E41: Valor Unit. (R$) | F41: Horas | G41: Sem Cob. (h) | H41: Valor Hora (R$) | I41: Valor após Descontos (R$) | K41: (aux) Mensal
B42: 1 | C42: Vigilância armada de 12x36 horas diurnas de Segunda Feira a Domingo | D42: 4 | E42: 5677.75 | F42: =IF(N(D42)>0,D42*220,0) | H42: =IF(N(D42)>0,ROUNDDOWN(E42/220,2),0) | I42: =IF(AND(N(D42)>0,N(E42)>0),MAX(0,ROUNDDOWN((D42*E42-H42*N(G42))/30*C38*F33,2)),0) | K42: =ROUNDDOWN(N(D42)*N(E42),2)
B43: 2 | C43: Vigilância armada de 12x36 horas noturnas de Segunda Feira a Domingo | D43: 12 | E43: 6228.99 | F43: =IF(N(D43)>0,D43*220,0) | H43: =IF(N(D43)>0,ROUNDDOWN(E43/220,2),0) | I43: =IF(AND(N(D43)>0,N(E43)>0),MAX(0,ROUNDDOWN((D43*E43-H43*N(G43))/30*C38*F33,2)),0) | K43: =ROUNDDOWN(N(D43)*N(E43),2)
B44: 3 | C44: Vigilância desarmada de 12x36 horas diurnas de Segunda Feira a Domingo | D44: 18 | E44: 5672.89 | F44: =IF(N(D44)>0,D44*220,0) | H44: =IF(N(D44)>0,ROUNDDOWN(E44/220,2),0) | I44: =IF(AND(N(D44)>0,N(E44)>0),MAX(0,ROUNDDOWN((D44*E44-H44*N(G44))/30*C38*F33,2)),0) | K44: =ROUNDDOWN(N(D44)*N(E44),2)
B45: 4 | C45: Vigilância desarmada de 12x36 horas noturnas de Segunda Feira a Domingo | D45: 10 | E45: 6224.09 | F45: =IF(N(D45)>0,D45*220,0) | H45: =IF(N(D45)>0,ROUNDDOWN(E45/220,2),0) | I45: =IF(AND(N(D45)>0,N(E45)>0),MAX(0,ROUNDDOWN((D45*E45-H45*N(G45))/30*C38*F33,2)),0) | K45: =ROUNDDOWN(N(D45)*N(E45),2)
B46: 5 | C46: Vigilância desarmada de 44h (8:48 horas) diurnas de Segunda Feira a Sexta | D46: 1 | E46: 6019.58 | F46: =IF(N(D46)>0,D46*220,0) | H46: =IF(N(D46)>0,ROUNDDOWN(E46/220,2),0) | I46: =IF(AND(N(D46)>0,N(E46)>0),MAX(0,ROUNDDOWN((D46*E46-H46*N(G46))/30*C38*F33,2)),0) | K46: =ROUNDDOWN(N(D46)*N(E46),2)
B47: 6 | C47: Vigilância desarmada de 12x36 horas diurnas de Segunda Feira a Domingo COM INTRAJORNADA | D47: 2 | E47: 6064.91 | F47: =IF(N(D47)>0,D47*220,0) | H47: =IF(N(D47)>0,ROUNDDOWN(E47/220,2),0) | I47: =IF(AND(N(D47)>0,N(E47)>0),MAX(0,ROUNDDOWN((D47*E47-H47*N(G47))/30*C38*F33,2)),0) | K47: =ROUNDDOWN(N(D47)*N(E47),2)
B48: 7 | C48: Vigilância desarmada de 12x36 horas noturnas de Segunda Feira a Domingo COM INTRAJORNADA | D48: 2 | E48: 6654.1 | F48: =IF(N(D48)>0,D48*220,0) | H48: =IF(N(D48)>0,ROUNDDOWN(E48/220,2),0) | I48: =IF(AND(N(D48)>0,N(E48)>0),MAX(0,ROUNDDOWN((D48*E48-H48*N(G48))/30*C38*F33,2)),0) | K48: =ROUNDDOWN(N(D48)*N(E48),2)
B49: TOTAIS | D49: =SUM(D42:D48) | E49: ◀ Qtde contratada | I49: =SUM(I42:I48) | K49: =SUM(K42:K48)
B51: INSTRUMENTO DE COBRANÇA
B52: Item | C52: Posto | D52: Qtde Fat. | E52: Valor Unit. Faturado (R$)
B53: =B42 | C53: =C42 | D53: =N(D42) | E53: =IF(N(D42)>0,ROUNDDOWN(I42/D42,2),0)
B54: =B43 | C54: =C43 | D54: =N(D43) | E54: =IF(N(D43)>0,ROUNDDOWN(I43/D43,2),0)
B55: =B44 | C55: =C44 | D55: =N(D44) | E55: =IF(N(D44)>0,ROUNDDOWN(I44/D44,2),0)
B56: =B45 | C56: =C45 | D56: =N(D45) | E56: =IF(N(D45)>0,ROUNDDOWN(I45/D45,2),0)
B57: =B46 | C57: =C46 | D57: =N(D46) | E57: =IF(N(D46)>0,ROUNDDOWN(I46/D46,2),0)
B58: =B47 | C58: =C47 | D58: =N(D47) | E58: =IF(N(D47)>0,ROUNDDOWN(I47/D47,2),0)
B59: =B48 | C59: =C48 | D59: =N(D48) | E59: =IF(N(D48)>0,ROUNDDOWN(I48/D48,2),0)
B61: RESUMO FINANCEIRO
B62: Contratado Mensal – Total (R$) | E62: =K49
B63: Conceito | E63: =C33
B64: % do Faturamento a ser Liberado | E64: =F33
B65: Valor Glosado por QUALIDADE (R$) | E65: =ROUNDDOWN(K49-K49*F33,2)
B66: Valor Aprovado para Pagamento (R$) | E66: =MAX(0,ROUNDDOWN(I49+E82,2))
B68: FAIXA DE AJUSTE
B69: Conceito | C69: % a Pagar | E69: Nota Média
B70: A | C70: 100% | E70: 9,00–8,10
B71: B | C71: 95% | E71: 8,09–7,65
B72: C | C72: 90% | E72: 7,64–6,75
B73: D | C73: 85% | E73: 6,74–5,85
B74: E | C74: 80% | E74: 5,84–5,40
B75: F | C75: 75% | E75: < 5,40
B77: REEMBOLSO DE CRECHE
B78: Valor estimado unitário (R$) | E78: 0
B79: Valor Reembolso Creche Retido (R$) (estimado × qtde contratada) | E79: =ROUNDDOWN(E78*D49,2)
B80: Reembolsos Aprovados (quantidade)
B81: Reembolso por dependente (R$) | E81: 526.64
B82: Valor Total dos Reembolsos (R$) (Aprovados × Reembolso por dependente) | E82: =ROUNDDOWN(E80*E81,2)
B83: Saldo do mês anterior (R$) | E83: ='Janeiro 2026'!E84
B84: Saldo de Reembolso (R$) (Saldo anterior + Retido − Total) | E84: =E83+E79-E82
B85: =IF(E84<0,"⚠ Saldo negativo — se houver mais de uma unidade favor somar o saldo de todas; se permanecer negativo, aditivar o contrato.","")
B88: JUSTIFICATIVAS E OBSERVAÇÕES

Sheet Março 2026
B1: UNIVERSIDADE FEDERAL DO RIO DE JANEIRO — PR-6
B3: INSTRUMENTO DE MEDIÇÃO DE RESULTADO (IMR)
B7: IDENTIFICAÇÃO
B8: CONTRATO Nº | C8: 05/24
B9: UNIDADE | C9: MACAÉ
B10: CONTRATADA | C10: ANGEL'S SEGURANÇA E VIGILÂNCIA - EM RECUPERAÇÃO JUDICIAL LTDA
B11: FISCAL OPERACIONAL
B12: PERÍODO DE REFERÊNCIA | C12: Março 2026
B14: AVALIAÇÃO DE DESEMPENHO
B15: Critério de Avaliação | C15: PESO (a) | D15: NOTA (b) (0,1,3) | E15: SUBTOTAL (c=a×b)
B16: ▶ GRUPO 1 – DESEMPENHO PROFISSIONAL
B17: Cumprimento das Atividades | C17: 0.4 | D17: 3 | E17: =C17*D17 | G17: =IF(OR(D17=0,D17=1),"Obrigatória justificativa no campo Justificativa e observações","")
B18: Qualificação / Atendimento ao Público / Postura | C18: 0.35 | D18: 3 | E18: =C18*D18 | G18: =IF(OR(D18=0,D18=1),"Obrigatória justificativa no campo Justificativa e observações","")
B19: Uniformes e Identificação | C19: 0.25 | D19: 3 | E19: =C19*D19 | G19: =IF(OR(D19=0,D19=1),"Obrigatória justificativa no campo Justificativa e observações","")
B20: TOTAL GRUPO 1 | C20: 1 | E20: =E17+E18+E19
B21: ▶ GRUPO 2 – DESEMPENHO DAS ATIVIDADES
B22: Especificação Técnica dos Serviços | C22: 0.4 | D22: 3 | E22: =C22*D22 | G22: =IF(OR(D22=0,D22=1),"Obrigatória justificativa no campo Justificativa e observações","")
B23: Equipamentos e Acessórios | C23: 0.2 | D23: 3 | E23: =C23*D23 | G23: =IF(OR(D23=0,D23=1),"Obrigatória justificativa no campo Justificativa e observações","")
